Workbook

Sheet IS Raw
C5: Tiêu đề
C6: Ngày xuất dữ liệu | J6: 1000000000
J7: 0.071963067 | K7: 0.59816546 | L7: 0.29260159 | M7: -0.014316251 | N7: 0.28097852
C8: Mã CK | D8: DBD | F8: Xem theo | G8: Năm | H8: 2018 | J8: 1225.14 | K8: 1385.5 | L8: 1388.52 | M8: 1401.01 | N8: 1262.01
C9: Loại | D9: Hợp nhất | F9: Tiền tệ | G9: VNĐ | H9: VNĐ | M9: 1256952371543
D11: 2009 | E11: 2010 | F11: 2011 | G11: 2012 | H11: 2013 | I11: 2014 | J11: 2015 | K11: 2016 | L11: 2017 | M11: 2018 | N11: 2019 | O11: 2020 | P11: 2021
C12: Trạng thái kiểm toán | D12: Đã kiểm toán | E12: Đã kiểm toán | F12: Đã kiểm toán | G12: Đã kiểm toán | H12: Đã kiểm toán | I12: Đã kiểm toán | J12: Đã kiểm toán | K12: Đã kiểm toán | L12: Đã kiểm toán | M12: Đã kiểm toán | N12: Đã kiểm toán | O12: Đã kiểm toán | P12: Đã kiểm toán
C13: Công ty Kiểm toán | G13: Kiểm toán AASC | H13: Kiểm toán AASC | I13: Kiểm toán AASC | J13: Kiểm toán AASC | K13: Kiểm toán AASC | L13: Kiểm toán AASC | M13: Kiểm toán AASC | N13: Kiểm toán AASC | O13: Kiểm toán AASC | P13: Kiểm toán AASC
C14: Loại Ý kiến Kiểm toán | G14: N/A | H14: Chấp nhận toàn phần | I14: Chấp nhận toàn phần | J14: Chấp nhận toàn phần | K14: Chấp nhận toàn phần | L14: Chấp nhận toàn phần | M14: Chấp nhận toàn phần | N14: Chấp nhận toàn phần | O14: Chấp nhận toàn phần | P14: Chấp nhận toàn phần
C15: Doanh số | D15: 1365.0395 | E15: 1649.6384 | F15: 1786.8936 | G15: 1739.0177 | H15: 2145.0329 | I15: 2452.8286 | J15: 1266.1456 | K15: 1442.5093 | L15: 1459.5214 | M15: 1474.019 | N15: 1321.0062 | O15: 1329.7752 | P15: 0
C16: Các khoản giảm trừ | D16: -2.2321604 | E16: -3.6416401 | F16: -2.5402983 | G16: -0.49021099 | H16: -0.86816562 | I16: -0.94931483 | J16: -41.077583 | K16: -57.607455 | L16: -71.294045 | M16: -72.994715 | N16: -59.277208 | O16: -72.82279 | P16: 0
C17: Doanh số thuần | D17: 1362.8073 | E17: 1645.9968 | F17: 1784.3533 | G17: 1738.5275 | H17: 2144.1647 | I17: 2451.8793 | J17: 1225.068 | K17: 1384.9018 | L17: 1388.2274 | M17: 1401.0243 | N17: 1261.729 | O17: 1256.9524 | P17: 1558.5043
C18: Doanh thu dược phẩm | J18: 1119.03 | K18: 1260.14 | L18: 1255.63 | M18: 1220.84 | N18: 1143.14 | O18: 1148.3 | P18: 1191.05
C19: Doanh thu vật tư y tế | J19: 94.46 | K19: 115.1 | L19: 117.07 | M19: 169.49 | N19: 103.75 | O19: 92.31 | P19: 352.87
C20: Doanh thu khác | J20: 11.65 | K20: 10.26 | L20: 15.82 | M20: 10.68 | N20: 15.12 | O20: 16.35 | P20: 14.58
C21: Giá vốn hàng bán | D21: -1238.4551 | E21: -1469.5634 | F21: -1554.1667 | G21: -1520.0936 | H21: -1869.0719 | I21: -2128.8437 | J21: -773.07692 | K21: -875.70244 | L21: -897.55493 | M21: -972.89628 | N21: -846.93308 | O21: -765.81309 | P21: -935.93871
C22: Giá vốn dược phẩm | J22: 674.4237 | K22: 753.29845 | L22: 767.29591 | M22: 782.32085 | N22: 728.5726 | O22: 669.32143 | P22: 597.8722
C23: Giá vốn vật tư y tế | J23: 88.907278 | K23: 108.55258 | L23: 113.70558 | M23: 179.61155 | N23: 104.47008 | O23: 83.476642 | P23: 323.75084
C24: Giá vốn khác | J24: 9.7459408 | K24: 13.851407 | L24: 16.553434 | M24: 10.963883 | N24: 13.8904 | O24: 13.015024 | P24: 14.315668
C25: Lãi gộp | D25: 124.35226 | E25: 176.43338 | F25: 230.18661 | G25: 218.43393 | H25: 275.0928 | I25: 323.03559 | J25: 451.99112 | K25: 509.1994 | L25: 490.67247 | M25: 428.12804 | N25: 414.79594 | O25: 491.13928 | P25: 0
C26: Thu nhập tài chính | D26: 11.54075 | E26: 6.2530333 | F26: 7.5311207 | G26: 5.855125 | H26: 3.6704648 | I26: 4.2809301 | J26: 17.714871 | K26: 16.213594 | L26: 18.773405 | M26: 16.074493 | N26: 13.251147 | O26: 7.7517822 | P26: 6.3201839
C27: Chi phí tài chính | D27: -36.268105 | E27: -39.16598 | F27: -55.878307 | G27: -31.547993 | H27: -23.772301 | I27: -30.303225 | J27: -15.816123 | K27: -9.1025277 | L27: -10.811343 | M27: -12.200034 | N27: -14.622931 | O27: -14.325531 | P27: -8.647017
C28: Trong đó: Chi phí lãi vay | D28: -28.02467 | E28: -36.630793 | F28: -45.318451 | G28: -30.49184 | H28: -19.654885 | I28: -25.505476 | J28: -5.4477753 | K28: -4.498013 | L28: -6.8281941 | M28: -8.3658397 | N28: -10.314155 | O28: -6.5888547 | P28: 0
C29: Lãi/(lỗ) từ công ty liên doanh (từ năm 2015) | D29: 0 | E29: 0 | F29: 0 | G29: 0 | H29: 0 | I29: 0 | J29: 0 | K29: 10.724382 | L29: 8.0301361 | M29: 10.579769 | N29: 14.43949 | O29: 15.238404 | P29: 16.083129
C30: Chi phí bán hàng | D30: -40.333567 | E30: -51.05357 | F30: -63.830106 | G30: -67.539288 | H30: -68.628661 | I30: -83.251927 | J30: -222.0959 | K30: -260.80345 | L30: -210.95744 | M30: -174.04986 | N30: -169.93779 | O30: -220.85513 | P30: -276.43932
C31: Chi phí quản lý doanh nghiệp | D31: -40.655915 | E31: -43.689503 | F31: -49.310941 | G31: -58.072038 | H31: -62.676267 | I31: -71.410843 | J31: -102.01819 | K31: -90.386997 | L31: -92.776906 | M31: -67.52121 | N31: -84.108598 | O31: -88.501076 | P31: -128.99778
C32: Lãi/(lỗ) từ hoạt động kinh doanh | D32: 18.635418 | E32: 48.777361 | F32: 68.698375 | G32: 67.129732 | H32: 123.68604 | I32: 142.35052 | J32: 129.77578 | K32: 175.84439 | L32: 202.93032 | M32: 201.0112 | N32: 173.81726 | O32: 190.44773 | P32: 230.88482
C33: Thu nhập khác | D33: 4.7799168 | E33: 5.8330356 | F33: 7.3574941 | G33: 23.189036 | H33: 6.2556639 | I33: 8.7732738 | J33: 144.1416 | K33: 0.22343835 | L33: 0.68875095 | M33: 0.23141078 | N33: 0.34645156 | O33: 2.8734188 | P33: 1.8696857
C34: Chi phí khác | D34: -0.94818806 | E34: -2.0307211 | F34: -2.9170078 | G34: -3.0392074 | H34: -1.5028517 | I34: -0.98062655 | J34: -0.061872556 | K34: -0.1867886 | L34: -0.022626147 | M34: -0.21626276 | N34: -0.15042521 | O34: -0.12983325 | P34: 0.30660157
C35: Thu nhập khác, ròng | D35: 3.8317287 | E35: 3.8023144 | F35: 4.4404864 | G35: 20.149829 | H35: 4.7528122 | I35: 7.7926473 | J35: 144.07973 | K35: 0.036649756 | L35: 0.6661248 | M35: 0.015148018 | N35: 0.19602636 | O35: 2.7435855 | P35: 0
C36: Lãi/(lỗ) từ công ty liên doanh | D36: 0 | E36: 0 | F36: 0 | G36: 0 | H36: 0 | I36: 0 | J36: 0 | K36: 0 | L36: 0 | M36: 0 | N36: 0 | O36: 0 | P36: 0
... C45: Lãi trên cổ phiếu pha loãng (VND) | D45: 0 | E45: 0 | F45: 0 | G45: 0 | H45: 0 | I45: 0 | J45: 0 | K45: 0 | L45: 0 | M45: 0 | N45: 0 | O45: 2712 | P45: 0
C47: STOXPLUS CORPORATION
C48: Trụ sở: Tầng 5, Tòa nhà Anh Minh, 36 Hoàng Cầu, Đống Đa, Hà Nội
C49: Chi nhánh TP HCM: Tầng 2 May Plaza - 63D Võ Văn Tần, Phường 6, Quận 3, TP.HCM
C50: Email: Stoxplus@StoxPlus.com
C52: TRUNG TÂM CHĂM SÓC KHÁCH HÀNG
C53: Tại Hà Nội
C54: Ms. Đỗ Thị Lan - chuyên viên chăm sóc Khách hàng
C55: T: (844) - 3562 6962 - Ext: 103 M: 0989 219 401
C56: Email: lan.do@StoxPlus.com
C58: Tại HCM
C59: Ms. Lý Thị Hiền - Chuyên viên chăm sóc Khách hàng
C60: T: (848)- 3933 3586 - ext: 201 M: 0942863986
C61: Email: hien.ly@stoxplus.com

Sheet BS Raw
C5: Tiêu đề
C6: Ngày xuất dữ liệu | P6: 1000000000
P7: 48716.392
C8: Mã CK | D8: DBD | F8: Xem theo | G8: Năm | H8: 2018 | K8: 112-114-117-127-130
C9: Loại | D9: Hợp nhất | F9: Tiền tệ | G9: VNĐ | H9: VNĐ
J10: 106.71933 | K10: 156.02776 | L10: 204.07064 | M10: 249.38578 | N10: 281.75467 | O10: 326.31663 | P10: 412.21559
D11: 2009 | E11: 2010 | F11: 2011 | G11: 2012 | H11: 2013 | I11: 2014 | J11: 2015 | K11: 2016 | L11: 2017 | M11: 2018 | N11: 2019 | O11: 2020 | P11: 2021
C12: Trạng thái kiểm toán | D12: Đã kiểm toán | E12: Đã kiểm toán | F12: Đã kiểm toán | G12: Đã kiểm toán | H12: Đã kiểm toán | I12: Đã kiểm toán | J12: Đã kiểm toán | K12: Đã kiểm toán | L12: Đã kiểm toán | M12: Đã kiểm toán | N12: Đã kiểm toán | O12: Đã kiểm toán | P12: Đã kiểm toán
C13: Công ty Kiểm toán | G13: Kiểm toán AASC | H13: Kiểm toán AASC | I13: Kiểm toán AASC | J13: Kiểm toán AASC | K13: Kiểm toán AASC | L13: Kiểm toán AASC | M13: Kiểm toán AASC | N13: Kiểm toán AASC | O13: Kiểm toán AASC | P13: Kiểm toán AASC
C14: Loại Ý kiến Kiểm toán | G14: N/A | H14: Chấp nhận toàn phần | I14: Chấp nhận toàn phần | J14: Chấp nhận toàn phần | K14: Chấp nhận toàn phần | L14: Chấp nhận toàn phần | M14: Chấp nhận toàn phần | N14: Chấp nhận toàn phần | O14: Chấp nhận toàn phần | P14: Chấp nhận toàn phần
C15: TÀI SẢN NGẮN HẠN | D15: 304.08162 | E15: 425.4692 | F15: 430.74773 | G15: 540.80049 | H15: 639.36504 | I15: 756.45028 | J15: 772.56636 | K15: 1023.14 | L15: 1115.4177 | M15: 1021.2372 | N15: 1028.8082 | O15: 835.84574 | P15: 972.31054
C16: Tiền và tương đương tiền | D16: 21.196006 | E16: 44.016582 | F16: 36.96126 | G16: 98.834989 | H16: 100.57208 | I16: 127.49809 | J16: 210.69177 | K16: 135.54888 | L16: 96.499799 | M16: 92.556725 | N16: 138.16218 | O16: 108.72871 | P16: 68.45378
C17: Tiền | D17: 21.196006 | E17: 44.016582 | F17: 36.96126 | G17: 47.3021 | H17: 100.57208 | I17: 56.371803 | J17: 53.691771 | K17: 63.048882 | L17: 53.999799 | M17: 80.556725 | N17: 47.442333 | O17: 35.184671 | P17: 31.45378
C18: Các khoản tương đương tiền | D18: 0 | E18: 0 | F18: 0 | G18: 51.53289 | H18: 0 | I18: 71.126283 | J18: 157 | K18: 72.5 | L18: 42.5 | M18: 12 | N18: 90.719845 | O18: 73.544044 | P18: 37
C19: Giá trị thuần đầu tư ngắn hạn | D19: 4.2701751 | E19: 4.2419197 | F19: 3.8007988 | G19: 4.2409005 | H19: 3.4392469 | I19: 0.8737981 | J19: 110.00139 | K19: 274.11239 | L19: 313.80139 | M19: 222.70139 | N19: 113.94139 | O19: 93.341393 | P19: 139.20139
C20: Đầu tư ngắn hạn | D20: 8.0514103 | E20: 9.0707917 | F20: 9.1910027 | G20: 8.3588577 | H20: 7.570896 | I20: 1.17953 | J20: 0.0013933 | K20: 0.0013933 | L20: 0.0013933 | M20: 0.0013933 | N20: 0.0013933 | O20: 0.0013933 | P20: 0.0013933
C21: Dự phòng đầu tư ngắn hạn | D21: -3.7812352 | E21: -4.828872 | F21: -5.3902039 | G21: -4.1179572 | H21: -4.1316491 | I21: -0.3057319 | J21: 0 | K21: 0 | L21: 0 | M21: 0 | N21: 0 | O21: 0 | P21: 0
C22: Đầu tư nắm giữ đến ngày đáo hạn | D22: 0 | E22: 0 | F22: 0 | G22: 0 | H22: 0 | I22: 0 | J22: 110 | K22: 274.111 | L22: 313.8 | M22: 222.7 | N22: 113.94 | O22: 93.34 | P22: 139.2
C23: Các khoản phải thu | D23: 132.69903 | E23: 254.15788 | F23: 211.96627 | G23: 212.35944 | H23: 192.18521 | I23: 276.91296 | J23: 272.48072 | K23: 372.12792 | L23: 405.93248 | M23: 428.87787 | N23: 445.14765 | O23: 412.70151 | P23: 503.84008
C24: Phải thu khách hàng | D24: 118.0936 | E24: 239.82706 | F24: 195.28014 | G24: 204.28602 | H24: 167.36503 | I24: 242.88833 | J24: 255.39416 | K24: 319.40608 | L24: 339.16997 | M24: 380.7234 | N24: 407.28591 | O24: 412.78328 | P24: 496.56441
C25: Trả trước người bán | D25: 13.488462 | E25: 13.00845 | F25: 18.408142 | G25: 17.516065 | H25: 33.439064 | I25: 41.254525 | J25: 30.333859 | K25: 57.615319 | L25: 72.424661 | M25: 54.191459 | N25: 58.587922 | O25: 37.671562 | P25: 41.540322
C26: Phải thu nội bộ | D26: 0 | E26: 0 | F26: 0 | G26: 0 | H26: 0 | I26: 0 | J26: 0 | K26: 0 | L26: 0 | M26: 0 | N26: 0 | O26: 0 | P26: 0
... C73: Lợi thế thương mại (trước 2015) | D73: 2.3078375 | E73: 1.9781464 | F73: 1.6484554 | G73: 1.3187643 | H73: 1.7203994 | I73: 0 | J73: 0 | K73: 0 | L73: 0 | M73: 0 | N73: 0 | O73: 0 | P73: 0
C74: Tài sản dài hạn khác | D74: 5.1601745 | E74: 5.5266888 | F74: 8.2865175 | G74: 6.8283502 | H74: 12.267887 | I74: 9.5248181 | J74: 3.6169953 | K74: 12.188688 | L74: 30.486433 | M74: 25.586234 | N74: 40.525556 | O74: 40.759715 | P74: 34.41005 | R74: -6.3496648
C75: Trả trước dài hạn | D75: 4.1803029 | E75: 4.2901068 | F75: 6.7187366 | G75: 4.8364252 | H75: 9.2858691 | I75: 7.8724232 | J75: 3.6169953 | K75: 12.188688 | L75: 30.486433 | M75: 25.586234 | N75: 40.417123 | O75: 40.666421 | P75: 0
C76: Thuế thu nhập hoãn lại phải thu | D76: 0.60095561 | E76: 0.42176594 | F76: 0.23461757 | G76: 0.13609603 | H76: 0.1530109 | I76: 0.33669437 | J76: 0 | K76: 0 | L76: 0 | M76: 0 | N76: 0.10843274 | O76: 0.093293942 | P76: 0
C77: Thiết bị, vật tư, phụ tùng thay thế dài hạn | D77: 0 | E77: 0 | F77: 0 | G77: 0 | H77: 0 | I77: 0 | J77: 0 | K77: 0 | L77: 0 | M77: 0 | N77: 0 | O77: 0 | P77: 0
C78: Các tài sản dài hạn khác | D78: 0.378916 | E78: 0.814816 | F78: 1.3331634 | G78: 1.855829 | H78: 2.8290071 | I78: 0 | J78: 0 | K78: 0 | L78: 0 | M78: 0 | N78: 0 | O78: 0 | P78: 0
C79: Lợi thế thương mại | D79: 0 | E79: 0 | F79: 0 | G79: 0 | H79: 0 | I79: 1.3157005 | J79: 0 | K79: 0 | L79: 0 | M79: 0 | N79: 0 | O79: 0 | P79: 0
C80: TỔNG CỘNG TÀI SẢN | D80: 488.63764 | E80: 603.07961 | F80: 626.2223 | G80: 742.90043 | H80: 920.41146 | I80: 1090.9459 | J80: 1067.9332 | K80: 1434.26 | L80: 1544.19 | M80: 1434.3409 | N80: 1620.5529 | O80: 1437.4094 | P80: 1553.4944
C81: NỢ PHẢI TRẢ | D81: 373.50485 | E81: 459.70899 | F81: 438.37542 | G81: 532.40189 | H81: 632.32325 | I81: 736.59705 | J81: 513.78854 | K81: 661.23068 | L81: 711.17977 | M81: 543.68659 | N81: 688.0446 | O81: 448.78391 | P81: 418.35302
C82: Nợ ngắn hạn | D82: 333.47711 | E82: 435.36409 | F82: 412.70041 | G82: 514.18875 | H82: 594.82196 | I82: 699.65556 | J82: 482.08875 | K82: 612.15608 | L82: 655.81064 | M82: 497.31971 | N82: 580.31211 | O82: 347.87234 | P82: 293.26127
C83: Phải trả người bán | D83: 46.46339 | E83: 54.069454 | F83: 65.016445 | G83: 75.670533 | H83: 75.345927 | I83: 85.018742 | J83: 151.67171 | K83: 249.65009 | L83: 196.24762 | M83: 204.50767 | N83: 211.39591 | O83: 102.65215 | P83: 96.81303
C84: Người mua trả tiền trước | D84: 7.9910681 | E84: 8.2572546 | F84: 8.5527674 | G84: 14.556539 | H84: 17.928537 | I84: 15.125623 | J84: 15.068433 | K84: 6.5513423 | L84: 31.13507 | M84: 14.769554 | N84: 5.1531493 | O84: 28.952275 | P84: 10.607673
C85: Thuế và các khoản phải trả Nhà nước | D85: 4.3599082 | E85: 5.7650382 | F85: 8.4025578 | G85: 13.042855 | H85: 16.245141 | I85: 12.714346 | J85: 28.588905 | K85: 23.567266 | L85: 30.183982 | M85: 9.72081 | N85: 27.98454 | O85: 18.47604 | P85: 0
C86: Phải trả người lao động | D86: 16.594478 | E86: 30.740877 | F86: 34.439871 | G86: 36.000169 | H86: 39.525746 | I86: 54.151323 | J86: 53.490475 | K86: 70.359021 | L86: 40.739387 | M86: 14.603357 | N86: 27.415983 | O86: 36.378113 | P86: 0
... C136: TỔNG CỘNG NGUỒN VỐN | D136: 488.63764 | E136: 603.07961 | F136: 626.2223 | G136: 742.90043 | H136: 920.41146 | I136: 1090.9459 | J136: 1067.9332 | K136: 1434.26 | L136: 1544.19 | M136: 1434.3409 | N136: 1620.5529 | O136: 1437.4094 | P136: 1553.4944
C138: STOXPLUS CORPORATION
C139: Trụ sở: Tầng 5, Tòa nhà Anh Minh, 36 Hoàng Cầu, Đống Đa, Hà Nội
C140: Chi nhánh TP HCM: Tầng 2 May Plaza - 63D Võ Văn Tần, Phường 6, Quận 3, TP.HCM
C141: Email: Stoxplus@StoxPlus.com
C143: TRUNG TÂM CHĂM SÓC KHÁCH HÀNG
C144: Tại Hà Nội
C145: Ms. Đỗ Thị Lan - chuyên viên chăm sóc Khách hàng
C146: T: (844) - 3562 6962 - Ext: 103 M: 0989 219 401
C147: Email: lan.do@StoxPlus.com
C149: Tại HCM
C150: Ms. Lý Thị Hiền - Chuyên viên chăm sóc Khách hàng
C151: T: (848)- 3933 3586 - ext: 201 M: 0942863986
C152: Email: hien.ly@stoxplus.com

Sheet CF Raw
C5: Tiêu đề
C6: Ngày xuất dữ liệu
C8: Mã CK | D8: DBD | E8: DBD | F8: Xem theo | G8: Năm | H8: 2018
C9: Loại | D9: Hợp nhất | F9: Tiền tệ | G9: VNĐ | H9: VNĐ
J10: 308.06553
C11: Gián tiếp | D11: 2009 | E11: 2010 | F11: 2011 | G11: 2012 | H11: 2013 | I11: 2014 | J11: 2015 | K11: 2016 | L11: 2017 | M11: 2018 | N11: 2019 | O11: 2020 | P11: 2021
C12: Trạng thái kiểm toán | D12: Đã kiểm toán | E12: Đã kiểm toán | F12: Đã kiểm toán | G12: Đã kiểm toán | H12: Đã kiểm toán | I12: Đã kiểm toán | J12: Đã kiểm toán | K12: Đã kiểm toán | L12: Đã kiểm toán | M12: Đã kiểm toán | N12: Đã kiểm toán | O12: Đã kiểm toán | P12: Đã kiểm toán
C13: Công ty Kiểm toán | G13: Kiểm toán AASC | H13: Kiểm toán AASC | I13: Kiểm toán AASC | J13: Kiểm toán AASC | K13: Kiểm toán AASC | L13: Kiểm toán AASC | M13: Kiểm toán AASC | N13: Kiểm toán AASC | O13: Kiểm toán AASC | P13: Kiểm toán AASC
C14: Loại Ý kiến Kiểm toán | G14: N/A | H14: Chấp nhận toàn phần | I14: Chấp nhận toàn phần | J14: Chấp nhận toàn phần | K14: Chấp nhận toàn phần | L14: Chấp nhận toàn phần | M14: Chấp nhận toàn phần | N14: Chấp nhận toàn phần | O14: Chấp nhận toàn phần | P14: Chấp nhận toàn phần
C15: Lãi trước thuế | D15: 0 | E15: 52.579675 | F15: 73.138861 | G15: 87.27956 | H15: 128.43885 | I15: 150.14317 | J15: 273.85551 | K15: 175.88104 | L15: 203.59645 | M15: 201.02634 | N15: 174.01329 | O15: 193.19132 | P15: 0
C16: Khấu hao TSCĐ | D16: 0 | E16: 28.622377 | F16: 31.478679 | G16: 36.860873 | H16: 48.00734 | I16: 68.371455 | J16: 39.216982 | K16: 33.793831 | L16: 36.813842 | M16: 36.516915 | N16: 27.945022 | O16: 31.808991 | P16: 40.674128
C17: Phân bổ lợi thế thương mại | D17: 0 | E17: 0 | F17: 0 | G17: 0 | H17: 0 | I17: 0 | J17: 0 | K17: 0 | L17: 0 | M17: 0 | N17: 0 | O17: 0 | P17: 0
C18: Chi phí dự phòng | D18: 0 | E18: -15.692028 | F18: 2.2117206 | G18: 0.2162593 | H18: -0.43876799 | I18: -3.1254635 | J18: 25.788019 | K18: -5.1495658 | L18: -2.6443794 | M18: 1.1207052 | N18: 14.547849 | O18: 14.288447 | P18: 14.288447
C19: (Lãi)/lỗ chênh lệch tỷ giá chưa thực hiện | D19: 0 | E19: 0 | F19: 0 | G19: 0.092933761 | H19: 0.11801748 | I19: -0.59503311 | J19: -0.42643001 | K19: 0.30575327 | L19: -0.003749822 | M19: -0.089566701 | N19: 0.069131555 | O19: 0.69521357 | P19: 0
C20: (Lãi)/lỗ từ thanh lý tài sản cố định | D20: 0 | E20: 0 | F20: 0 | G20: 0 | H20: 0 | I20: 0 | J20: 0 | K20: 0 | L20: 0 | M20: 0 | N20: 0 | O20: 0 | P20: 0
C21: (Lãi)/lỗ từ hoạt động đầu tư | D21: 0 | E21: -1.1133429 | F21: -1.4633982 | G21: 3.2282626 | H21: -1.4803883 | I21: -4.5389949 | J21: -47.816327 | K21: -25.707874 | L21: -25.73558 | M21: -26.323733 | N21: -27.371186 | O21: -24.246805 | P21: -24.246805
C22: Chi phí lãi vay | D22: 0 | E22: 36.630793 | F22: 45.318451 | G22: 30.483197 | H22: 19.654885 | I22: 25.505476 | J22: 5.4477753 | K22: 4.498013 | L22: 6.8281941 | M22: 8.3658397 | N22: 10.314155 | O22: 6.5888547 | P22: 1.3245274
C23: Thu lãi và cổ tức | D23: 0 | E23: 0 | F23: 0 | G23: 0 | H23: 0 | I23: 0 | J23: 0 | K23: 0 | L23: 0 | M23: 0 | N23: 0 | O23: 0 | P23: 0
C24: Các khoản điều chỉnh khác | D24: 0 | E24: 0 | F24: 0 | G24: 0 | H24: 0 | I24: 0 | J24: 12 | K24: 17 | L24: 15 | M24: 0 | N24: -1.5017455 | O24: 0.014646581 | P24: 0
C25: Lãi/(lỗ) trước những thay đổi vốn lưu động | D25: 0 | E25: 101.02747 | F25: 150.68431 | G25: 158.16109 | H25: 194.29994 | I25: 235.76061 | J25: 308.06553 | K25: 200.6212 | L25: 233.85478 | M25: 220.61651 | N25: 198.01651 | O25: 222.34066 | P25: 0
C26: (Tăng)/giảm các khoản phải thu | D26: 0 | E26: -128.53364 | F26: 40.928178 | G26: -11.715985 | H26: 15.652325 | I26: -78.427583 | J26: 131.73249 | K26: -94.86457 | L26: -27.298478 | M26: -9.0717265 | N26: -58.92951 | O26: 29.325194 | P26: -84.79
... C55: Tiền và tương đương tiền cuối kỳ | D55: 21.196006 | E55: 44.016582 | F55: 36.96126 | G55: 98.834989 | H55: 100.57208 | I55: 127.49809 | J55: 210.69177 | K55: 135.54888 | L55: 96.499799 | M55: 92.556725 | N55: 138.16218 | O55: 108.72871 | P55: 0
C57: STOXPLUS CORPORATION
C58: Trụ sở: Tầng 5, Tòa nhà Anh Minh, 36 Hoàng Cầu, Đống Đa, Hà Nội
C59: Chi nhánh TP HCM: Tầng 2 May Plaza - 63D Võ Văn Tần, Phường 6, Quận 3, TP.HCM
C60: Email: Stoxplus@StoxPlus.com
C62: TRUNG TÂM CHĂM SÓC KHÁCH HÀNG
C63: Tại Hà Nội
C64: Ms. Đỗ Thị Lan - chuyên viên chăm sóc Khách hàng
C65: T: (844) - 3562 6962 - Ext: 103 M: 0989 219 401
C66: Email: lan.do@StoxPlus.com
C68: Tại HCM
C69: Ms. Lý Thị Hiền - Chuyên viên chăm sóc Khách hàng
C70: T: (848)- 3933 3586 - ext: 201 M: 0942863986
C71: Email: hien.ly@stoxplus.com

Sheet Notes
C5: Tiêu đề
C6: Ngày xuất dữ liệu | H6: 1000000000 | P6: 1000000000
C8: Mã CK | D8: DBD | F8: Xem theo | G8: Năm | H8: 2018
C9: Loại | D9: Hợp nhất | F9: Tiền tệ | G9: VNĐ | H9: VNĐ
D11: 2009 | E11: 2010 | F11: 2011 | G11: 2012 | H11: 2013 | I11: 2014 | J11: 2015 | K11: 2016 | L11: 2017 | M11: 2018 | N11: 2019 | O11: 2020 | P11: 2021
C12: Trạng thái kiểm toán | D12: Đã kiểm toán | E12: Đã kiểm toán | F12: Đã kiểm toán | G12: Đã kiểm toán | H12: Đã kiểm toán | I12: Đã kiểm toán | J12: Đã kiểm toán | K12: Đã kiểm toán | L12: Đã kiểm toán | M12: Đã kiểm toán | N12: Đã kiểm toán | O12: Đã kiểm toán | P12: Đã kiểm toán
C13: Công ty Kiểm toán | G13: Kiểm toán AASC | H13: Kiểm toán AASC | I13: Kiểm toán AASC | J13: Kiểm toán AASC | K13: Kiểm toán AASC | L13: Kiểm toán AASC | M13: Kiểm toán AASC | N13: Kiểm toán AASC | O13: Kiểm toán AASC | P13: Kiểm toán AASC
C14: Loại Ý kiến Kiểm toán | G14: N/A | H14: Chấp nhận toàn phần | I14: Chấp nhận toàn phần | J14: Chấp nhận toàn phần | K14: Chấp nhận toàn phần | L14: Chấp nhận toàn phần | M14: Chấp nhận toàn phần | N14: Chấp nhận toàn phần | O14: Chấp nhận toàn phần | P14: Chấp nhận toàn phần
C15: Tiền | D15: 21.196006 | E15: 44.016582 | F15: 36.96126 | G15: 98.834989 | H15: 100.57208 | I15: 127.49809 | J15: 210.7 | K15: 135.54888 | L15: 96.499799 | M15: 92.556725 | N15: 138.16218 | O15: 110.52871 | P15: 0
C16: Tiền mặt | D16: 1.9636838 | E16: 1.7728805 | F16: 4.0392071 | G16: 1.1286801 | H16: 6.0291765 | I16: 3.7866959 | J16: 0.87 | K16: 0.98680987 | L16: 0.6614968 | M16: 0.56186445 | N16: 0.7090141 | O16: 0.47311068 | P16: 0
C17: Tiền gửi Ngân hàng | D17: 19.232323 | E17: 42.243702 | F17: 32.922053 | G17: 46.17342 | H17: 94.5429 | I17: 51.140107 | J17: 52.8 | K17: 62.062072 | L17: 53.338302 | M17: 79.994861 | N17: 46.733319 | O17: 34.71156 | P17: 0
C18: Tiền đang chuyển | D18: 0 | E18: 0 | F18: 0 | G18: 0 | H18: 0 | I18: 1.445 | J18: 0 | K18: 0 | L18: 0 | M18: 0 | N18: 0 | O18: 0 | P18: 0
C19: Tiền và tương đương tiền | D19: 0 | E19: 0 | F19: 0 | G19: 51.53289 | H19: 0 | I19: 71.126283 | J19: 157 | K19: 72.5 | L19: 42.5 | M19: 12 | N19: 90.719845 | O19: 75.344044 | P19: 0
C20: Đầu tư tài chính NH | D20: 4.2701751 | E20: 4.2419197 | F20: 3.8007988 | G20: 4.2409005 | H20: 3.4392469 | I20: 0.8737981 | J20: 110 | K20: 274.11239 | L20: 313.80139 | M20: 222.70279 | N20: 113.94139 | O20: 93.341393 | P20: 0
C21: Chứng khoán đầu tư ngắn hạn | D21: 8.0514103 | E21: 9.0707917 | F21: 9.1910027 | G21: 7.570896 | H21: 7.570896 | I21: 1.17953 | J21: 0 | K21: 0.0013933 | L21: 0.0013933 | M21: 0.0013933 | N21: 0.0013933 | O21: 0.0013933 | P21: 0
C22: Đầu tư nắm giữ đến ngày đáo hạn | D22: 0 | E22: 0 | F22: 0 | G22: 0 | H22: 0 | I22: 0 | J22: 110 | K22: 274.111 | L22: 313.8 | M22: 222.70139 | N22: 113.94 | O22: 93.34 | P22: 0
C23: Ngắn hạn | D23: 0 | E23: 0 | F23: 0 | G23: 0 | H23: 0 | I23: 0 | J23: 110 | K23: 274.111 | L23: 313.8 | M23: 222.70139 | N23: 113.94 | O23: 93.34 | P23: 0
C24: Dài hạn | D24: 0 | E24: 0 | F24: 0 | G24: 0 | H24: 0 | I24: 0 | J24: 0 | K24: 0 | L24: 0 | M24: 0 | N24: 0 | O24: 0 | P24: 0
C25: Đầu tư NH khác | D25: -3.7812352 | E25: 0 | F25: 0 | G25: 0.7879617 | H25: 0 | I25: 0 | J25: 0 | K25: 0 | L25: 0 | M25: 0 | N25: 0 | O25: 0 | P25: 0
C26: Dự phòng giảm giá ĐTNH | D26: 0 | E26: -4.828872 | F26: -5.3902039 | G26: -4.1179572 | H26: -4.1316491 | I26: -0.3057319 | J26: 0 | K26: 0 | L26: 0 | M26: 0 | N26: 0 | O26: 0 | P26: 0
... C171: Chi phí khác bằng tiền | D171: 0 | E171: 0 | F171: 18.64346 | G171: 27.323059 | H171: 24.694254 | I171: 41.795572 | J171: 126.54904 | K171: 91.579131 | L171: 86.204506 | M171: 64.881516 | N171: 59.755824 | O171: 66.566996 | P171: 74.032369
C172: (Hoàn nhập)/Dự phòng phải thu khó đòi | J172: 18.695516 | K172: -4.8780667 | L172: -2.6443794 | M172: 1.1207052 | N172: 21.921386 | O172: 14.288447 | P172: 22.229182

Sheet Welfare & Dividends
B1: =1 -> 1 | K1: Số liệu 2021 chưa có vì chưa tổ chức ĐHCĐTN 2022, sử dụng số kế hoạch của ĐHCĐTN 2021 | Q1: 1 | R1: 2 | S1: 3 | T1: 4 | U1: 5 | V1: 6 | W1: 7 | X1: 8 | Y1: 9 | Z1: 10
N2: =IF(TODAY()<N3,"Proj","") | O2: =IF(TODAY()<O3,"Proj","") | P2: =IF(TODAY()<P3,"Proj","") | Q2: =IF(TODAY()<Q3,"Proj","") | R2: =IF(TODAY()<R3,"Proj","") | S2: =IF(TODAY()<S3,"Proj","") | T2: =IF(TODAY()<T3,"Proj","") -> Proj | U2: =IF(TODAY()<U3,"Proj","") -> Proj | ... Z2: =IF(TODAY()<Z3,"Proj","") -> Proj
B3: WELFARE & DIVIDENDS | D3: 40178 | E3: =DATE(YEAR(D3),MONTH(D3)+13,0) -> 40543 | F3: =DATE(YEAR(E3),MONTH(E3)+13,0) -> 40908 | G3: =DATE(YEAR(F3),MONTH(F3)+13,0) -> 41274 | H3: =DATE(YEAR(G3),MONTH(G3)+13,0) -> 41639 | I3: =DATE(YEAR(H3),MONTH(H3)+13,0) -> 42004 | J3: =DATE(YEAR(I3),MONTH(I3)+13,0) -> 42369 | K3: =DATE(YEAR(J3),MONTH(J3)+13,0) -> 42735 | L3: =DATE(YEAR(K3),MONTH(K3)+13,0) -> 43100 | ... Z3: =DATE(YEAR(Y3),MONTH(Y3)+13,0) -> 48213
A4: 1 | B4: LNST | J4: =Input!J94 -> 214.7655 | K4: =Input!K94 -> 141.49154 | L4: =Input!L94 -> 164.39079 | M4: =Input!M94 -> 163.0048 | N4: =Input!N94 -> 142.22742 | O4: =Input!O94 -> 157.85956 | P4: =Input!P94 -> 184.39928
A5: 2 | B5: Trích lập các quỹ | J5: =J6+J8 -> 51.4 | K5: =K6+K8 -> 32.8 | L5: =L6+L8 -> 37.779412 | M5: =M6+M8 -> 39.121156 | N5: =N6+N8 -> 31.290032 | O5: =O6+O8 -> 34.729104 | P5: =P6+P8 -> 44.255826
A6: 2.1 | B6: Quỹ thuộc công ty | J6: =J7 -> 21.4 | K6: =K7 -> 13.7 | L6: =L7 -> 15.741422 | M6: =M7 -> 16.300481 | N6: =N7 -> 14.222742 | O6: =O7 -> 15.785956 | P6: =P7 -> 18.439928
B7: + Quỹ ĐTPT | J7: 21.4 | K7: 13.7 | L7: =15741421589/10^9 -> 15.741422 | M7: =16300481470/10^9 -> 16.300481 | N7: =14222741724/10^9 -> 14.222742 | O7: =15785956482/10^9 -> 15.785956 | P7: =0.1*P4 -> 18.439928
A8: 2.2 | B8: Quỹ chi ra | I8: =J8 -> 30 | J8: =SUM(J9,J10,J11) -> 30 | K8: =SUM(K9,K10,K11) -> 19.1 | L8: =SUM(L9,L10,L11) -> 22.03799 | M8: =SUM(M9,M10,M11) -> 22.820674 | N8: =SUM(N9,N10,N11) -> 17.06729 | O8: =SUM(O9,O10,O11) -> 18.943148 | P8: =SUM(P9,P10,P11) -> 25.815899
B9: + Quỹ khen thưởng phúc lợi | J9: 21.4 | K9: 13.7 | L9: =15741421589/10^9 -> 15.741422 | M9: =16300481470/10^9 -> 16.300481 | N9: =14222741724/10^9 -> 14.222742 | O9: =15785956482/10^9 -> 15.785956 | P9: =0.1*P4 -> 18.439928
B10: + Quỹ khen thưởng BLĐ, HĐQT, BKS | J10: =4.3+4.3 -> 8.6 | K10: =2.7*2 -> 5.4 | L10: =3148284318*2/10^9 -> 6.2965686 | M10: =3260096296*2/10^9 -> 6.5201926 | N10: =1422274172/10^9*2 -> 2.8445483 | O10: =1578595648*2/10^9 -> 3.1571913 | P10: =0.02*2*P4 -> 7.375971
B11: + Quỹ khác | J11: 0 | K11: 0 | L11: 0 | M11: 0 | N11: 0 | O11: 0 | P11: 0
A12: 3 | B12: Chi cổ tức | I12: =J12 -> 62.8 | J12: =J13+J15 -> 62.8 | K12: =K13+K15 -> 78.6 | L12: =L13+L15 -> 78.5685 | M12: =M13+M15 -> 78.568372 | N12: =N13+N15 -> 78.5685 | O12: =O13+O15 -> 78.5685 | P12: =P13+P15 -> 0.466
B13: - Lần 1 | J13: 62.8 | K13: 78.6 | L13: =78568500000/10^9 -> 78.5685 | M13: =78568372500/10^9 -> 78.568372 | N13: =78568500000/10^9 -> 78.5685 | O13: =78568500000/10^9 -> 78.5685 | P13: 0.466
B14: % mệnh giá
B15: - Lần 2 | J15: 0 | K15: 0 | L15: 0 | M15: 0
B16: % mệnh giá
B17: LNST CPP | J17: =J4-J5-J12 -> 100.5655 | K17: =K4-K5-K12 -> 30.091538 | L17: =L4-L5-L12 -> 48.042882 | M17: =M4-M5-M12 -> 45.31527 | N17: =N4-N5-N12 -> 32.368885 | O17: =O4-O5-O12 -> 44.561961 | P17: =P4-P5-P12 -> 139.67745
B19: THE NUMBER OF COMMON SHARE (triệu CP)
A20: 1 | B20: SLCP phát hành đầu năm
A21: 2 | B21: Cổ tức bằng cổ phiếu
A22: 3 | B22: Cổ phiếu thưởng
A23: 4 | B23: Phát hành riêng lẻ/ công khai
B24: - đợt 1
B25: - đợt 2
A26: 5 | B26: ESOP
A27: 6 | B27: SLCP phát hành cuối năm | I27: =41918279 -> 41918279 | J27: =41918279 -> 41918279 | K27: =52379000 -> 52379000 | L27: =52379000 -> 52379000 | M27: =52379000 -> 52379000 | N27: =52379000 -> 52379000 | O27: =52379000 -> 52379000 | P27: =57612444 -> 57612444
A28: 7 | B28: CP quỹ | I28: 71 | J28: 71 | K28: 71 | L28: 85 | M28: 85 | N28: 85 | O28: 40085 | P28: 40085
A29: 8 | B29: SLCP lưu hành | I29: =I27-I28 -> 41918208 | J29: =J27-J28 -> 41918208 | K29: =K27-K28 -> 52378929 | L29: =L27-L28 -> 52378915 | M29: =M27-M28 -> 52378915 | N29: =N27-N28 -> 52378915 | O29: =O27-O28 -> 52338915 | P29: =P27-P28 -> 57572359

Sheet Phân loại dược phẩm
A3: Column1 | B3: Column2 | C3: Thuốc kháng sinh | D3: Column3 | E3: Column4 | F3: Column5 | G3: Column6 | H3: Xưởng | I3: ĐVT | J3: Ngày kê khai | K3: Giá kê khai | L3: Giá đấu thầu | M3: Chênh lệch giữa giá kê khai và giá đấu thầu | N3: Phần trăm chênh lệch | O3: Giá ước lượng | P3: Giá dùng làm cơ sở dự phóng
A4: STT | B4: Tên thuốc | C4: Hoạt chất | D4: Dạng thuốc | E4: Nhóm kháng sinh | F4: Beta Lactam | G4: Non Beta Lactam
A5: 1 | B5: BIDINAM | C5: Imipenem monohydrat | D5: Thuốc bột pha tiêm - Lỏng | E5: Carbapenems | F5: x | H5: (7) | I5: Lọ | J5: 44582 | K5: 103000 | L5: 51660 | M5: =K5-L5 -> 51340 | N5: =M5/K5 -> 0.4984466 | O5: =AVERAGE(K5,L5) -> 77330 | P5: =O5*1.2 -> 92796
A6: 2 | B6: Bicebid 200 H/20 | C6: Cefixim | D6: Viên nang cứng - Rắn | E6: Cephalosporins - 3rd | F6: x | H6: (3) | I6: Viên | J6: 42926 | K6: 4200 | L6: 1069 | M6: =K6-L6 -> 3131 | N6: =M6/K6 -> 0.74547619 | O6: =AVERAGE(K6,L6) -> 2634.5 | P6: =O6*1.2 -> 3161.4
A7: 3 | B7: Bicebid 100 | C7: Cefixim | D7: Viên nang cứng - Rắn | E7: Cephalosporins - 3rd | F7: x | H7: (3) | I7: Viên | J7: 42486 | K7: 2520 | L7: 750 | M7: =K7-L7 -> 1770 | N7: =M7/K7 -> 0.70238095 | O7: =AVERAGE(K7,L7) -> 1635 | P7: =O7*1.2 -> 1962
A8: 4 | B8: Bifumax 750 H/10 | C8: Cefuroxim | D8: Thuốc bột pha tiêm - Lỏng | E8: Cephalosporins - 2nd | F8: x | H8: (7) | I8: Lọ | J8: 42604 | K8: 28400 | L8: 16989 | M8: =K8-L8 -> 11411 | N8: =M8/K8 -> 0.40179577 | O8: =AVERAGE(K8,L8) -> 22694.5 | P8: =O8*1.2 -> 27233.4
A9: 5 | B9: Colirex 1MIU | C9: Colistimethat natri | D9: Thuốc bột pha tiêm - Lỏng | E9: polypeptid - peptid | G9: x | H9: (7) | I9: Lọ | J9: 42237 | K9: 375000 | L9: 359100 | M9: =K9-L9 -> 15900 | N9: =M9/K9 -> 0.0424 | O9: =AVERAGE(K9,L9) -> 367050 | P9: =O9*1.2 -> 440460
A10: 6 | B10: VANCOMYCIN 500 mg | C10: Vancomycin | D10: Bột đông khô pha tiêm - Lỏng | E10: glycopeptid - peptid | G10: x | H10: (1) | I10: Lọ | J10: 43425 | K10: 52000 | L10: 19887 | M10: =K10-L10 -> 32113 | N10: =M10/K10 -> 0.61755769 | O10: =AVERAGE(K10,L10) -> 35943.5 | P10: =O10*1.2 -> 43132.2
A11: 7 | B11: BIFOTIN 1G | C11: Cefoxitin | D11: Thuốc bột pha tiêm - Lỏng | E11: Cephalosporins - 2nd | F11: x | H11: (7) | I11: Lọ | J11: 43209 | K11: 47250 | L11: 16695 | M11: =K11-L11 -> 30555 | N11: =M11/K11 -> 0.64666667 | O11: =AVERAGE(K11,L11) -> 31972.5 | P11: =O11*1.2 -> 38367
A12: 8 | B12: Bicefzidim 1g | C12: Ceftazidim | D12: Thuốc bột pha tiêm - Lỏng | E12: Cephalosporins - 3rd | F12: x | H12: (7) | I12: Lọ | J12: 43013 | K12: 39900 | L12: 9990 | M12: =K12-L12 -> 29910 | N12: =M12/K12 -> 0.74962406 | O12: =AVERAGE(K12,L12) -> 24945 | P12: =O12*1.2 -> 29934
A13: 9 | B13: Augbidil 500mg/62.5mg | C13: Acid clavulanic + Amoxicillin | D13: Thuốc bột pha hỗn dịch uống - Lỏng | E13: Penicillins + Beta - lactamase Inhibitors - Aminopenicillins - Phổ rộng | F13: x | H13: (6) | I13: Gói | J13: 42712 | K13: 8400 | L13: 1840 | M13: =K13-L13 -> 6560 | N13: =M13/K13 -> 0.78095238 | O13: =AVERAGE(K13,L13) -> 5120 | P13: =O13*1.2 -> 6144
A14: 10 | B14: Cefotaxone 1 g | C14: Cefotaxim | D14: Thuốc bột pha tiêm - Lỏng | E14: Cephalosporins - 3rd | F14: x | H14: (7) | I14: Lọ | J14: 42438 | K14: 15000 | L14: 5769 | M14: =K14-L14 -> 9231 | N14: =M14/K14 -> 0.6154 | O14: =AVERAGE(K14,L14) -> 10384.5 | P14: =O14*1.2 -> 12461.4
A15: 11 | B15: Bironem 1g | C15: Meropenem | D15: Thuốc bột pha tiêm - Lỏng | E15: Carbapenems | F15: x | H15: (7) | I15: Lọ | J15: 42269 | K15: 161700 | L15: 57750 | M15: =K15-L15 -> 103950 | N15: =M15/K15 -> 0.64285714 | O15: =AVERAGE(K15,L15) -> 109725 | P15: =O15*1.2 -> 131670
A16: 12 | B16: Bironem 500 mg | C16: Meropenem | D16: Thuốc bột pha tiêm - Lỏng | E16: Carbapenems | F16: x | H16: (7) | I16: Lọ | J16: 42269 | K16: 96600 | L16: 36981 | M16: =K16-L16 -> 59619 | N16: =M16/K16 -> 0.61717391 | O16: =AVERAGE(K16,L16) -> 66790.5 | P16: =O16*1.2 -> 80148.6
A17: 13 | B17: Bifumax 750 | C17: Cefuroxim | D17: Thuốc bột pha tiêm - Lỏng | E17: Cephalosporins - 2nd | F17: x | H17: (7) | I17: Lọ | J17: 42604 | K17: 28400 | L17: 16989 | M17: =K17-L17 -> 11411 | N17: =M17/K17 -> 0.40179577 | O17: =AVERAGE(K17,L17) -> 22694.5 | P17: =O17*1.2 -> 27233.4
A18: 14 | B18: Tazopelin 4,5g | C18: Piperacillin natri &Tazobactam natri | D18: Thuốc bột pha tiêm - Lỏng | E18: Penicillins + Beta - lactamase Inhibitors - Ureidopenicilin - Phổ rộng | F18: x | H18: (7) | I18: Lọ | J18: 42247 | K18: 94500 | L18: 65982 | M18: =K18-L18 -> 28518 | N18: =M18/K18 -> 0.30177778 | O18: =AVERAGE(K18,L18) -> 80241 | P18: =O18*1.2 -> 96289.2
A19: 15 | B19: Bidiclor® 125 | C19: Cefaclor | D19: Thuốc bột pha hỗn dịch uống - Lỏng | E19: Cephalosporins - 2nd | F19: x | H19: (6) | I19: Gói | J19: 43013 | K19: 3675 | L19: 1239 | M19: =K19-L19 -> 2436 | N19: =M19/K19 -> 0.66285714 | O19: =AVERAGE(K19,L19) -> 2457 | P19: =O19*1.2 -> 2948.4
A20: 16 | B20: Clyodas® 150 | C20: Clindamycin hydroclorid | D20: Viên nang cứng - Rắn | E20: lincosamid | G20: x | H20: (2) | I20: viên | J20: 43955 | K20: 1995 | L20: 735 | M20: =K20-L20 -> 1260 | N20: =M20/K20 -> 0.63157895 | O20: =AVERAGE(K20,L20) -> 1365 | P20: =O20*1.2 -> 1638
A21: 17 | B21: Bicebid 100 | C21: Cefixim | D21: Thuốc bột pha hỗn dịch uống - Lỏng | E21: Cephalosporins - 3rd | F21: x | H21: (6) | I21: Gói | J21: 43013 | K21: 3990 | L21: 1386 | M21: =K21-L21 -> 2604 | N21: =M21/K21 -> 0.65263158 | O21: =AVERAGE(K21,L21) -> 2688 | P21: =O21*1.2 -> 3225.6
A22: 18 | B22: AUGBIDIL® 250 mg/31,25 mg | C22: Acid clavulanic + Amoxicillin | D22: Thuốc bột pha hỗn dịch uống - Lỏng | E22: Penicillins + Beta - lactamase Inhibitors - Aminopenicillins - Phổ rộng | F22: x | H22: (6) | I22: Gói | J22: 42783 | K22: 5500 | L22: 1189 | M22: =K22-L22 -> 4311 | N22: =M22/K22 -> 0.78381818 | O22: =AVERAGE(K22,L22) -> 3344.5 | P22: =O22*1.2 -> 4013.4
A23: 19 | B23: CEFUBI- 100 DT | C23: Cefpodoxim | D23: Viên nén phân tán - Rắn | E23: Cephalosporins - 3rd | F23: x | H23: (3) | I23: Viên | J23: 42604 | K23: 7455 | L23: 4893 | M23: =K23-L23 -> 2562 | N23: =M23/K23 -> 0.34366197 | O23: =AVERAGE(K23,L23) -> 6174 | P23: =O23*1.2 -> 7408.8
A24: 20 | B24: Sunewtam 2g | C24: Cefoperazon natri + Sulbactam natri | D24: Thuốc bột pha tiêm - Lỏng | E24: Cephalosporins + Beta - lactamase Inhibitors - 3rd | F24: x | H24: (7) | I24: Lọ | J24: 42247 | K24: 44940 | L24: 15183 | M24: =K24-L24 -> 29757 | N24: =M24/K24 -> 0.66214953 | O24: =AVERAGE(K24,L24) -> 30061.5 | P24: =O24*1.2 -> 36073.8
A25: 21 | B25: Bifucil | C25: Levofloxacin | D25: Viên nén bao phim - Rắn | E25: Quinolon | G25: x | H25: (2) | I25: Viên | J25: 42642 | K25: 5250 | L25: 756 | M25: =K25-L25 -> 4494 | N25: =M25/K25 -> 0.856 | O25: =AVERAGE(K25,L25) -> 3003 | P25: =O25*1.2 -> 3603.6
A26: 22 | B26: Bifumax 1,5g | C26: Cefuroxim | D26: Thuốc bột pha tiêm - Lỏng | E26: Cephalosporins - 2nd | F26: x | H26: (7) | I26: Lọ | J26: 41873 | K26: 41000 | L26: 25998 | M26: =K26-L26 -> 15002 | N26: =M26/K26 -> 0.36590244 | O26: =AVERAGE(K26,L26) -> 33499 | P26: =O26*1.2 -> 40198.8
A27: 23 | B27: Bicefzidim 2 g | C27: Ceftazidim pentahydrat | D27: Thuốc bột pha tiêm - Lỏng | E27: Cephalosporins - 3rd | F27: x | H27: (7) | I27: Lọ | J27: 44490 | K27: 63000 | L27: 17997 | M27: =K27-L27 -> 45003 | N27: =M27/K27 -> 0.71433333 | O27: =AVERAGE(K27,L27) -> 40498.5 | P27: =O27*1.2 -> 48598.2
A28: 24 | B28: Biceflexin Powder | C28: Cefalexin | D28: Thuốc bột pha hỗn dịch uống - Lỏng | E28: Cephalosporins - 1st | F28: x | H28: (6) | I28: Gói | J28: 41386 | K28: 1890 | L28: 711 | M28: =K28-L28 -> 1179 | N28: =M28/K28 -> 0.62380952 | O28: =AVERAGE(K28,L28) -> 1300.5 | P28: =O28*1.2 -> 1560.6
A29: 25 | B29: Bicefdox 500 | C29: Cefadroxil | D29: Viên nang cứng - Rắn | E29: Cephalosporins - 1st | F29: x | H29: (3) | I29: viên | J29: 43914 | K29: 2940 | L29: 1743 | M29: =K29-L29 -> 1197 | N29: =M29/K29 -> 0.40714286 | O29: =AVERAGE(K29,L29) -> 2341.5 | P29: =O29*1.2 -> 2809.8
A30: 26 | B30: Clyodas 300 | C30: Clindamycin hydroclorid | D30: Viên nang cứng - Rắn | E30: lincosamid | G30: x | H30: (2) | I30: viên | J30: 43955 | K30: 3255 | L30: 1848 | M30: =K30-L30 -> 1407 | N30: =M30/K30 -> 0.43225806 | O30: =AVERAGE(K30,L30) -> 2551.5 | P30: =O30*1.2 -> 3061.8
A31: 27 | B31: AUGBIDIL 1g | C31: Amoxicillin trihydrat + Potassium clavulanat | D31: Viên nén bao phim - Rắn | E31: Penicillins + Beta - lactamase Inhibitors - Aminopenicillins - Phổ rộng | F31: x | H31: (3) | I31: Viên | J31: 42926 | K31: 9450 | L31: 2370 | M31: =K31-L31 -> 7080 | N31: =M31/K31 -> 0.74920635 | O31: =AVERAGE(K31,L31) -> 5910 | P31: =O31*1.2 -> 7092
A32: 28 | B32: Micbibleucin | C32: Cloramphenicol + Xanh methylen | D32: Viên nén bao đường - Rắn | E32: phenicol | G32: x | H32: (2) | I32: viên | J32: 43955 | K32: 1155 | L32: 520 | M32: =K32-L32 -> 635 | N32: =M32/K32 -> 0.54978355 | O32: =AVERAGE(K32,L32) -> 837.5 | P32: =O32*1.2 -> 1005
A33: 29 | B33: BIDICLOR 500 | C33: Cefaclor | D33: Viên nang cứng - Rắn | E33: Cephalosporins - 2nd | F33: x | H33: (3) | I33: Viên | J33: 42247 | K33: 8400 | L33: 4977 | M33: =K33-L33 -> 3423 | N33: =M33/K33 -> 0.4075 | O33: =AVERAGE(K33,L33) -> 6688.5 | P33: =O33*1.2 -> 8026.2
A34: 30 | B34: BIFUMAX 125 | C34: Cefuroxim axetil | D34: Thuốc cốm - Rắn | E34: Cephalosporins - 2nd | F34: x | H34: (6) | I34: Gói | J34: 41408 | K34: 6825 | L34: 2268 | M34: =K34-L34 -> 4557 | N34: =M34/K34 -> 0.66769231 | O34: =AVERAGE(K34,L34) -> 4546.5 | P34: =O34*1.2 -> 5455.8
A35: 31 | B35: SPOBAVAS 3 MIU | C35: Spiramycin | D35: Viên nén bao phim - Rắn | E35: macrolid | G35: x | H35: (2) | I35: viên | J35: 44551 | K35: 7140 | L35: 3192 | M35: =K35-L35 -> 3948 | N35: =M35/K35 -> 0.55294118 | O35: =AVERAGE(K35,L35) -> 5166 | P35: =O35*1.2 -> 6199.2
A36: 32 | B36: SPOBAVAS 1,5 MIU | C36: Spiramycin | D36: Viên nén bao phim - Rắn | E36: macrolid | G36: x | H36: (2) | I36: viên | J36: 44551 | K36: 3885 | L36: 3885 | M36: =K36-L36 -> 0 | N36: =M36/K36 -> 0 | O36: =AVERAGE(K36,L36) -> 3885 | P36: =O36*1.2 -> 4662
A37: 33 | B37: Metronidazol 250mg | C37: Metronidazol | D37: Viên nén bao phim - Rắn | E37: 5-nitro-imidazol | G37: x | H37: (2) | I37: Viên | J37: 43013 | K37: 357 | L37: 168 | M37: =K37-L37 -> 189 | N37: =M37/K37 -> 0.52941176 | O37: =AVERAGE(K37,L37) -> 262.5 | P37: =O37*1.2 -> 315
A38: 34 | B38: Biceflexin 500 | C38: Cefalexin monohydrat | D38: Viên nang cứng - Rắn | E38: Cephalosporins - 1st | F38: x | H38: (3) | I38: Viên | J38: 42486 | K38: 1680 | L38: 714 | M38: =K38-L38 -> 966 | N38: =M38/K38 -> 0.575 | O38: =AVERAGE(K38,L38) -> 1197 | P38: =O38*1.2 -> 1436.4
A39: 35 | B39: Bidimoxy 500 | C39: Amoxicilin trihydrat | D39: Viên nang cứng - Rắn | E39: Penicillins - Aminopenicillin - Phổ rộng | F39: x | H39: (3) | I39: Viên | J39: 42388 | K39: 1365 | L39: 680 | M39: =K39-L39 -> 685 | N39: =M39/K39 -> 0.5018315 | O39: =AVERAGE(K39,L39) -> 1022.5 | P39: =O39*1.2 -> 1227
A40: 36 | B40: Bifotirin 1g | C40: Cefotiam hydroclorid | D40: Thuốc bột pha tiêm - Lỏng | E40: Cephalosporins - 2nd | F40: x | H40: (7) | I40: Lọ | J40: 41653 | K40: 84000 | L40: 27489 | M40: =K40-L40 -> 56511 | N40: =M40/K40 -> 0.67275 | O40: =AVERAGE(K40,L40) -> 55744.5 | P40: =O40*1.2 -> 66893.4
A41: 37 | B41: AUGBIDIL 625 | C41: Amoxicillin trihydrat + Potassium clavulanat | D41: Viên nén bao phim - Rắn | E41: Penicillins + Beta - lactamase Inhibitors - Aminopenicillins - Phổ rộng | F41: x | H41: (3) | I41: Viên | J41: 43013 | K41: 6825 | L41: 1848 | M41: =K41-L41 -> 4977 | N41: =M41/K41 -> 0.72923077 | O41: =AVERAGE(K41,L41) -> 4336.5 | P41: =O41*1.2 -> 5203.8
A42: 38 | B42: Bipisyn | C42: Ampicilin natri + Sulbactam natri | D42: Thuốc bột pha tiêm - Lỏng | E42: Penicillins + Beta - lactamase Inhibitors - Aminopenicillins - Phổ rộng | F42: x | H42: (7) | I42: Lọ | J42: 42395 | K42: 42000 | L42: 21987 | M42: =K42-L42 -> 20013 | N42: =M42/K42 -> 0.4765 | O42: =AVERAGE(K42,L42) -> 31993.5 | P42: =O42*1.2 -> 38392.2
A43: 39 | B43: Oxacillin 1g | C43: Oxacillin natri | D43: Thuốc bột pha tiêm - Lỏng | E43: Penicillins - Beta lactamase Resistant | F43: x | H43: (7) | I43: Lọ | J43: 43301 | K43: 32000 | L43: 29904 | M43: =K43-L43 -> 2096 | N43: =M43/K43 -> 0.0655 | O43: =AVERAGE(K43,L43) -> 30952 | P43: =O43*1.2 -> 37142.4
A44: 40 | B44: CLYODAS® | C44: Clindamycin | D44: Bột đông khô pha tiêm - Lỏng | E44: lincosamid | G44: x | H44: (1) | I44: Ống | J44: 44230 | K44: 41600 | L44: 20895 | M44: =K44-L44 -> 20705 | N44: =M44/K44 -> 0.49771635 | O44: =AVERAGE(K44,L44) -> 31247.5 | P44: =O44*1.2 -> 37497
A45: 41 | B45: SUNEWTAM 1g | C45: Cefoperazon + Sulbactam | D45: Thuốc bột pha tiêm - Lỏng | E45: Cephalosporins+ Beta - lactamase Inhibitors - 3rd | F45: x | H45: (7) | I45: Lọ | J45: 42926 | K45: 31500 | L45: 9786 | M45: =K45-L45 -> 21714 | N45: =M45/K45 -> 0.68933333 | O45: =AVERAGE(K45,L45) -> 20643 | P45: =O45*1.2 -> 24771.6
A46: 42 | B46: BICEBID 200 | C46: Cefixim | D46: Viên nang cứng - Rắn | E46: Cephalosporins - 3rd | F46: x | H46: (3) | I46: Viên | J46: 42926 | K46: 4200 | L46: 1069 | M46: =K46-L46 -> 3131 | N46: =M46/K46 -> 0.74547619 | O46: =AVERAGE(K46,L46) -> 2634.5 | P46: =O46*1.2 -> 3161.4
A47: 43 | B47: BICEBID 100 | C47: Cefixim | D47: Viên nang cứng - Rắn | E47: Cephalosporins - 3rd | F47: x | H47: (3) | I47: Viên | J47: 42486 | K47: 2520 | L47: 750 | M47: =K47-L47 -> 1770 | N47: =M47/K47 -> 0.70238095 | O47: =AVERAGE(K47,L47) -> 1635 | P47: =O47*1.2 -> 1962
A48: 44 | B48: Zolgyl | C48: Spiramycin + Metronidazol | D48: Viên nén bao phim - Rắn | E48: macrolid 16 C + 5-nitro-imidazol | G48: x | H48: (2) | I48: Viên | J48: 44551 | K48: 2205 | L48: 859 | M48: =K48-L48 -> 1346 | N48: =M48/K48 -> 0.61043084 | O48: =AVERAGE(K48,L48) -> 1532 | P48: =O48*1.2 -> 1838.4
A49: 45 | B49: TINIDAZOL 500mg | C49: Tinidazol | D49: Viên nén bao phim - Rắn | E49: 5-nitro-imidazol | G49: x | H49: (2) | I49: Viên | J49: 42467 | K49: 1050 | L49: 462 | M49: =K49-L49 -> 588 | N49: =M49/K49 -> 0.56 | O49: =AVERAGE(K49,L49) -> 756 | P49: =O49*1.2 -> 907.2
A50: 46 | B50: CLARITAB 500 | C50: Clarithromycin | D50: Viên nén bao phim - Rắn | E50: macrolid 14 C | G50: x | H50: (2) | I50: viên | J50: 43914 | K50: 8400 | L50: 2898 | M50: =K50-L50 -> 5502 | N50: =M50/K50 -> 0.655 | O50: =AVERAGE(K50,L50) -> 5649 | P50: =O50*1.2 -> 6778.8
A51: 47 | B51: CIPROFLOXACIN 500 | C51: Ciprofloxacin HCl | D51: Viên nén bao phim - Rắn | E51: fluoroquinolon - 2nd | G51: x | H51: (2) | I51: viên | J51: 43914 | K51: 1785 | L51: 525 | M51: =K51-L51 -> 1260 | N51: =M51/K51 -> 0.70588235 | O51: =AVERAGE(K51,L51) -> 1155 | P51: =O51*1.2 -> 1386
A52: 48 | B52: CEPHALEXIN 500mg | C52: Cephalexin | D52: Viên nang cứng - Rắn | E52: Cephalosporins - 1st | F52: x | H52: (3) | I52: viên | J52: 43955 | K52: 2499 | L52: 672 | M52: =K52-L52 -> 1827 | N52: =M52/K52 -> 0.73109244 | O52: =AVERAGE(K52,L52) -> 1585.5 | P52: =O52*1.2 -> 1902.6
A53: 49 | B53: Bigentil 100 | C53: Netilmicin sulfat | D53: Dung dịch tiêm - Lỏng | E53: aminoglycoside | G53: x | H53: (7) | I53: Lọ | J53: 42388 | K53: 36800 | L53: 17787 | M53: =K53-L53 -> 19013 | N53: =M53/K53 -> 0.51665761 | O53: =AVERAGE(K53,L53) -> 27293.5 | P53: =O53*1.2 -> 32752.2
A54: 50 | B54: Bifradin | C54: Cefradin | D54: Viên nang cứng - Rắn | E54: Cephalosporins - 1st | F54: x | H54: (3) | I54: viên | J54: 43955 | K54: 4998 | L54: 1239 | M54: =K54-L54 -> 3759 | N54: =M54/K54 -> 0.75210084 | O54: =AVERAGE(K54,L54) -> 3118.5 | P54: =O54*1.2 -> 3742.2
A55: 51 | B55: Bidiseptol | C55: Sulfamethoxazol + Trimethoprim | D55: Viên nén - Rắn | E55: Co-trimoxazol | G55: x | H55: (2) | I55: viên | J55: 43955 | K55: 693 | L55: 294 | M55: =K55-L55 -> 399 | N55: =M55/K55 -> 0.57575758 | O55: =AVERAGE(K55,L55) -> 493.5 | P55: =O55*1.2 -> 592.2
A56: 52 | B56: BIDICOTRIM F | C56: Sulfamethoxazol + Trimethoprim | D56: Viên nén - Rắn | E56: Co-trimoxazol | G56: x | H56: (2) | I56: viên | J56: 43013 | K56: 945 | L56: 462 | M56: =K56-L56 -> 483 | N56: =M56/K56 -> 0.51111111 | O56: =AVERAGE(K56,L56) -> 703.5 | P56: =O56*1.2 -> 844.2
A57: 53 | B57: AMOXICILIN 500mg | C57: Amoxicilin trihydrat | D57: Viên nang cứng - Rắn | E57: Penicillins - Aminopenicillin - Phổ rộng | F57: x | H57: (3) | I57: viên | J57: 41579 | K57: 1260 | L57: 445 | M57: =K57-L57 -> 815 | N57: =M57/K57 -> 0.6468254 | O57: =AVERAGE(K57,L57) -> 852.5 | P57: =O57*1.2 -> 1023
A58: 54 | B58: Bifumax 500 | C58: Cefuroxim axetil | D58: Viên nén bao phim - Rắn | E58: Cephalosporins - 2nd | F58: x | H58: (3) | I58: viên | J58: 44271 | K58: 12650 | L58: 12650 | M58: =K58-L58 -> 0 | N58: =M58/K58 -> 0 | O58: =AVERAGE(K58,L58) -> 12650 | P58: =O58*1.2 -> 15180
A59: 55 | B59: Bifumax 250 | C59: Cefuroxim axetil | D59: Viên nén bao phim - Rắn | E59: Cephalosporins - 2nd | F59: x | H59: (3) | I59: viên | J59: 44271 | K59: 6825 | L59: 6825 | M59: =K59-L59 -> 0 | N59: =M59/K59 -> 0 | O59: =AVERAGE(K59,L59) -> 6825 | P59: =O59*1.2 -> 8190
A60: 56 | B60: Ceftrione 1g | C60: Ceftriaxon | D60: Thuốc bột pha tiêm - Lỏng | E60: Cephalosporins - 3rd | F60: x | H60: (7) | I60: Lọ | J60: 43013 | K60: 16900 | L60: 10235 | M60: =K60-L60 -> 6665 | N60: =M60/K60 -> 0.3943787 | O60: =AVERAGE(K60,L60) -> 13567.5 | P60: =O60*1.2 -> 16281
A61: 57 | B61: Cefotaxone 1g | C61: Cefotaxim natri | D61: Thuốc bột pha tiêm - Lỏng | E61: Cephalosporins - 3rd | F61: x | H61: (7) | I61: Lọ | J61: 42438 | K61: 15000 | L61: 5769 | M61: =K61-L61 -> 9231 | N61: =M61/K61 -> 0.6154 | O61: =AVERAGE(K61,L61) -> 10384.5 | P61: =O61*1.2 -> 12461.4
A62: 58 | B62: AUGBIDIL | C62: Amoxicilin natri + Kali Clavulanat | D62: Thuốc bột pha tiêm - Lỏng | E62: Penicillins + Beta - lactamase Inhibitors - Aminopenicillins - Phổ rộng | F62: x | H62: (7) | I62: Lọ | J62: 41653 | K62: 35385 | L62: 21693 | M62: =K62-L62 -> 13692 | N62: =M62/K62 -> 0.38694362 | O62: =AVERAGE(K62,L62) -> 28539 | P62: =O62*1.2 -> 34246.8
A63: 59 | B63: Amoxicilin 250mg | C63: Amoxicilin trihydrat | D63: Thuốc bột pha hỗn dịch uống - Lỏng | E63: Penicillins - Aminopenicillin - Phổ rộng | F63: x | H63: (6) | I63: Gói | J63: 41386 | K63: 1680 | L63: 525 | M63: =K63-L63 -> 1155 | N63: =M63/K63 -> 0.6875 | O63: =AVERAGE(K63,L63) -> 1102.5 | P63: =O63*1.2 -> 1323
C65: Thuốc chống nắm | H65: Xưởng | I65: ĐVT | J65: Ngày kê khai | K65: Giá kê khai | L65: Giá đấu thầu | M65: Chênh lệch giữa giá kê khai và giá đấu thầu | N65: Phần trăm chênh lệch | O65: Giá ước lượng | P65: Giá dùng làm cơ sở dự phóng
A66: STT | B66: Tên thuốc | C66: Hoạt chất | D66: Dạng thuốc | F66: Beta Lactam | G66: Non Beta Lactam
A67: 1 | B67: Vaginax | C67: Metronidazol + Miconazol | D67: Viên đạn đặt âm đạo - Rắn | G67: x | H67: (4) | I67: viên | J67: 44271 | K67: 9975 | L67: 7833 | M67: =K67-L67 -> 2142 | N67: =M67/K67 -> 0.21473684 | O67: =AVERAGE(K67,L67) -> 8904 | P67: =O67*1.2 -> 10684.8
A68: 2 | B68: Menystin | C68: Metronidazol + Nystatin + Dexamethason acetat | D68: Viên nén đặt âm đạo - Rắn | G68: x | H68: (2) | I68: viên | J68: 42247 | K68: 1575 | L68: 1050 | M68: =K68-L68 -> 525 | N68: =M68/K68 -> 0.33333333 | O68: =AVERAGE(K68,L68) -> 1312.5 | P68: =O68*1.2 -> 1575
C70: Thuốc giảm đau - hạ sốt - chống viêm | H70: Xưởng | I70: ĐVT | J70: Ngày kê khai | K70: Giá kê khai | L70: Giá đấu thầu | M70: Chênh lệch giữa giá kê khai và giá đấu thầu | N70: Phần trăm chênh lệch | O70: Giá ước lượng | P70: Giá dùng làm cơ sở dự phóng
A71: STT | B71: Tên thuốc | C71: Hoạt chất | D71: Dạng thuốc | F71: Beta Lactam | G71: Non Beta Lactam
A72: 1 | B72: Biragan 500 | C72: Paracetamol | D72: Viên nén bao phim - Rắn | G72: x | H72: (2) | I72: viên | J72: 43955 | K72: 798 | L72: 798 | M72: =K72-L72 -> 0 | N72: =M72/K72 -> 0 | O72: =AVERAGE(K72,L72) -> 798 | P72: =O72*1.2 -> 957.6
A73: 2 | B73: Bidivon | C73: Ibuprofen | D73: Viên nén bao phim - Rắn | G73: x | H73: (2) | I73: viên | J73: 43955 | K73: 903 | L73: 315 | M73: =K73-L73 -> 588 | N73: =M73/K73 -> 0.65116279 | O73: =AVERAGE(K73,L73) -> 609 | P73: =O73*1.2 -> 730.8
A74: 3 | B74: Tenoxicam 20mg | C74: Tenoxicam | D74: Bột đông khô pha tiêm - Lỏng | G74: x | H74: (1) | I74: Lọ | J74: 43545 | K74: 24150 | L74: 24150 | M74: =K74-L74 -> 0 | N74: =M74/K74 -> 0 | O74: =AVERAGE(K74,L74) -> 24150 | P74: =O74*1.2 -> 28980
A75: 4 | B75: Biragan Kids 250 | C75: Paracetamol | D75: Thuốc cốm sủi bọt - Lỏng | G75: x | H75: (6) | I75: Gói | J75: 43175 | K75: 2500 | L75: 735 | M75: =K75-L75 -> 1765 | N75: =M75/K75 -> 0.706 | O75: =AVERAGE(K75,L75) -> 1617.5 | P75: =O75*1.2 -> 1941
A76: 5 | B76: PARACETAMOL 500mg | C76: Paracetamol | D76: Viên nén - Rắn | G76: x | H76: (2) | I76: viên | J76: 44551 | K76: 378 | L76: 114 | M76: =K76-L76 -> 264 | N76: =M76/K76 -> 0.6984127 | O76: =AVERAGE(K76,L76) -> 246 | P76: =O76*1.2 -> 295.2
A77: 6 | B77: α - Chymotrypsin | C77: Chymotrypsin | D77: Viên nén - Rắn | G77: x | H77: (2) | I77: viên | J77: 42395 | K77: 1050 | L77: 1050 | M77: =K77-L77 -> 0 | N77: =M77/K77 -> 0 | O77: =AVERAGE(K77,L77) -> 1050 | P77: =O77*1.2 -> 1260
A78: 7 | B78: Biragan 150 | C78: Paracetamol | D78: Thuốc đạn - Rắn | G78: x | H78: (4) | I78: viên | J78: 44302 | K78: 2730 | L78: 1638 | M78: =K78-L78 -> 1092 | N78: =M78/K78 -> 0.4 | O78: =AVERAGE(K78,L78) -> 2184 | P78: =O78*1.2 -> 2620.8
A79: 8 | B79: α - Chymotrypsin 5000 | C79: Chymotrypsin | D79: Bột đông khô pha tiêm - Lỏng | G79: x | H79: (1) | I79: Lọ | J79: 43013 | K79: 8618 | L79: 4095 | M79: =K79-L79 -> 4523 | N79: =M79/K79 -> 0.52483175 | O79: =AVERAGE(K79,L79) -> 6356.5 | P79: =O79*1.2 -> 7627.8
A80: 9 | B80: PYROLOX | C80: Piroxicam | D80: Bột đông khô pha tiêm - Lỏng | G80: x | H80: (1) | I80: Lọ | J80: 41793 | K80: 11000 | L80: 8190 | M80: =K80-L80 -> 2810 | N80: =M80/K80 -> 0.25545455 | O80: =AVERAGE(K80,L80) -> 9595 | P80: =O80*1.2 -> 11514
A81: 10 | B81: BIRAGAN 500 Viên Sủi | C81: Paracetamol | D81: Viên nén sủi bọt - Rắn | G81: x | H81: (2) | I81: viên | J81: 43955 | K81: 2415 | L81: 2415 | M81: =K81-L81 -> 0 | N81: =M81/K81 -> 0 | O81: =AVERAGE(K81,L81) -> 2415 | P81: =O81*1.2 -> 2898
A82: 11 | B82: Bixicam | C82: Meloxicam | D82: Viên nén - Rắn | G82: x | H82: (2) | I82: viên | J82: 42388 | K82: 798 | L82: 798 | M82: =K82-L82 -> 0 | N82: =M82/K82 -> 0 | O82: =AVERAGE(K82,L82) -> 798 | P82: =O82*1.2 -> 957.6
A83: 12 | B83: BIRAGAN 500 (vỉ nhôm) | C83: Paracetamol | D83: Viên nén bao phim - Rắn | G83: x | H83: (2) | I83: viên | J83: 43955 | K83: 798 | L83: 798 | M83: =K83-L83 -> 0 | N83: =M83/K83 -> 0 | O83: =AVERAGE(K83,L83) -> 798 | P83: =O83*1.2 -> 957.6
... A89: 18 | B89: BIRAGAN 300 | C89: Paracetamol | D89: Thuốc đạn - Rắn | G89: x | H89: (4) | I89: viên | J89: 44302 | K89: 2940 | L89: 1680 | M89: =K89-L89 -> 1260 | N89: =M89/K89 -> 0.42857143 | O89: =AVERAGE(K89,L89) -> 2310 | P89: =O89*1.2 -> 2772
C91: Thuốc hormon - nội tiết tố | H91: Xưởng | I91: ĐVT | J91: Ngày kê khai | K91: Giá kê khai | L91: Giá đấu thầu | M91: Chênh lệch giữa giá kê khai và giá đấu thầu | N91: Phần trăm chênh lệch | O91: Giá ước lượng | P91: Giá dùng làm cơ sở dự phóng
A92: STT | B92: Tên thuốc | C92: Hoạt chất | D92: Dạng thuốc | F92: Beta Lactam | G92: Non Beta Lactam
A93: 1 | B93: Soli-Medon 125 | C93: Methylprednisolon natri succinat | D93: Bột đông khô pha tiêm - Lỏng | G93: x | H93: (1) | I93: Lọ | J93: 41612 | K93: 72000 | L93: 72000 | M93: =K93-L93 -> 0 | N93: =M93/K93 -> 0 | O93: =AVERAGE(K93,L93) -> 72000 | P93: =O93*1.2 -> 86400
A94: 2 | B94: SOLI - MEDON 4 | C94: Methylprednisolon | D94: Viên nén - Rắn | G94: x | H94: (2) | I94: viên | J94: 42395 | K94: 1050 | L94: 231 | M94: =K94-L94 -> 819 | N94: =M94/K94 -> 0.78 | O94: =AVERAGE(K94,L94) -> 640.5 | P94: =O94*1.2 -> 768.6
A95: 3 | B95: SOLI - MEDON 16 | C95: Methylprednisolon | D95: Viên nén - Rắn | G95: x | H95: (2) | I95: viên | J95: 42395 | K95: 2940 | L95: 1092 | M95: =K95-L95 -> 1848 | N95: =M95/K95 -> 0.62857143 | O95: =AVERAGE(K95,L95) -> 2016 | P95: =O95*1.2 -> 2419.2
A96: 4 | B96: SOLI - MEDON 40 | C96: Methylprednisolon natri succinat | D96: Bột đông khô pha tiêm - Lỏng | G96: x | H96: (1) | I96: Lọ | K96: 31500 | L96: 31500 | M96: =K96-L96 -> 0 | N96: =M96/K96 -> 0 | O96: =AVERAGE(K96,L96) -> 31500 | P96: =O96*1.2 -> 37800
A97: 5 | B97: HYDROCORTISON | C97: Hydrocortison | D97: Bột đông khô pha tiêm - Lỏng | G97: x | H97: (1) | I97: Lọ | J97: 41612 | K97: 18900 | L97: 7602 | M97: =K97-L97 -> 11298 | N97: =M97/K97 -> 0.59777778 | O97: =AVERAGE(K97,L97) -> 13251 | P97: =O97*1.2 -> 15901.2
C99: Thuốc đường tiêu hóa - gan mật | H99: Xưởng | I99: ĐVT | J99: Ngày kê khai | K99: Giá kê khai | L99: Giá đấu thầu | M99: Chênh lệch giữa giá kê khai và giá đấu thầu | N99: Phần trăm chênh lệch | O99: Giá ước lượng | P99: Giá dùng làm cơ sở dự phóng
A100: STT | B100: Tên thuốc | C100: Hoạt chất | D100: Dạng thuốc | F100: Beta Lactam | G100: Non Beta Lactam
A101: 1 | B101: Phospha gaspain 12,38g | C101: Gel nhôm phosphat | D101: Hỗn dịch uống - Lỏng | G101: x | H101: (6) | I101: Gói | J101: 44302 | K101: 4200 | L101: 4200 | M101: =K101-L101 -> 0 | N101: =M101/K101 -> 0 | O101: =AVERAGE(K101,L101) -> 4200 | P101: =O101*1.2 -> 5040
A102: 2 | B102: Berberin 100mg | C102: Berberin clorid | D102: Viên nén - Rắn | G102: x | H102: (2) | I102: viên | J102: 41408 | K102: 630 | L102: 630 | M102: =K102-L102 -> 0 | N102: =M102/K102 -> 0 | O102: =AVERAGE(K102,L102) -> 630 | P102: =O102*1.2 -> 756
A103: 3 | B103: Lacbiosyn® Viên | C103: Lactobacillus acidophilus108CFU | D103: Viên nang cứng - Rắn | G103: x | H103: (2) | I103: viên | J103: 44469 | K103: 1575 | L103: 1575 | M103: =K103-L103 -> 0 | N103: =M103/K103 -> 0 | O103: =AVERAGE(K103,L103) -> 1575 | P103: =O103*1.2 -> 1890
A104: 4 | B104: Bidisubtilis | C104: Bacillus subtilis | D104: Thuốc bột pha uống - Lỏng | G104: x | H104: (6) | I104: Gói | J104: 42486 | K104: 685 | L104: 685 | M104: =K104-L104 -> 0 | N104: =M104/K104 -> 0 | O104: =AVERAGE(K104,L104) -> 685 | P104: =O104*1.2 -> 822
A105: 5 | B105: Lacbiosyn® | C105: Lactobacillus acidophilus | D105: Thuốc bột pha uống - Lỏng | G105: x | H105: (6) | I105: Gói | J105: 42247 | K105: 1890 | L105: 1890 | M105: =K105-L105 -> 0 | N105: =M105/K105 -> 0 | O105: =AVERAGE(K105,L105) -> 1890 | P105: =O105*1.2 -> 2268
A106: 6 | B106: LIVETHINE Tab | C106: L-Ornithin-L-Aspartat | D106: Viên nén bao phim - Rắn | G106: x | H106: (2) | I106: viên | J106: 41873 | K106: 2000 | L106: 714 | M106: =K106-L106 -> 1286 | N106: =M106/K106 -> 0.643 | O106: =AVERAGE(K106,L106) -> 1357 | P106: =O106*1.2 -> 1628.4
A107: 7 | B107: Berberin Bidiphar | C107: Berberin clorid | D107: Viên nén - Rắn | G107: x | H107: (2) | I107: viên | J107: 43209 | K107: 441 | L107: 210 | M107: =K107-L107 -> 231 | N107: =M107/K107 -> 0.52380952 | O107: =AVERAGE(K107,L107) -> 325.5 | P107: =O107*1.2 -> 390.6
A108: 8 | B108: NATRI BICARBONAT 500mg | C108: Natri hydrocarbonat | D108: Viên nén - Rắn | G108: x | H108: (2) | I108: viên | J108: 43955 | K108: 168 | L108: 84 | M108: =K108-L108 -> 84 | N108: =M108/K108 -> 0.5 | O108: =AVERAGE(K108,L108) -> 126 | P108: =O108*1.2 -> 151.2
A109: 9 | B109: COMENAZOL | C109: Pantoprazol | D109: Bột đông khô pha tiêm - Lỏng | G109: x | H109: (1) | I109: Lọ | J109: 44491 | K109: 45000 | L109: 10899 | M109: =K109-L109 -> 34101 | N109: =M109/K109 -> 0.7578 | O109: =AVERAGE(K109,L109) -> 27949.5 | P109: =O109*1.2 -> 33539.4
A110: 10 | B110: ESOGAS | C110: Esomeprazol | D110: Bột đông khô pha tiêm - Lỏng | G110: x | H110: (1) | I110: Lọ | J110: 43259 | K110: 60000 | L110: 9891 | M110: =K110-L110 -> 50109 | N110: =M110/K110 -> 0.83515 | O110: =AVERAGE(K110,L110) -> 34945.5 | P110: =O110*1.2 -> 41934.6
A111: 11 | B111: Altamin | C111: Cao khô Actiso (Extractum Folium Cynarae scolymi) + Cao khô Rau đắng đất (Extractum Glini oppositifolii siccum) + Cao khô hạt Bìm bìm biếc (Extractum Semen Pharbitidis ) | D111: Viên nang mềm - Rắn | G111: x | H111: (4) | I111: viên | J111: 42395 | K111: 1470 | L111: 798 | M111: =K111-L111 -> 672 | N111: =M111/K111 -> 0.45714286 | O111: =AVERAGE(K111,L111) -> 1134 | P111: =O111*1.2 -> 1360.8
...

Sheet Mảng dược phẩm
Q1: 1 | R1: 2 | S1: 3 | T1: 4 | U1: 5 | V1: 6 | W1: 7 | X1: 8 | Y1: 9 | Z1: 10 | AA1: 11 | AB1: 12 | AC1: 13 | AD1: 14 | AE1: 15 | AF1: 16 | AG1: 17 | AH1: 18 | AI1: 19 | AJ1: 20 | AK1: 21 | AL1: 22 | AM1: 23 | AN1: 24 | AO1: 25 | AP1: 26 | AQ1: 27 | AR1: 28 | AS1: 29 | AT1: 30 | AU1: 31 | AV1: 32 | AW1: 33 | AX1: 34 | AY1: 35 | AZ1: 36 | BA1: 37 | BB1: 38 | BC1: 39 | BD1: 40
E2: =IF(TODAY()<E3,"Proj","") | F2: =IF(TODAY()<F3,"Proj","") | I2: =IF(TODAY()<I3,"Proj","") | J2: =IF(TODAY()<J3,"Proj","") | K2: =IF(TODAY()<K3,"Proj","") | L2: =IF(TODAY()<L3,"Proj","") | M2: =IF(TODAY()<M3,"Proj","") | N2: =IF(TODAY()<N3,"Proj","") | O2: =IF(TODAY()<O3,"Proj","") | P2: =IF(TODAY()<P3,"Proj","") | ... BD2: =IF(TODAY()<BD3,"Proj","") -> Proj
F3: 39813 | G3: =DATE(YEAR(F3),MONTH(F3)+13,0) -> 40178 | H3: =DATE(YEAR(G3),MONTH(G3)+13,0) -> 40543 | I3: =DATE(YEAR(H3),MONTH(H3)+13,0) -> 40908 | J3: =DATE(YEAR(I3),MONTH(I3)+13,0) -> 41274 | K3: =DATE(YEAR(J3),MONTH(J3)+13,0) -> 41639 | L3: =DATE(YEAR(K3),MONTH(K3)+13,0) -> 42004 | M3: =DATE(YEAR(L3),MONTH(L3)+13,0) -> 42369 | N3: =DATE(YEAR(M3),MONTH(M3)+13,0) -> 42735 | ... BD3: =DATE(YEAR(BC3),MONTH(BC3)+13,0) -> 58075
B6: REVENUE (price - sale - volume)
A8: 1 | B8: DOANH THU (1.000 tỷ đồng)
B9: Xưởng sản xuất thuốc đông khô – sản phẩm vô trùng | C9: (1) | D9: GMP-WHO | R9: =R192*R219/1000 -> 2819.1864 | S9: =S192*S219/1000 -> 2819.1864 | T9: =T192*T219/1000 -> 2905.4881 | U9: =U192*U219/1000 -> 2934.5429 | V9: =V192*V219/1000 -> 2963.8884 | W9: =W192*W219/1000 -> 2993.5273 | X9: =X192*X219/1000 -> 3023.4625 | Y9: =Y192*Y219/1000 -> 3053.6972 | ... AD9: =AD192*AD219/1000 -> 3209.4664
B10: Xưởng sản xuất thuốc viên (Non – Betalactam); | C10: (2) | D10: GMP-WHO | R10: =R193*R220/1000 -> 196.99242 | S10: =S193*S220/1000 -> 196.99242 | T10: =T193*T220/1000 -> 203.0228 | U10: =U193*U220/1000 -> 205.05303 | V10: =V193*V220/1000 -> 207.10356 | W10: =W193*W220/1000 -> 209.1746 | X10: =X193*X220/1000 -> 211.26634 | Y10: =Y193*Y220/1000 -> 213.37901 | ... AD10: =AD193*AD220/1000 -> 224.26348
B11: Xưởng sản xuất thuốc viên (Betalactam) | C11: (3) | D11: GMP-WHO | R11: =R194*R221/1000 -> 184.35803 | S11: =S194*S221/1000 -> 184.35803 | T11: =T194*T221/1000 -> 190.00164 | U11: =U194*U221/1000 -> 191.90166 | V11: =V194*V221/1000 -> 193.82067 | W11: =W194*W221/1000 -> 195.75888 | X11: =X194*X221/1000 -> 197.71647 | Y11: =Y194*Y221/1000 -> 199.69364 | ... AD11: =AD194*AD221/1000 -> 209.88002
B12: Xưởng sản xuất thuốc viên nang mềm - thuốc đạn | C12: (4) | D12: GMP-WHO | R12: =R195*R222/1000 -> 69.323517 | S12: =S195*S222/1000 -> 69.323517 | T12: =T195*T222/1000 -> 70.738282 | U12: =U195*U222/1000 -> 70.738282 | V12: =V195*V222/1000 -> 70.738282 | W12: =W195*W222/1000 -> 70.738282 | X12: =X195*X222/1000 -> 70.738282 | Y12: =Y195*Y222/1000 -> 70.738282 | ... AD12: =AD195*AD222/1000 -> 70.738282
B13: Xưởng sản xuất thuốc kem - mỡ - nước | C13: (5) | D13: GMP-WHO | R13: =R196*R223/1000 -> 155.49374 | S13: =S196*S223/1000 -> 155.49374 | T13: =T196*T223/1000 -> 160.25375 | U13: =U196*U223/1000 -> 161.85629 | V13: =V196*V223/1000 -> 163.47485 | W13: =W196*W223/1000 -> 165.1096 | X13: =X196*X223/1000 -> 166.7607 | Y13: =Y196*Y223/1000 -> 168.4283 | ... AD13: =AD196*AD223/1000 -> 177.01984
B14: Xưởng sản xuất thuốc bột vi sinh | C14: (6) | D14: GMP-WHO | R14: =R197*R224/1000 -> 4.5474752 | S14: =S197*S224/1000 -> 4.5474752 | T14: =T197*T224/1000 -> 4.6402808 | U14: =U197*U224/1000 -> 4.6402808 | V14: =V197*V224/1000 -> 4.6402808 | W14: =W197*W224/1000 -> 4.6402808 | X14: =X197*X224/1000 -> 4.6402808 | Y14: =Y197*Y224/1000 -> 4.6402808 | ... AD14: =AD197*AD224/1000 -> 4.6402808
B15: Xưởng sản xuất thuốc tiêm bột | C15: (7) | D15: GMP-WHO | R15: =R198*R225/1000 -> 6341.6799 | S15: =S198*S225/1000 -> 6341.6799 | T15: =T198*T225/1000 -> 6600.524 | U15: =U198*U225/1000 -> 6732.5345 | V15: =V198*V225/1000 -> 6867.1852 | W15: =W198*W225/1000 -> 7004.5289 | X15: =X198*X225/1000 -> 7144.6195 | Y15: =Y198*Y225/1000 -> 7158.2986 | ... AD15: =AD198*AD225/1000 -> 7158.2986
B16: Nhà máy sản xuất dược phẩm Bidiphar Công nghệ Cao tại Công ty TNHH Bidiphar Công nghệ Cao
B17: i) Nhà máy sản xuất thuốc điều trị ung thư
B18: Thuốc viên điều trị ung thư | C18: (8) | D18: GMP-PICS/EU | S18: =S201 * S228 -> 1349.1479 | T18: =T201 * T228 -> 9623.9216 | U18: =U201 * U228 -> 10297.596 | V18: =V201 * V228 -> 35222.628 | W18: =W201 * W228 -> 40153.796 | X18: =X201 * X228 -> 45775.328 | Y18: =Y201 * Y228 -> 52183.874 | Z18: =Z201 * Z228 -> 59489.616 | ... AD18: =AD201 * AD228 -> 100475.59
B19: Thuốc tiêm điều trị ung thư | C19: (9) | D19: GMP-PICS/EU | S19: =S202 * S229 -> 252029.55 | T19: =T202 * T229 -> 1797810.8 | U19: =U202 * U229 -> 1923657.5 | V19: =V202 * V229 -> 6579814.7 | W19: =W202 * W229 -> 7500988.7 | X19: =X202 * X229 -> 8551127.1 | Y19: =Y202 * Y229 -> 9748284.9 | Z19: =Z202 * Z229 -> 11113045 | ... AD19: =AD202 * AD229 -> 18769490
B20: ii) Nhà máy sản xuất thuốc uống dạng rắn không chứa nhóm Betalactam | C20: (10) | D20: GMP-PICS/EU | T20: =T230*T203 -> 115626.76
B21: Nhà máy sản xuất dược phẩm Bidiphar Non – Betalactam tại Công ty TNHH Bidiphar Non - Betalactam
B22: Non Betalactam - Lỏng | C22: (11) | D22: GMP-WHO | T22: =T155*T205 -> 0 | U22: =U155*U205 -> 0 | V22: =V155*V205 -> 542.89 | W22: =W155*W205 -> 564.82276 | X22: =X155*X205 -> 587.6416 | Y22: =Y155*Y205 -> 611.38232 | Z22: =Z155*Z205 -> 636.08216 | AA22: =AA155*AA205 -> 661.77988 | ... AD22: =AD155*AD205 -> 745.27163
B23: Non Betalactam - Rắn | C23: (12) | D23: GMP-WHO | T23: =T156*T206 -> 0 | U23: =U156*U206 -> 0 | V23: =V156*V206 -> 278.89 | W23: =W156*W206 -> 290.15716 | X23: =X156*X206 -> 301.87951 | Y23: =Y156*Y206 -> 314.07544 | Z23: =Z156*Z206 -> 326.76408 | AA23: =AA156*AA206 -> 339.96535 | ... AD23: =AD156*AD206 -> 382.85621
B24: Nhà máy sản xuất dược phẩm Bidiphar Betalactam tại Công ty TNHH Bidiphar Betalactam
B25: Thuốc tiêm bột nhóm Cepharlosporin | C25: (13) | D25: GMP-PICS/EU | T25: =T158*T208 -> 0 | U25: =U158*U208 -> 0 | V25: =V158*V208 -> 0 | W25: =W158*W208 -> 2.25 | X25: =X158*X208 -> 2.5281 | Y25: =Y158*Y208 -> 2.8405732 | Z25: =Z158*Z208 -> 3.3132445 | AA25: =AA158*AA208 -> 3.8645684 | ... AD25: =AD158*AD208 -> 6.1325844
B26: Thuốc viên nhóm Cepharlosporin | C26: (14) | D26: GMP-WHO | T26: =T159*T209 -> 0 | U26: =U159*U209 -> 0 | V26: =V159*V209 -> 0 | W26: =W159*W209 -> 0 | X26: =X159*X209 -> 0 | Y26: =Y159*Y209 -> 0 | Z26: =Z159*Z209 -> 16 | AA26: =AA159*AA209 -> 16.9744 | ... AD26: =AD159*AD209 -> 20.268321
B27: Thuốc tiêm bột nhóm Penicillin | C27: (15) | D27: GMP-WHO | T27: =T160*T210 -> 0 | U27: =U160*U210 -> 0 | V27: =V160*V210 -> 0 | W27: =W160*W210 -> 0 | X27: =X160*X210 -> 0.2025 | Y27: =Y160*Y210 -> 0.21483225 | Z27: =Z160*Z210 -> 0.22791553 | AA27: =AA160*AA210 -> 0.24179559 | ... AD27: =AD160*AD210 -> 0.28871658
B28: Thuốc viên nhóm Penicillin | C28: (16) | D28: GMP-WHO | T28: =T161*T211 -> 0 | U28: =U161*U211 -> 0 | V28: =V161*V211 -> 0 | W28: =W161*W211 -> 0 | X28: =X161*X211 -> 0.0625 | Y28: =Y161*Y211 -> 0.06630625 | Z28: =Z161*Z211 -> 0.070344301 | AA28: =AA161*AA211 -> 0.074628269 | ... AD28: =AD161*AD211 -> 0.089110055
B29: Khác | C29: (17) | T29: =T162*T212 -> 0 | U29: =U162*U212 -> 0 | V29: =V162*V212 -> 0 | W29: =W162*W212 -> 0 | X29: =X162*X212 -> 0 | Y29: =Y162*Y212 -> 0 | Z29: =Z162*Z212 -> 0 | AA29: =AA162*AA212 -> 0 | ... AD29: =AD162*AD212 -> 0
B30: Tổng doanh thu | E30: tỷ đồng | M30: ='IS Raw'!J18 -> 1119.03 | N30: ='IS Raw'!K18 -> 1260.14 | O30: ='IS Raw'!L18 -> 1255.63 | P30: ='IS Raw'!M18 -> 1220.84 | Q30: ='IS Raw'!N18 -> 1143.14 | R30: ='IS Raw'!O18 -> 1148.3 | S30: ='IS Raw'!P18 -> 1191.05 | T30: =(T213*10^6*T240)/(10^9) -> 1508.1887 | U30: =(U213*10^6*U240)/(10^9) -> 1539.1105 | V30: =(V213*10^6*V240)/(10^9) -> 1960.4427 | W30: =(W213*10^6*W240)/(10^9) -> 2084.2085 | X30: =(X213*10^6*X240)/(10^9) -> 2217.9866 | Y30: =(Y213*10^6*Y240)/(10^9) -> 2325.2353 | Z30: =(Z213*10^6*Z240)/(10^9) -> 2461.8973 | AA30: =(AA213*10^6*AA240)/(10^9) -> 2559.6764 | ... AD30: =(AD213*10^6*AD240)/(10^9) -> 2907.9352 | AI30: =AI240*AI215/10^9 -> 0 | AJ30: =AJ240*AJ215/10^9 -> 0 | AK30: =AK240*AK215/10^9 -> 0 | AL30: =AL240*AL215/10^9 -> 0 | AM30: =AM240*AM215/10^9 -> 0 | AN30: =AN240*AN215/10^9 -> 0 | AO30: =AO240*AO215/10^9 -> 0 | AP30: =AP240*AP215/10^9 -> 0 | ... BD30: =BD240*BD215/10^9 -> 0
N32: =N30/M30-1 -> 0.12610028 | O32: =O30/N30-1 -> -0.0035789674 | P32: =P30/O30-1 -> -0.027707207 | Q32: =Q30/P30-1 -> -0.063644704 | R32: =R30/Q30-1 -> 0.0045138828 | S32: =S30/R30-1 -> 0.037228947 | T32: =T30/S30-1 -> 0.26626816 | U32: =U30/T30-1 -> 0.02050258 | ... AD32: =AD30/AC30-1 -> 0.045348036
A34: 2 | B34: Growth (1.000 tỷ đồng)
B35: Xưởng sản xuất thuốc đông khô – sản phẩm vô trùng | C35: (1) | D35: GMP-WHO
B36: Xưởng sản xuất thuốc viên (Non – Betalactam); | C36: (2) | D36: GMP-WHO
B37: Xưởng sản xuất thuốc viên (Betalactam) | C37: (3) | D37: GMP-WHO
B38: Xưởng sản xuất thuốc viên nang mềm - thuốc đạn | C38: (4) | D38: GMP-WHO
B39: Xưởng sản xuất thuốc kem - mỡ - nước | C39: (5) | D39: GMP-WHO
B40: Xưởng sản xuất thuốc bột vi sinh | C40: (6) | D40: GMP-WHO
B41: Xưởng sản xuất thuốc tiêm bột | C41: (7) | D41: GMP-WHO
B42: Nhà máy sản xuất dược phẩm Bidiphar Công nghệ Cao tại Công ty TNHH Bidiphar Công nghệ Cao
B43: i) Nhà máy sản xuất thuốc điều trị ung thư
B44: Thuốc viên điều trị ung thư | C44: (8) | D44: GMP-PICS/EU
B45: Thuốc tiêm điều trị ung thư | C45: (9) | D45: GMP-PICS/EU
B46: ii) Nhà máy sản xuất thuốc uống dạng rắn không chứa nhóm Betalactam | C46: (10) | D46: GMP-PICS/EU
B47: Nhà máy sản xuất dược phẩm Bidiphar Non – Betalactam tại Công ty TNHH Bidiphar Non - Betalactam
B48: Non Betalactam - Lỏng | C48: (11) | D48: GMP-WHO
B49: Non Betalactam - Rắn | C49: (12) | D49: GMP-WHO
B50: Nhà máy sản xuất dược phẩm Bidiphar Betalactam tại Công ty TNHH Bidiphar Betalactam
B51: Thuốc tiêm bột nhóm Cepharlosporin | C51: (13) | D51: GMP-PICS/EU
B52: Thuốc viên nhóm Cepharlosporin | C52: (14) | D52: GMP-WHO
B53: Thuốc tiêm bột nhóm Penicillin | C53: (15) | D53: GMP-WHO
B54: Thuốc viên nhóm Penicillin | C54: (16) | D54: GMP-WHO
B55: Khác | C55: (17)
B56: Growth | L56: =IFERROR(L30/K30-1,"") | AI56: =IFERROR(AI30/AH30-1,"") | AJ56: =IFERROR(AJ30/AI30-1,"") | AK56: =IFERROR(AK30/AJ30-1,"") | AL56: =IFERROR(AL30/AK30-1,"") | AM56: =IFERROR(AM30/AL30-1,"") | AN56: =IFERROR(AN30/AM30-1,"") | AO56: =IFERROR(AO30/AN30-1,"") | AP56: =IFERROR(AP30/AO30-1,"") | ... BD56: =IFERROR(BD30/BC30-1,"")
A58: 3 | B58: Công suất thiết kê nhà máy
B59: Xưởng sản xuất thuốc tiêm đông khô – sản phẩm vô trùng | C59: (1) | D59: GMP-WHO | E59: triệu lọ/năm | P59: 24 | Q59: 24 | R59: 24 | S59: 24 | T59: 24 | U59: 24 | V59: 24 | W59: 24 | X59: 24 | Y59: 24 | Z59: 24 | AA59: 24 | AB59: 24 | AC59: 24 | AD59: 24
B60: Xưởng sản xuất thuốc viên (Non – Betalactam); | C60: (2) | D60: GMP-WHO | E60: triệu viên/năm | P60: 1000 | Q60: 1000 | R60: 1000 | S60: 1000 | T60: 1000 | U60: 1000 | V60: 1000 | W60: 1000 | X60: 1000 | Y60: 1000 | Z60: 1000 | AA60: 1000 | AB60: 1000 | AC60: 1000 | AD60: 1000
B61: Xưởng sản xuất thuốc viên (Betalactam) | C61: (3) | D61: GMP-WHO | E61: triệu viên/năm | P61: 500 | Q61: 500 | R61: 500 | S61: 500 | T61: 500 | U61: 500 | V61: 500 | W61: 500 | X61: 500 | Y61: 500 | Z61: 500 | AA61: 500 | AB61: 500 | AC61: 500 | AD61: 500
B62: Xưởng sản xuất thuốc viên nang mềm - thuốc đạn | C62: (4) | D62: GMP-WHO | E62: triệu viên/năm | P62: =P86 -> 32.62 | Q62: =P62 -> 32.62 | R62: =Q62 -> 32.62 | S62: =R62 -> 32.62 | T62: =S62 -> 32.62 | U62: =T62 -> 32.62 | V62: =U62 -> 32.62 | W62: =V62 -> 32.62 | X62: =W62 -> 32.62 | ... AD62: =AC62 -> 32.62
B63: Xưởng sản xuất thuốc kem - mỡ - nước | C63: (5) | D63: GMP-WHO | E63: triệu lọ/năm | P63: 36 | Q63: 36 | R63: 36 | S63: 36 | T63: 36 | U63: 36 | V63: 36 | W63: 36 | X63: 36 | Y63: 36 | Z63: 36 | AA63: 36 | AB63: 36 | AC63: 36 | AD63: 36
B64: Xưởng sản xuất thuốc bột vi sinh | C64: (6) | D64: GMP-WHO | E64: triệu sp/năm | P64: =P88 -> 3.262 | Q64: =Q88 -> 3.262 | R64: =R88 -> 3.262 | S64: =S88 -> 3.262 | T64: =T88 -> 3.262 | U64: =U88 -> 3.262 | V64: =V88 -> 3.262 | W64: =W88 -> 3.262 | ... AD64: =AD88 -> 3.262
B65: Xưởng sản xuất thuốc tiêm bột | C65: (7) | D65: GMP-WHO | E65: triệu lọ/năm | P65: 35 | Q65: 35 | R65: 35 | S65: 35 | T65: 35 | U65: 35 | V65: 35 | W65: 35 | X65: 35 | Y65: 35 | Z65: 35 | AA65: 35 | AB65: 35 | AC65: 35 | AD65: 35
B66: Nhà máy sản xuất dược phẩm Bidiphar Công nghệ Cao tại Công ty TNHH Bidiphar Công nghệ Cao
B67: i) Nhà máy sản xuất thuốc điều trị ung thư
B68: Thuốc viên điều trị ung thư | C68: (8) | D68: GMP-PICS/EU | E68: triệu viên/năm | S68: 2 | T68: 2 | U68: =T68 -> 2 | V68: =U68 -> 2 | W68: =V68 -> 2 | X68: =W68 -> 2 | Y68: =X68 -> 2 | Z68: =Y68 -> 2 | AA68: =Z68 -> 2 | AB68: =AA68 -> 2 | ... AD68: =AC68 -> 2
B69: Thuốc tiêm điều trị ung thư | C69: (9) | D69: GMP-PICS/EU | E69: triệu lọ/năm | S69: 25 | T69: 25 | U69: =T69 -> 25 | V69: =U69 -> 25 | W69: =V69 -> 25 | X69: =W69 -> 25 | Y69: =X69 -> 25 | Z69: =Y69 -> 25 | AA69: =Z69 -> 25 | AB69: =AA69 -> 25 | ... AD69: =AC69 -> 25
B70: ii) Nhà máy sản xuất thuốc uống dạng rắn không chứa nhóm Betalactam | C70: (10) | D70: GMP-PICS/EU | E70: triệu viên/năm | T70: 1300 | U70: =T70 -> 1300 | V70: =U70 -> 1300 | W70: =V70 -> 1300 | X70: =W70 -> 1300 | Y70: =X70 -> 1300 | Z70: =Y70 -> 1300 | AA70: =Z70 -> 1300 | AB70: =AA70 -> 1300 | ... AD70: =AC70 -> 1300
B71: Nhà máy sản xuất dược phẩm Bidiphar Non – Betalactam tại Công ty TNHH Bidiphar Non - Betalactam | E71: triệu sp/năm | V71: 400 | W71: 400 | X71: 400 | Y71: 400 | Z71: 400 | AA71: 400 | AB71: 400 | AC71: 400 | AD71: 400
B72: Non Betalactam - Lỏng | C72: (11) | D72: GMP-WHO | E72: triệu lọ/năm | V72: =V71*'Phân loại dược phẩm'!E309 -> 232.65306 | W72: =V72 -> 232.65306 | X72: =W72 -> 232.65306 | Y72: =X72 -> 232.65306 | Z72: =Y72 -> 232.65306 | AA72: =Z72 -> 232.65306 | AB72: =AA72 -> 232.65306 | AC72: =AB72 -> 232.65306 | AD72: =AC72 -> 232.65306
B73: Non Betalactam - Rắn | C73: (12) | D73: GMP-WHO | E73: triệu viên/năm | V73: =V71*'Phân loại dược phẩm'!E308 -> 167.34694 | W73: =V73 -> 167.34694 | X73: =W73 -> 167.34694 | Y73: =X73 -> 167.34694 | Z73: =Y73 -> 167.34694 | AA73: =Z73 -> 167.34694 | AB73: =AA73 -> 167.34694 | AC73: =AB73 -> 167.34694 | AD73: =AC73 -> 167.34694
B74: Nhà máy sản xuất dược phẩm Bidiphar Betalactam tại Công ty TNHH Bidiphar Betalactam | E74: triệu sp/năm | W74: 62 | X74: =W74 -> 62 | Y74: =X74 -> 62 | Z74: =Y74 -> 62 | AA74: =Z74 -> 62 | AB74: =AA74 -> 62 | AC74: =AB74 -> 62 | AD74: =AC74 -> 62
B75: Thuốc tiêm bột nhóm Cepharlosporin | C75: (13) | D75: GMP-PICS/EU | E75: triệu lọ/năm | W75: 15 | X75: =W75 -> 15 | Y75: =X75 -> 15 | Z75: =Y75 -> 15 | AA75: =Z75 -> 15 | AB75: =AA75 -> 15 | AC75: =AB75 -> 15 | AD75: =AC75 -> 15
B76: Thuốc viên nhóm Cepharlosporin | C76: (14) | D76: GMP-WHO | E76: triệu viên/năm | Z76: 40 | AA76: 40 | AB76: 40 | AC76: 40 | AD76: 40
B77: Thuốc tiêm bột nhóm Penicillin | C77: (15) | D77: GMP-WHO | E77: triệu lọ/năm | X77: =7*'Phân loại dược phẩm'!E315 -> 4.4545455 | Y77: =X77 -> 4.4545455 | Z77: =Y77 -> 4.4545455 | AA77: =Z77 -> 4.4545455 | AB77: =AA77 -> 4.4545455 | AC77: =AB77 -> 4.4545455 | AD77: =AC77 -> 4.4545455
B78: Thuốc viên nhóm Penicillin | C78: (16) | D78: GMP-WHO | E78: triệu viên/năm | X78: =7*'Phân loại dược phẩm'!E316 -> 2.5454545 | Y78: =X78 -> 2.5454545 | Z78: =Y78 -> 2.5454545 | AA78: =Z78 -> 2.5454545 | AB78: =AA78 -> 2.5454545 | AC78: =AB78 -> 2.5454545 | AD78: =AC78 -> 2.5454545
B79: Khác | C79: (17)
B80: Tổng công suất sản xuất | E80: triệu sp/năm | P80: =SUM(P59,P60,P61,P62,P63,P64,P65,P68,P69,P70,P72,P73,P75,P76,P77,P78) -> 1630.882 | Q80: =SUM(Q59,Q60,Q61,Q62,Q63,Q64,Q65,Q68,Q69,Q70,Q72,Q73,Q75,Q76,Q77,Q78) -> 1630.882 | R80: =SUM(R59,R60,R61,R62,R63,R64,R65,R68,R69,R70,R72,R73,R75,R76,R77,R78) -> 1630.882 | S80: =SUM(S59,S60,S61,S62,S63,S64,S65,S68,S69,S70,S72,S73,S75,S76,S77,S78) -> 1657.882 | T80: =SUM(T59,T60,T61,T62,T63,T64,T65,T68,T69,T70,T72,T73,T75,T76,T77,T78) -> 2957.882 | U80: =SUM(U59,U60,U61,U62,U63,U64,U65,U68,U69,U70,U72,U73,U75,U76,U77,U78) -> 2957.882 | V80: =SUM(V59,V60,V61,V62,V63,V64,V65,V68,V69,V70,V72,V73,V75,V76,V77,V78) -> 3357.882 | W80: =SUM(W59,W60,W61,W62,W63,W64,W65,W68,W69,W70,W72,W73,W75,W76,W77,W78) -> 3372.882 | ... AD80: =SUM(AD59,AD60,AD61,AD62,AD63,AD64,AD65,AD68,AD69,AD70,AD72,AD73,AD75,AD76,AD77,AD78) -> 3419.882 | AI80: =SUM(AI62:AI64) -> 0 | AJ80: =SUM(AJ62:AJ64) -> 0 | AK80: =SUM(AK62:AK64) -> 0 | AL80: =SUM(AL62:AL64) -> 0 | AM80: =SUM(AM62:AM64) -> 0 | AN80: =SUM(AN62:AN64) -> 0 | AO80: =SUM(AO62:AO64) -> 0 | AP80: =SUM(AP62:AP64) -> 0 | ... BD80: =SUM(BD62:BD64) -> 0
A82: 4 | B82: Công suất vận hành tối đa
B83: Xưởng sản xuất thuốc đông khô – sản phẩm vô trùng | C83: (1) | D83: GMP-WHO | E83: triệu lọ/năm | P83: 24 | Q83: 24 | R83: 24 | S83: 24 | T83: 24 | U83: 24 | V83: 24 | W83: 24 | X83: 24 | Y83: 24 | Z83: 24 | AA83: 24 | AB83: 24 | AC83: 24 | AD83: 24
B84: Xưởng sản xuất thuốc viên (Non – Betalactam); | C84: (2) | D84: GMP-WHO | E84: triệu viên/năm | P84: 1000 | Q84: 1000 | R84: 1000 | S84: 1000 | T84: 1000 | U84: 1000 | V84: 1000 | W84: 1000 | X84: 1000 | Y84: 1000 | Z84: 1000 | AA84: 1000 | AB84: 1000 | AC84: 1000 | AD84: 1000
B85: Xưởng sản xuất thuốc viên (Betalactam) | C85: (3) | D85: GMP-WHO | E85: triệu viên/năm | P85: 500 | Q85: 500 | R85: 500 | S85: 500 | T85: 500 | U85: 500 | V85: 500 | W85: 500 | X85: 500 | Y85: 500 | Z85: 500 | AA85: 500 | AB85: 500 | AC85: 500 | AD85: 500
B86: Xưởng sản xuất thuốc viên nang mềm - thuốc đạn | C86: (4) | D86: GMP-WHO | E86: triệu viên/năm | P86: =1631*0.02 -> 32.62 | Q86: =P86 -> 32.62 | R86: =Q86 -> 32.62 | S86: =R86 -> 32.62 | T86: =S86 -> 32.62 | U86: =T86 -> 32.62 | V86: =U86 -> 32.62 | W86: =V86 -> 32.62 | X86: =W86 -> 32.62 | ... AD86: =AC86 -> 32.62
B87: Xưởng sản xuất thuốc kem - mỡ - nước | C87: (5) | D87: GMP-WHO | E87: triệu lọ/năm | P87: 36 | Q87: 36 | R87: 36 | S87: 36 | T87: 36 | U87: 36 | V87: 36 | W87: 36 | X87: 36 | Y87: 36 | Z87: 36 | AA87: 36 | AB87: 36 | AC87: 36 | AD87: 36
B88: Xưởng sản xuất thuốc bột vi sinh | C88: (6) | D88: GMP-WHO | E88: triệu sp/năm | P88: =1631*0.002 -> 3.262 | Q88: =P88 -> 3.262 | R88: =Q88 -> 3.262 | S88: =R88 -> 3.262 | T88: =S88 -> 3.262 | U88: =T88 -> 3.262 | V88: =U88 -> 3.262 | W88: =V88 -> 3.262 | X88: =W88 -> 3.262 | ... AD88: =AC88 -> 3.262
B89: Xưởng sản xuất thuốc tiêm bột | C89: (7) | D89: GMP-WHO | E89: triệu lọ/năm | P89: 35 | Q89: 35 | R89: 35 | S89: 35 | T89: 35 | U89: 35 | V89: 35 | W89: 35 | X89: 35 | Y89: 35 | Z89: 35 | AA89: 35 | AB89: 35 | AC89: 35 | AD89: 35
B90: Nhà máy sản xuất dược phẩm Bidiphar Công nghệ Cao tại Công ty TNHH Bidiphar Công nghệ Cao
B91: i) Nhà máy sản xuất thuốc điều trị ung thư
B92: Thuốc viên điều trị ung thư | C92: (8) | D92: GMP-PICS/EU | E92: triệu viên/năm | S92: 2 | T92: 2 | U92: 2 | V92: 2 | W92: 2 | X92: 2 | Y92: 2 | Z92: 2 | AA92: 2 | AB92: 2 | AC92: 2 | AD92: 2
B93: Thuốc tiêm điều trị ung thư | C93: (9) | D93: GMP-PICS/EU | E93: triệu lọ/năm | S93: 25 | T93: 25 | U93: 25 | V93: 25 | W93: 25 | X93: 25 | Y93: 25 | Z93: 25 | AA93: 25 | AB93: 25 | AC93: 25 | AD93: 25
B94: ii) Nhà máy sản xuất thuốc uống dạng rắn không chứa nhóm Betalactam | C94: (10) | D94: GMP-PICS/EU | E94: triệu viên/năm | T94: 1300 | U94: 1300 | V94: 1300 | W94: 1300 | X94: 1300 | Y94: 1300 | Z94: 1300 | AA94: 1300 | AB94: 1300 | AC94: 1300 | AD94: 1300
B95: Nhà máy sản xuất dược phẩm Bidiphar Non – Betalactam tại Công ty TNHH Bidiphar Non - Betalactam | E95: triệu sp/năm
B96: Non Betalactam - Lỏng | C96: (11) | D96: GMP-WHO | E96: triệu lọ/năm | V96: 233 | W96: 233 | X96: 233 | Y96: 233 | Z96: 233 | AA96: 233 | AB96: 233 | AC96: 233 | AD96: 233
B97: Non Betalactam - Rắn | C97: (12) | D97: GMP-WHO | E97: triệu viên/năm | V97: 167 | W97: 167 | X97: 167 | Y97: 167 | Z97: 167 | AA97: 167 | AB97: 167 | AC97: 167 | AD97: 167
B98: Nhà máy sản xuất dược phẩm Bidiphar Betalactam tại Công ty TNHH Bidiphar Betalactam | E98: triệu sp/năm
B99: Thuốc tiêm bột nhóm Cepharlosporin | C99: (13) | D99: GMP-PICS/EU | E99: triệu lọ/năm | W99: 15 | X99: 15 | Y99: 15 | Z99: 15 | AA99: 15 | AB99: 15 | AC99: 15 | AD99: 15
B100: Thuốc viên nhóm Cepharlosporin | C100: (14) | D100: GMP-WHO | E100: triệu viên/năm | Z100: 40 | AA100: =Z100 -> 40 | AB100: =AA100 -> 40 | AC100: =AB100 -> 40 | AD100: 40
B101: Thuốc tiêm bột nhóm Penicillin | C101: (15) | D101: GMP-WHO | E101: triệu lọ/năm | X101: 4.5 | Y101: 4.5 | Z101: 4.5 | AA101: 4.5 | AB101: 4.5 | AC101: 4.5 | AD101: 4.5
B102: Thuốc viên nhóm Penicillin | C102: (16) | D102: GMP-WHO | E102: triệu viên/năm | X102: 2.5 | Y102: 2.5 | Z102: 2.5 | AA102: 2.5 | AB102: 2.5 | AC102: 2.5 | AD102: 2.5
B103: Khác | C103: (17)
B104: Tổng công suất sản xuất | E104: triệu sp/năm | P104: =SUM(P83,P84,P85,P86,P87,P88,P89,P92,P93,P94,P96,P97,P99,P100,P101,P102,P103) -> 1630.882 | Q104: =SUM(Q83,Q84,Q85,Q86,Q87,Q88,Q89,Q92,Q93,Q94,Q96,Q97,Q99,Q100,Q101,Q102,Q103) -> 1630.882 | R104: =SUM(R83,R84,R85,R86,R87,R88,R89,R92,R93,R94,R96,R97,R99,R100,R101,R102,R103) -> 1630.882 | S104: =SUM(S83,S84,S85,S86,S87,S88,S89,S92,S93,S94,S96,S97,S99,S100,S101,S102,S103) -> 1657.882 | T104: =SUM(T83,T84,T85,T86,T87,T88,T89,T92,T93,T94,T96,T97,T99,T100,T101,T102,T103) -> 2957.882 | U104: =SUM(U83,U84,U85,U86,U87,U88,U89,U92,U93,U94,U96,U97,U99,U100,U101,U102,U103) -> 2957.882 | V104: =SUM(V83,V84,V85,V86,V87,V88,V89,V92,V93,V94,V96,V97,V99,V100,V101,V102,V103) -> 3357.882 | W104: =SUM(W83,W84,W85,W86,W87,W88,W89,W92,W93,W94,W96,W97,W99,W100,W101,W102,W103) -> 3372.882 | ... AD104: =SUM(AD83,AD84,AD85,AD86,AD87,AD88,AD89,AD92,AD93,AD94,AD96,AD97,AD99,AD100,AD101,AD102,AD103) -> 3419.882 | AI104: =SUM(AI94:AI103) -> 0 | AJ104: =SUM(AJ94:AJ103) -> 0 | AK104: =SUM(AK94:AK103) -> 0 | AL104: =SUM(AL94:AL103) -> 0 | AM104: =SUM(AM94:AM103) -> 0 | AN104: =SUM(AN94:AN103) -> 0 | AO104: =SUM(AO94:AO103) -> 0 | AP104: =SUM(AP94:AP103) -> 0 | ... BD104: =SUM(BD94:BD103) -> 0
A106: 5 | B106: % hoạt động theo CSTK thông thường
B107: NM Phù Cát_ Gỗ ván ghép | E107: m3 | F107: Gỗ ván ghép
B108: NM Phù Cát_ Gỗ nội thất | E108: m3 | F108: Nội ngoại thất
...

Sheet Mảng thiết bị y tế
O1: 1 | P1: 2 | Q1: 3 | R1: 4 | S1: 5 | T1: 6 | U1: 7 | V1: 8 | W1: 9 | X1: 10 | Y1: 11 | Z1: 12 | AA1: 13 | AB1: 14 | AC1: 15 | AD1: 16 | AE1: 17 | AF1: 18 | AG1: 19 | AH1: 20 | AI1: 21 | AJ1: 22 | AK1: 23 | AL1: 24 | AM1: 25 | AN1: 26 | AO1: 27 | AP1: 28 | AQ1: 29 | AR1: 30 | AS1: 31 | AT1: 32 | AU1: 33 | AV1: 34 | AW1: 35 | AX1: 36 | AY1: 37 | AZ1: 38 | BA1: 39 | BB1: 40
Q2: Proj | R2: Proj | S2: Proj | T2: Proj | U2: Proj | V2: Proj | W2: Proj | X2: Proj | Y2: Proj | Z2: Proj | AA2: Proj | AB2: Proj | AC2: Proj | AD2: Proj | AE2: Proj | AF2: Proj | AG2: Proj | AH2: Proj | AI2: Proj | AJ2: Proj | AK2: Proj | AL2: Proj | AM2: Proj | AN2: Proj | AO2: Proj | AP2: Proj | AQ2: Proj | AR2: Proj | AS2: Proj | AT2: Proj | AU2: Proj | AV2: Proj | AW2: Proj | AX2: Proj | AY2: Proj | AZ2: Proj | BA2: Proj | BB2: Proj
D3: 40178 | E3: 40543 | F3: 40908 | G3: 41274 | H3: 41639 | I3: 42004 | J3: 42369 | K3: 42735 | L3: 43100 | M3: 43465 | N3: 43830 | O3: 44196 | P3: 44561 | Q3: 44926 | R3: 45291 | S3: 45657 | T3: 46022 | U3: 46387 | V3: 46752 | W3: 47118 | X3: 47483 | Y3: 47848 | Z3: 48213 | AA3: 48579 | AB3: 48944 | AC3: 48944 | AD3: 49309 | AE3: 49674 | AF3: 50040 | AG3: 50405 | AH3: 50770 | AI3: 51135 | AJ3: 51501 | AK3: 51866 | AL3: 52231 | AM3: 52596 | AN3: 52962 | AO3: 53327 | AP3: 53692 | AQ3: 54057 | AR3: 54423 | AS3: 54788 | AT3: 55153 | AU3: 55518 | AV3: 55884 | AW3: 56249 | AX3: 56614 | AY3: 56979 | AZ3: 57345 | BA3: 57710 | BB3: 58075
B6: REVENUE (price - sale - volume)
A8: 1 | B8: DOANH THU (tỷ đồng)
B9: Bán vật tư y tế | J9: ='IS Raw'!J19 -> 94.46 | K9: ='IS Raw'!K19 -> 115.1 | L9: ='IS Raw'!L19 -> 117.07 | M9: ='IS Raw'!M19 -> 169.49 | N9: ='IS Raw'!N19 -> 103.75 | O9: ='IS Raw'!O19 -> 92.31 | P9: ='IS Raw'!P19 -> 352.87 | Q9: =AVERAGE(AVERAGE(K9:O9), AVERAGE(K9:P9)) -> 138.98783 | R9: =Q9*(1+R14) -> 177.17952 | S9: =R9*(1+S14) -> 212.61543 | T9: =S9*(1+T14) -> 233.87697 | U9: =T9*(1+U14) -> 245.57082 | V9: =U9*(1+V14) -> 257.84936 | W9: =V9*(1+W14) -> 270.74183 | X9: =W9*(1+X14) -> 278.86408 | Y9: =X9*(1+Y14) -> 287.23001 | ... AC9: =AB9*(1+AC14) -> 313.86398 | AS9: 0 | AT9: 0 | AU9: 0 | AV9: 0 | AW9: 0 | AX9: 0 | AY9: 0 | AZ9: 0 | BA9: 0 | BB9: 0
B10: Bán nguyên liệu,bao bì, công cụ, dụng cụ, khác | J10: ='IS Raw'!J20 -> 11.65 | K10: ='IS Raw'!K20 -> 10.26 | L10: ='IS Raw'!L20 -> 15.82 | M10: ='IS Raw'!M20 -> 10.68 | N10: ='IS Raw'!N20 -> 15.12 | O10: ='IS Raw'!O20 -> 16.35 | P10: ='IS Raw'!P20 -> 14.58 | Q10: =AVERAGE(AVERAGE(K10:O10), AVERAGE(K10:P10)) -> 13.723833 | R10: =Q10*(1+R15) -> 15.386689 | S10: =R10*(1+S15) -> 16.309891 | T10: =S10*(1+T15) -> 17.288484 | U10: =T10*(1+U15) -> 18.325793 | V10: =U10*(1+V15) -> 19.425341 | W10: =V10*(1+W15) -> 20.590861 | X10: =W10*(1+X15) -> 21.208587 | Y10: =X10*(1+Y15) -> 21.844845 | ... AB10: =AA10*(1+AB15) -> 23.870452 | AS10: 0 | AT10: 0 | AU10: 0 | AV10: 0 | AW10: 0 | AX10: 0 | AY10: 0 | AZ10: 0 | BA10: 0 | BB10: 0
B11: Tổng | J11: =J9+J10 -> 106.11 | K11: =K9+K10 -> 125.36 | L11: =L9+L10 -> 132.89 | M11: =M9+M10 -> 180.17 | N11: =N9+N10 -> 118.87 | O11: =O9+O10 -> 108.66 | P11: =P9+P10 -> 367.45 | Q11: =Q9+Q10 -> 152.71167 | ... AB11: =AB9+AB10 -> 337.73444 | AS11: 0 | AT11: 0 | AU11: 0 | AV11: 0 | AW11: 0 | AX11: 0 | AY11: 0 | AZ11: 0 | BA11: 0 | BB11: 0
A13: 2 | B13: Growth (1.000 tỷ đồng)
B14: Bán vật tư y tế | L14: =L9/K9-1 -> 0.017115552 | M14: =M9/L9-1 -> 0.44776629 | N14: =N9/M9-1 -> -0.38786949 | O14: =O9/N9-1 -> -0.11026506 | P14: =P9/O9-1 -> 2.8226628 | Q14: =Q9/P9-1 -> -0.60612171 | R14: =AVERAGE(AVERAGE(L14:O14), AVERAGE(L14:P14)) -> 0.27478442 | S14: 0.2 | T14: =S14/2 -> 0.1 | U14: =T14/2 -> 0.05 | V14: =U14 -> 0.05 | W14: =V14 -> 0.05 | X14: 0.03 | Y14: =X14 -> 0.03 | Z14: =Y14 -> 0.03 | AA14: =Z14 -> 0.03 | AB14: =AA14 -> 0.03 | AS14: 0 | AT14: 0 | AU14: 0 | AV14: 0 | AW14: 0 | AX14: 0 | AY14: 0 | AZ14: 0 | BA14: 0 | BB14: 0
B15: Bán nguyên liệu,bao bì, công cụ, dụng cụ,khác | L15: =L10/K10-1 -> 0.54191033 | M15: =M10/L10-1 -> -0.32490518 | N15: =N10/M10-1 -> 0.41573034 | O15: =O10/N10-1 -> 0.081349206 | P15: =P10/O10-1 -> -0.10825688 | Q15: =Q10/P10-1 -> -0.058721994 | R15: =AVERAGE(L15:P15) -> 0.12116556 | S15: 0.06 | T15: =S15 -> 0.06 | U15: =T15 -> 0.06 | V15: =U15 -> 0.06 | W15: =V15 -> 0.06 | X15: =W15/2 -> 0.03 | Y15: =X15 -> 0.03 | Z15: =Y15 -> 0.03 | AA15: =Z15 -> 0.03 | AB15: =AA15 -> 0.03 | AC15: =AB15/2 -> 0.015 | AD15: =AC15/2 -> 0.0075 | AE15: =AD15/2 -> 0.00375 | AF15: =AE15/2 -> 0.001875 | AG15: =AF15/2 -> 0.0009375 | AH15: =AG15/2 -> 0.00046875 | AI15: =AH15/2 -> 0.000234375 | AJ15: =AI15/2 -> 0.0001171875 | ... BB15: =BA15/2 -> 4.4703484e-10
B16: Growth | L16: =L11/K11-1 -> 0.060067007 | M16: =M11/L11-1 -> 0.35578298 | N16: =N11/M11-1 -> -0.34023422 | O16: =O11/N11-1 -> -0.085892151 | P16: =P11/O11-1 -> 2.3816492 | Q16: =Q11/P11-1 -> -0.58440151 | R16: =R11/Q11-1 -> 0.26097906 | S16: =S11/R11-1 -> 0.18881353 | ... BB16: =BB11/BA11-1 -> #DIV/0!
A19: 3 | B19: Giá bán trung bình (vnđ/sp)
B20: Bán vật tư y tế | AE20: 0 | AF20: 0 | AG20: 0 | AH20: 0 | AI20: 0 | AJ20: 0 | AK20: 0 | AL20: 0 | AM20: 0 | AN20: 0 | AO20: 0 | AP20: 0 | AQ20: 0 | AR20: 0 | AS20: 0 | AT20: 0 | AU20: 0 | AV20: 0 | AW20: 0 | AX20: 0 | AY20: 0 | AZ20: 0 | BA20: 0 | BB20: 0
B21: Bán nguyên liệu,bao bì, công cụ, dụng cụ,khác
B22: Tổng
A24: 4 | B24: Tăng trưởng giá bán
B25: Bán vật tư y tế
B26: Bán nguyên liệu,bao bì, công cụ, dụng cụ,khác
B27: Tổng
B30: GVHB
A32: 1 | B32: GVHB
B33: Bán vật tư y tế | J33: ='IS Raw'!J23 -> 88.907278 | K33: ='IS Raw'!K23 -> 108.55258 | L33: ='IS Raw'!L23 -> 113.70558 | M33: ='IS Raw'!M23 -> 179.61155 | N33: ='IS Raw'!N23 -> 104.47008 | O33: ='IS Raw'!O23 -> 83.476642 | P33: ='IS Raw'!P23 -> 323.75084 | Q33: =Q9-Q51 -> 133.90561 | R33: =R9-R51 -> 170.70078 | S33: =S9-S51 -> 204.84094 | T33: =T9-T51 -> 225.32503 | U33: =U9-U51 -> 236.59128 | V33: =V9-V51 -> 248.42084 | W33: =W9-W51 -> 260.84189 | X33: =X9-X51 -> 268.66714 | ... BB33: =BB9-BB51 -> 0
B34: Bán nguyên liệu,bao bì, công cụ, dụng cụ,khác | J34: ='IS Raw'!J24 -> 9.7459408 | K34: ='IS Raw'!K24 -> 13.851407 | L34: ='IS Raw'!L24 -> 16.553434 | M34: ='IS Raw'!M24 -> 10.963883 | N34: ='IS Raw'!N24 -> 13.8904 | O34: ='IS Raw'!O24 -> 13.015024 | P34: ='IS Raw'!P24 -> 14.315668 | Q34: =Q10-Q52 -> 13.637798 | R34: =R10-R52 -> 15.290229 | S34: =S10-S52 -> 16.207643 | T34: =T10-T52 -> 17.180101 | U34: =U10-U52 -> 18.210907 | V34: =V10-V52 -> 19.303562 | W34: =W10-W52 -> 20.461776 | X34: =X10-X52 -> 21.075629 | ... AC34: =AC10-AC52 -> 0 | AD34: 0 | AE34: 0 | AF34: 0 | AG34: 0 | AH34: 0 | AI34: 0 | AJ34: 0 | AK34: 0 | AL34: 0 | AM34: 0 | AN34: 0 | AO34: 0 | AP34: 0 | AQ34: 0 | AR34: 0 | AS34: 0 | AT34: 0 | AU34: 0 | AV34: 0 | AW34: 0 | AX34: 0 | AY34: 0 | AZ34: 0 | BA34: 0 | BB34: 0
B35: Tổng | J35: =J33+J34 -> 98.653218 | K35: =K33+K34 -> 122.40399 | L35: =L33+L34 -> 130.25902 | M35: =M33+M34 -> 190.57543 | N35: =N33+N34 -> 118.36048 | O35: =O33+O34 -> 96.491666 | P35: =P33+P34 -> 338.06651 | Q35: =Q33+Q34 -> 147.5434 | ... BB35: =BB33+BB34 -> 0
B36: % As Revenue
A38: 2 | B38: GVHB 01 đơn vị sp
B39: Bán vật tư y tế | AC39: 0 | AD39: 0 | AE39: 0 | AF39: 0 | AG39: 0 | AH39: 0 | AI39: 0 | AJ39: 0 | AK39: 0 | AL39: 0 | AM39: 0 | AN39: 0 | AO39: 0 | AP39: 0 | AQ39: 0 | AR39: 0 | AS39: 0 | AT39: 0 | AU39: 0 | AV39: 0 | AW39: 0 | AX39: 0 | AY39: 0 | AZ39: 0 | BA39: 0 | BB39: 0
B40: Bán nguyên liệu,bao bì, công cụ, dụng cụ,khác
B41: Tổng
A43: 3 | B43: Tăng trưởng giá vốn (1.000vnđ/m3)
B44: Bán vật tư y tế | AC44: 0 | AD44: 0 | AE44: 0 | AF44: 0 | AG44: 0 | AH44: 0 | AI44: 0 | AJ44: 0 | AK44: 0 | AL44: 0 | AM44: 0 | AN44: 0 | AO44: 0 | AP44: 0 | AQ44: 0 | AR44: 0 | AS44: 0 | AT44: 0 | AU44: 0 | AV44: 0 | AW44: 0 | AX44: 0 | AY44: 0 | AZ44: 0 | BA44: 0 | BB44: 0
B45: Bán nguyên liệu,bao bì, công cụ, dụng cụ,khác | AC45: 0 | AD45: 0 | AE45: 0 | AF45: 0 | AG45: 0 | AH45: 0 | AI45: 0 | AJ45: 0 | AK45: 0 | AL45: 0 | AM45: 0 | AN45: 0 | AO45: 0 | AP45: 0 | AQ45: 0 | AR45: 0 | AS45: 0 | AT45: 0 | AU45: 0 | AV45: 0 | AW45: 0 | AX45: 0 | AY45: 0 | AZ45: 0 | BA45: 0 | BB45: 0
B46: Tổng
B48: LNG
A50: 1 | B50: LNG
B51: Bán vật tư y tế | J51: =J9-J33 -> 5.5527225 | K51: =K9-K33 -> 6.5474174 | L51: =L9-L33 -> 3.3644158 | M51: =M9-M33 -> -10.12155 | N51: =N9-N33 -> -0.72008382 | O51: =O9-O33 -> 8.833358 | P51: =P9-P33 -> 29.119157 | Q51: =Q9*Q57 -> 5.0822278 | R51: =R9*R57 -> 6.4787448 | S51: =S9*S57 -> 7.7744938 | T51: =T9*T57 -> 8.5519431 | U51: =U9*U57 -> 8.9795403 | V51: =V9*V57 -> 9.4285173 | W51: =W9*W57 -> 9.8999432 | X51: =X9*X57 -> 10.196941 | ... AB51: =AB9*AB57 -> 11.476747 | AC51: 0 | AD51: 0 | AE51: 0 | AF51: 0 | AG51: 0 | AH51: 0 | AI51: 0 | AJ51: 0 | AK51: 0 | AL51: 0 | AM51: 0 | AN51: 0 | AO51: 0 | AP51: 0 | AQ51: 0 | AR51: 0 | AS51: 0 | AT51: 0 | AU51: 0 | AV51: 0 | AW51: 0 | AX51: 0 | AY51: 0 | AZ51: 0 | BA51: 0 | BB51: 0
B52: Bán nguyên liệu,bao bì, công cụ, dụng cụ,khác | J52: =J10-J34 -> 1.9040592 | K52: =K10-K34 -> -3.5914072 | L52: =L10-L34 -> -0.73343403 | M52: =M10-M34 -> -0.28388259 | N52: =N10-N34 -> 1.2295995 | O52: =O10-O34 -> 3.3349758 | P52: =P10-P34 -> 0.26433239 | Q52: =Q10*Q58 -> 0.086035661 | R52: =R10*R58 -> 0.09646022 | S52: =S10*S58 -> 0.10224783 | T52: =T10*T58 -> 0.1083827 | U52: =U10*U58 -> 0.11488567 | V52: =V10*V58 -> 0.12177881 | W52: =W10*W58 -> 0.12908553 | X52: =X10*X58 -> 0.1329581 | ... BB52: =BB10*BB58 -> 0
B53: Tổng | J53: =J51+J52 -> 7.4567817 | K53: =K51+K52 -> 2.9560102 | L53: =L51+L52 -> 2.6309818 | M53: =M51+M52 -> -10.405433 | N53: =N51+N52 -> 0.50951571 | O53: =O51+O52 -> 12.168334 | P53: =P51+P52 -> 29.383489 | Q53: =Q51+Q52 -> 5.1682635 | ... BB53: =BB51+BB52 -> 0
B54: Growth
A56: 2 | B56: Biên LNG
B57: Bán vật tư y tế | J57: =J51/J9 -> 0.05878385 | K57: =K51/K9 -> 0.0568846 | L57: =L51/L9 -> 0.028738497 | M57: =M51/M9 -> -0.059717685 | N57: =N51/N9 -> -0.0069405669 | O57: =O51/O9 -> 0.095692319 | P57: =P51/P9 -> 0.08252092 | Q57: =AVERAGE(J57:P57) -> 0.036565991 | R57: =Q57 -> 0.036565991 | S57: =R57 -> 0.036565991 | T57: =S57 -> 0.036565991 | U57: =T57 -> 0.036565991 | V57: =U57 -> 0.036565991 | W57: =V57 -> 0.036565991 | X57: =W57 -> 0.036565991 | Y57: =X57 -> 0.036565991 | ... AB57: =AA57 -> 0.036565991 | AS57: 0 | AT57: 0 | AU57: 0 | AV57: 0 | AW57: 0 | AX57: 0 | AY57: 0 | AZ57: 0 | BA57: 0 | BB57: 0
B58: Bán nguyên liệu,bao bì, công cụ, dụng cụ,khác | J58: =J52/J10 -> 0.16343856 | K58: =K52/K10 -> -0.35003969 | L58: =L52/L10 -> -0.04636119 | M58: =M52/M10 -> -0.026580767 | N58: =N52/N10 -> 0.08132272 | O58: =O52/O10 -> 0.20397405 | P58: =P52/P10 -> 0.018129793 | Q58: =AVERAGE(J58:P58) -> 0.0062690692 | R58: =Q58 -> 0.0062690692 | S58: =R58 -> 0.0062690692 | T58: =S58 -> 0.0062690692 | U58: =T58 -> 0.0062690692 | V58: =U58 -> 0.0062690692 | W58: =V58 -> 0.0062690692 | X58: =W58 -> 0.0062690692 | Y58: =X58 -> 0.0062690692 | ... AC58: =AB58 -> 0.0062690692 | AS58: 0 | AT58: 0 | AU58: 0 | AV58: 0 | AW58: 0 | AX58: 0 | AY58: 0 | AZ58: 0 | BA58: 0 | BB58: 0
B59: Biên LNG | J59: =J53/J11 -> 0.070274071 | K59: =K53/K11 -> 0.023580171 | L59: =L53/L11 -> 0.019798193 | M59: =M53/M11 -> -0.057753416 | N59: =N53/N11 -> 0.0042863272 | O59: =O53/O11 -> 0.1119854 | P59: =P53/P11 -> 0.079965953 | Q59: =Q53/Q11 -> 0.033843278 | ... AB59: =AB53/AB11 -> 0.03442466 | AS59: #DIV/0! | AT59: #DIV/0! | AU59: #DIV/0! | AV59: #DIV/0! | AW59: #DIV/0! | AX59: #DIV/0! | AY59: #DIV/0! | AZ59: #DIV/0! | BA59: #DIV/0! | BB59: #DIV/0!

Sheet Consol. Rev.
B1: 1 | N1: 1 | O1: 2 | P1: 3 | Q1: 4 | R1: 5 | S1: 6 | T1: 7 | U1: 8 | V1: 9 | W1: 10 | X1: 11 | Y1: 12 | Z1: 13 | AA1: 14 | AB1: 15 | AC1: 16 | AD1: 17 | AE1: 18 | AF1: 19 | AG1: 20 | AH1: 21 | AI1: 22 | AJ1: 23 | AK1: 24 | AL1: 25 | AM1: 26 | AN1: 27 | AO1: 28 | AP1: 29 | AQ1: 30 | AR1: 31 | AS1: 32 | AT1: 33 | AU1: 34 | AV1: 35 | AW1: 36 | AX1: 37 | AY1: 38 | AZ1: 39 | BA1: 40
C2: =IF(TODAY()<C3,"Proj","") | D2: =IF(TODAY()<D3,"Proj","") | F2: =IF(TODAY()<F3,"Proj","") | G2: =IF(TODAY()<G3,"Proj","") | H2: =IF(TODAY()<H3,"Proj","") | I2: =IF(TODAY()<I3,"Proj","") | J2: =IF(TODAY()<J3,"Proj","") | K2: =IF(TODAY()<K3,"Proj","") | L2: =IF(TODAY()<L3,"Proj","") | M2: =IF(TODAY()<M3,"Proj","") | ... BA2: =IF(TODAY()<BA3,"Proj","") -> Proj
D3: 40178 | E3: =DATE(YEAR(D3),MONTH(D3)+13,0) -> 40543 | F3: =DATE(YEAR(E3),MONTH(E3)+13,0) -> 40908 | G3: =DATE(YEAR(F3),MONTH(F3)+13,0) -> 41274 | H3: =DATE(YEAR(G3),MONTH(G3)+13,0) -> 41639 | I3: =DATE(YEAR(H3),MONTH(H3)+13,0) -> 42004 | J3: =DATE(YEAR(I3),MONTH(I3)+13,0) -> 42369 | K3: =DATE(YEAR(J3),MONTH(J3)+13,0) -> 42735 | L3: =DATE(YEAR(K3),MONTH(K3)+13,0) -> 43100 | ... BA3: =DATE(YEAR(AZ3),MONTH(AZ3)+13,0) -> 58075 | BC3: Notes
H4: % growth rev | J4: 0.12610028 | K4: -0.0035789674 | L4: -0.027707207 | M4: -0.063644704 | N4: 0.0045138828 | O4: 0.037228947 | P4: 0.26626816 | Q4: 0.02050258 | R4: 0.2737505 | S4: 0.063131553 | T4: 0.064186526 | U4: 0.048354073 | V4: 0.058773391 | W4: 0.039716983 | X4: 0.041545029 | Y4: 0.043423716 | Z4: 0.045348036
B6: REVENUE (price - sale - volume)
B8: Consol. revenue (FC) | J8: =SUM(J9:J11) -> 1236.79 | K8: =SUM(K9:K11) -> 1395.76 | L8: =SUM(L9:L11) -> 1404.34 | M8: =SUM(M9:M11) -> 1411.69 | N8: =SUM(N9:N11) -> 1277.13 | O8: =SUM(O9:O11) -> 1273.31 | P8: =SUM(P9:P11) -> 1573.08 | Q8: =SUM(Q9:Q11) -> 1674.6242 | ... AB8: =SUM(AB9:AB11) -> 361.60489
B9: Mảng dược phẩm | J9: ='Mảng dược phẩm'!M30 -> 1119.03 | K9: ='Mảng dược phẩm'!N30 -> 1260.14 | L9: ='Mảng dược phẩm'!O30 -> 1255.63 | M9: ='Mảng dược phẩm'!P30 -> 1220.84 | N9: ='Mảng dược phẩm'!Q30 -> 1143.14 | O9: ='Mảng dược phẩm'!R30 -> 1148.3 | P9: ='Mảng dược phẩm'!S30 -> 1191.05 | Q9: ='Mảng dược phẩm'!T30 -> 1508.1887 | ... AB9: ='Mảng dược phẩm'!AE30 -> 0
B10: Mảng kinh doanh vật tư y tế | J10: ='Mảng thiết bị y tế'!J11 -> 106.11 | K10: ='Mảng thiết bị y tế'!K11 -> 125.36 | L10: ='Mảng thiết bị y tế'!L11 -> 132.89 | M10: ='Mảng thiết bị y tế'!M11 -> 180.17 | N10: ='Mảng thiết bị y tế'!N11 -> 118.87 | O10: ='Mảng thiết bị y tế'!O11 -> 108.66 | P10: ='Mảng thiết bị y tế'!P11 -> 367.45 | Q10: ='Mảng thiết bị y tế'!Q11 -> 152.71167 | ... AX10: ='Mảng thiết bị y tế'!AX11 -> 0
B11: Mảng nguyên liêu, bao bì, công cụ, dụng cụ, dịch vụ khác | J11: ='Mảng thiết bị y tế'!J10 -> 11.65 | K11: ='Mảng thiết bị y tế'!K10 -> 10.26 | L11: ='Mảng thiết bị y tế'!L10 -> 15.82 | M11: ='Mảng thiết bị y tế'!M10 -> 10.68 | N11: ='Mảng thiết bị y tế'!N10 -> 15.12 | O11: ='Mảng thiết bị y tế'!O10 -> 16.35 | P11: ='Mảng thiết bị y tế'!P10 -> 14.58 | Q11: ='Mảng thiết bị y tế'!Q10 -> 13.723833 | ... AB11: ='Mảng thiết bị y tế'!AB10 -> 23.870452
B12: Consol. revenue | J12: =IF('IS Raw'!J17,'IS Raw'!J17/'Consol. Rev.'!$B$1,'Consol. Rev.'!J8) -> 1225.068 | K12: =IF('IS Raw'!K17,'IS Raw'!K17/'Consol. Rev.'!$B$1,'Consol. Rev.'!K8) -> 1384.9018 | L12: =IF('IS Raw'!L17,'IS Raw'!L17/'Consol. Rev.'!$B$1,'Consol. Rev.'!L8) -> 1388.2274 | M12: =IF('IS Raw'!M17,'IS Raw'!M17/'Consol. Rev.'!$B$1,'Consol. Rev.'!M8) -> 1401.0243 | N12: =IF('IS Raw'!N17,'IS Raw'!N17/'Consol. Rev.'!$B$1,'Consol. Rev.'!N8) -> 1261.729 | O12: =IF('IS Raw'!O17,'IS Raw'!O17/'Consol. Rev.'!$B$1,'Consol. Rev.'!O8) -> 1256.9524 | P12: =IF('IS Raw'!P17,'IS Raw'!P17/'Consol. Rev.'!$B$1,'Consol. Rev.'!P8) -> 1558.5043 | Q12: =IF('IS Raw'!Q17,'IS Raw'!Q17/'Consol. Rev.'!$B$1,'Consol. Rev.'!Q8) -> 1674.6242 | ... AA12: =IF('IS Raw'!AA17,'IS Raw'!AA17/'Consol. Rev.'!$B$1,'Consol. Rev.'!AA8) -> 3259.0079
B14: Rev. Growth (FC) | D14: =IFERROR(D8/C8-1," ") | E14: =IFERROR(E8/D8-1," ") | F14: =IFERROR(F8/E8-1," ") | G14: =IFERROR(G8/F8-1," ") | H14: =IFERROR(H8/G8-1," ") | I14: =IFERROR(I8/H8-1," ") | K14: =K8/J8-1 -> 0.12853435 | L14: =L8/K8-1 -> 0.0061471886 | M14: =M8/L8-1 -> 0.0052337753 | N14: =N8/M8-1 -> -0.095318377 | O14: =O8/N8-1 -> -0.0029910816 | P14: =P8/O8-1 -> 0.23542578 | Q14: =Q8/P8-1 -> 0.064551196 | R14: =R8/Q8-1 -> 0.043256967 | ... AA14: =AA8/Z8-1 -> 0.04367274
B15: Mảng dược phẩm | D15: =IFERROR(D9/C9-1," ") | E15: =IFERROR(E9/D9-1," ") | F15: =IFERROR(F9/E9-1," ") | G15: =IFERROR(G9/F9-1," ") | H15: =IFERROR(H9/G9-1," ") | I15: =IFERROR(I9/H9-1," ") | K15: =K9/J9-1 -> 0.12610028 | L15: =L9/K9-1 -> -0.0035789674 | M15: =M9/L9-1 -> -0.027707207 | N15: =N9/M9-1 -> -0.063644704 | O15: =O9/N9-1 -> 0.0045138828 | P15: =P9/O9-1 -> 0.037228947 | Q15: =Q9/P9-1 -> 0.26626816 | R15: =R9/Q9-1 -> 0.02050258 | ... AA15: =AA9/Z9-1 -> 0.045348036
B16: Mảng kinh doanh vật tư y tế | D16: =IFERROR(D10/C10-1," ") | E16: =IFERROR(E10/D10-1," ") | F16: =IFERROR(F10/E10-1," ") | G16: =IFERROR(G10/F10-1," ") | H16: =IFERROR(H10/G10-1," ") | I16: =IFERROR(I10/H10-1," ") | K16: =K10/J10-1 -> 0.18141551 | L16: =L10/K10-1 -> 0.060067007 | M16: =M10/L10-1 -> 0.35578298 | N16: =N10/M10-1 -> -0.34023422 | O16: =O10/N10-1 -> -0.085892151 | P16: =P10/O10-1 -> 2.3816492 | Q16: =Q10/P10-1 -> -0.58440151 | R16: =R10/Q10-1 -> 0.26097906 | ... AA16: =AA10/Z10-1 -> 0.03
B17: Mảng nguyên liêu, bao bì, công cụ, dụng cụ, dịch vụ khác | K17: =K11/J11-1 -> -0.1193133 | L17: =L11/K11-1 -> 0.54191033 | M17: =M11/L11-1 -> -0.32490518 | N17: =N11/M11-1 -> 0.41573034 | O17: =O11/N11-1 -> 0.081349206 | P17: =P11/O11-1 -> -0.10825688 | Q17: =Q11/P11-1 -> -0.058721994 | R17: =R11/Q11-1 -> 0.12116556 | ... AA17: =AA11/Z11-1 -> 0.03
B18: Rev. Growth | D18: =IFERROR(D12/C12-1," ") | E18: =IFERROR(E12/D12-1," ") | F18: =IFERROR(F12/E12-1," ") | G18: =IFERROR(G12/F12-1," ") | H18: =IFERROR(H12/G12-1," ") | I18: =IFERROR(I12/H12-1," ") | K18: =K12/J12-1 -> 0.13046932 | L18: =L12/K12-1 -> 0.0024012993 | M18: =M12/L12-1 -> 0.0092181712 | N18: =N12/M12-1 -> -0.099423895 | O18: =O12/N12-1 -> -0.003785797 | P18: =P12/O12-1 -> 0.23990723 | Q18: =Q12/P12-1 -> 0.074507244 | R18: =R12/Q12-1 -> 0.043256967 | ... AA18: =AA12/Z12-1 -> 0.04367274
B21: COGS
B23: COGS (FC) (Cách 1: theo từng mảng) | J23: =SUM(J25:J27) -> 773.07692 | K23: =SUM(K25:K27) -> 875.70244 | L23: =SUM(L25:L27) -> 897.55493 | M23: =SUM(M25:M27) -> 972.89628 | N23: =SUM(N25:N27) -> 846.93308 | O23: =SUM(O25:O27) -> 765.81309 | P23: =SUM(P25:P27) -> 935.93871 | Q23: =SUM(Q25:Q27) -> 1012.6252 | ... AB23: =SUM(AB25:AB27) -> 326.10804
B24: % As Revenue | J24: =J23/J8 -> 0.62506725 | K24: =K23/K8 -> 0.62740187 | L24: =L23/L8 -> 0.63912936 | M24: =M23/M8 -> 0.68917133 | N24: =N23/N8 -> 0.66315338 | O24: =O23/O8 -> 0.60143492 | P24: =P23/P8 -> 0.5949721 | Q24: =Q23/Q8 -> 0.60468802 | ... AX24: =AX23/AX8 -> #DIV/0!
B25: Mảng dược phẩm | J25: ='Mảng dược phẩm'!M293 -> 674.4237 | K25: ='Mảng dược phẩm'!N293 -> 753.29845 | L25: ='Mảng dược phẩm'!O293 -> 767.29591 | M25: ='Mảng dược phẩm'!P293 -> 782.32085 | N25: ='Mảng dược phẩm'!Q293 -> 728.5726 | O25: ='Mảng dược phẩm'!R293 -> 669.32143 | P25: ='Mảng dược phẩm'!S293 -> 597.8722 | Q25: ='Mảng dược phẩm'!T293 -> 865.08179 | ... AX25: ='Mảng dược phẩm'!BA293 -> 0
B26: Mảng kinh doanh vật tư y tế | J26: ='Mảng thiết bị y tế'!J33 -> 88.907278 | K26: ='Mảng thiết bị y tế'!K33 -> 108.55258 | L26: ='Mảng thiết bị y tế'!L33 -> 113.70558 | M26: ='Mảng thiết bị y tế'!M33 -> 179.61155 | N26: ='Mảng thiết bị y tế'!N33 -> 104.47008 | O26: ='Mảng thiết bị y tế'!O33 -> 83.476642 | P26: ='Mảng thiết bị y tế'!P33 -> 323.75084 | Q26: ='Mảng thiết bị y tế'!Q33 -> 133.90561 | ... AB26: ='Mảng thiết bị y tế'!AB33 -> 302.38724
B27: Mảng nguyên liêu, bao bì, công cụ, dụng cụ, dịch vụ khác | J27: ='Mảng thiết bị y tế'!J34 -> 9.7459408 | K27: ='Mảng thiết bị y tế'!K34 -> 13.851407 | L27: ='Mảng thiết bị y tế'!L34 -> 16.553434 | M27: ='Mảng thiết bị y tế'!M34 -> 10.963883 | N27: ='Mảng thiết bị y tế'!N34 -> 13.8904 | O27: ='Mảng thiết bị y tế'!O34 -> 13.015024 | P27: ='Mảng thiết bị y tế'!P34 -> 14.315668 | Q27: ='Mảng thiết bị y tế'!Q34 -> 13.637798 | ... AB27: ='Mảng thiết bị y tế'!AB34 -> 23.720806
B28: COGS Cách 1: theo từng mảng) | J28: =IF('IS Raw'!J21, -'IS Raw'!J21/'Consol. Rev.'!$B$1,'Consol. Rev.'!J23) -> 773.07692 | K28: =IF('IS Raw'!K21, -'IS Raw'!K21/'Consol. Rev.'!$B$1,'Consol. Rev.'!K23) -> 875.70244 | L28: =IF('IS Raw'!L21, -'IS Raw'!L21/'Consol. Rev.'!$B$1,'Consol. Rev.'!L23) -> 897.55493 | M28: =IF('IS Raw'!M21, -'IS Raw'!M21/'Consol. Rev.'!$B$1,'Consol. Rev.'!M23) -> 972.89628 | N28: =IF('IS Raw'!N21, -'IS Raw'!N21/'Consol. Rev.'!$B$1,'Consol. Rev.'!N23) -> 846.93308 | O28: =IF('IS Raw'!O21, -'IS Raw'!O21/'Consol. Rev.'!$B$1,'Consol. Rev.'!O23) -> 765.81309 | P28: =IF('IS Raw'!P21, -'IS Raw'!P21/'Consol. Rev.'!$B$1,'Consol. Rev.'!P23) -> 935.93871 | Q28: =IF('IS Raw'!Q21, -'IS Raw'!Q21/'Consol. Rev.'!$B$1,'Consol. Rev.'!Q23) -> 1012.6252 | ... AB28: =IF('IS Raw'!AB21, -'IS Raw'!AB21/'Consol. Rev.'!$B$1,'Consol. Rev.'!AB23) -> 326.10804
B29: % As Revenue | D29: =IFERROR(D28/D12," ") | E29: =IFERROR(E28/E12," ") | J29: =J28/J12 -> 0.63104815 | K29: =K28/K12 -> 0.63232095 | L29: =L28/L12 -> 0.64654748 | M29: =M28/M12 -> 0.69441784 | N29: =N28/N12 -> 0.671248 | O29: =O28/O12 -> 0.60926182 | P29: =P28/P12 -> 0.60053648 | Q29: =Q28/Q12 -> 0.60468802 | ... AX29: =AX28/AX12 -> #DIV/0!
B32: COGS (FC) (Cách 2: theo chi phí) | J32: =SUM(J34:J39) -> 487.76481 | K32: =SUM(K34:K39) -> 606.15413 | L32: =SUM(L34:L39) -> 584.33981 | M32: =SUM(M34:M39) -> 519.73255 | N32: =SUM(N34:N39) -> 599.23006 | O32: =SUM(O34:O39) -> 699.59285 | P32: =SUM(P34:P39) -> 738.97817 | Q32: =SUM(Q34:Q39) -> 748.85859 | ... AA32: =SUM(AA34:AA39) -> 1348.88
B33: % As Revenue | J33: =J32/J12 -> 0.39815324 | K33: =K32/K12 -> 0.43768743 | L33: =L32/L12 -> 0.42092514 | M33: =M32/M12 -> 0.37096612 | N33: =N32/N12 -> 0.4749277 | O33: =O32/O12 -> 0.55657864 | P33: =P32/P12 -> 0.47415856 | Q33: =Q32/Q12 -> 0.44718008 | ... AB33: =AB32/AB12 -> #DIV/0!
B34: Chi phí nguyên liệu, vật liệu | J34: =J124-J107-J89 -> 303.23109 | K34: =K124-K107-K89 -> 380.35389 | L34: =L124-L107-L89 -> 394.12482 | M34: =M124-M107-M89 -> 353.37877 | N34: =N124-N107-N89 -> 432.11671 | O34: =O124-O107-O89 -> 491.22753 | P34: =P124-P107-P89 -> 487.43204 | Q34: =Q124-Q107-Q89 -> 503.42636 | ... AA34: =AA124-AA107-AA89 -> 979.72459
B35: Chi phí nhân công | J35: =J126-J109-J89 -> 113.9138 | K35: =K126-K109-K89 -> 162.69443 | L35: =L126-L109-L89 -> 121.85908 | M35: =M126-M109-M89 -> 111.18712 | N35: =N126-N109-N89 -> 120.6713 | O35: =O126-O109-O89 -> 158.56456 | P35: =P126-P109-P89 -> 197.31999 | Q35: =Q126-Q109-Q89 -> 173.68312 | ... AA35: =AA126-AA109-AA89 -> 338.00697
B36: Chi phí khấu hao tài sản cố định | J36: =J128-J111-J93 -> 29.985032 | K36: =K128-K111-K93 -> 19.855461 | L36: =L128-L111-L93 -> 20.0985 | M36: =M128-M111-M93 -> 19.027074 | N36: =N128-N111-N93 -> 11.266032 | O36: =O128-O111-O93 -> 16.181945 | P36: =P128-P111-P93 -> 20.821484 | Q36: =Q128-Q111-Q93 -> 23.659716 | ... AA36: =AA128-AA111-AA93 -> 46.044481
B37: Chi phí dịch vụ mua ngoài | J37: =J130-J113-J95 -> 35.274296 | K37: =K130-K113-K95 -> 37.879721 | L37: =L130-L113-L95 -> 44.180731 | M37: =M130-M113-M95 -> 34.061067 | N37: =N130-N113-N95 -> 30.242648 | O37: =O130-O113-O95 -> 30.578094 | P37: =P130-P113-P95 -> 31.787727 | Q37: =Q130-Q113-Q95 -> 43.295058 | ... AA37: =AA130-AA113-AA95 -> 84.257075
B38: Chi phí khác bằng tiền | J38: =J132-J115-J97 -> 5.360594 | K38: =K132-K115-K97 -> 5.370623 | L38: =L132-L115-L97 -> 4.076672 | M38: =M132-M115-M97 -> 2.0785175 | N38: =N132-N115-N97 -> 4.9333741 | O38: =O132-O115-O97 -> 3.0407155 | P38: =P132-P115-P97 -> 1.6169324 | Q38: =Q132-Q115-Q97 -> 4.7943351 | ... AA38: =AA132-AA115-AA97 -> -87.012612
B39: (Hoàn nhập)/Dự phòng phải thu khó đòi | J39: =J134-J117-J99 -> 0 | K39: =K134-K117-K99 -> 0 | L39: =L134-L117-L99 -> 0 | M39: =M134-M117-M99 -> 0 | N39: =N134-N117-N99 -> 0 | O39: =O134-O117-O99 -> 0 | P39: =P134-P117-P99 -> 0 | Q39: =Q134-Q117-Q99 -> 0 | ... AA39: =AA134-AA117-AA99 -> -12.140522
B40: Sai số | J40: =J28-J32 -> 285.31211 | K40: =K28-K32 -> 269.54831 | L40: =L28-L32 -> 313.21513 | M40: =M28-M32 -> 453.16373 | N40: =N28-N32 -> 247.70302 | O40: =O28-O32 -> 66.220247 | P40: =P28-P32 -> 196.96054 | Q40: =Q28-Q32 -> 263.76661 | ... AA40: =AA28-AA32 -> 445.29782
B41: COGS (Cách 2: theo chi phí)
B42: % As Revenue | D42: =IFERROR(D41/D21," ") | E42: =IFERROR(E41/E21," ") | F42: =IFERROR(F41/F21," ") | G42: =IFERROR(G41/G21," ") | J42: =J32/J12 -> 0.39815324 | K42: =K32/K12 -> 0.43768743 | L42: =L32/L12 -> 0.42092514 | M42: =M32/M12 -> 0.37096612 | N42: =N32/N12 -> 0.4749277 | O42: =O32/O12 -> 0.55657864 | P42: =P32/P12 -> 0.47415856 | Q42: =Q32/Q12 -> 0.44718008 | ... AA42: =AA32/AA12 -> 0.41389282
B44: % COGS theo Doanh thu (FC) (Cách 2: theo chi phí) | J44: =SUM(J46:J51) -> 0.39815324 | K44: =SUM(K46:K51) -> 0.43768743 | L44: =SUM(L46:L51) -> 0.42092514 | M44: =SUM(M46:M51) -> 0.37096612 | N44: =SUM(N46:N51) -> 0.4749277 | O44: =SUM(O46:O51) -> 0.55657864 | P44: =SUM(P46:P51) -> 0.47415856 | Q44: =SUM(Q46:Q51) -> 0.44718008 | ... AA44: =SUM(AA46:AA51) -> 0.41389282
B45: % As Revenue
B46: Chi phí nguyên liệu, vật liệu | I46: =IFERROR(I34/I$12,"") | J46: =J34/J12 -> 0.24752184 | K46: =K34/K12 -> 0.27464322 | L46: =L34/L12 -> 0.28390509 | M46: =M34/M12 -> 0.25222887 | N46: =N34/N12 -> 0.3424798 | O46: =O34/O12 -> 0.39080839 | P46: =P34/P12 -> 0.31275629 | Q46: =Q34/Q12 -> 0.3006205 | ... AA46: =AA34/AA12 -> 0.3006205
B47: Chi phí nhân công | I47: =IFERROR(I35/I$12,"") | J47: =J35/J12 -> 0.092985691 | K47: =K35/K12 -> 0.11747723 | L47: =L35/L12 -> 0.087780344 | M47: =M35/M12 -> 0.079361305 | N47: =N35/N12 -> 0.095639634 | O47: =O35/O12 -> 0.12615002 | P47: =P35/P12 -> 0.12660856 | Q47: =Q35/Q12 -> 0.10371468 | ... AA47: =AA35/AA12 -> 0.10371468
B48: Chi phí khấu hao tài sản cố định | I48: =IFERROR(I36/I$12,"") | J48: =J36/J12 -> 0.024476217 | K48: =K36/K12 -> 0.014337089 | L48: =L36/L12 -> 0.014477815 | M48: =M36/M12 -> 0.013580831 | N48: =N36/N12 -> 0.0089290425 | O48: =O36/O12 -> 0.012873952 | P48: =P36/P12 -> 0.013359914 | Q48: =Q36/Q12 -> 0.014128374 | ... AA48: =AA36/AA12 -> 0.014128374
B49: Chi phí dịch vụ mua ngoài | I49: =IFERROR(I37/I$12,"") | J49: =J37/J12 -> 0.028793745 | K49: =K37/K12 -> 0.027351917 | L49: =L37/L12 -> 0.031825284 | M49: =M37/M12 -> 0.024311546 | N49: =N37/N12 -> 0.02396921 | O49: =O37/O12 -> 0.02432717 | P49: =P37/P12 -> 0.020396303 | Q49: =Q37/Q12 -> 0.025853596 | ... AA49: =AA37/AA12 -> 0.025853596
B50: Chi phí khác bằng tiền | I50: =IFERROR(I38/I$12,"") | J50: =J38/J12 -> 0.0043757521 | K50: =K38/K12 -> 0.003877981 | L50: =L38/L12 -> 0.0029366025 | M50: =M38/M12 -> 0.0014835699 | N50: =N38/N12 -> 0.0039100108 | O50: =O38/O12 -> 0.0024191175 | P50: =P38/P12 -> 0.0010374898 | Q50: =Q38/Q12 -> 0.0028629319 | ... AA50: =AA38/AA12 -> -0.02669911
B51: (Hoàn nhập)/Dự phòng phải thu khó đòi | I51: =IFERROR(I39/I$12,"") | J51: =J39/J12 -> 0 | K51: =K39/K12 -> 0 | L51: =L39/L12 -> 0 | M51: =M39/M12 -> 0 | N51: =N39/N12 -> 0 | O51: =O39/O12 -> 0 | P51: =P39/P12 -> 0 | Q51: =Q39/Q12 -> 0 | ... AA51: =AA39/AA12 -> -0.0037252202
B52: Sai số | I52: =IFERROR(I40/I$12,"") | J52: =J40/J12 -> 0.23289491 | K52: =K40/K12 -> 0.19463351 | L52: =L40/L12 -> 0.22562235 | M52: =M40/M12 -> 0.32345172 | N52: =N40/N12 -> 0.1963203 | O52: =O40/O12 -> 0.052683179 | P52: =P40/P12 -> 0.12637793 | Q52: =Q40/Q12 -> 0.15750794 | ... AA52: =AA40/AA12 -> 0.136636
B53: % COGS theo Doanh thu (Cách 2: theo chi phí)
B54: % As Revenue
B58: GROSS PROFIT MARGIN
B60: Gross profit (FC) (Cách 1: theo từng mảng) | J60: =J8-J23 -> 463.71308 | K60: =K8-K23 -> 520.05756 | L60: =L8-L23 -> 506.78507 | M60: =M8-M23 -> 438.79372 | N60: =N8-N23 -> 430.19692 | O60: =O8-O23 -> 507.49691 | P60: =P8-P23 -> 637.14129 | Q60: =Q8-Q23 -> 661.999 | ... AA60: =AA8-AA23 -> 1464.8301
B61: Growth | I61: =IFERROR(I60/H60-1," ") | K61: =K60/J60-1 -> 0.12150721 | L61: =L60/K60-1 -> -0.025521203 | M61: =M60/L60-1 -> -0.1341621 | N61: =N60/M60-1 -> -0.019591897 | O61: =O60/N60-1 -> 0.17968512 | P61: =P60/O60-1 -> 0.25545846 | Q61: =Q60/P60-1 -> 0.039014447 | R61: =R60/Q60-1 -> 0.024554642 | ... AA61: =AA60/Z60-1 -> 0.044981692
B62: Mảng dược phẩm | J62: =J9-J25 -> 444.6063 | K62: =K9-K25 -> 506.84155 | L62: =L9-L25 -> 488.33409 | M62: =M9-M25 -> 438.51915 | N62: =N9-N25 -> 414.5674 | O62: =O9-O25 -> 478.97857 | P62: =P9-P25 -> 593.1778 | Q62: =Q9-Q25 -> 643.1069 | ... AA62: =AA9-AA25 -> 1430.3672
B63: Mảng kinh doanh vật tư y tế | J63: =J10-J26 -> 17.202722 | K63: =K10-K26 -> 16.807417 | L63: =L10-L26 -> 19.184416 | M63: =M10-M26 -> 0.5584496 | N63: =N10-N26 -> 14.399916 | O63: =O10-O26 -> 25.183358 | P63: =P10-P26 -> 43.699157 | Q63: =Q10-Q26 -> 18.806061 | ... AA63: =AA10-AA26 -> 34.317669
B64: Mảng nguyên liêu, bao bì, công cụ, dụng cụ, dịch vụ khác | J64: =J11-J27 -> 1.9040592 | K64: =K11-K27 -> -3.5914072 | L64: =L11-L27 -> -0.73343403 | M64: =M11-M27 -> -0.28388259 | N64: =N11-N27 -> 1.2295995 | O64: =O11-O27 -> 3.3349758 | P64: =P11-P27 -> 0.26433239 | Q64: =Q11-Q27 -> 0.086035661 | ... AA64: =AA11-AA27 -> 0.14528691
B65: Gross profit (Cách 1: theo từng mảng) | J65: =IF('IS Raw'!J25, 'IS Raw'!J25, 'Consol. Rev.'!J60) -> 451.99112 | K65: =IF('IS Raw'!K25, 'IS Raw'!K25, 'Consol. Rev.'!K60) -> 509.1994 | L65: =IF('IS Raw'!L25, 'IS Raw'!L25, 'Consol. Rev.'!L60) -> 490.67247 | M65: =IF('IS Raw'!M25, 'IS Raw'!M25, 'Consol. Rev.'!M60) -> 428.12804 | N65: =IF('IS Raw'!N25, 'IS Raw'!N25, 'Consol. Rev.'!N60) -> 414.79594 | O65: =IF('IS Raw'!O25, 'IS Raw'!O25, 'Consol. Rev.'!O60) -> 491.13928 | P65: =IF('IS Raw'!P25, 'IS Raw'!P25, 'Consol. Rev.'!P60) -> 637.14129 | Q65: =IF('IS Raw'!Q25, 'IS Raw'!Q25, 'Consol. Rev.'!Q60) -> 661.999 | ... AA65: =IF('IS Raw'!AA25, 'IS Raw'!AA25, 'Consol. Rev.'!AA60) -> 1464.8301
B66: Growth | K66: =K65/J65-1 -> 0.12656948 | L66: =L65/K65-1 -> -0.036384432 | M66: =M65/L65-1 -> -0.12746676 | N66: =N65/M65-1 -> -0.031140442 | O66: =O65/N65-1 -> 0.18405035 | P66: =P65/O65-1 -> 0.29727211 | Q66: =Q65/P65-1 -> 0.039014447 | R66: =R65/Q65-1 -> 0.024554642 | ... AA66: =AA65/Z65-1 -> 0.044981692
B68: GPM (FC) (Cách 1: theo từng mảng) | D68: =IFERROR(D60/D8," ") | E68: =IFERROR(E60/E8," ") | F68: =IFERROR(F60/F8," ") | G68: =IFERROR(G60/G8," ") | H68: =IFERROR(H60/H8," ") | I68: =IFERROR(I60/I8," ")
B69: Mảng dược phẩm | D69: =IFERROR(D62/D9," ") | E69: =IFERROR(E62/E9," ") | F69: =IFERROR(F62/F9," ") | G69: =IFERROR(G62/G9," ") | H69: =IFERROR(H62/H9," ") | I69: =IFERROR(I62/I9," ") | J69: =J62/J9 -> 0.39731401 | K69: =K62/K9 -> 0.40221051 | L69: =L62/L9 -> 0.38891559 | M69: =M62/M9 -> 0.35919462 | N69: =N62/N9 -> 0.36265672 | O69: =O62/O9 -> 0.41711972 | P69: =P62/P9 -> 0.4980293 | Q69: =Q62/Q9 -> 0.42641011 | ... AA69: =AA62/AA9 -> 0.49188412
B70: Mảng kinh doanh vật tư y tế | D70: =IFERROR(D63/D10," ") | E70: =IFERROR(E63/E10," ") | F70: =IFERROR(F63/F10," ") | G70: =IFERROR(G63/G10," ") | H70: =IFERROR(H63/H10," ") | I70: =IFERROR(I63/I10," ") | J70: =J63/J10 -> 0.1621216 | K70: =K63/K10 -> 0.13407321 | L70: =L63/L10 -> 0.14436313 | M70: =M63/M10 -> 0.0030995704 | N70: =N63/N10 -> 0.12114004 | O70: =O63/O10 -> 0.23176291 | P70: =P63/P10 -> 0.11892545 | Q70: =Q63/Q10 -> 0.12314751 | ... AA70: =AA63/AA10 -> 0.10465974
B71: Mảng nguyên liêu, bao bì, công cụ, dụng cụ, dịch vụ khác | D71: =IFERROR(D64/D11," ") | E71: =IFERROR(E64/E11," ") | F71: =IFERROR(F64/F11," ") | G71: =IFERROR(G64/G11," ") | H71: =IFERROR(H64/H11," ") | I71: =IFERROR(I64/I11," ") | J71: =J64/J11 -> 0.16343856 | K71: =K64/K11 -> -0.35003969 | L71: =L64/L11 -> -0.04636119 | M71: =M64/M11 -> -0.026580767 | N71: =N64/N11 -> 0.08132272 | O71: =O64/O11 -> 0.20397405 | P71: =P64/P11 -> 0.018129793 | Q71: =Q64/Q11 -> 0.0062690692 | ... AA71: =AA64/AA11 -> 0.0062690692
B72: GPM (Cách 1: theo từng mảng) | D72: =IFERROR(D65/D12," ") | E72: =IFERROR(E65/E12," ") | F72: =IFERROR(F65/F12," ") | G72: =IFERROR(G65/G12," ") | H72: =IFERROR(H65/H12," ") | I72: =IFERROR(I65/I12," ") | J72: =J65/J12 -> 0.36895185 | K72: =K65/K12 -> 0.36767905 | L72: =L65/L12 -> 0.35345252 | M72: =M65/M12 -> 0.30558216 | N72: =N65/N12 -> 0.328752 | O72: =O65/O12 -> 0.39073818 | P72: =P65/P12 -> 0.40881586 | Q72: =Q65/Q12 -> 0.39531198 | ... AA72: =AA65/AA12 -> 0.44947117
B76: Gross profit (FC) (Cách 2: theo chi phí) | I76: =+I8-I32 -> 0
B77: Growth | I77: =IFERROR(I76/H76-1," ")
B78: Gross profit (FC) (Cách 2: theo chi phí)
B79: Growth
B81: GPM (FC) (Cách 2: theo chi phí) | D81: =IFERROR(D76/D23," ") | E81: =IFERROR(E76/E23," ") | F81: =IFERROR(F76/F23," ") | G81: =IFERROR(G76/G23," ") | H81: =IFERROR(H76/H23," ") | I81: =IFERROR(I76/I23," ")
B82: GPM (Cách 2: theo chi phí) | D82: =IFERROR(D78/#REF!," ") | E82: =IFERROR(E78/#REF!," ") | F82: =IFERROR(F78/#REF!," ") | G82: =IFERROR(G78/#REF!," ") | H82: =IFERROR(H78/#REF!," ") | I82: =IFERROR(I78/I12," ")
B85: SG&A
D86: =10^9 -> 1000000000
B87: Selling expense (FC) | J87: =-'IS Raw'!J30/'Consol. Rev.'!$B$1 -> 222.0959 | K87: =-'IS Raw'!K30/'Consol. Rev.'!$B$1 -> 260.80345 | L87: =-'IS Raw'!L30/'Consol. Rev.'!$B$1 -> 210.95744 | M87: =-'IS Raw'!M30/'Consol. Rev.'!$B$1 -> 174.04986 | N87: =-'IS Raw'!N30/'Consol. Rev.'!$B$1 -> 169.93779 | O87: =-'IS Raw'!O30/'Consol. Rev.'!$B$1 -> 220.85513 | P87: =-'IS Raw'!P30/'Consol. Rev.'!$B$1 -> 276.43932 | Q87: =SUM(Q89,Q91,Q93,Q95,Q97,Q99) -> 271.18673 | R87: =SUM(R89,R91,R93,R95,R97,R99) -> 282.91744 | S87: =SUM(S89,S91,S93,S95,S97,S99) -> 357.18496 | T87: =SUM(T89,T91,T93,T95,T97,T99) -> 380.98746 | U87: =SUM(U89,U91,U93,U95,U97,U99) -> 404.88099 | V87: =SUM(V89,V91,V93,V95,V97,V99) -> 424.59321 | W87: =SUM(W89,W91,W93,W95,W97,W99) -> 449.18937 | X87: =SUM(X89,X91,X93,X95,X97,X99) -> 466.53899 | ... AA87: =SUM(AA89,AA91,AA93,AA95,AA97,AA99) -> 527.76001
B88: % As revenue (incl Depr) | J88: =J87/J12 -> 0.1812927 | K88: =K87/K12 -> 0.18831909 | L88: =L87/L12 -> 0.15196173 | M88: =M87/M12 -> 0.12423043 | N88: =N87/N12 -> 0.13468644 | O88: =O87/O12 -> 0.17570684 | P88: =P87/P12 -> 0.17737475 | Q88: =Q87/Q12 -> 0.16193886 | ... AA88: =AA87/AA12 -> 0.16193886
B89: CP nguyên liệu, vật liệu | J89: 0 | K89: 0 | L89: 0 | M89: 0 | N89: 0 | O89: 0 | P89: 0 | Q89: 0 | R89: =Q89 -> 0 | S89: =R89 -> 0 | T89: =S89 -> 0 | U89: =T89 -> 0 | V89: =U89 -> 0 | W89: =V89 -> 0 | X89: =W89 -> 0 | Y89: =X89 -> 0 | ... AA89: =Z89 -> 0
B90: % revenue | J90: =J89/J12 -> 0 | K90: =K89/K12 -> 0 | L90: =L89/L12 -> 0 | M90: =M89/M12 -> 0 | N90: =N89/N12 -> 0 | O90: =O89/O12 -> 0 | P90: =P89/P12 -> 0 | Q90: =Q89/J12 -> 0 | R90: =R89/K12 -> 0 | S90: =S89/L12 -> 0 | T90: =T89/M12 -> 0 | U90: =U89/N12 -> 0 | V90: =V89/O12 -> 0 | W90: =W89/P12 -> 0 | X90: =X89/Q12 -> 0 | ... AA90: =AA89/T12 -> 0
B91: CP nhân công | J91: =82618649636/D86 -> 82.61865 | K91: =129989062484/D86 -> 129.98906 | L91: =86312749591/D86 -> 86.31275 | M91: =75464333907/D86 -> 75.464334 | N91: =77489792147/D86 -> 77.489792 | O91: =117686018668/D86 -> 117.68602 | P91: =(73786773386+41081857108+45312619582)/D86 -> 160.18125 | Q91: =Q92*Q12 -> 128.02802 | R91: =R92*R12 -> 133.56613 | S91: =S92*S12 -> 168.62803 | T91: =T92*T12 -> 179.86526 | U91: =U92*U12 -> 191.14546 | V91: =V92*V12 -> 200.45166 | W91: =W92*W12 -> 212.06358 | X91: =X92*X12 -> 220.25438 | ... AA91: =AA92*AA12 -> 249.157
B92: % revenue | J92: =J91/J12 -> 0.06744005 | K92: =K91/K12 -> 0.093861571 | L92: =L91/L12 -> 0.062174792 | M92: =M91/M12 -> 0.053863686 | N92: =N91/N12 -> 0.061415558 | O92: =O91/O12 -> 0.093628065 | P92: =P91/P12 -> 0.10277883 | Q92: =AVERAGE(J92:P92) -> 0.076451793 | R92: =Q92 -> 0.076451793 | S92: =R92 -> 0.076451793 | T92: =S92 -> 0.076451793 | U92: =T92 -> 0.076451793 | V92: =U92 -> 0.076451793 | W92: =V92 -> 0.076451793 | X92: =W92 -> 0.076451793 | Y92: =X92 -> 0.076451793 | ... AA92: =Z92 -> 0.076451793
B93: CP khấu hao TSCĐ | J93: =2807200031/D86 -> 2.8072 | K93: =4474307228/D86 -> 4.4743072 | L93: =5759145827/D86 -> 5.7591458 | M93: =4973811530/D86 -> 4.9738115 | N93: =5261000162/D86 -> 5.2610002 | O93: =5756726433/D86 -> 5.7567264 | P93: =(2521643474+1089489562+1091074360)/D86 -> 4.7022074 | Q93: =Q94*Q12 -> 5.9778433 | R93: =R94*R12 -> 6.2364266 | S93: =S94*S12 -> 7.8735259 | T93: =T94*T12 -> 8.398211 | U93: =U94*U12 -> 8.9249025 | V93: =V94*V12 -> 9.3594244 | W93: =W94*W12 -> 9.9016043 | X93: =X94*X12 -> 10.284047 | ... AA93: =AA94*AA12 -> 11.633558
B94: % revenue | J94: =J93/J12 -> 0.0022914646 | K94: =K93/K12 -> 0.0032307757 | L94: =L93/L12 -> 0.0041485608 | M94: =M93/M12 -> 0.0035501251 | N94: =N93/N12 -> 0.0041696752 | O94: =O93/O12 -> 0.0045799082 | P94: =P93/P12 -> 0.0030171282 | Q94: =AVERAGE(J94:P94) -> 0.0035696625 | R94: =Q94 -> 0.0035696625 | S94: =R94 -> 0.0035696625 | T94: =S94 -> 0.0035696625 | U94: =T94 -> 0.0035696625 | V94: =U94 -> 0.0035696625 | W94: =V94 -> 0.0035696625 | X94: =W94 -> 0.0035696625 | Y94: =X94 -> 0.0035696625 | ... AA94: =Z94 -> 0.0035696625
B95: CP dịch vụ mua ngoài | J95: =43477322871/D86 -> 43.477323 | K95: =49608916070/D86 -> 49.608916 | L95: =48169889666/D86 -> 48.16989 | M95: =42957411731/D86 -> 42.957412 | N95: =44360098297/D86 -> 44.360098 | O95: =46680883197/D86 -> 46.680883 | P95: =(20381472822+15741472659+32953364987)/D86 -> 69.07631 | Q95: =Q96*Q12 -> 60.595023 | R95: =R96*R12 -> 63.21618 | S95: =S96*S12 -> 79.810805 | T95: =T96*T12 -> 85.12933 | U95: =U96*U12 -> 90.468192 | V95: =V96*V12 -> 94.872768 | W95: =W96*W12 -> 100.36863 | X95: =X96*X12 -> 104.2453 | ... AA95: =AA96*AA12 -> 117.92476
B96: % revenue | J96: =J95/J12 -> 0.035489721 | K96: =K95/K12 -> 0.035821251 | L96: =L95/L12 -> 0.034698847 | M96: =M95/M12 -> 0.030661432 | N96: =N95/N12 -> 0.035158182 | O96: =O95/O12 -> 0.037138148 | P96: =P95/P12 -> 0.044322181 | Q96: =AVERAGE(J96:P96) -> 0.036184252 | R96: =Q96 -> 0.036184252 | S96: =R96 -> 0.036184252 | T96: =S96 -> 0.036184252 | U96: =T96 -> 0.036184252 | V96: =U96 -> 0.036184252 | W96: =V96 -> 0.036184252 | X96: =W96 -> 0.036184252 | Y96: =X96 -> 0.036184252 | ... AA96: =Z96 -> 0.036184252
B97: CP khác bằng tiền | J97: =93192723547/D86 -> 93.192724 | K97: =76731169214/D86 -> 76.731169 | L97: =70715650029/D86 -> 70.71565 | M97: =50654301751/D86 -> 50.654302 | N97: =42826897675/D86 -> 42.826898 | O97: =50731499725/D86 -> 50.7315 | P97: =(23596377770+32234682042-13351504802)/D86 -> 42.479555 | Q97: =Q98*Q12 -> 76.585837 | R97: =R98*R12 -> 79.898708 | S97: =S98*S12 -> 100.8726 | T97: =T98*T12 -> 107.59466 | U97: =U98*U12 -> 114.34243 | V97: =V98*V12 -> 119.90936 | W97: =W98*W12 -> 126.85556 | X97: =X98*X12 -> 131.75526 | ... AA97: =AA98*AA12 -> 149.04469
B98: % revenue | J98: =J97/J12 -> 0.076071468 | K98: =K97/K12 -> 0.055405493 | L98: =L97/L12 -> 0.050939529 | M98: =M97/M12 -> 0.036155191 | N98: =N97/N12 -> 0.033943023 | O98: =O97/O12 -> 0.040360718 | P98: =P97/P12 -> 0.027256617 | Q98: =AVERAGE(J98:P98) -> 0.045733148 | R98: =Q98 -> 0.045733148 | S98: =R98 -> 0.045733148 | T98: =S98 -> 0.045733148 | U98: =T98 -> 0.045733148 | V98: =U98 -> 0.045733148 | W98: =V98 -> 0.045733148 | X98: =W98 -> 0.045733148 | Y98: =X98 -> 0.045733148 | ... AA98: =Z98 -> 0.045733148
B99: (Hoàn nhập)/Dự phòng phải thu khó đòi | J99: 0 | K99: =J99 -> 0 | L99: =K99 -> 0 | M99: =L99 -> 0 | N99: =M99 -> 0 | O99: =N99 -> 0 | P99: =O99 -> 0 | Q99: 0 | R99: =Q99 -> 0 | S99: =R99 -> 0 | T99: =S99 -> 0 | U99: =T99 -> 0 | V99: =U99 -> 0 | W99: =V99 -> 0 | X99: =W99 -> 0 | Y99: =X99 -> 0 | ... AA99: =Z99 -> 0
B100: % revenue | J100: =J99/J12 -> 0 | K100: =K99/K12 -> 0 | L100: =L99/L12 -> 0 | M100: =M99/M12 -> 0 | N100: =N99/N12 -> 0 | O100: =O99/O12 -> 0 | P100: =P99/P12 -> 0 | Q100: 0 | R100: =Q100 -> 0 | S100: =R100 -> 0 | T100: =S100 -> 0 | U100: =T100 -> 0 | V100: =U100 -> 0 | W100: =V100 -> 0 | X100: =W100 -> 0 | Y100: =X100 -> 0 | ... AA100: =Z100 -> 0
B101: Selling expense | J101: =IF('IS Raw'!J30,-'IS Raw'!J30/'Consol. Rev.'!$B$1,'Consol. Rev.'!J87) -> 222.0959 | K101: =IF('IS Raw'!K30,-'IS Raw'!K30/'Consol. Rev.'!$B$1,'Consol. Rev.'!K87) -> 260.80345 | L101: =IF('IS Raw'!L30,-'IS Raw'!L30/'Consol. Rev.'!$B$1,'Consol. Rev.'!L87) -> 210.95744 | M101: =IF('IS Raw'!M30,-'IS Raw'!M30/'Consol. Rev.'!$B$1,'Consol. Rev.'!M87) -> 174.04986 | N101: =IF('IS Raw'!N30,-'IS Raw'!N30/'Consol. Rev.'!$B$1,'Consol. Rev.'!N87) -> 169.93779 | O101: =IF('IS Raw'!O30,-'IS Raw'!O30/'Consol. Rev.'!$B$1,'Consol. Rev.'!O87) -> 220.85513 | P101: =IF('IS Raw'!P30,-'IS Raw'!P30/'Consol. Rev.'!$B$1,'Consol. Rev.'!P87) -> 276.43932 | Q101: =IF('IS Raw'!Q30,-'IS Raw'!Q30/'Consol. Rev.'!$B$1,'Consol. Rev.'!Q87) -> 271.18673 | ... AA101: =IF('IS Raw'!AA30,-'IS Raw'!AA30/'Consol. Rev.'!$B$1,'Consol. Rev.'!AA87) -> 527.76001
B102: % As revenue (excl Depr)
B103: % As revenue (incl Depr) | D103: =IFERROR(D101/D12," ") | E103: =IFERROR(E101/E12," ") | F103: =IFERROR(F101/F12," ") | G103: =IFERROR(G101/G12," ") | H103: =IFERROR(H101/H12," ") | I103: =IFERROR(I101/I12," ")
B105: G&A expenses (FC) | D105: =10^9 -> 1000000000 | J105: =SUM(J107,J109,J111,J113,J115,J117) -> 102.01829 | K105: =SUM(K107,K109,K111,K113,K115,K117) -> 90.386997 | L105: =SUM(L107,L109,L111,L113,L115,L117) -> 92.776906 | M105: =SUM(M107,M109,M111,M113,M115,M117) -> 67.52121 | N105: =SUM(N107,N109,N111,N113,N115,N117) -> 84.108598 | O105: =SUM(O107,O109,O111,O113,O115,O117) -> 88.501076 | P105: =SUM(P107,P109,P111,P113,P115,P117) -> 135.93274 | Q105: =SUM(Q107,Q109,Q111,Q113,Q115,Q117) -> 117.46146 | ... AA105: =SUM(AA107,AA109,AA111,AA113,AA115,AA117) -> 228.59327
B106: % As revenue (incl Depr) | J106: =J105/J12 -> 0.083275611 | K106: =K105/K12 -> 0.065265996 | L106: =L105/L12 -> 0.066831203 | M106: =M105/M12 -> 0.048194174 | N106: =N105/N12 -> 0.06666138 | O106: =O105/O12 -> 0.070409251 | P106: =P105/P12 -> 0.087219994 | Q106: =Q105/Q12 -> 0.070141979 | ... AA106: =AA105/AA12 -> 0.070141979
B107: CP nguyên liệu, vật liệu | J107: =0 -> 0 | K107: =J107 -> 0 | L107: =K107 -> 0 | M107: =L107 -> 0 | N107: =M107 -> 0 | O107: =N107 -> 0 | P107: =O107 -> 0 | Q107: 0 | R107: =Q107 -> 0 | S107: =R107 -> 0 | T107: =S107 -> 0 | U107: =T107 -> 0 | V107: =U107 -> 0 | W107: =V107 -> 0 | X107: =W107 -> 0 | Y107: =X107 -> 0 | ... AA107: =Z107 -> 0
B108: % revenue | J108: =J107/J12 -> 0 | K108: =K107/K12 -> 0 | L108: =L107/L12 -> 0 | M108: =M107/M12 -> 0 | N108: =N107/N12 -> 0 | O108: =O107/O12 -> 0 | P108: =P107/P12 -> 0 | Q108: 0 | R108: =Q108 -> 0 | S108: =R108 -> 0 | T108: =S108 -> 0 | U108: =T108 -> 0 | V108: =U108 -> 0 | W108: =V108 -> 0 | X108: =W108 -> 0 | Y108: =X108 -> 0 | ... AA108: =Z108 -> 0
B109: CP nhân công | J109: =36438915119/D105 -> 36.438915 | K109: =43681653036/D105 -> 43.681653 | L109: =37734215831/D105 -> 37.734216 | M109: =24549983139/D105 -> 24.549983 | N109: =23754054757/D105 -> 23.754055 | O109: =29811793072/D105 -> 29.811793 | P109: =(19359408568+25183315586+3467480538)/D105 -> 48.010205 | Q109: =Q110*Q12 -> 42.90378 | R109: =R110*R12 -> 44.759667 | S109: =S110*S12 -> 56.509348 | T109: =T110*T12 -> 60.275083 | U109: =U110*U12 -> 64.055218 | V109: =V110*V12 -> 67.17384 | W109: =W110*W12 -> 71.065137 | X109: =X110*X12 -> 73.809977 | ... AA109: =AA110*AA12 -> 83.495604
B110: % revenue | J110: =J109/J12 -> 0.029744401 | K110: =K109/K12 -> 0.031541335 | L110: =L109/L12 -> 0.027181581 | M110: =M109/M12 -> 0.017522882 | N110: =N109/N12 -> 0.01882659 | O110: =O109/O12 -> 0.02371752 | P110: =P109/P12 -> 0.030805307 | Q110: =AVERAGE(J110:P110) -> 0.025619945 | R110: =Q110 -> 0.025619945 | S110: =R110 -> 0.025619945 | T110: =S110 -> 0.025619945 | U110: =T110 -> 0.025619945 | V110: =U110 -> 0.025619945 | W110: =V110 -> 0.025619945 | X110: =W110 -> 0.025619945 | Y110: =X110 -> 0.025619945 | ... AA110: =Z110 -> 0.025619945
B111: CP khấu hao TSCĐ | J111: =6424902287/D105 -> 6.4249023 | K111: =9464063411/D105 -> 9.4640634 | L111: =10956196676/D105 -> 10.956197 | M111: =12516029605/D105 -> 12.51603 | N111: =11420505965/D105 -> 11.420506 | O111: =9870319490/D105 -> 9.8703195 | P111: =(4513747538+2290513638+8346175399)/D105 -> 15.150437 | Q111: =Q112*Q12 -> 14.034646 | R111: =R112*R12 -> 14.641742 | S111: =S112*S12 -> 18.485287 | T111: =T112*T12 -> 19.717131 | U111: =U112*U12 -> 20.953685 | V111: =V112*V12 -> 21.973846 | W111: =W112*W12 -> 23.246764 | X111: =X112*X12 -> 24.144653 | ... AA111: =AA112*AA12 -> 27.313007
B112: % revenue | J112: =J111/J12 -> 0.0052445269 | K112: =K111/K12 -> 0.0068337431 | L112: =L111/L12 -> 0.0078922205 | M112: =M111/M12 -> 0.0089334849 | N112: =N111/N12 -> 0.0090514728 | O112: =O111/O12 -> 0.0078525803 | P112: =P111/P12 -> 0.0097211386 | Q112: =AVERAGE(K112:P112) -> 0.0083807734 | R112: =Q112 -> 0.0083807734 | S112: =R112 -> 0.0083807734 | T112: =S112 -> 0.0083807734 | U112: =T112 -> 0.0083807734 | V112: =U112 -> 0.0083807734 | W112: =V112 -> 0.0083807734 | X112: =W112 -> 0.0083807734 | Y112: =X112 -> 0.0083807734 | ... AA112: =Z112 -> 0.0083807734
B113: CP dịch vụ mua ngoài | J113: =12463231719/D105 -> 12.463232 | K113: =32642008058/D105 -> 32.642008 | L113: =35318689673/D105 -> 35.31869 | M113: =17185795348/D105 -> 17.185795 | N113: =15017098564/D105 -> 15.017099 | O113: =21735735012/D105 -> 21.735735 | P113: =(6839958303+4158504196+9608570749)/D105 -> 20.607033 | Q113: =Q114*Q12 -> 27.240944 | R113: =R114*R12 -> 28.419305 | S113: =S114*S12 -> 35.879542 | T113: =T114*T12 -> 38.270524 | U113: =U114*U12 -> 40.67065 | V113: =V114*V12 -> 42.65076 | W113: =W114*W12 -> 45.121465 | X113: =X114*X12 -> 46.86425 | ... AA113: =AA114*AA12 -> 53.013955
B114: % revenue | J114: =J113/J12 -> 0.010173502 | K114: =K113/K12 -> 0.023569907 | L114: =L113/L12 -> 0.025441574 | M114: =M113/M12 -> 0.012266593 | N114: =N113/N12 -> 0.011902 | O114: =O113/O12 -> 0.017292409 | P114: =P113/P12 -> 0.013222314 | Q114: =AVERAGE(J114:P114) -> 0.0162669 | R114: =Q114 -> 0.0162669 | S114: =R114 -> 0.0162669 | T114: =S114 -> 0.0162669 | U114: =T114 -> 0.0162669 | V114: =U114 -> 0.0162669 | W114: =V114 -> 0.0162669 | X114: =W114 -> 0.0162669 | Y114: =X114 -> 0.0162669 | ... AA114: =Z114 -> 0.0162669
B115: CP khác bằng tiền | J115: =27995723203/D105 -> 27.995723 | K115: =9477339180/D105 -> 9.4773392 | L115: =11412183722/D105 -> 11.412184 | M115: =12148696772/D105 -> 12.148697 | N115: =11995552410/D105 -> 11.995552 | O115: =12794781096/D105 -> 12.794781 | P115: =(4583159755+1529430775+23823291038)/D105 -> 29.935882 | Q115: =Q116*Q12 -> 20.450085 | R115: =R116*R12 -> 21.334694 | S115: =S116*S12 -> 26.935178 | T115: =T116*T12 -> 28.730116 | U115: =U116*U12 -> 30.531917 | V115: =V116*V12 -> 32.018408 | W115: =W116*W12 -> 33.873195 | X115: =X116*X12 -> 35.181523 | ... AA115: =AA116*AA12 -> 39.798177
B116: % revenue | J116: =J115/J12 -> 0.022852382 | K116: =K115/K12 -> 0.0068433292 | L116: =L115/L12 -> 0.0082206876 | M116: =M115/M12 -> 0.0086712962 | N116: =N115/N12 -> 0.0095072335 | O116: =O115/O12 -> 0.010179209 | P116: =P115/P12 -> 0.019208084 | Q116: =AVERAGE(J116:P116) -> 0.012211746 | R116: =Q116 -> 0.012211746 | S116: =R116 -> 0.012211746 | T116: =S116 -> 0.012211746 | U116: =T116 -> 0.012211746 | V116: =U116 -> 0.012211746 | W116: =V116 -> 0.012211746 | X116: =W116 -> 0.012211746 | Y116: =X116 -> 0.012211746 | ... AA116: =Z116 -> 0.012211746
B117: (Hoàn nhập)/Dự phòng phải thu khó đòi | J117: =18695516395/D105 -> 18.695516 | K117: =-4878066678/D105 -> -4.8780667 | L117: =-2644379422/D105 -> -2.6443794 | M117: =1120705235/D105 -> 1.1207052 | N117: =21921386233/D105 -> 21.921386 | O117: =14288446894/D105 -> 14.288447 | P117: =(112488415+15000000000+7116693459)/D105 -> 22.229182 | Q117: =Q118*Q12 -> 12.832 | R117: =R118*R12 -> 13.387074 | S117: =S118*S12 -> 16.901261 | T117: =T118*T12 -> 18.027546 | U117: =U118*U12 -> 19.158139 | V117: =V118*V12 -> 20.090881 | W117: =W118*W12 -> 21.254721 | X117: =X118*X12 -> 22.075669 | ... AA117: =AA118*AA12 -> 24.972523
B118: % revenue | J118: =J117/J12 -> 0.015260798 | K118: =K117/K12 -> -0.0035223195 | L118: =L117/L12 -> -0.0019048604 | M118: =M117/M12 -> 0.00079991848 | N118: =N117/N12 -> 0.017374084 | O118: =O117/O12 -> 0.011367532 | P118: =P117/P12 -> 0.014263151 | Q118: =AVERAGE(J118:P118) -> 0.0076626149 | R118: =Q118 -> 0.0076626149 | S118: =R118 -> 0.0076626149 | T118: =S118 -> 0.0076626149 | U118: =T118 -> 0.0076626149 | V118: =U118 -> 0.0076626149 | W118: =V118 -> 0.0076626149 | X118: =W118 -> 0.0076626149 | Y118: =X118 -> 0.0076626149 | ... AA118: =Z118 -> 0.0076626149
B119: G&A expenses | J119: =IF('IS Raw'!J31, -'IS Raw'!J31,'Consol. Rev.'!J105) -> 102.01819 | K119: =IF('IS Raw'!K31, -'IS Raw'!K31,'Consol. Rev.'!K105) -> 90.386997 | L119: =IF('IS Raw'!L31, -'IS Raw'!L31,'Consol. Rev.'!L105) -> 92.776906 | M119: =IF('IS Raw'!M31, -'IS Raw'!M31,'Consol. Rev.'!M105) -> 67.52121 | N119: =IF('IS Raw'!N31, -'IS Raw'!N31,'Consol. Rev.'!N105) -> 84.108598 | O119: =IF('IS Raw'!O31, -'IS Raw'!O31,'Consol. Rev.'!O105) -> 88.501076 | P119: =IF('IS Raw'!P31, -'IS Raw'!P31,'Consol. Rev.'!P105) -> 128.99778 | Q119: =IF('IS Raw'!Q31, -'IS Raw'!Q31,'Consol. Rev.'!Q105) -> 117.46146 | ... AA119: =IF('IS Raw'!AA31, -'IS Raw'!AA31,'Consol. Rev.'!AA105) -> 228.59327
B120: % As revenue (excl Depr)
B121: % As revenue (incl Depr) | D121: =IFERROR(D119/D12," ") | E121: =IFERROR(E119/E12," ") | F121: =IFERROR(F119/F12," ") | G121: =IFERROR(G119/G12," ") | H121: =IFERROR(H119/H12," ") | I121: =IFERROR(I119/I12," ")
...

Sheet Debt
B1: ='Consol. Rev.'!B1 -> 1 | C1: THÔNG TIN KHOẢN VAY | R1: DỰ PHÓNG KHOẢN VAY
I2: Phân bổ cho các nhà máy | S2: 1 | T2: 2 | U2: 3 | V2: 4 | W2: 5 | X2: 6 | Y2: 7 | Z2: 8 | AA2: 9 | AB2: 10 | AC2: 11 | AD2: 12 | AE2: 13 | AF2: 14 | AG2: 15 | AH2: 16 | AI2: 17 | AJ2: 18 | AK2: 19 | AL2: 20 | AM2: 21 | AN2: 22 | AO2: 23 | AP2: 24 | AQ2: 25 | AR2: 26 | AS2: 27 | AT2: 28 | AU2: 29 | AV2: 30 | AW2: 31 | AX2: 32 | AY2: 33 | AZ2: 34 | BA2: 35 | BB2: 36 | BC2: 37 | BD2: 38 | BE2: 39 | BF2: 40
R3: =IF(TODAY()<R4,"Proj","") | S3: =IF(TODAY()<S4,"Proj","") | T3: =IF(TODAY()<T4,"Proj","") | U3: =IF(TODAY()<U4,"Proj","") | V3: =IF(TODAY()<V4,"Proj","") -> Proj | W3: =IF(TODAY()<W4,"Proj","") -> Proj | X3: =IF(TODAY()<X4,"Proj","") -> Proj | Y3: =IF(TODAY()<Y4,"Proj","") -> Proj | ... BF3: =IF(TODAY()<BF4,"Proj","") -> Proj
B4: Debt | C4: Gốc vay | D4: Thời điểm vay | E4: Kỳ hạn (tháng) | F4: Lãi suất năm | G4: Loại lãi suất | H4: Kỳ điều chỉnh | R4: 44561 | S4: =DATE(YEAR(R4),MONTH(R4)+13,0) -> 44926 | T4: =DATE(YEAR(S4),MONTH(S4)+13,0) -> 45291 | U4: =DATE(YEAR(T4),MONTH(T4)+13,0) -> 45657 | V4: =DATE(YEAR(U4),MONTH(U4)+13,0) -> 46022 | W4: =DATE(YEAR(V4),MONTH(V4)+13,0) -> 46387 | X4: =DATE(YEAR(W4),MONTH(W4)+13,0) -> 46752 | Y4: =DATE(YEAR(X4),MONTH(X4)+13,0) -> 47118 | Z4: =DATE(YEAR(Y4),MONTH(Y4)+13,0) -> 47483 | ... BF4: =DATE(YEAR(BE4),MONTH(BE4)+13,0) -> 59171 | BH4: Notes
B6: ƯỚC TÍNH LÃI SUẤT NGÂN HÀNG
B7: Tổng nợ vay ngân hàng ngắn và dài hạn | BH7: Chênh lệch nợ vay dài và ngắn hạn | BI7: 0.017
B8: Dư nợ gốc đầu năm | R8: =IF(ISTEXT('BS Raw'!O11),('BS Raw'!O92+'BS Raw'!O105)/Debt!$B$1,R17+R24) -> 82.820317 | S8: =IF(ISTEXT('BS Raw'!P11),('BS Raw'!P92+'BS Raw'!P105)/Debt!$B$1,S17+S24) -> 97.029471 | T8: =IF(ISTEXT('BS Raw'!Q11),('BS Raw'!Q92+'BS Raw'!Q105)/Debt!$B$1,T17+T24) -> 309.97534 | U8: =IF(ISTEXT('BS Raw'!R11),('BS Raw'!R92+'BS Raw'!R105)/Debt!$B$1,U17+U24) -> 403.5974 | V8: =IF(ISTEXT('BS Raw'!S11),('BS Raw'!S92+'BS Raw'!S105)/Debt!$B$1,V17+V24) -> 362.14911 | W8: =IF(ISTEXT('BS Raw'!T11),('BS Raw'!T92+'BS Raw'!T105)/Debt!$B$1,W17+W24) -> 280.75209 | X8: =IF(ISTEXT('BS Raw'!U11),('BS Raw'!U92+'BS Raw'!U105)/Debt!$B$1,X17+X24) -> 227.86493 | Y8: =IF(ISTEXT('BS Raw'!V11),('BS Raw'!V92+'BS Raw'!V105)/Debt!$B$1,Y17+Y24) -> 158.83839 | ... AB8: =IF(ISTEXT('BS Raw'!Y11),('BS Raw'!Y92+'BS Raw'!Y105)/Debt!$B$1,AB17+AB24) -> 149.81887
B9: + Trả nợ gốc hàng năm
B10: + Vay mới trong năm
B11: Dư nợ gốc cuối năm | R11: =IF(ISTEXT('BS Raw'!P11),('BS Raw'!P92+'BS Raw'!P105)/Debt!$B$1,R20+R27) -> 97.029471 | S11: =IF(ISTEXT('BS Raw'!Q11),('BS Raw'!Q92+'BS Raw'!Q105)/Debt!$B$1,S20+S27) -> 309.97534 | T11: =IF(ISTEXT('BS Raw'!R11),('BS Raw'!R92+'BS Raw'!R105)/Debt!$B$1,T20+T27) -> 403.5974 | U11: =IF(ISTEXT('BS Raw'!S11),('BS Raw'!S92+'BS Raw'!S105)/Debt!$B$1,U20+U27) -> 362.14911 | V11: =IF(ISTEXT('BS Raw'!T11),('BS Raw'!T92+'BS Raw'!T105)/Debt!$B$1,V20+V27) -> 280.75209 | W11: =IF(ISTEXT('BS Raw'!U11),('BS Raw'!U92+'BS Raw'!U105)/Debt!$B$1,W20+W27) -> 227.86493 | X11: =IF(ISTEXT('BS Raw'!V11),('BS Raw'!V92+'BS Raw'!V105)/Debt!$B$1,X20+X27) -> 158.83839 | Y11: =IF(ISTEXT('BS Raw'!W11),('BS Raw'!W92+'BS Raw'!W105)/Debt!$B$1,Y20+Y27) -> 139.60407 | ... AB11: =IF(ISTEXT('BS Raw'!Z11),('BS Raw'!Z92+'BS Raw'!Z105)/Debt!$B$1,AB20+AB27) -> 158.88218
B12: + Lãi vay hàng năm | R12: =Notes!P158/Debt!$B$1 -> 1.3245274
B13: + Lãi suất chung ước tính | R13: =IFERROR(R12/AVERAGE(R8,R11),0) + 0.04 -> 0.054729262 | S13: =IF(S12="",R13,S12/AVERAGE(S8,S11)) -> 0.054729262 | T13: =IF(T12="",S13,T12/AVERAGE(T8,T11)) -> 0.054729262 | U13: =IF(U12="",T13,U12/AVERAGE(U8,U11)) -> 0.054729262 | V13: =IF(V12="",U13,V12/AVERAGE(V8,V11)) -> 0.054729262 | W13: =IF(W12="",V13,W12/AVERAGE(W8,W11)) -> 0.054729262 | X13: =IF(X12="",W13,X12/AVERAGE(X8,X11)) -> 0.054729262 | Y13: =IF(Y12="",X13,Y12/AVERAGE(Y8,Y11)) -> 0.054729262 | Z13: =IF(Z12="",Y13,Z12/AVERAGE(Z8,Z11)) -> 0.054729262 | ... AB13: =IF(AB12="",AA13,AB12/AVERAGE(AB8,AB11)) -> 0.054729262
B15: TỔNG HỢP NỢ VAY
A16: 1 | B16: Vay ngắn hạn ngân hàng
B17: Dư nợ gốc đầu năm | R17: =R43 -> 20.094669 | S17: =S43 -> 21.029471 | T17: =T43 -> 72.647504 | U17: =U43 -> 76.070303 | V17: =V43 -> 94.961282 | W17: =W43 -> 101.3354 | X17: =X43 -> 107.52302 | Y17: =Y43 -> 113.31187 | ... AB17: =AB43 -> 146.63039
B18: + Trả nợ gốc hàng năm
B19: + Vay mới trong năm
B20: Dư nợ gốc cuối năm | R20: =R46 -> 21.029471 | S20: =S46 -> 72.647504 | T20: =T46 -> 76.070303 | U20: =U46 -> 94.961282 | V20: =V46 -> 101.3354 | W20: =W46 -> 107.52302 | X20: =X46 -> 113.31187 | Y20: =Y46 -> 121.16784 | ... AB20: =AB46 -> 158.88218
B21: + Lãi vay hàng năm | R21: =+R48 -> 0.85572041 | S21: =+S48 -> 1.9504489 | T21: =+T48 -> 3.0689617 | U21: =+U48 -> 3.5511509 | V21: =+V48 -> 4.2125134 | W21: =+W48 -> 4.6690446 | X21: =+X48 -> 5.2379232 | Y21: =+Y48 -> 5.9892905 | ... AB21: =+AB48 -> 8.3334165
A23: 2 | B23: Vay dài hạn ngân hàng
B24: Dư nợ gốc đầu năm | R24: =R54 -> 62.725648 | S24: =+S54+S110+S163+S178+S189+S204+S215+S226+S237+S248+S259 -> 76 | T24: =+T54+T110+T163+T178+T189+T204+T215+T226+T237+T248+T259 -> 237.32784 | U24: =+U54+U110+U163+U178+U189+U204+U215+U226+U237+U248+U259 -> 327.5271 | V24: =+V54+V110+V163+V178+V189+V204+V215+V226+V237+V248+V259 -> 267.18783 | W24: =+W54+W110+W163+W178+W189+W204+W215+W226+W237+W248+W259 -> 179.41668 | X24: =+X54+X110+X163+X178+X189+X204+X215+X226+X237+X248+X259 -> 120.34192 | Y24: =+Y54+Y110+Y163+Y178+Y189+Y204+Y215+Y226+Y237+Y248+Y259 -> 45.526526 | Z24: =+Z54+Z110+Z163+Z178+Z189+Z204+Z215+Z226+Z237+Z248+Z259 -> 18.436234 | ... AB24: =+AB54+AB110+AB163+AB178+AB189+AB204+AB215+AB226+AB237+AB248+AB259 -> 3.1884857
B25: + Trả nợ gốc hàng năm | S25: =+S55+S112+S165+S180+S191+S206+S217+S228+S239+S250+S261 -> 51.332112 | T25: =+T55+T112+T165+T180+T191+T206+T217+T228+T239+T250+T261 -> 82.783529 | U25: =+U55+U112+U165+U180+U191+U206+U217+U228+U239+U250+U261 -> 87.771141 | V25: =+V55+V112+V165+V180+V191+V206+V217+V228+V239+V250+V261 -> 87.771141 | W25: =+W55+W112+W165+W180+W191+W206+W217+W228+W239+W250+W261 -> 94.148112 | X25: =+X55+X112+X165+X180+X191+X206+X217+X228+X239+X250+X261 -> 74.815389 | Y25: =+Y55+Y112+Y165+Y180+Y191+Y206+Y217+Y228+Y239+Y250+Y261 -> 27.090292 | Z25: =+Z55+Z112+Z165+Z180+Z191+Z206+Z217+Z228+Z239+Z250+Z261 -> 8.8707774 | ... AB25: =+AB55+AB112+AB165+AB180+AB191+AB206+AB217+AB228+AB239+AB250+AB261 -> 3.1884857
B26: + Vay mới trong năm | S26: =+S56+S111+S164+S179+S190+S205+S216+S227+S238+S249+S260 -> 193.32723 | T26: =+T56+T111+T164+T179+T190+T205+T216+T227+T238+T249+T260 -> 157.25708 | U26: =+U56+U111+U164+U179+U190+U205+U216+U227+U238+U249+U260 -> 24.938059 | V26: =+V56+V111+V164+V179+V190+V205+V216+V227+V238+V249+V260 -> 0 | W26: =+W56+W111+W164+W179+W190+W205+W216+W227+W238+W249+W260 -> 31.884857 | X26: =+X56+X111+X164+X179+X190+X205+X216+X227+X238+X249+X260 -> 0 | Y26: =+Y56+Y111+Y164+Y179+Y190+Y205+Y216+Y227+Y238+Y249+Y260 -> 0 | Z26: =+Z56+Z111+Z164+Z179+Z190+Z205+Z216+Z227+Z238+Z249+Z260 -> 0 | ... AB26: =+AB56+AB111+AB164+AB179+AB190+AB205+AB216+AB227+AB238+AB249+AB260 -> 0
B27: Dư nợ gốc cuối năm | R27: =R57 -> 76 | S27: =+S57+S113+S166+S181+S192+S207+S218+S229+S240+S251+S262 -> 237.32784 | T27: =+T57+T113+T166+T181+T192+T207+T218+T229+T240+T251+T262 -> 327.5271 | U27: =+U57+U113+U166+U181+U192+U207+U218+U229+U240+U251+U262 -> 267.18783 | V27: =+V57+V113+V166+V181+V192+V207+V218+V229+V240+V251+V262 -> 179.41668 | W27: =+W57+W113+W166+W181+W192+W207+W218+W229+W240+W251+W262 -> 120.34192 | X27: =+X57+X113+X166+X181+X192+X207+X218+X229+X240+X251+X262 -> 45.526526 | Y27: =+Y57+Y113+Y166+Y181+Y192+Y207+Y218+Y229+Y240+Y251+Y262 -> 18.436234 | Z27: =+Z57+Z113+Z166+Z181+Z192+Z207+Z218+Z229+Z240+Z251+Z262 -> 9.5654571 | ... AB27: =+AB57+AB113+AB166+AB181+AB192+AB207+AB218+AB229+AB240+AB251+AB262 -> 0
B28: + Lãi vay hàng năm | R28: =+R59+R115+R168+R183+R194+R209+R220+R231+R242+R253+R264 -> 4.8553977 | S28: =+S59+S115+S168+S183+S194+S209+S220+S231+S242+S253+S264 -> 10.966474 | T28: =+T59+T115+T168+T183+T194+T209+T220+T231+T242+T253+T264 -> 19.769923 | U28: =+U59+U115+U168+U183+U194+U209+U220+U231+U242+U253+U264 -> 20.815022 | V28: =+V59+V115+V168+V183+V194+V209+V220+V231+V242+V253+V264 -> 15.631158 | W28: =+W59+W115+W168+W183+W194+W209+W220+W231+W242+W253+W264 -> 10.491551 | X28: =+X59+X115+X168+X183+X194+X209+X220+X231+X242+X253+X264 -> 5.8053955 | Y28: =+Y59+Y115+Y168+Y183+Y194+Y209+Y220+Y231+Y242+Y253+Y264 -> 2.2386966 | ... AB28: =+AB59+AB115+AB168+AB183+AB194+AB209+AB220+AB231+AB242+AB253+AB264 -> 0.111597
A30: 3 | B30: Vay dài hạn trái phiếu
B31: Dư nợ gốc đầu năm
B32: + Trả nợ gốc hàng năm
B33: + Vay mới trong năm
B34: Dư nợ gốc cuối năm
B35: + Lãi vay hàng năm
B38: CHI TIẾT NỢ VAY HIỆN HỮU
A39: 1 | B39: Vay ngắn hạn Ngân hàng
A41: 1.1 | B41: Ngân hàng 1
B42: Khoản 1 | D42: 44531 | E42: 12 | G42: floating | H42: 0.5
B43: Dư nợ gốc đầu năm | R43: ='BS Raw'!O92/B1 -> 20.094669 | S43: =R46 -> 21.029471 | T43: =S46 -> 72.647504 | U43: =T46 -> 76.070303 | V43: =U46 -> 94.961282 | W43: =V46 -> 101.3354 | X43: =W46 -> 107.52302 | Y43: =X46 -> 113.31187 | Z43: =Y46 -> 121.16784 | ... AB43: =AA46 -> 146.63039
B44: + Trả nợ gốc hàng năm
B45: + Vay mới trong năm
B46: Dư nợ gốc cuối năm | R46: ='BS Raw'!P92/Debt!$B$1 -> 21.029471 | S46: =Input!Q279 -> 72.647504 | T46: =Input!R279 -> 76.070303 | U46: =Input!S279 -> 94.961282 | V46: =Input!T279 -> 101.3354 | W46: =Input!U279 -> 107.52302 | X46: =Input!V279 -> 113.31187 | Y46: =Input!W279 -> 121.16784 | Z46: =Input!X279 -> 139.32054 | ... AB46: =Input!Z279 -> 158.88218
B47: + Lãi suất | R47: =IF($F$42,$F$42,IFERROR(R13-$BI$7*AVERAGE(R24,R27)/AVERAGE(R8,R11),0)) -> 0.041616453 | S47: =IF(S12="",S13-$BI$7*AVERAGE(S24,S27)/AVERAGE(S8,S11),R47) -> 0.041642014 | T47: =IF(T12="",T13-$BI$7*AVERAGE(T24,T27)/AVERAGE(T8,T11),S47) -> 0.041272283 | U47: =IF(U12="",U13-$BI$7*AVERAGE(U24,U27)/AVERAGE(U8,U11),T47) -> 0.041526259 | V47: =IF(V12="",V13-$BI$7*AVERAGE(V24,V27)/AVERAGE(V8,V11),U47) -> 0.042919863 | W47: =IF(W12="",W13-$BI$7*AVERAGE(W24,W27)/AVERAGE(W8,W11),V47) -> 0.04471014 | X47: =IF(X12="",X13-$BI$7*AVERAGE(X24,X27)/AVERAGE(X8,X11),W47) -> 0.047437462 | Y47: =IF(Y12="",Y13-$BI$7*AVERAGE(Y24,Y27)/AVERAGE(Y8,Y11),X47) -> 0.05108579 | Z47: =IF(Z12="",Z13-$BI$7*AVERAGE(Z24,Z27)/AVERAGE(Z8,Z11),Y47) -> 0.053079193 | ... AB47: =IF(AB12="",AB13-$BI$7*AVERAGE(AB24,AB27)/AVERAGE(AB8,AB11),AA47) -> 0.054553674 | BH47: Lãi suất ước tính dựa vào: (1) CP lãi vay trong kỳ, (2) tổng dư nợ đầu, cuối kỳ và (3) chênh lệch thực tế giữa lãi suất ngắn hạn và dài hạn
B48: + Lãi vay hàng năm | R48: =R47*AVERAGE(R43,R46) -> 0.85572041 | S48: =S47*AVERAGE(S43,S46) -> 1.9504489 | T48: =T47*AVERAGE(T43,T46) -> 3.0689617 | U48: =U47*AVERAGE(U43,U46) -> 3.5511509 | V48: =V47*AVERAGE(V43,V46) -> 4.2125134 | W48: =W47*AVERAGE(W43,W46) -> 4.6690446 | X48: =X47*AVERAGE(X43,X46) -> 5.2379232 | Y48: =Y47*AVERAGE(Y43,Y46) -> 5.9892905 | ... AB48: =AB47*AVERAGE(AB43,AB46) -> 8.3334165
A50: 2 | B50: Vay dài hạn Ngân hàng
A52: 2.1 | B52: Ngân hàng 1 | C52: Khoản vay dài hạn từ quỹ đầu tư phát triển Bình Định hết hạn vào năm 2027, các thông tin khoản vay coi trong thuyết minh BCTC 2020
B53: Khoản 1/ long-term debt A | C53: ='BS Raw'!P105/$B$1 -> 76 | D53: 44553 | E53: 72 | F53: 0.07 | G53: floating | H53: 0.5 | BH53: Chú thích: Long-term debt A là toàn bộ nợ dài hạn cuối 2021 của công ty
B54: Dư nợ gốc đầu năm | R54: ='BS Raw'!O105/Debt!$B$1 -> 62.725648 | S54: =R57 -> 76 | T54: =S57 -> 63.333333 | U54: =T57 -> 50.666667 | V54: =U57 -> 38 | W54: =V57 -> 25.333333 | X54: =W57 -> 12.666667 | Y54: =X57 -> 0 | Z54: =Y57 -> 0 | ... AB54: =AA57 -> 0
B55: + Trả nợ gốc hàng năm | S55: =C53/(E53/12) -> 12.666667 | T55: =MIN(S55,S57) -> 12.666667 | U55: =MIN(T55,T57) -> 12.666667 | V55: =MIN(U55,U57) -> 12.666667 | W55: =MIN(V55,V57) -> 12.666667 | X55: =MIN(W55,W57) -> 12.666667 | Y55: =MIN(X55,X57) -> 0 | Z55: =MIN(Y55,Y57) -> 0 | AA55: =MIN(Z55,Z57) -> 0 | AB55: =MIN(AA55,AA57) -> 0
B56: + Vay mới trong năm
B57: Dư nợ gốc cuối năm | R57: ='BS Raw'!P105/Debt!$B$1 -> 76 | S57: =S54-S55 -> 63.333333 | T57: =T54-T55 -> 50.666667 | U57: =U54-U55 -> 38 | V57: =V54-V55 -> 25.333333 | W57: =W54-W55 -> 12.666667 | X57: =X54-X55 -> 0 | Y57: =Y54-Y55 -> 0 | Z57: =Z54-Z55 -> 0 | ... AB57: =AB54-AB55 -> 0
B58: + Lãi suất | R58: =IF($F$53="",R47+$BI$7,$F$53) -> 0.07 | S58: =IF($F$53="",S47+$BI$7,$F$53) -> 0.07 | T58: =IF($F$53="",T47+$BI$7,$F$53) -> 0.07 | U58: =IF($F$53="",U47+$BI$7,$F$53) -> 0.07 | V58: =IF($F$53="",V47+$BI$7,$F$53) -> 0.07 | W58: =IF($F$53="",W47+$BI$7,$F$53) -> 0.07 | X58: =IF($F$53="",X47+$BI$7,$F$53) -> 0.07 | Y58: =IF($F$53="",Y47+$BI$7,$F$53) -> 0.07 | ... AB58: =IF($F$53="",AB47+$BI$7,$F$53) -> 0.07 | BH58: Lãi suất ước tính dựa vào: (1) CP lãi vay trong kỳ, (2) tổng dư nợ đầu, cuối kỳ và (3) chênh lệch thực tế giữa lãi suất ngắn hạn và dài hạn
B59: + Lãi vay hàng năm | R59: =R58*AVERAGE(R54,R57) -> 4.8553977 | S59: =S58*AVERAGE(S54,S57) -> 4.8766667 | T59: =T58*AVERAGE(T54,T57) -> 3.99 | U59: =U58*AVERAGE(U54,U57) -> 3.1033333 | V59: =V58*AVERAGE(V54,V57) -> 2.2166667 | W59: =W58*AVERAGE(W54,W57) -> 1.33 | X59: =X58*AVERAGE(X54,X57) -> 0.44333333 | Y59: =Y58*AVERAGE(Y54,Y57) -> 0 | ... AB59: =AB58*AVERAGE(AB54,AB57) -> 0
A61: 2.2 | B61: Ngân hàng 2
B62: Khoản 1
B63: Dư nợ gốc đầu năm
B64: + Trả nợ gốc hàng năm
B65: + Vay mới trong năm
B66: Dư nợ gốc cuối năm
B67: + Lãi vay hàng năm
B69: Khoản 2
B70: Dư nợ gốc đầu năm
B71: + Trả nợ gốc hàng năm
B72: + Vay mới trong năm
B73: Dư nợ gốc cuối năm
B74: + Lãi vay hàng năm
A76: 2.3 | B76: Vay cá nhân (vi)
B77: Nguyễn Văn A
A83: 2.4 | B83: Trái phiếu phát hành (vii)
B84: Đợt 1
B90: Đợt 2
B99: CHI TIẾT NỢ VAY MỚI
A100: 1 | B100: Vay dài hạn Ngân hàng năm 2022
C101: Tổng doanh thu xưởng (8) giả định | D101: =AVERAGE('Mảng dược phẩm'!T228+'Mảng dược phẩm'!V228)/'Mảng dược phẩm'!V243*'Mảng dược phẩm'!V242*'Mảng dược phẩm'!T92/1000 -> 4.7395027 | E101: Xưởng (8) (9) dự kiến hoàn thành đi vào sản xuất từ 2021 rồi | R101: Xưởng (11) và (12) dự kiến hoạt động vào 2024 như vậy thời điểm bắt đầu vay dài hạn để xây dựng nhà máy là 70% trong 2022, 30% trong 2023
C102: Tổng doanh thu xưởng (9) giả định | D102: =AVERAGE('Mảng dược phẩm'!T229+'Mảng dược phẩm'!V229)/'Mảng dược phẩm'!V243*'Mảng dược phẩm'!V242*'Mảng dược phẩm'!T93/1000 -> 885.36975 | R102: Tổng vay xưởng (11) và (12) | U102: =65.7%*350 -> 229.95
C103: Tổng doanh thu xưởng (10) giả định | D103: =AVERAGE('Mảng dược phẩm'!T230+'Mảng dược phẩm'!W230)/'Mảng dược phẩm'!W243*'Mảng dược phẩm'!W242*'Mảng dược phẩm'!T94/1000 -> 100.84772 | R103: Vốn chủ tài trợ xưởng (10) | U103: =0.4*530*D104 -> 21.574818
C104: Tỷ trọng khoản vay phân bổ cho xưởng (10) | D104: =D103/SUM(D101:D103) -> 0.10176801 | R104: Vốn chủ tài trợ xưởng (11),(12) trong 2022 | U104: =34.3%*350*0.7 -> 84.035
C105: Tổng vay cả 3 xưởng (8), (9), (10) | D105: =0.6*530 -> 318 | R105: Tổng tiền DBD phải có để tài trợ 2022 | U105: =U103+U104 -> 105.60982
Q107: =C109+U105 -> 298.93705
A108: 1.1 | B108: Ngân hàng 1
B109: Khoản 1/ long-term debt B | C109: =D104*D105+U102*0.7 -> 193.32723 | D109: 44713 | E109: 60 | F109: =R58 -> 0.07 | G109: floating | H109: 0.5 | BH109: Chi tiết các khoản vay mới dài hạn để tài trợ các dự án xây mới và mở rộng nhà máy sản xuất được ước lượng dựa vào thông tin dưới đây, lấy trong bản cáo bạch niêm yết HSX 2018
B110: Dư nợ gốc đầu năm | R110: ='BS Raw'!L153/Debt!$B$1 -> 0 | S110: 0 | T110: =S113 -> 173.9945 | U110: =T113 -> 135.32906 | V110: =U113 -> 96.663614 | W110: =V113 -> 57.998168 | X110: =W113 -> 19.332723 | Y110: =X113 -> 0 | Z110: =Y113 -> 0 | AA110: =Z113 -> 0 | AB110: =AA113 -> 0
B111: + Vay mới trong năm | S111: =IF(YEAR($D$109)=YEAR(S4),$C$109,0) -> 193.32723 | T111: 0 | U111: =IF(YEAR($D$109)=YEAR(U4),$C$109,0) -> 0 | V111: =IF(YEAR($D$109)=YEAR(V4),$C$109,0) -> 0 | W111: =IF(YEAR($D$109)=YEAR(W4),$C$109,0) -> 0 | X111: =IF(YEAR($D$109)=YEAR(X4),$C$109,0) -> 0 | Y111: =IF(YEAR($D$109)=YEAR(Y4),$C$109,0) -> 0 | Z111: =IF(YEAR($D$109)=YEAR(Z4),$C$109,0) -> 0 | AA111: =IF(YEAR($D$109)=YEAR(AA4),$C$109,0) -> 0 | AB111: =IF(YEAR($D$109)=YEAR(AB4),$C$109,0) -> 0
B112: + Trả nợ gốc hàng năm | S112: =IF($C109=S111,$C109/($E109/12),MIN(R113,R112)) -> 38.665445 | T112: =IF($C109=T111,$C109/($E109/12),MIN(S113,S112)) -> 38.665445 | U112: =IF($C109=U111,$C109/($E109/12),MIN(T113,T112)) -> 38.665445 | V112: =IF($C109=V111,$C109/($E109/12),MIN(U113,U112)) -> 38.665445 | W112: =IF($C109=W111,$C109/($E109/12),MIN(V113,V112)) -> 38.665445 | X112: =IF($C109=X111,$C109/($E109/12),MIN(W113,W112)) -> 19.332723 | Y112: =IF($C109=Y111,$C109/($E109/12),MIN(X113,X112)) -> 0 | Z112: =IF($C109=Z111,$C109/($E109/12),MIN(Y113,Y112)) -> 0 | ... AB112: =IF($C109=AB111,$C109/($E109/12),MIN(AA113,AA112)) -> 0
B113: Dư nợ gốc cuối năm | R113: ='BS Raw'!M153/Debt!$B$1 -> 0 | S113: =S110+S111-S112*0.5 -> 173.9945 | T113: =T110+T111-T112 -> 135.32906 | U113: =U110+U111-U112 -> 96.663614 | V113: =V110+V111-V112 -> 57.998168 | W113: =W110+W111-W112 -> 19.332723 | X113: =X110+X111-X112 -> 0 | Y113: =Y110+Y111-Y112 -> 0 | Z113: =Z110+Z111-Z112 -> 0 | AA113: =AA110+AA111-AA112 -> 0 | AB113: =AB110+AB111-AB112 -> 0
B114: + Lãi suất | R114: =F109 -> 0.07 | S114: =R114 -> 0.07 | T114: =S114 -> 0.07 | U114: =T114 -> 0.07 | V114: =U114 -> 0.07 | W114: =V114 -> 0.07 | X114: =W114 -> 0.07 | Y114: =X114 -> 0.07 | Z114: =Y114 -> 0.07 | ... AB114: =AA114 -> 0.07
B115: + Lãi vay hàng năm | R115: =R114*AVERAGE(R110,R113) -> 0 | S115: =S114*AVERAGE(S110,S113) -> 6.0898077 | T115: =T114*AVERAGE(T110,T113) -> 10.826325 | U115: =U114*AVERAGE(U110,U113) -> 8.1197435 | V115: =V114*AVERAGE(V110,V113) -> 5.4131624 | W115: =W114*AVERAGE(W110,W113) -> 2.7065812 | X115: =X114*AVERAGE(X110,X113) -> 0.6766453 | Y115: =Y114*AVERAGE(Y110,Y113) -> 0 | ... AB115: =AB114*AVERAGE(AB110,AB113) -> 0
X116: =AVERAGE(X110,X113) -> 9.6663614
A117: 1.2 | B117: Ngân hàng 2
B118: Khoản 1
B119: Dư nợ gốc đầu năm
B120: + Trả nợ gốc hàng năm
B121: + Vay mới trong năm
B122: Dư nợ gốc cuối năm
B123: + Lãi vay hàng năm
B125: Khoản 2
B126: Dư nợ gốc đầu năm
B127: + Trả nợ gốc hàng năm
B128: + Vay mới trong năm
B129: Dư nợ gốc cuối năm
B130: + Lãi vay hàng năm
A132: 1.3 | B132: Vay cá nhân (vi)
B133: Nguyễn Văn A
...

Sheet LT. Asset
B1: =1 -> 1 | N1: 1 | O1: 2 | P1: 3 | Q1: 1 | R1: 2 | S1: 3 | T1: 4 | U1: 5 | V1: 6 | W1: 7 | X1: 8 | Y1: 9 | Z1: 10 | AA1: 11 | AB1: 12 | AC1: 13 | AD1: 14 | AE1: 15 | AF1: 16 | AG1: 17 | AH1: 18 | AI1: 19 | AJ1: 1 | AK1: 2 | AL1: 3 | AM1: 4 | AN1: 5 | AO1: 6 | AP1: 7 | AQ1: 8 | AR1: 9 | AS1: 10 | AT1: 11 | AU1: 12 | AV1: 13 | AW1: 14 | AX1: 15 | AY1: 16 | AZ1: 17 | BA1: 18
E2: =IF(TODAY()<E3,"Proj","") | F2: =IF(TODAY()<F3,"Proj","") | H2: =IF(TODAY()<H3,"Proj","") | I2: =IF(TODAY()<I3,"Proj","") | J2: =IF(TODAY()<J3,"Proj","") | K2: =IF(TODAY()<K3,"Proj","") | L2: =IF(TODAY()<L3,"Proj","") | M2: =IF(TODAY()<M3,"Proj","") | N2: =IF(TODAY()<N3,"Proj","") | O2: =IF(TODAY()<O3,"Proj","") | ... BA2: =IF(TODAY()<BA3,"Proj","") -> Proj
B3: Fixed Assets | D3: 40178 | E3: =DATE(YEAR(D3),MONTH(D3)+13,0) -> 40543 | F3: =DATE(YEAR(E3),MONTH(E3)+13,0) -> 40908 | G3: =DATE(YEAR(F3),MONTH(F3)+13,0) -> 41274 | H3: =DATE(YEAR(G3),MONTH(G3)+13,0) -> 41639 | I3: =DATE(YEAR(H3),MONTH(H3)+13,0) -> 42004 | J3: =DATE(YEAR(I3),MONTH(I3)+13,0) -> 42369 | K3: =DATE(YEAR(J3),MONTH(J3)+13,0) -> 42735 | L3: =DATE(YEAR(K3),MONTH(K3)+13,0) -> 43100 | ... BA3: =DATE(YEAR(AZ3),MONTH(AZ3)+13,0) -> 58075
B5: TỔNG HỢP CÁC LOẠI TÀI SẢN CỐ ĐỊNH (1+2+3)
B6: Nguyên giá cuối kỳ | J6: =SUM(J28,J63,J96,J130) -> 348.55 | K6: =SUM(K28,K63,K96,K130) -> 445.34392 | L6: =SUM(L28,L63,L96,L130) -> 502.61943 | M6: =SUM(M28,M63,M96,M130) -> 518.42094 | N6: =SUM(N28,N63,N96,N130) -> 565.98338 | O6: =SUM(O28,O63,O96,O130) -> 612.19179 | P6: =SUM(P28,P63,P96,P130) -> 651.28063 | Q6: =SUM(Q28,Q63,Q96,Q130) -> 1073.2836 | ... Z6: =SUM(Z28,Z63,Z96,Z130) -> 2115.538
B7: GTCL cuối kỳ | J7: =SUM(J41,J75,J108,J142) -> 168.26 | K7: =SUM(K41,K75,K108,K142) -> 235.76472 | L7: =SUM(L41,L75,L108,L142) -> 246.92609 | M7: =SUM(M41,M75,M108,M142) -> 218.86286 | N7: =SUM(N41,N75,N108,N142) -> 236.6689 | O7: =SUM(O41,O75,O108,O142) -> 248.62256 | P7: =SUM(P41,P75,P108,P142) -> 247.08426 | Q7: =SUM(Q41,Q75,Q108,Q142) -> 567.37435 | ... Z7: =SUM(Z41,Z75,Z108,Z142) -> 510.10073
B8: Khấu hao trong kỳ | J8: =SUM(J37,J71,J104,J138) -> 142.03 | K8: =SUM(K37,K71,K104,K138) -> 38.099248 | L8: =SUM(L37,L71,L104,L138) -> 47.031054 | M8: =SUM(M37,M71,M104,M138) -> 46.842924 | N8: =SUM(N37,N71,N104,N138) -> 33.407823 | O8: =SUM(O37,O71,O104,O138) -> 37.507422 | P8: =SUM(P37,P71,P104,P138) -> 61.166782 | Q8: =SUM(Q37,Q71,Q104,Q138) -> 101.71289 | ... AA8: =SUM(AA37,AA71,AA104,AA138) -> 0
B9: Capex | J9: =(J26+J27)+(J61+J62)+(J94+J95)+(J128)+(J216-J215) -> 192.30337 | K9: =(K26+K27)+(K61+K62)+(K94+K95)+(K128)+(K216-K215) -> 106.48068 | L9: =(L26+L27)+(L61+L62)+(L94+L95)+(L128)+(L216-L215) -> 37.438634 | M9: =(M26+M27)+(M61+M62)+(M94+M95)+(M128)+(M216-M215) -> 29.663251 | N9: =(N26+N27)+(N61+N62)+(N94+N95)+(N128)+(N216-N215) -> 187.1913 | O9: =(O26+O27)+(O61+O62)+(O94+O95)+(O128)+(O216-O215) -> 52.020841 | P9: =(P26+P27)+(P61+P62)+(P94+P95)+(P128)+(P216-P215) -> 28.101864 | Q9: =Q10*Input!Q45 -> 451.02885 | R9: =R10*Input!R45 -> 354.6325 | S9: =S10*Input!S45 -> 79.482835 | T9: =T10*Input!T45 -> 89.864941 | U9: =U10*Input!U45 -> 91.651436 | V9: =V10*Input!V45 -> 98.591713 | W9: =W10*Input!W45 -> 107.61073 | X9: =X10*Input!X45 -> 93.298141 | ... Z9: =Z10*Input!Z45 -> 101.56086
B10: As % EBIT | J10: =J9/Input!J47 -> 1.5038148 | K10: =K9/Input!K47 -> 0.6738902 | L10: =L9/Input!L47 -> 0.20027287 | M10: =M9/Input!M47 -> 0.15900372 | N10: =N9/Input!N47 -> 1.1644903 | O10: =O9/Input!O47 -> 0.28616988 | P10: =P9/Input!P47 -> 0.12942503 | Q10: 1.65 | R10: 1.3 | S10: 0.2 | T10: 0.2 | U10: 0.18 | V10: 0.18 | W10: 0.18 | X10: 0.15 | Y10: 0.15 | Z10: 0.15
G11: Cứ 4 năm thì capex/ebit sẽ tăng mạnh sau đó giảm dần, như vậy có nên áp dụng việc này vào dự phóng %ebit ko hay là tăng 80% năm 2022 sau đó giảm còn 40% các năm còn lại
B12: Trong đó: Capex duy trì
B13: Capex TSCĐ hữu hình | J13: =(J26+J27)/J9 -> 1.025879 | K13: =(K26+K27)/K9 -> 0.79302496 | L13: =(L26+L27)/L9 -> 1.5123061 | M13: =(M26+M27)/M9 -> 0.52258267 | N13: =(N26+N27)/N9 -> 0.21924852 | O13: =(O26+O27)/O9 -> 0.74582944 | P13: =(P26+P27)/P9 -> 1.3572184 | Q13: =AVERAGE(J13:P13) -> 0.88229845 | R13: =Q13 -> 0.88229845 | S13: =R13 -> 0.88229845 | T13: =S13 -> 0.88229845 | U13: =T13 -> 0.88229845 | V13: =U13 -> 0.88229845 | W13: =V13 -> 0.88229845 | X13: =W13 -> 0.88229845 | Y13: =X13 -> 0.88229845 | ... AA13: =Z13 -> 0.88229845
B14: Capex TSCĐ thuê tài chính | J14: =(J61+J62)/J9 -> 0 | K14: =(K61+K62)/K9 -> 0 | L14: =(L61+L62)/L9 -> 0 | M14: =(M61+M62)/M9 -> 0 | N14: =(N61+N62)/N9 -> 0 | O14: =(O61+O62)/O9 -> 0 | P14: =(P61+P62)/P9 -> 0 | Q14: 0 | R14: =Q14 -> 0 | S14: =R14 -> 0 | T14: =S14 -> 0 | U14: =T14 -> 0 | V14: =U14 -> 0 | W14: =V14 -> 0 | X14: =W14 -> 0 | Y14: =X14 -> 0 | ... BA14: =AZ14 -> 0
B15: Capex TSCĐ vô hình | J15: =(J94+J95)/J9 -> 0.018720421 | K15: =(K94+K95)/K9 -> 0.11598204 | L15: =(L94+L95)/L9 -> 0.017544297 | M15: =(M94+M95)/M9 -> 0.010113524 | N15: =(N94+N95)/N9 -> 0.034818692 | O15: =(O94+O95)/O9 -> 0.14237188 | P15: =(P94+P95)/P9 -> 0.0338764 | Q15: =AVERAGE(J15:P15) -> 0.053346751 | R15: =Q15 -> 0.053346751 | S15: =R15 -> 0.053346751 | T15: =S15 -> 0.053346751 | U15: =T15 -> 0.053346751 | V15: =U15 -> 0.053346751 | W15: =V15 -> 0.053346751 | X15: =W15 -> 0.053346751 | Y15: =X15 -> 0.053346751 | Z15: =Y15 -> 0.053346751
B16: Capex BĐS đầu tư | J16: =J128/J9 -> 0 | K16: =K128/K9 -> 0 | L16: =L128/L9 -> 0 | M16: =M128/M9 -> 0 | N16: =N128/N9 -> 0 | O16: =O128/O9 -> 0 | P16: =P128/P9 -> 0 | Q16: =0 -> 0 | R16: =Q16 -> 0 | S16: =R16 -> 0 | T16: =S16 -> 0 | U16: =T16 -> 0 | V16: =U16 -> 0 | W16: =V16 -> 0 | X16: =W16 -> 0 | Y16: =X16 -> 0 | Z16: =Y16 -> 0
B17: Capex TS dở dang | J17: =(J216-J215)/J9 -> -0.044599465 | K17: =(K216-K215)/K9 -> 0.090993004 | L17: =(L216-L215)/L9 -> -0.52985043 | M17: =(M216-M215)/M9 -> 0.46730381 | N17: =(N216-N215)/N9 -> 0.74593278 | O17: =(O216-O215)/O9 -> 0.11179867 | P17: =(P216-P215)/P9 -> -0.39109479 | Q17: =AVERAGE(J17:P17) -> 0.064354797 | R17: =Q17 -> 0.064354797 | S17: =R17 -> 0.064354797 | T17: =S17 -> 0.064354797 | U17: =T17 -> 0.064354797 | V17: =U17 -> 0.064354797 | W17: =V17 -> 0.064354797 | X17: =W17 -> 0.064354797 | Y17: =X17 -> 0.064354797 | ... AA17: =Z17 -> 0.064354797
B19: CHI TIẾT CÁC LOẠI TSCĐ
B21: 1. TÀI SẢN CỐ ĐỊNH HỮU HÌNH
B22: Nguyên giá
B23: Số dư đầu kỳ | J23: =Notes!J53 -> 107.19 | K23: =Notes!K53 -> 304.47471 | L23: =Notes!L53 -> 388.91655 | M23: =Notes!M53 -> 445.53522 | N23: =Notes!N53 -> 461.04 | O23: =Notes!O53 -> 502.08484 | P23: =Notes!P53 -> 540.88 | Q23: =P28 -> 579.02037 | R23: =Q28 -> 976.96243 | S23: =R28 -> 1289.8541 | T23: =S28 -> 1359.9817 | U23: =T28 -> 1439.2694 | V23: =U28 -> 1520.1333 | W23: =V28 -> 1607.1206 | X23: =W28 -> 1702.0654 | ... Z23: =Y28 -> 1870.1846
B24: Tăng trong kỳ (FC) | Q24: =Q9*Q13 -> 397.94206 | R24: =R9*R13 -> 312.8917 | S24: =S9*S13 -> 70.127582 | T24: =T9*T13 -> 79.287698 | U24: =U9*U13 -> 80.86392 | V24: =V9*V13 -> 86.987316 | W24: =W9*W13 -> 94.944784 | X24: =X9*X13 -> 82.316805 | ... Z24: =Z9*Z13 -> 89.606986
B25: Giảm trong kỳ (FC)
B26: Tăng trong kỳ | J26: =IF(ISTEXT(Notes!J11),Notes!J54,'LT. Asset'!J24) -> 199 | K26: =IF(ISTEXT(Notes!K11),Notes!K54,'LT. Asset'!K24) -> 84.781571 | L26: =IF(ISTEXT(Notes!L11),Notes!L54,'LT. Asset'!L24) -> 57.535595 | M26: =IF(ISTEXT(Notes!M11),Notes!M54,'LT. Asset'!M24) -> 18.478405 | N26: =IF(ISTEXT(Notes!N11),Notes!N54,'LT. Asset'!N24) -> 43.991416 | O26: =IF(ISTEXT(Notes!O11),Notes!O54,'LT. Asset'!O24) -> 42.051354 | P26: =IF(ISTEXT(Notes!P11),Notes!P54,'LT. Asset'!P24) -> 64.841582 | Q26: =Q24 -> 397.94206 | R26: =R24 -> 312.8917 | S26: =S24 -> 70.127582 | T26: =T24 -> 79.287698 | U26: =U24 -> 80.86392 | V26: =V24 -> 86.987316 | W26: =W24 -> 94.944784 | X26: =X24 -> 82.316805 | ... Z26: =Z24 -> 89.606986
B27: Giảm trong kỳ | J27: =IF(ISTEXT(Notes!J11),Notes!J55,'LT. Asset'!J25) -> -1.72 | K27: =IF(ISTEXT(Notes!K11),Notes!K55,'LT. Asset'!K25) -> -0.3397344 | L27: =IF(ISTEXT(Notes!L11),Notes!L55,'LT. Asset'!L25) -> -0.91691913 | M27: =IF(ISTEXT(Notes!M11),Notes!M55,'LT. Asset'!M25) -> -2.976904 | N27: =IF(ISTEXT(Notes!N11),Notes!N55,'LT. Asset'!N25) -> -2.95 | O27: =IF(ISTEXT(Notes!O11),Notes!O55,'LT. Asset'!O25) -> -3.2526788 | P27: =IF(ISTEXT(Notes!P11),Notes!P55,'LT. Asset'!P25) -> -26.701216 | Q27: 0 | R27: 0 | S27: =R27 -> 0 | T27: =S27 -> 0 | U27: =T27 -> 0 | V27: =U27 -> 0 | W27: =V27 -> 0 | X27: =W27 -> 0 | Y27: =X27 -> 0 | Z27: =Y27 -> 0
B28: Nguyên giá cuối kỳ | J28: =SUM(J23,J26,J27) -> 304.47 | K28: =SUM(K23,K26,K27) -> 388.91655 | L28: =SUM(L23,L26,L27) -> 445.53522 | M28: =SUM(M23,M26,M27) -> 461.03672 | N28: =SUM(N23,N26,N27) -> 502.08142 | O28: =SUM(O23,O26,O27) -> 540.88352 | P28: =SUM(P23,P26,P27) -> 579.02037 | Q28: =SUM(Q23,Q26,Q27) -> 976.96243 | ... Z28: =SUM(Z23,Z26,Z27) -> 1959.7916
K29: =K28/J28-1 -> 0.27735589 | L29: =L28/K28-1 -> 0.14558053 | M29: =M28/L28-1 -> 0.034792987 | N29: =N28/M28-1 -> 0.089026947 | O29: =O28/N28-1 -> 0.077282492 | P29: =P28/O28-1 -> 0.07050843 | Q29: =Q28/P28-1 -> 0.68726781 | R29: =R28/Q28-1 -> 0.32026994 | ... Z29: =Z28/Y28-1 -> 0.047913444
B30: Trong đó đã khấu hao hết nhưng còn sử dụng
B31: Check nguyên giá cuối kỳ | J31: =IF(ISTEXT(Notes!J11),J28-'BS Raw'!J52/$B$1,"Chưa có BCTC") -> -0.004710086 | K31: =IF(ISTEXT(Notes!K11),K28-'BS Raw'!K52/$B$1,"Chưa có BCTC") -> 0 | L31: =IF(ISTEXT(Notes!L11),L28-'BS Raw'!L52/$B$1,"Chưa có BCTC") -> 5.6843419e-14 | M31: =IF(ISTEXT(Notes!M11),M28-'BS Raw'!M52/$B$1,"Chưa có BCTC") -> 0 | N31: =IF(ISTEXT(Notes!N11),N28-'BS Raw'!N52/$B$1,"Chưa có BCTC") -> -0.003428196 | O31: =IF(ISTEXT(Notes!O11),O28-'BS Raw'!O52/$B$1,"Chưa có BCTC") -> 0 | P31: =IF(ISTEXT(Notes!P11),P28-'BS Raw'!P52/$B$1,"Chưa có BCTC") -> -0.003518911 | Q31: =IF(ISTEXT(Notes!Q11),Q28-'BS Raw'!Q52/$B$1,"Chưa có BCTC") -> Chưa có BCTC | ... Z31: =IF(ISTEXT(Notes!Z11),Z28-'BS Raw'!Z52/$B$1,"Chưa có BCTC") -> Chưa có BCTC
B33: Giá trị hao mòn lũy kế
B34: Số dư đầu kỳ | J34: =Notes!J57/$B$1 -> 38.55 | K34: =Notes!K57/$B$1 -> 178.88048 | L34: =Notes!L57/$B$1 -> 206.43424 | M34: =Notes!M57/$B$1 -> 250.96 | N34: =Notes!N57/$B$1 -> 293.13988 | O34: =Notes!O57/$B$1 -> 321.82624 | P34: =Notes!P57/$B$1 -> 353.99 | Q34: =P39 -> 392.34748 | R34: =Q39 -> 491.03637 | S34: =R39 -> 621.01442 | T34: =S39 -> 758.00524 | U34: =T39 -> 854.01899 | V34: =U39 -> 948.13028 | W34: =V39 -> 1050.9403 | X34: =W39 -> 1163.2448 | ... Z34: =Y39 -> 1412.8974
B35: Tăng trong kỳ (FC) | Q35: =Q242 -> 98.688887 | R35: =R242 -> 129.97806 | S35: =S242 -> 136.99082 | T35: =T242 -> 96.013749 | U35: =U242 -> 94.111296 | V35: =V242 -> 102.81003 | W35: =W242 -> 112.30451 | X35: =X242 -> 120.53619 | ... AH35: =AH242 -> 0
B36: Giảm trong kỳ (FC)
B37: Tăng trong kỳ | J37: =IF(ISTEXT(Notes!J11),Notes!J58/$B$1,J35) -> 141.3 | K37: =IF(ISTEXT(Notes!K11),Notes!K58/$B$1,K35) -> 36.35849 | L37: =IF(ISTEXT(Notes!L11),Notes!L58/$B$1,L35) -> 45.443967 | M37: =IF(ISTEXT(Notes!M11),Notes!M58/$B$1,M35) -> 45.155502 | N37: =IF(ISTEXT(Notes!N11),Notes!N58/$B$1,N35) -> 31.629649 | O37: =IF(ISTEXT(Notes!O11),Notes!O58/$B$1,O35) -> 35.418883 | P37: =IF(ISTEXT(Notes!P11),Notes!P58/$B$1,P35) -> 58.894681 | Q37: =Q35 -> 98.688887 | R37: =R35 -> 129.97806 | S37: =S35 -> 136.99082 | T37: =T35 -> 96.013749 | U37: =U35 -> 94.111296 | V37: =V35 -> 102.81003 | W37: =W35 -> 112.30451 | X37: =X35 -> 120.53619 | ... Z37: =Z35 -> 138.07713
B38: Giảm trong kỳ | J38: =IF(ISTEXT(Notes!J11),Notes!J59/$B$1,J36) -> -0.97 | K38: =IF(ISTEXT(Notes!K11),Notes!K59/$B$1,K36) -> -8.8047294 | L38: =IF(ISTEXT(Notes!L11),Notes!L59/$B$1,L36) -> -0.91691913 | M38: =IF(ISTEXT(Notes!M11),Notes!M59/$B$1,M36) -> -2.976904 | N38: =IF(ISTEXT(Notes!N11),Notes!N59/$B$1,N36) -> -2.9432956 | O38: =IF(ISTEXT(Notes!O11),Notes!O59/$B$1,O36) -> -3.2526788 | P38: =IF(ISTEXT(Notes!P11),Notes!P59/$B$1,P36) -> -20.537201
B39: Giá trị hao mòn lũy kế cuối kỳ | J39: =SUM(J34,J37,J38) -> 178.88 | K39: =SUM(K34,K37,K38) -> 206.43424 | L39: =SUM(L34,L37,L38) -> 250.96129 | M39: =SUM(M34,M37,M38) -> 293.1386 | N39: =SUM(N34,N37,N38) -> 321.82624 | O39: =SUM(O34,O37,O38) -> 353.99244 | P39: =SUM(P34,P37,P38) -> 392.34748 | Q39: =SUM(Q34,Q37,Q38) -> 491.03637 | ... Z39: =SUM(Z34,Z37,Z38) -> 1550.9746
B40: GTCL đầu kỳ | J40: =J23-J34 -> 68.64 | K40: =K23-K34 -> 125.59423 | L40: =L23-L34 -> 182.48231 | M40: =M23-M34 -> 194.57522 | N40: =N23-N34 -> 167.90012 | O40: =O23-O34 -> 180.25861 | P40: =P23-P34 -> 186.89 | Q40: =Q23-Q34 -> 186.67289 | ... Z40: =Z23-Z34 -> 457.2872
B41: GTCL cuối kỳ | J41: =J28-J39 -> 125.59 | K41: =K28-K39 -> 182.48231 | L41: =L28-L39 -> 194.57394 | M41: =M28-M39 -> 167.89813 | N41: =N28-N39 -> 180.25518 | O41: =O28-O39 -> 186.89108 | P41: =P28-P39 -> 186.67289 | Q41: =Q28-Q39 -> 485.92606 | ... Z41: =Z28-Z39 -> 408.81706
B42: Check GTCL cuối kỳ | J42: =IF(ISTEXT(Notes!J11),J41-'BS Raw'!J51/$B$1,"Chưa có BCTC") -> -0.004233461 | K42: =IF(ISTEXT(Notes!K11),K41-'BS Raw'!K51/$B$1,"Chưa có BCTC") -> 5.6843419e-14 | L42: =IF(ISTEXT(Notes!L11),L41-'BS Raw'!L51/$B$1,"Chưa có BCTC") -> 2.8421709e-14 | M42: =IF(ISTEXT(Notes!M11),M41-'BS Raw'!M51/$B$1,"Chưa có BCTC") -> 0.001285651 | N42: =IF(ISTEXT(Notes!N11),N41-'BS Raw'!N51/$B$1,"Chưa có BCTC") -> -0.003428196 | O42: =IF(ISTEXT(Notes!O11),O41-'BS Raw'!O51/$B$1,"Chưa có BCTC") -> -2.8421709e-14 | P42: =IF(ISTEXT(Notes!P11),P41-'BS Raw'!P51/$B$1,"Chưa có BCTC") -> -0.001077586 | Q42: =IF(ISTEXT(Notes!Q11),Q41-'BS Raw'!Q51/$B$1,"Chưa có BCTC") -> Chưa có BCTC | ... AA42: =IF(ISTEXT(Notes!AA11),AA41-'BS Raw'!AA51/$B$1,"Chưa có BCTC") -> Chưa có BCTC
B43: ="- Giá trị còn lại của tài sản đầu tư thêm năm "&YEAR($P$3) -> - Giá trị còn lại của tài sản đầu tư thêm năm 2021 | P43: =P41 -> 186.67289 | Q43: =P43-Q230 -> 127.77821 | R43: =Q43-R230 -> 68.883526 | S43: =R43-S230 -> 9.9888452 | T43: =S43-T230 -> 0 | U43: =T43-U230 -> 0 | V43: =U43-V230 -> 0 | W43: =V43-W230 -> 0 | X43: =W43-X230 -> 0 | ... Z43: =Y43-Z230 -> 0
B44: ="- Giá trị còn lại của tài sản đầu tư thêm năm "&YEAR($P$3)+1 -> - Giá trị còn lại của tài sản đầu tư thêm năm 2022 | Q44: =(Q26+Q27)-Q231 -> 358.14785 | R44: =+Q44-R231 -> 318.35365 | S44: =+R44-S231 -> 278.55944 | T44: =+S44-T231 -> 238.76524 | U44: =+T44-U231 -> 198.97103 | V44: =+U44-V231 -> 159.17682 | W44: =+V44-W231 -> 119.38262 | X44: =+W44-X231 -> 79.588412 | Y44: =+X44-Y231 -> 39.794206 | Z44: =+Y44-Z231 -> 0
B45: ="- Giá trị còn lại của tài sản đầu tư thêm năm "&YEAR($P$3)+2 -> - Giá trị còn lại của tài sản đầu tư thêm năm 2023 | R45: =(R26+R27-R232) -> 281.60253 | S45: =+R45-S232 -> 250.31336 | T45: =+S45-T232 -> 219.02419 | U45: =+T45-U232 -> 187.73502 | V45: =+U45-V232 -> 156.44585 | W45: =+V45-W232 -> 125.15668 | X45: =+W45-X232 -> 93.867511 | Y45: =+X45-Y232 -> 62.57834 | Z45: =+Y45-Z232 -> 31.28917
B46: ="- Giá trị còn lại của tài sản đầu tư thêm năm "&YEAR($P$3)+3 -> - Giá trị còn lại của tài sản đầu tư thêm năm 2024 | S46: =S26+S27-S233 -> 63.114824 | T46: =+S46-T233 -> 56.102066 | U46: =+T46-U233 -> 49.089307 | V46: =+U46-V233 -> 42.076549 | W46: =+V46-W233 -> 35.063791 | X46: =+W46-X233 -> 28.051033 | Y46: =+X46-Y233 -> 21.038275 | Z46: =+Y46-Z233 -> 14.025516
B47: ="- Giá trị còn lại của tài sản đầu tư thêm năm "&YEAR($P$3)+4 -> - Giá trị còn lại của tài sản đầu tư thêm năm 2025 | T47: =T26+T27-T234 -> 71.358928 | U47: =T47-U234 -> 63.430158 | V47: =U47-V234 -> 55.501389 | W47: =V47-W234 -> 47.572619 | X47: =W47-X234 -> 39.643849 | Y47: =X47-Y234 -> 31.715079 | Z47: =Y47-Z234 -> 23.786309
B48: ="- Giá trị còn lại của tài sản đầu tư thêm năm "&YEAR($P$3)+5 -> - Giá trị còn lại của tài sản đầu tư thêm năm 2026 | U48: =U26+U27-U235 -> 72.777528 | V48: =U48-V235 -> 64.691136 | W48: =V48-W235 -> 56.604744 | X48: =W48-X235 -> 48.518352 | Y48: =X48-Y235 -> 40.43196 | Z48: =Y48-Z235 -> 32.345568
B49: ="- Giá trị còn lại của tài sản đầu tư thêm năm "&YEAR($P$3)+6 -> - Giá trị còn lại của tài sản đầu tư thêm năm 2027 | V49: =V26+V27-V236 -> 78.288584 | W49: =V49-W236 -> 69.589853 | X49: =W49-X236 -> 60.891121 | Y49: =X49-Y236 -> 52.192389 | Z49: =Y49-Z236 -> 43.493658 | AA49: =Z49-AA236 -> 43.493658 | AB49: =AA49-AB236 -> 43.493658 | AC49: =AB49-AC236 -> 43.493658 | AD49: =AC49-AD236 -> 43.493658 | ... AH49: =AG49-AH236 -> 43.493658
B50: ="- Giá trị còn lại của tài sản đầu tư thêm năm "&YEAR($P$3)+7 -> - Giá trị còn lại của tài sản đầu tư thêm năm 2028 | W50: =W26+W27-W237 -> 85.450306 | X50: =W50-X237 -> 75.955828 | Y50: =X50-Y237 -> 66.461349 | Z50: =Y50-Z237 -> 56.966871
B51: ="- Giá trị còn lại của tài sản đầu tư thêm năm "&YEAR($P$3)+8 -> - Giá trị còn lại của tài sản đầu tư thêm năm 2029 | X51: =X26+X27-X238 -> 74.085125 | Y51: =Y26+Y27-Y238 -> 77.570717 | Z51: =Z26+Z27-Z238 -> 81.375305
B52: ="- Giá trị còn lại của tài sản đầu tư thêm năm "&YEAR($P$3)+9 -> - Giá trị còn lại của tài sản đầu tư thêm năm 2030 | Y52: =Y26+Y27-Y239 -> 77.222158 | Z52: =Y52-Z239 -> 68.641918
B53: ="- Giá trị còn lại của tài sản đầu tư thêm năm "&YEAR($P$3)+10 -> - Giá trị còn lại của tài sản đầu tư thêm năm 2031 | Z53: =Z26+Z27-Z240 -> 80.646287
B54: ="- Giá trị còn lại của tài sản đầu tư thêm năm "&YEAR($P$3)+11 -> - Giá trị còn lại của tài sản đầu tư thêm năm 2032
B56: 2. TÀI SẢN THUÊ TÀI CHÍNH
B57: Nguyên giá
B58: Số dư đầu kỳ | J58: =Notes!J61/$B$1 -> 0 | K58: =Notes!K61/$B$1 -> 0 | L58: =Notes!L61/$B$1 -> 0 | M58: =Notes!M61/$B$1 -> 0 | N58: =Notes!N61/$B$1 -> 0 | O58: =Notes!O61/$B$1 -> 0 | P58: =Notes!P61/$B$1 -> 0 | Q58: =P63 -> 0 | R58: =Q63 -> 0 | S58: =R63 -> 0 | T58: =S63 -> 0 | U58: =T63 -> 0 | V58: =U63 -> 0 | W58: =V63 -> 0 | X58: =W63 -> 0 | ... Z58: =Y63 -> 0
B59: Tăng trong kỳ (FC) | Q59: =Q9*Q14 -> 0 | R59: =R9*R14 -> 0 | S59: =S9*S14 -> 0 | T59: =T9*T14 -> 0 | U59: =U9*U14 -> 0 | V59: =V9*V14 -> 0 | W59: =W9*W14 -> 0 | X59: =X9*X14 -> 0 | ... Z59: =Z9*Z14 -> 0
B60: Giảm trong kỳ (FC)
B61: Tăng trong kỳ | J61: =IF(ISTEXT(Notes!J11),Notes!J62/$B$1,J59) -> 0 | K61: =IF(ISTEXT(Notes!K11),Notes!K62/$B$1,K59) -> 0 | L61: =IF(ISTEXT(Notes!L11),Notes!L62/$B$1,L59) -> 0 | M61: =IF(ISTEXT(Notes!M11),Notes!M62/$B$1,M59) -> 0 | N61: =IF(ISTEXT(Notes!N11),Notes!N62/$B$1,N59) -> 0 | O61: =IF(ISTEXT(Notes!O11),Notes!O62/$B$1,O59) -> 0 | P61: =IF(ISTEXT(Notes!P11),Notes!P62/$B$1,P59) -> 0 | Q61: =Q59 -> 0 | R61: =R59 -> 0 | S61: =S59 -> 0 | T61: =T59 -> 0 | U61: =U59 -> 0 | V61: =V59 -> 0 | W61: =W59 -> 0 | X61: =X59 -> 0 | ... Z61: =Z59 -> 0
B62: Giảm trong kỳ | J62: =IF(ISTEXT(Notes!J11),Notes!J63/$B$1,J59) -> 0 | K62: =IF(ISTEXT(Notes!K11),Notes!K63/$B$1,K59) -> 0 | L62: =IF(ISTEXT(Notes!L11),Notes!L63/$B$1,L59) -> 0 | M62: =IF(ISTEXT(Notes!M11),Notes!M63/$B$1,M59) -> 0 | N62: =IF(ISTEXT(Notes!N11),Notes!N63/$B$1,N59) -> 0 | O62: =IF(ISTEXT(Notes!O11),Notes!O63/$B$1,O59) -> 0 | P62: =IF(ISTEXT(Notes!P11),Notes!P63/$B$1,P59) -> 0 | Q62: 0 | R62: =Q62 -> 0 | S62: =R62 -> 0 | T62: =S62 -> 0 | U62: =T62 -> 0 | V62: =U62 -> 0 | W62: =V62 -> 0 | X62: =W62 -> 0 | Y62: =X62 -> 0 | Z62: =Y62 -> 0
B63: Nguyên giá cuối kỳ | J63: =SUM(J58,J61,J62) -> 0 | K63: =SUM(K58,K61,K62) -> 0 | L63: =SUM(L58,L61,L62) -> 0 | M63: =SUM(M58,M61,M62) -> 0 | N63: =SUM(N58,N61,N62) -> 0 | O63: =SUM(O58,O61,O62) -> 0 | P63: =SUM(P58,P61,P62) -> 0 | Q63: =SUM(Q58,Q61,Q62) -> 0 | ... Z63: =SUM(Z58,Z61,Z62) -> 0
B64: Trong đó đã khấu hao hết nhưng còn sử dụng
B65: Check nguyên giá cuối kỳ | J65: =IF(ISTEXT(Notes!J11),J63-'BS Raw'!J55/$B$1,"Chưa có BCTC") -> 0 | K65: =IF(ISTEXT(Notes!K11),K63-'BS Raw'!K55/$B$1,"Chưa có BCTC") -> 0 | L65: =IF(ISTEXT(Notes!L11),L63-'BS Raw'!L55/$B$1,"Chưa có BCTC") -> 0 | M65: =IF(ISTEXT(Notes!M11),M63-'BS Raw'!M55/$B$1,"Chưa có BCTC") -> 0 | N65: =IF(ISTEXT(Notes!N11),N63-'BS Raw'!N55/$B$1,"Chưa có BCTC") -> 0 | O65: =IF(ISTEXT(Notes!O11),O63-'BS Raw'!O55/$B$1,"Chưa có BCTC") -> 0 | P65: =IF(ISTEXT(Notes!P11),P63-'BS Raw'!P55/$B$1,"Chưa có BCTC") -> 0 | Q65: =IF(ISTEXT(Notes!Q11),Q63-'BS Raw'!Q55/$B$1,"Chưa có BCTC") -> Chưa có BCTC | ... AA65: =IF(ISTEXT(Notes!AA11),AA63-'BS Raw'!AA55/$B$1,"Chưa có BCTC") -> Chưa có BCTC
B67: Giá trị hao mòn lũy kế
B68: Số dư đầu kỳ | J68: =Notes!J65/$B$1 -> 0 | K68: =Notes!K65/$B$1 -> 0 | L68: =Notes!L65/$B$1 -> 0 | M68: =Notes!M65/$B$1 -> 0 | N68: =Notes!N65/$B$1 -> 0 | O68: =Notes!O65/$B$1 -> 0 | P68: =Notes!P65/$B$1 -> 0 | Q68: =P73 -> 0 | R68: =Q73 -> 0 | S68: =R73 -> 0 | T68: =S73 -> 0 | U68: =T73 -> 0 | V68: =U73 -> 0 | W68: =V73 -> 0 | X68: =W73 -> 0 | ... Z68: =Y73 -> 0
B69: Tăng trong kỳ (FC) | Q69: =Q257 -> 0 | R69: =R257 -> 0 | S69: =S257 -> 0 | T69: =T257 -> 0 | U69: =U257 -> 0 | V69: =V257 -> 0 | W69: =W257 -> 0 | X69: =X257 -> 0 | ... Z69: =Z257 -> 0
B70: Giảm trong kỳ (FC)
B71: Tăng trong kỳ | J71: =IF(ISTEXT(Notes!J11),Notes!J66/$B$1,J69) -> 0 | K71: =IF(ISTEXT(Notes!K11),Notes!K66/$B$1,K69) -> 0 | L71: =IF(ISTEXT(Notes!L11),Notes!L66/$B$1,L69) -> 0 | M71: =IF(ISTEXT(Notes!M11),Notes!M66/$B$1,M69) -> 0 | N71: =IF(ISTEXT(Notes!N11),Notes!N66/$B$1,N69) -> 0 | O71: =IF(ISTEXT(Notes!O11),Notes!O66/$B$1,O69) -> 0 | P71: =IF(ISTEXT(Notes!P11),Notes!P66/$B$1,P69) -> 0 | Q71: =Q69 -> 0 | R71: =R69 -> 0 | S71: =S69 -> 0 | T71: =T69 -> 0 | U71: =U69 -> 0 | V71: =V69 -> 0 | W71: =W69 -> 0 | X71: =X69 -> 0 | ... Z71: =Z69 -> 0
B72: Giảm trong kỳ | J72: =IF(ISTEXT(Notes!J11),Notes!J67/$B$1,J70) -> 0 | K72: =IF(ISTEXT(Notes!K11),Notes!K67/$B$1,K70) -> 0 | L72: =IF(ISTEXT(Notes!L11),Notes!L67/$B$1,L70) -> 0 | M72: =IF(ISTEXT(Notes!M11),Notes!M67/$B$1,M70) -> 0 | N72: =IF(ISTEXT(Notes!N11),Notes!N67/$B$1,N70) -> 0 | O72: =IF(ISTEXT(Notes!O11),Notes!O67/$B$1,O70) -> 0 | P72: =IF(ISTEXT(Notes!P11),Notes!P67/$B$1,P70) -> 0
B73: Giá trị hao mòn lũy kế cuối kỳ | J73: =SUM(J68,J71,J72) -> 0 | K73: =SUM(K68,K71,K72) -> 0 | L73: =SUM(L68,L71,L72) -> 0 | M73: =SUM(M68,M71,M72) -> 0 | N73: =SUM(N68,N71,N72) -> 0 | O73: =SUM(O68,O71,O72) -> 0 | P73: =SUM(P68,P71,P72) -> 0 | Q73: =Q68+Q71+Q72 -> 0 | R73: =R68+R71+R72 -> 0 | S73: =S68+S71+S72 -> 0 | T73: =T68+T71+T72 -> 0 | U73: =U68+U71+U72 -> 0 | V73: =V68+V71+V72 -> 0 | W73: =W68+W71+W72 -> 0 | X73: =X68+X71+X72 -> 0 | ... Z73: =Z68+Z71+Z72 -> 0
B74: GTCL đầu kỳ | J74: =J58-J68 -> 0 | K74: =K58-K68 -> 0 | L74: =L58-L68 -> 0 | M74: =M58-M68 -> 0 | N74: =N58-N68 -> 0 | O74: =O58-O68 -> 0 | P74: =P58-P68 -> 0 | Q74: =Q58-Q68 -> 0 | ... Z74: =Z58-Z68 -> 0
B75: GTCL cuối kỳ | J75: =J63-J73 -> 0 | K75: =K63-K73 -> 0 | L75: =L63-L73 -> 0 | M75: =M63-M73 -> 0 | N75: =N63-N73 -> 0 | O75: =O63-O73 -> 0 | P75: =P63-P73 -> 0 | Q75: =Q63-Q73 -> 0 | ... Z75: =Z63-Z73 -> 0
B76: Check GTCL cuối kỳ | J76: =IF(ISTEXT(Notes!J11),J75-'BS Raw'!J54/$B$1,"Chưa có BCTC") -> 0 | K76: =IF(ISTEXT(Notes!K11),K75-'BS Raw'!K54/$B$1,"Chưa có BCTC") -> 0 | L76: =IF(ISTEXT(Notes!L11),L75-'BS Raw'!L54/$B$1,"Chưa có BCTC") -> 0 | M76: =IF(ISTEXT(Notes!M11),M75-'BS Raw'!M54/$B$1,"Chưa có BCTC") -> 0 | N76: =IF(ISTEXT(Notes!N11),N75-'BS Raw'!N54/$B$1,"Chưa có BCTC") -> 0 | O76: =IF(ISTEXT(Notes!O11),O75-'BS Raw'!O54/$B$1,"Chưa có BCTC") -> 0 | P76: =IF(ISTEXT(Notes!P11),P75-'BS Raw'!P54/$B$1,"Chưa có BCTC") -> 0 | Q76: =IF(ISTEXT(Notes!Q11),Q75-'BS Raw'!Q54/$B$1,"Chưa có BCTC") -> Chưa có BCTC | ... Z76: =IF(ISTEXT(Notes!Z11),Z75-'BS Raw'!Z54/$B$1,"Chưa có BCTC") -> Chưa có BCTC
B77: ="- Giá trị còn lại của tài sản đầu tư thêm năm "&YEAR($P$3) -> - Giá trị còn lại của tài sản đầu tư thêm năm 2021 | P77: =P75 -> 0 | Q77: =P77-Q245 -> 0 | R77: =Q77-R245 -> 0 | S77: =R77-S245 -> 0 | T77: =S77-T245 -> 0 | U77: =T77-U245 -> 0 | V77: =U77-V245 -> 0 | W77: =V77-W245 -> 0 | X77: =W77-X245 -> 0 | ... Z77: =Y77-Z245 -> 0
B78: ="- Giá trị còn lại của tài sản đầu tư thêm năm "&YEAR($P$3)+1 -> - Giá trị còn lại của tài sản đầu tư thêm năm 2022 | Q78: =Q61+Q62-Q246 -> 0 | R78: =Q78-R246 -> 0 | S78: =R78-S246 -> 0 | T78: =S78-T246 -> 0 | U78: =T78-U246 -> 0 | V78: =U78-V246 -> 0 | W78: =V78-W246 -> 0 | X78: =W78-X246 -> 0 | Y78: =X78-Y246 -> 0 | Z78: =Y78-Z246 -> 0
B79: ="- Giá trị còn lại của tài sản đầu tư thêm năm "&YEAR($P$3)+2 -> - Giá trị còn lại của tài sản đầu tư thêm năm 2023 | R79: =R61+R62-R247 -> 0 | S79: =R79-S247 -> 0 | T79: =S79-T247 -> 0 | U79: =T79-U247 -> 0 | V79: =U79-V247 -> 0 | W79: =V79-W247 -> 0 | X79: =W79-X247 -> 0 | Y79: =X79-Y247 -> 0 | Z79: =Y79-Z247 -> 0
B80: ="- Giá trị còn lại của tài sản đầu tư thêm năm "&YEAR($P$3)+3 -> - Giá trị còn lại của tài sản đầu tư thêm năm 2024 | S80: =S61+S62-S248 -> 0 | T80: =S80-T248 -> 0 | U80: =T80-U248 -> 0 | V80: =U80-V248 -> 0 | W80: =V80-W248 -> 0 | X80: =W80-X248 -> 0 | Y80: =X80-Y248 -> 0 | Z80: =Y80-Z248 -> 0
B81: ="- Giá trị còn lại của tài sản đầu tư thêm năm "&YEAR($P$3)+4 -> - Giá trị còn lại của tài sản đầu tư thêm năm 2025 | T81: =T61+T62-T249 -> 0 | U81: =T81-U249 -> 0 | V81: =U81-V249 -> 0 | W81: =V81-W249 -> 0 | X81: =W81-X249 -> 0 | Y81: =X81-Y249 -> 0 | Z81: =Y81-Z249 -> 0
B82: ="- Giá trị còn lại của tài sản đầu tư thêm năm "&YEAR($P$3)+5 -> - Giá trị còn lại của tài sản đầu tư thêm năm 2026 | U82: =U61+U62-U250 -> 0 | V82: =U82-V250 -> 0 | W82: =V82-W250 -> 0 | X82: =W82-X250 -> 0 | Y82: =X82-Y250 -> 0 | Z82: =Y82-Z250 -> 0
B83: ="- Giá trị còn lại của tài sản đầu tư thêm năm "&YEAR($P$3)+6 -> - Giá trị còn lại của tài sản đầu tư thêm năm 2027 | V83: =V61+V62-V251 -> 0 | W83: =V83-W251 -> 0 | X83: =W83-X251 -> 0 | Y83: =X83-Y251 -> 0 | Z83: =Y83-Z251 -> 0
B84: ="- Giá trị còn lại của tài sản đầu tư thêm năm "&YEAR($P$3)+7 -> - Giá trị còn lại của tài sản đầu tư thêm năm 2028 | W84: =W61+W62-W252 -> 0 | X84: =W84-X252 -> 0 | Y84: =X84-Y252 -> 0 | Z84: =Y84-Z252 -> 0
B85: ="- Giá trị còn lại của tài sản đầu tư thêm năm "&YEAR($P$3)+8 -> - Giá trị còn lại của tài sản đầu tư thêm năm 2029 | X85: =X61+X62-X253 -> 0 | Y85: =X85-Y253 -> 0 | Z85: =Y85-Z253 -> 0
B86: ="- Giá trị còn lại của tài sản đầu tư thêm năm "&YEAR($P$3)+9 -> - Giá trị còn lại của tài sản đầu tư thêm năm 2030 | Y86: =Y61+Y62-Y254 -> 0 | Z86: =Y86-Z254 -> 0
B87: ="- Giá trị còn lại của tài sản đầu tư thêm năm "&YEAR($P$3)+10 -> - Giá trị còn lại của tài sản đầu tư thêm năm 2031 | Z87: =Z61+Z62-Z255 -> 0
B88: ="- Giá trị còn lại của tài sản đầu tư thêm năm "&YEAR($P$3)+11 -> - Giá trị còn lại của tài sản đầu tư thêm năm 2032
B89: 3. TÀI SẢN CỐ ĐỊNH VÔ HÌNH
B90: Nguyên giá
B91: Số dư đầu kỳ | J91: =Notes!J69/$B$1 -> 40.48 | K91: =Notes!K69/$B$1 -> 44.077531 | L91: =Notes!L69/$B$1 -> 56.427377 | M91: =Notes!M69/$B$1 -> 57.084212 | N91: =Notes!N69/$B$1 -> 57.384212 | O91: =Notes!O69/$B$1 -> 63.901968 | P91: =Notes!P69/$B$1 -> 71.308273 | Q91: =P96 -> 72.260263 | R91: =Q96 -> 96.321187 | S91: =R96 -> 115.23968 | T91: =S96 -> 119.47983 | U91: =T96 -> 124.27383 | V91: =U96 -> 129.16314 | W91: =V96 -> 134.42269 | X91: =W96 -> 140.16337 | ... Z91: =Y96 -> 150.32842
B92: Tăng trong kỳ (FC) | Q92: =Q9*Q15 -> 24.060924 | R92: =R9*R15 -> 18.918491 | S92: =S9*S15 -> 4.240151 | T92: =T9*T15 -> 4.7940026 | U92: =U9*U15 -> 4.8893063 | V92: =V9*V15 -> 5.2595475 | W92: =W9*W15 -> 5.740683 | X92: =X9*X15 -> 4.9771526 | ... Z92: =Z9*Z15 -> 5.4179416
B93: Giảm trong kỳ (FC)
B94: Tăng trong kỳ | J94: =IF(ISTEXT(Notes!J11),Notes!J70/$B$1,J92) -> 3.6 | K94: =IF(ISTEXT(Notes!K11),Notes!K70/$B$1,K92) -> 12.349846 | L94: =IF(ISTEXT(Notes!L11),Notes!L70/$B$1,L92) -> 0.6568345 | M94: =IF(ISTEXT(Notes!M11),Notes!M70/$B$1,M92) -> 0.3 | N94: =IF(ISTEXT(Notes!N11),Notes!N70/$B$1,N92) -> 7.2271595 | O94: =IF(ISTEXT(Notes!O11),Notes!O70/$B$1,O92) -> 7.406305 | P94: =IF(ISTEXT(Notes!P11),Notes!P70/$B$1,P92) -> 0.95199 | Q94: =Q92 -> 24.060924 | R94: =R92 -> 18.918491 | S94: =S92 -> 4.240151 | T94: =T92 -> 4.7940026 | U94: =U92 -> 4.8893063 | V94: =V92 -> 5.2595475 | W94: =W92 -> 5.740683 | X94: =X92 -> 4.9771526 | ... Z94: =Z92 -> 5.4179416
B95: Giảm trong kỳ | J95: =IF(ISTEXT(Notes!J11),Notes!J71/$B$1,J93) -> 0 | K95: =IF(ISTEXT(Notes!K11),Notes!K71/$B$1,K93) -> 0 | L95: =IF(ISTEXT(Notes!L11),Notes!L71/$B$1,L93) -> 0 | M95: =IF(ISTEXT(Notes!M11),Notes!M71/$B$1,M93) -> 0 | N95: =IF(ISTEXT(Notes!N11),Notes!N71/$B$1,N93) -> -0.70940325 | O95: =IF(ISTEXT(Notes!O11),Notes!O71/$B$1,O93) -> 0 | P95: =IF(ISTEXT(Notes!P11),Notes!P71/$B$1,P93) -> 0 | Q95: 0 | R95: =Q95 -> 0 | S95: =R95 -> 0 | T95: =S95 -> 0 | U95: =T95 -> 0 | V95: =U95 -> 0 | W95: =V95 -> 0 | X95: =W95 -> 0 | Y95: =X95 -> 0 | Z95: =Y95 -> 0
B96: Nguyên giá cuối kỳ | J96: =SUM(J91,J94,J95) -> 44.08 | K96: =SUM(K91,K94,K95) -> 56.427377 | L96: =SUM(L91,L94,L95) -> 57.084212 | M96: =SUM(M91,M94,M95) -> 57.384212 | N96: =SUM(N91,N94,N95) -> 63.901968 | O96: =SUM(O91,O94,O95) -> 71.308273 | P96: =SUM(P91,P94,P95) -> 72.260263 | Q96: =SUM(Q91,Q94,Q95) -> 96.321187 | ... Z96: =SUM(Z91,Z94,Z95) -> 155.74637
B97: Trong đó đã khấu hao hết nhưng còn sử dụng & Quyền SD đất không KH
B98: Check nguyên giá cuối kỳ | J98: =IF(ISTEXT(Notes!J11),J96-'BS Raw'!J58/$B$1,"Chưa có BCTC") -> 0.0024691 | K98: =IF(ISTEXT(Notes!K11),K96-'BS Raw'!K58/$B$1,"Chưa có BCTC") -> -7.1054274e-15 | L98: =IF(ISTEXT(Notes!L11),L96-'BS Raw'!L58/$B$1,"Chưa có BCTC") -> 7.1054274e-15 | M98: =IF(ISTEXT(Notes!M11),M96-'BS Raw'!M58/$B$1,"Chưa có BCTC") -> -7.1054274e-15 | N98: =IF(ISTEXT(Notes!N11),N96-'BS Raw'!N58/$B$1,"Chưa có BCTC") -> 7.1054274e-15 | O98: =IF(ISTEXT(Notes!O11),O96-'BS Raw'!O58/$B$1,"Chưa có BCTC") -> 0 | P98: =IF(ISTEXT(Notes!P11),P96-'BS Raw'!P58/$B$1,"Chưa có BCTC") -> 0 | Q98: =IF(ISTEXT(Notes!Q11),Q96-'BS Raw'!Q58/$B$1,"Chưa có BCTC") -> Chưa có BCTC | ... Z98: =IF(ISTEXT(Notes!Z11),Z96-'BS Raw'!Z58/$B$1,"Chưa có BCTC") -> Chưa có BCTC
B100: Giá trị hao mòn lũy kế
B101: Số dư đầu kỳ | J101: =Notes!J73 -> 0.68 | K101: =Notes!K73 -> 1.4042136 | L101: =Notes!L73 -> 3.1449711 | M101: =Notes!M73 -> 4.732058 | N101: =Notes!N73 -> 6.4194796 | O101: =Notes!O73 -> 7.4882508 | P101: =Notes!P73 -> 9.5767891 | Q101: =P106 -> 11.848891 | R101: =Q106 -> 14.872896 | S101: =R106 -> 18.488104 | T101: =S106 -> 22.235817 | U101: =T106 -> 26.133342 | V101: =U106 -> 30.43831 | W101: =V106 -> 34.907638 | X101: =W106 -> 39.556363 | ... Z101: =Y106 -> 49.327007
B102: Tăng trong kỳ (FC) | Q102: =Q273 -> 3.0240053 | R102: =R273 -> 3.6152081 | S102: =S273 -> 3.7477128 | T102: =T273 -> 3.8975254 | U102: =U273 -> 4.3049676 | V102: =V273 -> 4.4693285 | W102: =W273 -> 4.6487248 | X102: =X273 -> 4.8042608 | ... Z102: =Z273 -> 5.1356935
B103: Giảm trong kỳ (FC)
B104: Tăng trong kỳ | J104: =IF(ISTEXT(Notes!J11),Notes!J74,J102) -> 0.73 | K104: =IF(ISTEXT(Notes!K11),Notes!K74,K102) -> 1.7407575 | L104: =IF(ISTEXT(Notes!L11),Notes!L74,L102) -> 1.5870869 | M104: =IF(ISTEXT(Notes!M11),Notes!M74,M102) -> 1.6874216 | N104: =IF(ISTEXT(Notes!N11),Notes!N74,N102) -> 1.7781745 | O104: =IF(ISTEXT(Notes!O11),Notes!O74,O102) -> 2.0885383 | P104: =IF(ISTEXT(Notes!P11),Notes!P74,P102) -> 2.2721014 | Q104: =Q102 -> 3.0240053 | R104: =R102 -> 3.6152081 | S104: =S102 -> 3.7477128 | T104: =T102 -> 3.8975254 | U104: =U102 -> 4.3049676 | V104: =V102 -> 4.4693285 | W104: =W102 -> 4.6487248 | X104: =X102 -> 4.8042608 | ... Z104: =Z102 -> 5.1356935
B105: Giảm trong kỳ | J105: =IF(ISTEXT(Notes!J11),Notes!J75,J102) -> 0 | K105: =IF(ISTEXT(Notes!K11),Notes!K75,K102) -> 0 | L105: =IF(ISTEXT(Notes!L11),Notes!L75,L102) -> 0 | M105: =IF(ISTEXT(Notes!M11),Notes!M75,M102) -> 0 | N105: =IF(ISTEXT(Notes!N11),Notes!N75,N102) -> -0.70940325 | O105: =IF(ISTEXT(Notes!O11),Notes!O75,O102) -> 0 | P105: =IF(ISTEXT(Notes!P11),Notes!P75,P102) -> 0 | Q105: 0 | R105: =Q105 -> 0 | S105: =R105 -> 0 | T105: =S105 -> 0 | U105: =T105 -> 0 | V105: =U105 -> 0 | W105: =V105 -> 0 | X105: =W105 -> 0 | Y105: =X105 -> 0 | Z105: =Y105 -> 0
B106: Giá trị hao mòn lũy kế cuối kỳ | J106: =SUM(J101,J104,J105) -> 1.41 | K106: =SUM(K101,K104,K105) -> 3.1449711 | L106: =SUM(L101,L104,L105) -> 4.732058 | M106: =SUM(M101,M104,M105) -> 6.4194796 | N106: =SUM(N101,N104,N105) -> 7.4882508 | O106: =SUM(O101,O104,O105) -> 9.5767891 | P106: =SUM(P101,P104,P105) -> 11.848891 | Q106: =Q101+Q104+Q105 -> 14.872896 | R106: =R101+R104+R105 -> 18.488104 | S106: =S101+S104+S105 -> 22.235817 | T106: =T101+T104+T105 -> 26.133342 | U106: =U101+U104+U105 -> 30.43831 | V106: =V101+V104+V105 -> 34.907638 | W106: =W101+W104+W105 -> 39.556363 | X106: =X101+X104+X105 -> 44.360624 | ... Z106: =Z101+Z104+Z105 -> 54.4627
B107: GTCL đầu kỳ | J107: =J91-J101 -> 39.8 | K107: =K91-K101 -> 42.673317 | L107: =L91-L101 -> 53.282406 | M107: =M91-M101 -> 52.352154 | N107: =N91-N101 -> 50.964732 | O107: =O91-O101 -> 56.413717 | P107: =P91-P101 -> 61.731484 | Q107: =Q91-Q101 -> 60.411372 | ... Z107: =Z91-Z101 -> 101.00142
...

Sheet Input
B1: =1 -> 1 | D1: Số liệu 2014 ko sử dụng để dự phóng nhưng 1 số dòng cần có số liệu để tính trung bình cộng hoặc so sánh tăng trưởng | N1: 1 | O1: 2 | P1: 3 | Q1: 1 | R1: 2 | S1: 3 | T1: 4 | U1: 5 | V1: 6 | W1: 7 | X1: 8 | Y1: 9 | Z1: 10 | AA1: 14 | AB1: 15 | AC1: 16 | AD1: 17 | AE1: 18 | AF1: 19 | AG1: 20 | AH1: 21 | AI1: 22 | AJ1: 23 | AK1: 24 | AL1: 25 | AM1: 26 | AN1: 27 | AO1: 28 | AP1: 29 | AQ1: 30 | AR1: 31 | AS1: 32 | AT1: 33 | AU1: 34 | AV1: 35 | AW1: 36 | AX1: 37 | AY1: 38 | AZ1: 39 | BA1: 40
E2: =IF(TODAY()<E3,"Proj","") | F2: =IF(TODAY()<F3,"Proj","") | G2: =IF(TODAY()<G3,"Proj","") | K2: =IF(TODAY()<K3,"Proj","") | L2: =IF(TODAY()<L3,"Proj","") | M2: =IF(TODAY()<M3,"Proj","") | N2: =IF(TODAY()<N3,"Proj","") | O2: =IF(TODAY()<O3,"Proj","") | P2: =IF(TODAY()<P3,"Proj","") | Q2: =IF(TODAY()<Q3,"Proj","") | R2: =IF(TODAY()<R3,"Proj","") | ... BA2: =IF(TODAY()<BA3,"Proj","") -> Proj
B3: INCOME STATEMENT | D3: 40178 | E3: =DATE(YEAR(D3),MONTH(D3)+13,0) -> 40543 | F3: =DATE(YEAR(E3),MONTH(E3)+13,0) -> 40908 | G3: =DATE(YEAR(F3),MONTH(F3)+13,0) -> 41274 | H3: =DATE(YEAR(G3),MONTH(G3)+13,0) -> 41639 | I3: =DATE(YEAR(H3),MONTH(H3)+13,0) -> 42004 | J3: =DATE(YEAR(I3),MONTH(I3)+13,0) -> 42369 | K3: =DATE(YEAR(J3),MONTH(J3)+13,0) -> 42735 | L3: =DATE(YEAR(K3),MONTH(K3)+13,0) -> 43100 | ... BA3: =DATE(YEAR(AZ3),MONTH(AZ3)+13,0) -> 58075 | BC3: Note
A5: 1 | B5: Revenue (FC) | I5: ='IS Raw'!I17/Input!$B$1 -> 2451.8793 | J5: ='IS Raw'!J17/Input!$B$1 -> 1225.068 | K5: ='IS Raw'!K17/Input!$B$1 -> 1384.9018 | L5: ='IS Raw'!L17/Input!$B$1 -> 1388.2274 | M5: ='IS Raw'!M17/Input!$B$1 -> 1401.0243 | N5: ='IS Raw'!N17/Input!$B$1 -> 1261.729 | O5: ='IS Raw'!O17/Input!$B$1 -> 1256.9524 | P5: ='IS Raw'!P17/Input!$B$1 -> 1558.5043 | Q5: ='Consol. Rev.'!Q8 -> 1674.6242 | R5: ='Consol. Rev.'!R8 -> 1747.0634 | S5: ='Consol. Rev.'!S8 -> 2205.6779 | T5: ='Consol. Rev.'!T8 -> 2352.6625 | U5: ='Consol. Rev.'!U8 -> 2500.209 | V5: ='Consol. Rev.'!V8 -> 2621.9353 | W5: ='Consol. Rev.'!W8 -> 2773.8208 | X5: ='Consol. Rev.'!X8 -> 2880.9577 | ... Z5: ='Consol. Rev.'!Z8 -> 3122.6339
B6: Growth % | J6: =IFERROR(J7/I7-1, " ") -> -0.50035549 | K6: =IFERROR(K7/J7-1, " ") -> 0.13046932 | L6: =IFERROR(L7/K7-1, " ") -> 0.0024012993 | M6: =IFERROR(M7/L7-1, " ") -> 0.0092181712 | N6: =IFERROR(N7/M7-1, " ") -> -0.099423895 | O6: =IFERROR(O7/N7-1, " ") -> -0.003785797 | P6: =IFERROR(P7/O7-1, " ") -> 0.23990723 | Q6: =IFERROR(Q7/P7-1, " ") -> 0.074507244 | ... Z6: =IFERROR(Z7/Y7-1, " ") -> 0.041941479
B7: Revenue | I7: =IF(ISTEXT('IS Raw'!I11), 'IS Raw'!I17, Input!I5) -> 2451.8793 | J7: =IF(ISTEXT('IS Raw'!J11), 'IS Raw'!J17, Input!J5) -> 1225.068 | K7: =IF(ISTEXT('IS Raw'!K11), 'IS Raw'!K17, Input!K5) -> 1384.9018 | L7: =IF(ISTEXT('IS Raw'!L11), 'IS Raw'!L17, Input!L5) -> 1388.2274 | M7: =IF(ISTEXT('IS Raw'!M11), 'IS Raw'!M17, Input!M5) -> 1401.0243 | N7: =IF(ISTEXT('IS Raw'!N11), 'IS Raw'!N17, Input!N5) -> 1261.729 | O7: =IF(ISTEXT('IS Raw'!O11), 'IS Raw'!O17, Input!O5) -> 1256.9524 | P7: =IF(ISTEXT('IS Raw'!P11), 'IS Raw'!P17, Input!P5) -> 1558.5043 | ... Z7: =IF(ISTEXT('IS Raw'!Z11), 'IS Raw'!Z17, Input!Z5) -> 3122.6339
A9: 2 | B9: COGS (FC) | I9: ='IS Raw'!I21 * (-1) / Input!$B$1 -> 2128.8437 | J9: ='IS Raw'!J21 * (-1) / Input!$B$1 -> 773.07692 | K9: ='IS Raw'!K21 * (-1) / Input!$B$1 -> 875.70244 | L9: ='IS Raw'!L21 * (-1) / Input!$B$1 -> 897.55493 | M9: ='IS Raw'!M21 * (-1) / Input!$B$1 -> 972.89628 | N9: ='IS Raw'!N21 * (-1) / Input!$B$1 -> 846.93308 | O9: ='IS Raw'!O21 * (-1) / Input!$B$1 -> 765.81309 | P9: ='IS Raw'!P21 * (-1) / Input!$B$1 -> 935.93871 | Q9: ='Consol. Rev.'!Q23 -> 1012.6252 | R9: ='Consol. Rev.'!R23 -> 1068.8092 | S9: ='Consol. Rev.'!S23 -> 1296.3682 | T9: ='Consol. Rev.'!T23 -> 1357.3299 | U9: ='Consol. Rev.'!U23 -> 1410.7838 | V9: ='Consol. Rev.'!V23 -> 1465.7027 | W9: ='Consol. Rev.'!W23 -> 1532.2328 | X9: ='Consol. Rev.'!X23 -> 1590.355 | ... Z9: ='Consol. Rev.'!Z23 -> 1720.8581
B10: As % revenue | I10: =IFERROR(I11/I7, " ") -> 0.8682498 | J10: =IFERROR(J11/J7, " ") -> 0.63104815 | K10: =IFERROR(K11/K7, " ") -> 0.63232095 | L10: =IFERROR(L11/L7, " ") -> 0.64654748 | M10: =IFERROR(M11/M7, " ") -> 0.69441784 | N10: =IFERROR(N11/N7, " ") -> 0.671248 | O10: =IFERROR(O11/O7, " ") -> 0.60926182 | P10: =IFERROR(P11/P7, " ") -> 0.60053648 | ... Z10: =IFERROR(Z11/Z7, " ") -> 0.55109184
B11: COGS | I11: =IF(ISTEXT('IS Raw'!I11), -'IS Raw'!I21/Input!$B$1, Input!I9) -> 2128.8437 | J11: =IF(ISTEXT('IS Raw'!J11), -'IS Raw'!J21/Input!$B$1, Input!J9) -> 773.07692 | K11: =IF(ISTEXT('IS Raw'!K11), -'IS Raw'!K21/Input!$B$1, Input!K9) -> 875.70244 | L11: =IF(ISTEXT('IS Raw'!L11), -'IS Raw'!L21/Input!$B$1, Input!L9) -> 897.55493 | M11: =IF(ISTEXT('IS Raw'!M11), -'IS Raw'!M21/Input!$B$1, Input!M9) -> 972.89628 | N11: =IF(ISTEXT('IS Raw'!N11), -'IS Raw'!N21/Input!$B$1, Input!N9) -> 846.93308 | O11: =IF(ISTEXT('IS Raw'!O11), -'IS Raw'!O21/Input!$B$1, Input!O9) -> 765.81309 | P11: =IF(ISTEXT('IS Raw'!P11), -'IS Raw'!P21/Input!$B$1, Input!P9) -> 935.93871 | ... Z11: =IF(ISTEXT('IS Raw'!Z11), -'IS Raw'!Z21/Input!$B$1, Input!Z9) -> 1720.8581
B13: Gross profit (FC) | I13: =I5-I9 -> 323.03559 | J13: =J5-J9 -> 451.99112 | K13: =K5-K9 -> 509.1994 | L13: =L5-L9 -> 490.67247 | M13: =M5-M9 -> 428.12804 | N13: =N5-N9 -> 414.79594 | O13: =O5-O9 -> 491.13928 | P13: =P5-P9 -> 622.56562 | ... Z13: =Z5-Z9 -> 1401.7759
B14: Gross margin | I14: =IFERROR(I15/I7, " ") -> 0.1317502 | J14: =IFERROR(J15/J7, " ") -> 0.36895185 | K14: =IFERROR(K15/K7, " ") -> 0.36767905 | L14: =IFERROR(L15/L7, " ") -> 0.35345252 | M14: =IFERROR(M15/M7, " ") -> 0.30558216 | N14: =IFERROR(N15/N7, " ") -> 0.328752 | O14: =IFERROR(O15/O7, " ") -> 0.39073818 | P14: =IFERROR(P15/P7, " ") -> 0.39946352 | ... Z14: =IFERROR(Z15/Z7, " ") -> 0.44890816
B15: Gross profit | I15: =I7-I11 -> 323.03559 | J15: =J7-J11 -> 451.99112 | K15: =K7-K11 -> 509.1994 | L15: =L7-L11 -> 490.67247 | M15: =M7-M11 -> 428.12804 | N15: =N7-N11 -> 414.79594 | O15: =O7-O11 -> 491.13928 | P15: =P7-P11 -> 622.56562 | ... Z15: =Z7-Z11 -> 1401.7759
B17: SG&A (FC) | I17: =I21+I25 -> 154.66277 | J17: =J21+J25 -> 324.11408 | K17: =K21+K25 -> 351.19045 | L17: =L21+L25 -> 303.73434 | M17: =M21+M25 -> 241.57107 | N17: =N21+N25 -> 254.04639 | O17: =O21+O25 -> 309.3562 | P17: =P21+P25 -> 405.4371 | ... Z17: =Z21+Z25 -> 724.70349
B18: As % revenue | I18: =I19/I7 -> 0.063079275 | J18: =J19/J7 -> 0.26456823 | K18: =K19/K7 -> 0.25358509 | L18: =L19/L7 -> 0.21879293 | M18: =M19/M7 -> 0.17242461 | N18: =N19/N7 -> 0.20134782 | O18: =O19/O7 -> 0.24611609 | P18: =P19/P7 -> 0.26014499 | ... Z18: =Z19/Z7 -> 0.23208083
B19: SG&A | I19: =I23+I27 -> 154.66277 | J19: =J23+J27 -> 324.11408 | K19: =K23+K27 -> 351.19045 | L19: =L23+L27 -> 303.73434 | M19: =M23+M27 -> 241.57107 | N19: =N23+N27 -> 254.04639 | O19: =O23+O27 -> 309.3562 | P19: =P23+P27 -> 405.4371 | ... Z19: =Z23+Z27 -> 724.70349
A21: 3 | B21: Selling expenses (FC) | I21: =-'IS Raw'!I30/$B$1 -> 83.251927 | J21: =-'IS Raw'!J30/$B$1 -> 222.0959 | K21: =-'IS Raw'!K30/$B$1 -> 260.80345 | L21: =-'IS Raw'!L30/$B$1 -> 210.95744 | M21: =-'IS Raw'!M30/$B$1 -> 174.04986 | N21: =-'IS Raw'!N30/$B$1 -> 169.93779 | O21: =-'IS Raw'!O30/$B$1 -> 220.85513 | P21: =-'IS Raw'!P30/$B$1 -> 276.43932 | Q21: ='Consol. Rev.'!Q87 -> 271.18673 | R21: ='Consol. Rev.'!R87 -> 282.91744 | S21: ='Consol. Rev.'!S87 -> 357.18496 | T21: ='Consol. Rev.'!T87 -> 380.98746 | U21: ='Consol. Rev.'!U87 -> 404.88099 | V21: ='Consol. Rev.'!V87 -> 424.59321 | W21: ='Consol. Rev.'!W87 -> 449.18937 | X21: ='Consol. Rev.'!X87 -> 466.53899 | ... Z21: ='Consol. Rev.'!Z87 -> 505.67577
B22: As % revenue | I22: =IFERROR(I23/I7, " ") -> 0.033954333 | J22: =IFERROR(J23/J7, " ") -> 0.1812927 | K22: =IFERROR(K23/K7, " ") -> 0.18831909 | L22: =IFERROR(L23/L7, " ") -> 0.15196173 | M22: =IFERROR(M23/M7, " ") -> 0.12423043 | N22: =IFERROR(N23/N7, " ") -> 0.13468644 | O22: =IFERROR(O23/O7, " ") -> 0.17570684 | P22: =IFERROR(P23/P7, " ") -> 0.17737475 | ... Z22: =IFERROR(Z23/Z7, " ") -> 0.16193886
B23: Selling expenses | I23: =IF(ISTEXT('IS Raw'!I11), -'IS Raw'!I30/Input!$B$1, Input!I21) -> 83.251927 | J23: =IF(ISTEXT('IS Raw'!J11), -'IS Raw'!J30/Input!$B$1, Input!J21) -> 222.0959 | K23: =IF(ISTEXT('IS Raw'!K11), -'IS Raw'!K30/Input!$B$1, Input!K21) -> 260.80345 | L23: =IF(ISTEXT('IS Raw'!L11), -'IS Raw'!L30/Input!$B$1, Input!L21) -> 210.95744 | M23: =IF(ISTEXT('IS Raw'!M11), -'IS Raw'!M30/Input!$B$1, Input!M21) -> 174.04986 | N23: =IF(ISTEXT('IS Raw'!N11), -'IS Raw'!N30/Input!$B$1, Input!N21) -> 169.93779 | O23: =IF(ISTEXT('IS Raw'!O11), -'IS Raw'!O30/Input!$B$1, Input!O21) -> 220.85513 | P23: =IF(ISTEXT('IS Raw'!P11), -'IS Raw'!P30/Input!$B$1, Input!P21) -> 276.43932 | ... Z23: =IF(ISTEXT('IS Raw'!Z11), -'IS Raw'!Z30/Input!$B$1, Input!Z21) -> 505.67577
A25: 4 | B25: Administration expenses (FC) | I25: =-'IS Raw'!I31/$B$1 -> 71.410843 | J25: =-'IS Raw'!J31/$B$1 -> 102.01819 | K25: =-'IS Raw'!K31/$B$1 -> 90.386997 | L25: =-'IS Raw'!L31/$B$1 -> 92.776906 | M25: =-'IS Raw'!M31/$B$1 -> 67.52121 | N25: =-'IS Raw'!N31/$B$1 -> 84.108598 | O25: =-'IS Raw'!O31/$B$1 -> 88.501076 | P25: =-'IS Raw'!P31/$B$1 -> 128.99778 | Q25: ='Consol. Rev.'!Q105 -> 117.46146 | R25: ='Consol. Rev.'!R105 -> 122.54248 | S25: ='Consol. Rev.'!S105 -> 154.71062 | T25: ='Consol. Rev.'!T105 -> 165.0204 | U25: ='Consol. Rev.'!U105 -> 175.36961 | V25: ='Consol. Rev.'!V105 -> 183.90773 | W25: ='Consol. Rev.'!W105 -> 194.56128 | X25: ='Consol. Rev.'!X105 -> 202.07607 | ... Z25: ='Consol. Rev.'!Z105 -> 219.02772
B26: As % revenue | I26: =I27/I7 -> 0.029124942 | J26: =J27/J7 -> 0.083275529 | K26: =K27/K7 -> 0.065265996 | L26: =L27/L7 -> 0.066831203 | M26: =M27/M7 -> 0.048194174 | N26: =N27/N7 -> 0.06666138 | O26: =O27/O7 -> 0.070409251 | P26: =P27/P7 -> 0.082770239 | ... Z26: =Z27/Z7 -> 0.070141979
B27: Administration expenses | I27: =IF(ISTEXT('IS Raw'!I25), 'IS Raw'!I30/Input!$B$1, Input!I25) -> 71.410843 | J27: =IF(ISTEXT('IS Raw'!J25), 'IS Raw'!J30/Input!$B$1, Input!J25) -> 102.01819 | K27: =IF(ISTEXT('IS Raw'!K25), 'IS Raw'!K30/Input!$B$1, Input!K25) -> 90.386997 | L27: =IF(ISTEXT('IS Raw'!L25), 'IS Raw'!L30/Input!$B$1, Input!L25) -> 92.776906 | M27: =IF(ISTEXT('IS Raw'!M25), 'IS Raw'!M30/Input!$B$1, Input!M25) -> 67.52121 | N27: =IF(ISTEXT('IS Raw'!N25), 'IS Raw'!N30/Input!$B$1, Input!N25) -> 84.108598 | O27: =IF(ISTEXT('IS Raw'!O25), 'IS Raw'!O30/Input!$B$1, Input!O25) -> 88.501076 | P27: =IF(ISTEXT('IS Raw'!P25), 'IS Raw'!P30/Input!$B$1, Input!P25) -> 128.99778 | ... Z27: =IF(ISTEXT('IS Raw'!Z25), 'IS Raw'!Z30/Input!$B$1, Input!Z25) -> 219.02772
B29: Operating Expenses (FC) | I29: =I9+I17 -> 2283.5065 | J29: =J9+J17 -> 1097.191 | K29: =K9+K17 -> 1226.8929 | L29: =L9+L17 -> 1201.2893 | M29: =M9+M17 -> 1214.4673 | N29: =N9+N17 -> 1100.9795 | O29: =O9+O17 -> 1075.1693 | P29: =P9+P17 -> 1341.3758 | Q29: =+Q17+Q9 -> 1401.2734 | R29: =+R17+R9 -> 1474.2691 | S29: =+S17+S9 -> 1808.2638 | T29: =+T17+T9 -> 1903.3377 | U29: =+U17+U9 -> 1991.0344 | V29: =+V17+V9 -> 2074.2036 | W29: =+W17+W9 -> 2175.9834 | X29: =+X17+X9 -> 2258.97 | ... Z29: =+Z17+Z9 -> 2445.5616
B30: As % revenue | I30: =I31/I7 -> 0.93132908 | J30: =J31/J7 -> 0.89561638 | K30: =K31/K7 -> 0.88590603 | L30: =L31/L7 -> 0.86534042 | M30: =M31/M7 -> 0.86684245 | N30: =N31/N7 -> 0.87259582 | O30: =O31/O7 -> 0.85537791 | P30: =P31/P7 -> 0.86068148 | ... Z30: =Z31/Z7 -> 0.78317267
B31: Operating Expense | I31: =I11+I19 -> 2283.5065 | J31: =J11+J19 -> 1097.191 | K31: =K11+K19 -> 1226.8929 | L31: =L11+L19 -> 1201.2893 | M31: =M11+M19 -> 1214.4673 | N31: =N11+N19 -> 1100.9795 | O31: =O11+O19 -> 1075.1693 | P31: =P11+P19 -> 1341.3758 | ... Z31: =Z11+Z19 -> 2445.5616
B33: EBITDA (FC) | I33: =I13-I17+I37 -> 236.74427 | J33: =J13-J17+J37 -> 167.09401 | K33: =K13-K17+K37 -> 191.80278 | L33: =L13-L17+L37 -> 223.75197 | M33: =M13-M17+M37 -> 223.07388 | N33: =N13-N17+N37 -> 188.69458 | O33: =O13-O17+O37 -> 213.59206 | P33: =P13-P17+P37 -> 257.80265 | ... Z33: =Z13-Z17+Z37 -> 820.28519
B34: EBITDA margin | I34: =I35/I7 -> 0.096556251 | J34: =J35/J7 -> 0.1363957 | K34: =K35/K7 -> 0.13849558 | L34: =L35/L7 -> 0.16117818 | M34: =M35/M7 -> 0.15922199 | N34: =N35/N7 -> 0.14955238 | O34: =O35/O7 -> 0.16992853 | P34: =P35/P7 -> 0.1654167 | ... Z34: =Z35/Z7 -> 0.26269015
B35: EBITDA | I35: =I15-I19+I40 -> 236.74427 | J35: =J15-J19+J40 -> 167.09401 | K35: =K15-K19+K40 -> 191.80278 | L35: =L15-L19+L40 -> 223.75197 | M35: =M15-M19+M40 -> 223.07388 | N35: =N15-N19+N40 -> 188.69458 | O35: =O15-O19+O40 -> 213.59206 | P35: =P15-P19+P40 -> 257.80265 | ... Z35: =Z15-Z19+Z40 -> 820.28519
A37: 5 | B37: Depreciation/ Amortization (FC) | I37: ='Output-FR (show)'!I132 -> 68.371455 | J37: ='Output-FR (show)'!J132 -> 39.216982 | K37: ='Output-FR (show)'!K132 -> 33.793831 | L37: ='Output-FR (show)'!L132 -> 36.813842 | M37: ='Output-FR (show)'!M132 -> 36.516915 | N37: ='Output-FR (show)'!N132 -> 27.945022 | O37: ='Output-FR (show)'!O132 -> 31.808991 | P37: ='Output-FR (show)'!P132 -> 40.674128 | Q37: ='LT. Asset'!Q8 -> 101.71289 | R37: ='LT. Asset'!R8 -> 133.59327 | S37: ='LT. Asset'!S8 -> 140.73853 | T37: ='LT. Asset'!T8 -> 99.911275 | U37: ='LT. Asset'!U8 -> 98.416264 | V37: ='LT. Asset'!V8 -> 107.27936 | W37: ='LT. Asset'!W8 -> 116.95323 | X37: ='LT. Asset'!X8 -> 125.34045 | ... Z37: ='LT. Asset'!Z8 -> 143.21282
B38: As % revenue | I38: =I40/I7 -> 0.027885327 | J38: =J40/J7 -> 0.032012085 | K38: =K40/K7 -> 0.024401608 | L38: =L40/L7 -> 0.026518597 | M38: =M40/M7 -> 0.026064441 | N38: =N40/N7 -> 0.022148196 | O38: =O40/O7 -> 0.025306441 | P38: =P40/P7 -> 0.026098181 | ... Z38: =Z40/Z7 -> 0.045862827
B39: As % prior fixed assets
B40: Depreciation/ Amortization | I40: =I37 -> 68.371455 | J40: =J37 -> 39.216982 | K40: =K37 -> 33.793831 | L40: =L37 -> 36.813842 | M40: =M37 -> 36.516915 | N40: =N37 -> 27.945022 | O40: =O37 -> 31.808991 | P40: =P37 -> 40.674128 | ... Z40: =Z37 -> 143.21282
B41: As % revenue | I41: =I38 -> 0.027885327 | J41: =J38 -> 0.032012085 | K41: =K38 -> 0.024401608 | L41: =L38 -> 0.026518597 | M41: =M38 -> 0.026064441 | N41: =N38 -> 0.022148196 | O41: =O38 -> 0.025306441 | P41: =P38 -> 0.026098181 | ... Z41: =Z38 -> 0.045862827
B42: Depreciation of tangibles
B43: Amortization of intangibles
B45: EBIT (FC) | I45: =I33-I37 -> 168.37282 | J45: =J33-J37 -> 127.87703 | K45: =K33-K37 -> 158.00895 | L45: =L33-L37 -> 186.93813 | M45: =M33-M37 -> 186.55697 | N45: =N33-N37 -> 160.74955 | O45: =O33-O37 -> 181.78307 | P45: =P33-P37 -> 217.12852 | Q45: =Q13-Q17 -> 273.35082 | R45: =R13-R17 -> 272.79423 | S45: =S13-S17 -> 397.41417 | T45: =T13-T17 -> 449.3247 | U45: =U13-U17 -> 509.17464 | V45: =V13-V17 -> 547.73174 | W45: =W13-W17 -> 597.83741 | X45: =X13-X17 -> 621.98761 | ... Z45: =Z13-Z17 -> 677.07237
B46: EBIT margin | I46: =I47/I7 -> 0.068670925 | J46: =J47/J7 -> 0.10438362 | K46: =K47/K7 -> 0.11409397 | L46: =L47/L7 -> 0.13465958 | M46: =M47/M7 -> 0.13315755 | N46: =N47/N7 -> 0.12740418 | O46: =O47/O7 -> 0.14462209 | P46: =P47/P7 -> 0.13931852 | ... Z46: =Z47/Z7 -> 0.21682733
B47: EBIT | I47: =I35-I40 -> 168.37282 | J47: =J35-J40 -> 127.87703 | K47: =K35-K40 -> 158.00895 | L47: =L35-L40 -> 186.93813 | M47: =M35-M40 -> 186.55697 | N47: =N35-N40 -> 160.74955 | O47: =O35-O40 -> 181.78307 | P47: =P35-P40 -> 217.12852 | ... Z47: =Z35-Z40 -> 677.07237
A49: 6 | B49: Gain (loss) on asset sales (FC) (thu nhập khác) | I49: ='IS Raw'!I33/Input!$B$1 -> 8.7732738 | J49: ='IS Raw'!J33/Input!$B$1 -> 144.1416 | K49: ='IS Raw'!K33/Input!$B$1 -> 0.22343835 | L49: ='IS Raw'!L33/Input!$B$1 -> 0.68875095 | M49: ='IS Raw'!M33/Input!$B$1 -> 0.23141078 | N49: ='IS Raw'!N33/Input!$B$1 -> 0.34645156 | O49: ='IS Raw'!O33/Input!$B$1 -> 2.8734188 | P49: ='IS Raw'!P33/Input!$B$1 -> 1.8696857 | Q49: =AVERAGE(K49:P49) -> 1.0388594 | R49: =AVERAGE(L49:Q49) -> 1.1747629 | S49: =AVERAGE(M49:R49) -> 1.2557648 | T49: =AVERAGE(N49:S49) -> 1.4264905 | U49: =AVERAGE(O49:T49) -> 1.606497 | V49: =AVERAGE(P49:U49) -> 1.3953434 | W49: =AVERAGE(Q49:V49) -> 1.3162863 | X49: =AVERAGE(R49:W49) -> 1.3625242 | ... Z49: =AVERAGE(T49:Y49) -> 1.4168265
B50: Gross proceeds from asset sales
B51: Book value of assets sold
B52: Gain (loss) on asset sales | I52: =IF(ISTEXT('IS Raw'!I11), 'IS Raw'!I33/Input!$B$1, Input!I49) -> 8.7732738 | J52: =IF(ISTEXT('IS Raw'!J11), 'IS Raw'!J33/Input!$B$1, Input!J49) -> 144.1416 | K52: =IF(ISTEXT('IS Raw'!K11), 'IS Raw'!K33/Input!$B$1, Input!K49) -> 0.22343835 | L52: =IF(ISTEXT('IS Raw'!L11), 'IS Raw'!L33/Input!$B$1, Input!L49) -> 0.68875095 | M52: =IF(ISTEXT('IS Raw'!M11), 'IS Raw'!M33/Input!$B$1, Input!M49) -> 0.23141078 | N52: =IF(ISTEXT('IS Raw'!N11), 'IS Raw'!N33/Input!$B$1, Input!N49) -> 0.34645156 | O52: =IF(ISTEXT('IS Raw'!O11), 'IS Raw'!O33/Input!$B$1, Input!O49) -> 2.8734188 | P52: =IF(ISTEXT('IS Raw'!P11), 'IS Raw'!P33/Input!$B$1, Input!P49) -> 1.8696857 | ... Z52: =IF(ISTEXT('IS Raw'!Z11), 'IS Raw'!Z33/Input!$B$1, Input!Z49) -> 1.4168265
A54: 7 | B54: Non-Operating expenses (FC) (chi phí khác) | I54: =-'IS Raw'!I34/Input!$B$1 -> 0.98062655 | J54: =-'IS Raw'!J34/Input!$B$1 -> 0.061872556 | K54: =-'IS Raw'!K34/Input!$B$1 -> 0.1867886 | L54: =-'IS Raw'!L34/Input!$B$1 -> 0.022626147 | M54: =-'IS Raw'!M34/Input!$B$1 -> 0.21626276 | N54: =-'IS Raw'!N34/Input!$B$1 -> 0.15042521 | O54: =-'IS Raw'!O34/Input!$B$1 -> 0.12983325 | P54: =-'IS Raw'!P34/Input!$B$1 -> -0.30660157 | Q54: =AVERAGE(J54:O54) -> 0.12796809 | R54: =Q54 -> 0.12796809 | S54: =R54 -> 0.12796809 | T54: =S54 -> 0.12796809 | U54: =T54 -> 0.12796809 | V54: =U54 -> 0.12796809 | W54: =V54 -> 0.12796809 | X54: =W54 -> 0.12796809 | Y54: =X54 -> 0.12796809 | Z54: =Y54 -> 0.12796809
B55: As % revenue | I55: =I54/I7 -> 0.00039994895 | J55: =J54/J7 -> 5.0505404e-05 | K55: =K54/K7 -> 0.00013487497 | L55: =L54/L7 -> 1.6298588e-05 | M55: =M54/M7 -> 0.00015436046 | N55: =N54/N7 -> 0.00011922148 | O55: =O54/O7 -> 0.0001032921 | P55: =P54/P7 -> -0.00019672808 | ... Z55: =Z54/Z7 -> 4.0980816e-05
B56: Non-Operating expenses | I56: =IF(ISTEXT('IS Raw'!I11), -'IS Raw'!I34/$B$1, Input!I54) -> 0.98062655 | J56: =IF(ISTEXT('IS Raw'!J11), -'IS Raw'!J34/$B$1, Input!J54) -> 0.061872556 | K56: =IF(ISTEXT('IS Raw'!K11), -'IS Raw'!K34/$B$1, Input!K54) -> 0.1867886 | L56: =IF(ISTEXT('IS Raw'!L11), -'IS Raw'!L34/$B$1, Input!L54) -> 0.022626147 | M56: =IF(ISTEXT('IS Raw'!M11), -'IS Raw'!M34/$B$1, Input!M54) -> 0.21626276 | N56: =IF(ISTEXT('IS Raw'!N11), -'IS Raw'!N34/$B$1, Input!N54) -> 0.15042521 | O56: =IF(ISTEXT('IS Raw'!O11), -'IS Raw'!O34/$B$1, Input!O54) -> 0.12983325 | P56: =IF(ISTEXT('IS Raw'!P11), -'IS Raw'!P34/$B$1, Input!P54) -> -0.30660157 | ... Z56: =IF(ISTEXT('IS Raw'!Z11), -'IS Raw'!Z34/$B$1, Input!Z54) -> 0.12796809
A58: 8 | B58: Financial Revenues (FC) | I58: ='IS Raw'!I26/$B$1 -> 4.2809301 | J58: ='IS Raw'!J26/$B$1 -> 17.714871 | K58: ='IS Raw'!K26/$B$1 -> 16.213594 | L58: ='IS Raw'!L26/$B$1 -> 18.773405 | M58: ='IS Raw'!M26/$B$1 -> 16.074493 | N58: ='IS Raw'!N26/$B$1 -> 13.251147 | O58: ='IS Raw'!O26/$B$1 -> 7.7517822 | P58: ='IS Raw'!P26/$B$1 -> 6.3201839 | Q58: =Q59+SUM(Q62:Q65) -> 17.147038 | R58: =R59+SUM(R62:R65) -> 22.53851 | S58: =S59+SUM(S62:S65) -> 25.728231 | T58: =T59+SUM(T62:T65) -> 32.164056 | U58: =U59+SUM(U62:U65) -> 40.59125 | V58: =V59+SUM(V62:V65) -> 52.437401 | W58: =W59+SUM(W62:W65) -> 64.008195 | X58: =X59+SUM(X62:X65) -> 72.944639 | ... Z58: =Z59+SUM(Z62:Z65) -> 97.600235
B59: Interest income | I59: =SUM(I60,I61) -> 1.3775034 | J59: =SUM(J60,J61) -> 10.617685 | K59: =SUM(K60,K61) -> 14.798432 | L59: =SUM(L60,L61) -> 16.871726 | M59: =SUM(M60,M61) -> 15.03361 | N59: =SUM(N60,N61) -> 11.915987 | O59: =SUM(O60,O61) -> 6.1646358 | P59: =SUM(P60,P61) -> 5.13748 | Q59: =Q60+Q61 -> 16.029505 | R59: =R60+R61 -> 21.372635 | S59: =S60+S61 -> 24.256306 | T59: =T60+T61 -> 30.594044 | U59: =U60+U61 -> 38.922775 | V59: =V60+V61 -> 50.687694 | W59: =W60+W61 -> 62.15713 | X59: =X60+X61 -> 71.022078 | ... Z59: =Z60+Z61 -> 95.516394
B60: Excess cash | Q60: =Q157 -> 0.49001041 | R60: =R157 -> 0.68284457 | S60: =S157 -> 0.24740199 | T60: =T157 -> 0.17648897 | U60: =U157 -> 0.22905285 | V60: =V157 -> 0.11276058 | W60: =W157 -> 0.14724957 | X60: =X157 -> 0.36627085 | ... Z60: =Z157 -> 0.39059684
B61: Operating cash | I61: =Notes!I148/$B$1 -> 1.3775034 | J61: =Notes!J148/$B$1 -> 10.617685 | K61: =Notes!K148/$B$1 -> 14.798432 | L61: =Notes!L148/$B$1 -> 16.871726 | M61: =Notes!M148/$B$1 -> 15.03361 | N61: =Notes!N148/$B$1 -> 11.915987 | O61: =Notes!O148/$B$1 -> 6.1646358 | P61: =Notes!P148/$B$1 -> 5.13748 | Q61: =Q165+Q175 -> 15.539494 | R61: =R165+R175 -> 20.689791 | S61: =S165+S175 -> 24.008904 | T61: =T165+T175 -> 30.417555 | U61: =U165+U175 -> 38.693722 | V61: =V165+V175 -> 50.574934 | W61: =W165+W175 -> 62.00988 | X61: =X165+X175 -> 70.655807 | ... Z61: =Z165+Z175 -> 95.125798
B62: Marketable securities (Lãi chuyển nhượng chứng khoán) | I62: =Notes!I149/$B$1 -> 0 | J62: =Notes!J149/$B$1 -> 0 | K62: =Notes!K149/$B$1 -> 0 | L62: =Notes!L149/$B$1 -> 0 | M62: =Notes!M149/$B$1 -> 0 | N62: =Notes!N149/$B$1 -> 0 | O62: =Notes!O149/$B$1 -> 0 | P62: =Notes!P149/$B$1 -> 0 | Q62: 0 | R62: =Q62 -> 0 | S62: =R62 -> 0 | T62: =S62 -> 0 | U62: =T62 -> 0 | V62: =U62 -> 0 | W62: =V62 -> 0 | X62: =W62 -> 0 | Y62: =X62 -> 0 | Z62: =Y62 -> 0
B63: Profits/dividends receive | I63: =Notes!I150/$B$1 -> 0.1159848 | J63: =Notes!J150/$B$1 -> 5.264568 | K63: =Notes!K150/$B$1 -> 0.1850598 | L63: =Notes!L150/$B$1 -> 0.83371767 | M63: =Notes!M150/$B$1 -> 0.7103539 | N63: =Notes!N150/$B$1 -> 1.01571 | O63: =Notes!O150/$B$1 -> 0.891 | P63: =Notes!P150/$B$1 -> 0 | Q63: 0 | R63: =Q63 -> 0 | S63: =R63 -> 0 | T63: =S63 -> 0 | U63: =T63 -> 0 | V63: =U63 -> 0 | W63: =V63 -> 0 | X63: =W63 -> 0 | Y63: =X63 -> 0 | Z63: =Y63 -> 0
B64: Lãi từ bán, thanh lý các khoản đầu tư | I64: =Notes!I151/$B$1 -> 0 | J64: =Notes!J151/$B$1 -> 0 | K64: =Notes!K151/$B$1 -> 0 | L64: =Notes!L151/$B$1 -> 0 | M64: =Notes!M151/$B$1 -> 0 | N64: =Notes!N151/$B$1 -> 0 | O64: =Notes!O151/$B$1 -> 0 | P64: =Notes!P151/$B$1 -> 0 | Q64: 0 | R64: =Q64 -> 0 | S64: =R64 -> 0 | T64: =S64 -> 0 | U64: =T64 -> 0 | V64: =U64 -> 0 | W64: =V64 -> 0 | X64: =W64 -> 0 | Y64: =X64 -> 0 | Z64: =Y64 -> 0
