Workbook

Sheet IS Raw
A5: Tính năng | B5: Kết quả kinh doanh - DCM
A6: Ngày trích xuất | B6: 45860.705
A8: Mã CK | B8: DCM | D8: Xem theo | E8: Hằng năm | F8: 2025
A9: Loại | B9: Hợp nhất | D9: Tiền tệ | E9: VND | F9: Tỷ VND
A11: Chỉ tiêuTỷ VND | B11: 2015 | C11: 2016 | D11: 2017 | E11: 2018 | F11: 2019 | G11: 2020 | H11: 2021 | I11: 2022 | J11: 2023 | K11: 2024
A12: Trạng thái kiểm toán | B12: Đã kiểm toán | C12: Đã kiểm toán | D12: Đã kiểm toán | E12: Đã kiểm toán | F12: Đã kiểm toán | G12: Đã kiểm toán | H12: Đã kiểm toán | I12: Đã kiểm toán | J12: Đã kiểm toán | K12: Đã kiểm toán
A13: Công ty kiểm toán | B13: Deloitte Vietnam Audit Co., Ltd | C13: Deloitte Vietnam Audit Co., Ltd | D13: Deloitte Vietnam Audit Co., Ltd | F13: Deloitte Vietnam Audit Co., Ltd | G13: Deloitte Vietnam Audit Co., Ltd | H13: PwC Vietnam | I13: Deloitte Vietnam Audit Co., Ltd | J13: Deloitte Vietnam Audit Co., Ltd | K13: Deloitte Vietnam Audit Co., Ltd
A14: Loại ý kiến kiểm toán | B14: Chấp nhận toàn phần | C14: Chấp nhận toàn phần | D14: Chấp nhận toàn phần | F14: Chấp nhận toàn phần | G14: Chấp nhận toàn phần | H14: Chấp nhận toàn phần | I14: Chấp nhận toàn phần | J14: Chấp nhận toàn phần | K14: Chấp nhận toàn phần
A15: Doanh thu bán hàng và cung cấp dịch vụ | B15: 6002.7467 | C15: 4971.7489 | D15: 5832.9733 | E15: 6827.3338 | F15: 7176.5755 | G15: 7716.8905 | H15: 10088.157 | I15: 16380.04 | J15: 12949.489 | K15: 13942.548
A16: Các khoản giảm trừ doanh thu | B16: -94.14422 | C16: -61.57826 | D16: -85.218359 | E16: -138.00525 | F16: -133.60855 | G16: -155.61538 | H16: -218.39418 | I16: -455.5129 | J16: -378.94707 | K16: -486.9631
A17: Doanh thu thuần | B17: 5908.6025 | C17: 4910.1707 | D17: 5747.755 | E17: 6689.3285 | F17: 7042.9669 | G17: 7561.2751 | H17: 9869.7629 | I17: 15924.527 | J17: 12570.542 | K17: 13455.585
A18: Giá vốn hàng bán | B18: -4098.6635 | C18: -3595.5077 | D18: -4366.4525 | E18: -5252.2705 | F18: -6083.7747 | G18: -6244.4273 | H18: -7088.826 | I18: -10221.097 | J18: -10538.742 | K18: -10942.101
A19: Lợi nhuận gộp về bán hàng và cung cấp dịch vụ | B19: 1809.939 | C19: 1314.6629 | D19: 1381.3025 | E19: 1437.058 | F19: 959.1922 | G19: 1316.8478 | H19: 2780.9369 | I19: 5703.4294 | J19: 2031.7997 | K19: 2513.4843
A20: Doanh thu hoạt động tài chính | B20: 232.67253 | C20: 281.35201 | D20: 168.76274 | E20: 176.15302 | F20: 127.01614 | G20: 128.31668 | H20: 167.53191 | I20: 301.00806 | J20: 577.08849 | K20: 381.8039
A21: Chi phí tài chính | B21: -648.18169 | C21: -432.71948 | D21: -202.88878 | E21: -260.13015 | F21: -102.75348 | G21: -63.234525 | H21: -45.07293 | I21: -60.402057 | J21: -27.372488 | K21: -76.569108
A22: Trong đó: Chi phí lãi vay | B22: -242.45234 | C22: -206.62239 | D22: -182.98653 | E22: -142.05277 | F22: -87.17253 | G22: -43.301059 | H22: -18.580201 | I22: -10.274784 | J22: -10.155714 | K22: -44.380805
A23: Lãi/(lỗ) từ công ty liên doanh (từ năm 2015) | B23: 0 | C23: 0 | D23: 0 | E23: 0 | F23: 0 | G23: 0 | H23: 0 | I23: 0 | J23: 0 | K23: 0
A24: Chi phí bán hàng | B24: -275.65392 | C24: -275.83301 | D24: -333.60031 | E24: -336.1147 | F24: -364.0587 | G24: -369.00032 | H24: -420.40125 | I24: -698.29487 | J24: -800.63146 | K24: -1014.3698
A25: Chi phí quản lý doanh nghiệp | B25: -203.31141 | C25: -254.75383 | D25: -337.35087 | E25: -320.10336 | F25: -201.3192 | G25: -304.40666 | H25: -528.49174 | I25: -652.59426 | J25: -548.55689 | K25: -481.047
A26: Lãi/(lỗ) từ hoạt động kinh doanh | B26: 915.46453 | C26: 632.70863 | D26: 676.22523 | E26: 696.86285 | F26: 418.07696 | G26: 708.52298 | H26: 1954.5029 | I26: 4593.1463 | J26: 1232.3273 | K26: 1323.3022
... A39: Lãi trên cổ phiếu pha loãng (VND) | B39: 0 | C39: 0 | D39: 0 | E39: 0 | F39: 0 | G39: 0 | H39: 3073 | I39: 0 | J39: 0 | K39: 0
A41: Contact
A42: CÔNG TY CỔ PHẦN FIINGROUP VIỆT NAM
A43: Trụ sở: Tầng 10, Tòa nhà PeakView, 36 Hoàng Cầu, Đống Đa, Hà Nội, Việt Nam
A44: Chi nhánh: Tầng 16, Tòa nhà Bitexco Financial Tower, số 2 Hải Triều , Phường Bến Nghé, Quận 1, TP. Hồ Chí Minh, Việt Nam
A45: Website: https://fiingroup.vn
A47: TRUNG TÂM CHĂM SÓC KHÁCH HÀNG
A48: T: (84-24) - 3562 6962 - Ext: 103
A49: Email: fiinpro.support@fiingroup.vn

Sheet BS Raw
A5: Tính năng | B5: Bảng cân đối kế toán - DCM
A6: Ngày trích xuất | B6: 45860.705
A8: Mã CK | B8: DCM | D8: Xem theo | E8: Hằng năm | F8: 2025
A9: Loại | B9: Hợp nhất | D9: Tiền tệ | E9: VND | F9: Tỷ VND
A11: Chỉ tiêuTỷ VND | B11: 2015 | C11: 2016 | D11: 2017 | E11: 2018 | F11: 2019 | G11: 2020 | H11: 2021 | I11: 2022 | J11: 2023 | K11: 2024
A12: Trạng thái kiểm toán | B12: Đã kiểm toán | C12: Đã kiểm toán | D12: Đã kiểm toán | E12: Đã kiểm toán | F12: Đã kiểm toán | G12: Đã kiểm toán | H12: Đã kiểm toán | I12: Đã kiểm toán | J12: Đã kiểm toán | K12: Đã kiểm toán
A13: Công ty kiểm toán | B13: Deloitte Vietnam Audit Co., Ltd | C13: Deloitte Vietnam Audit Co., Ltd | D13: Deloitte Vietnam Audit Co., Ltd | F13: Deloitte Vietnam Audit Co., Ltd | G13: Deloitte Vietnam Audit Co., Ltd | H13: PwC Vietnam | I13: Deloitte Vietnam Audit Co., Ltd | J13: Deloitte Vietnam Audit Co., Ltd | K13: Deloitte Vietnam Audit Co., Ltd
A14: Loại ý kiến kiểm toán | B14: Chấp nhận toàn phần | C14: Chấp nhận toàn phần | D14: Chấp nhận toàn phần | F14: Chấp nhận toàn phần | G14: Chấp nhận toàn phần | H14: Chấp nhận toàn phần | I14: Chấp nhận toàn phần | J14: Chấp nhận toàn phần | K14: Chấp nhận toàn phần
A15: TÀI SẢN NGẮN HẠN | B15: 4431.3566 | C15: 4034.4151 | D15: 4838.7091 | E15: 4318.349 | F15: 4250.037 | G15: 3978.1921 | H15: 7276.2916 | I15: 11624.187 | J15: 13504.495 | K15: 12920.863
A16: Tiền và tương đương tiền | B16: 1215.0793 | C16: 813.51875 | D16: 1896.1849 | E16: 285.77246 | F16: 471.17332 | G16: 509.99535 | H16: 427.65273 | I16: 2125.6253 | J16: 2284.3998 | K16: 1903.2483
A17: Tiền | B17: 183.07933 | C17: 481.51875 | D17: 393.83489 | E17: 165.77246 | F17: 371.17332 | G17: 289.99535 | H17: 427.65273 | I17: 2125.6253 | J17: 2274.3998 | K17: 1903.2483
A18: Các khoản tương đương tiền | B18: 1032 | C18: 332 | D18: 1502.35 | E18: 120 | F18: 100 | G18: 220 | H18: 0 | I18: 0 | J18: 10 | K18: 0
A19: Giá trị thuần đầu tư ngắn hạn | B19: 2702.5556 | C19: 2300 | D19: 2100 | E19: 2502 | F19: 2002 | G19: 2302 | H19: 4362 | I19: 6812 | J19: 8242 | K19: 7039.0512
A20: Đầu tư ngắn hạn | B20: 0 | C20: 0 | D20: 0 | E20: 0 | F20: 0 | G20: 0 | H20: 0 | I20: 0 | J20: 0 | K20: 0
A21: Dự phòng đầu tư ngắn hạn | B21: 0 | C21: 0 | D21: 0 | E21: 0 | F21: 0 | G21: 0 | H21: 0 | I21: 0 | J21: 0 | K21: 0
A22: Đầu tư nắm giữ đến ngày đáo hạn | B22: 2702.5556 | C22: 2300 | D22: 2100 | E22: 2502 | F22: 2002 | G22: 2302 | H22: 4362 | I22: 6812 | J22: 8242 | K22: 7039.0512
A23: Các khoản phải thu | B23: 79.842094 | C23: 481.71633 | D23: 400.47866 | E23: 452.94998 | F23: 401.90973 | G23: 217.3963 | H23: 187.45808 | I23: 188.14971 | J23: 365.83833 | K23: 528.62319
A24: Phải thu khách hàng | B24: 7.2613277 | C24: 6.8141083 | D24: 1.2981874 | E24: 17.543502 | F24: 2.9264002 | G24: 44.753555 | H24: 44.653507 | I24: 1.4047958 | J24: 198.51199 | K24: 298.9049
A25: Trả trước người bán | B25: 14.976365 | C25: 18.741754 | D25: 88.361011 | E25: 86.367566 | F25: 55.315028 | G25: 15.505616 | H25: 86.006714 | I25: 86.290004 | J25: 54.781184 | K25: 225.764
A26: Phải thu nội bộ | B26: 0 | C26: 0 | D26: 0 | E26: 0 | F26: 0 | G26: 0 | H26: 0 | I26: 0 | J26: 0 | K26: 0
... A108: Thuế thu nhập hoãn lại phải trả | B108: 0 | C108: 0 | D108: 0 | E108: 0 | F108: 0 | G108: 0 | H108: 0 | I108: 0 | J108: 0 | K108: 0
A109: Dự phòng trợ cấp thôi việc
A110: Dự phòng các khoản công nợ dài hạn | B110: 0 | C110: 0 | D110: 0 | E110: 0 | F110: 0 | G110: 0 | H110: 0 | I110: 0 | J110: 0 | K110: 0
A111: Quỹ phát triển khoa học công nghệ | B111: 35.127225 | C111: 41.572332 | D111: 103.43752 | E111: 156.50848 | F111: 137.79715 | G111: 203.81901 | H111: 404.73717 | I111: 685.92744 | J111: 754.36092 | K111: 751.41313
A112: VỐN CHỦ SỞ HỮU | B112: 6233.1928 | C112: 5850.2431 | D112: 6153.522 | E112: 6268.8723 | F112: 6106.3273 | G112: 6326.4477 | H112: 7478.0973 | I112: 10605.449 | J112: 9963.3832 | K112: 10177.177
A113: Vốn và các quỹ | B113: 6233.1928 | C113: 5850.2431 | D113: 6153.522 | E113: 6268.8723 | F113: 6106.3273 | G113: 6326.4477 | H113: 7478.0973 | I113: 10605.449 | J113: 9963.3832 | K113: 10177.177
A114: Vốn góp | B114: 5294 | C114: 5294 | D114: 5294 | E114: 5294 | F114: 5294 | G114: 5294 | H114: 5294 | I114: 5294 | J114: 5294 | K114: 5294
A115: Cổ phiếu phổ thông | B115: 5294 | C115: 5294 | D115: 5294 | E115: 5294 | F115: 5294 | G115: 5294 | H115: 5294 | I115: 5294 | J115: 5294 | K115: 5294
A116: Cổ phiếu ưu đãi | B116: 0 | C116: 0 | D116: 0 | E116: 0 | F116: 0 | G116: 0 | H116: 0 | I116: 0 | J116: 0 | K116: 0
A117: Thặng dư vốn cổ phần | B117: 0 | C117: 0 | D117: 0 | E117: 0 | F117: 0 | G117: 0 | H117: 0 | I117: 0 | J117: 0 | K117: 0
A118: Quyền chọn chuyển đổi trái phiếu | B118: 0 | C118: 0 | D118: 0 | E118: 0 | F118: 0 | G118: 0 | H118: 0 | I118: 0 | J118: 0 | K118: 0
A119: Vốn khác | B119: 0 | C119: 0 | D119: 0 | E119: 2.49915 | F119: 3.66542 | G119: 3.66542 | H119: 3.66542 | I119: 3.66542 | J119: 3.66542 | K119: 3.66542
A120: Cổ phiếu quỹ | B120: 0 | C120: 0 | D120: 0 | E120: 0 | F120: 0 | G120: 0 | H120: 0 | I120: 0 | J120: 0 | K120: 0
A121: Chênh lệch đánh giá lại tài sản | B121: 0 | C121: 0 | D121: 0 | E121: 0 | F121: 0 | G121: 0 | H121: 0 | I121: 0 | J121: 0 | K121: 0
... A124: Quỹ hỗ trợ sắp xếp doanh nghiệp | B124: 0 | C124: 0 | D124: 0 | E124: 0 | F124: 0 | G124: 0 | H124: 0 | I124: 0 | J124: 0 | K124: 0
A125: Quỹ dự phòng tài chính
A126: Quỹ khác | B126: 0 | C126: 0 | D126: 0 | E126: 0 | F126: 0 | G126: 0 | H126: 0 | I126: 0 | J126: 0 | K126: 0
A127: Lãi chưa phân phối | B127: 543.4136 | C127: 368.28854 | D127: 594.40372 | E127: 626.04216 | F127: 428.84563 | G127: 583.46741 | H127: 1187.9854 | I127: 3018.4551 | J127: 2044.8513 | K127: 1882.5131
A128: LNST chưa phân phối lũy kế đến cuối kỳ trước | B128: 1.6456001 | C128: 0.57033728 | D128: 98.105509 | E128: 114.02546 | F128: 146.20975 | G128: 110.77882 | H128: 106.42934 | I128: 234.72596 | J128: 1425.163 | K128: 984.14775
A129: LNST chưa phân phối kỳ này | B129: 541.768 | C129: 367.7182 | D129: 496.29821 | E129: 512.0167 | F129: 282.63589 | G129: 472.68859 | H129: 1081.5561 | I129: 2783.7291 | J129: 619.68831 | K129: 898.36535
A130: Lợi ích cổ đông không kiểm soát | B130: 23.141315 | C130: 26.890811 | D130: 26.382774 | E130: 28.597674 | F130: 27.277893 | G130: 26.347426 | H130: 26.588185 | I130: 29.143335 | J130: 27.591066 | K130: 32.786197
A131: Vốn Ngân sách nhà nước và quỹ khác | B131: 0 | C131: 0 | D131: 0 | E131: 0 | F131: 0 | G131: 0 | H131: 0 | I131: 0 | J131: 0 | K131: 0
A132: Quỹ khen thưởng, phúc lợi (trước 2010) | B132: 0 | C132: 0 | D132: 0 | E132: 0 | F132: 0 | G132: 0 | H132: 0 | I132: 0 | J132: 0 | K132: 0
A133: Vốn ngân sách nhà nước | B133: 0 | C133: 0 | D133: 0 | E133: 0 | F133: 0 | G133: 0 | H133: 0 | I133: 0 | J133: 0 | K133: 0
A134: Nguồn kinh phí đã hình thành TSCĐ | B134: 0 | C134: 0 | D134: 0 | E134: 0 | F134: 0 | G134: 0 | H134: 0 | I134: 0 | J134: 0 | K134: 0
A135: LỢI ÍCH CỦA CỔ ĐÔNG THIỂU SỐ | B135: 0 | C135: 0 | D135: 0 | E135: 0 | F135: 0 | G135: 0 | H135: 0 | I135: 0 | J135: 0 | K135: 0
A136: TỔNG CỘNG NGUỒN VỐN | B136: 14478.619 | C136: 12967.052 | D136: 12456.164 | E136: 11030.586 | F136: 10172.595 | G136: 8717.4807 | H136: 11072.121 | I136: 14166.861 | J136: 15237.966 | K136: 15728.847
A138: Contact
A139: CÔNG TY CỔ PHẦN FIINGROUP VIỆT NAM
A140: Trụ sở: Tầng 10, Tòa nhà PeakView, 36 Hoàng Cầu, Đống Đa, Hà Nội, Việt Nam
A141: Chi nhánh: Tầng 16, Tòa nhà Bitexco Financial Tower, số 2 Hải Triều , Phường Bến Nghé, Quận 1, TP. Hồ Chí Minh, Việt Nam
A142: Website: https://fiingroup.vn
A144: TRUNG TÂM CHĂM SÓC KHÁCH HÀNG
A145: T: (84-24) - 3562 6962 - Ext: 103
A146: Email: fiinpro.support@fiingroup.vn

Sheet CF Raw
A5: Tính năng | B5: Lưu chuyển tiền tệ - DCM
A6: Ngày trích xuất | B6: 45860.705
A8: Mã CK | B8: DCM | D8: Xem theo | E8: Hằng năm | F8: 2025
A9: Loại | B9: Hợp nhất | D9: Tiền tệ | E9: VND | F9: Tỷ VND
A11: Chỉ tiêuTỷ VND | B11: 2015 | C11: 2016 | D11: 2017 | E11: 2018 | F11: 2019 | G11: 2020 | H11: 2021 | I11: 2022 | J11: 2023 | K11: 2024
A12: Trạng thái kiểm toán | B12: Đã kiểm toán | C12: Đã kiểm toán | D12: Đã kiểm toán | E12: Đã kiểm toán | F12: Đã kiểm toán | G12: Đã kiểm toán | H12: Đã kiểm toán | I12: Đã kiểm toán | J12: Đã kiểm toán | K12: Đã kiểm toán
A13: Công ty kiểm toán | B13: Deloitte Vietnam Audit Co., Ltd | C13: Deloitte Vietnam Audit Co., Ltd | D13: Deloitte Vietnam Audit Co., Ltd | F13: Deloitte Vietnam Audit Co., Ltd | G13: Deloitte Vietnam Audit Co., Ltd | H13: PwC Vietnam | I13: Deloitte Vietnam Audit Co., Ltd | J13: Deloitte Vietnam Audit Co., Ltd | K13: Deloitte Vietnam Audit Co., Ltd
A14: Loại ý kiến kiểm toán | B14: Chấp nhận toàn phần | C14: Chấp nhận toàn phần | D14: Chấp nhận toàn phần | F14: Chấp nhận toàn phần | G14: Chấp nhận toàn phần | H14: Chấp nhận toàn phần | I14: Chấp nhận toàn phần | J14: Chấp nhận toàn phần | K14: Chấp nhận toàn phần
A15: Lợi nhuận/(lỗ) trước thuế | B15: 859.23791 | C15: 658.89139 | D15: 679.32513 | E15: 706.19864 | F15: 463.08817 | G15: 716.5338 | H15: 1956.27 | I15: 4596.3128 | J15: 1254.8096 | K15: 1522.0635
A16: Khấu hao TSCĐ và BĐSĐT | B16: 1279.6765 | C16: 1292.0368 | D16: 1309.0006 | E16: 1303.3756 | F16: 1318.8406 | G16: 1318.1525 | H16: 1385.8109 | I16: 1398.0294 | J16: 1083.3807 | K16: 268.08146
A17: Phân bổ lợi thế thương mại | B17: 0 | C17: 0 | D17: 0 | E17: 0 | F17: 0 | G17: 0 | H17: 0 | I17: 0 | J17: 0 | K17: 0
A18: Chi phí dự phòng | B18: 0.71284767 | C18: 0.79221648 | D18: -1.5050641 | E18: 0 | F18: 8.9182587 | G18: -8.4816782 | H18: 37.053214 | I18: 822.62005 | J18: -212.57578 | K18: 9.4771195
A19: Lãi/lỗ chênh lệch tỷ giá hối đoái do đánh giá lại các khoản mục tiền tệ có gốc ngoại tệ | B19: 275.36748 | C19: 72.779574 | D19: -10.234614 | E19: 49.850496 | F19: -2.435473 | G19: -1.5350377 | H19: -7.0093268 | I19: 9.3273665 | J19: -43.609637 | K19: 2.9503122
A20: Lãi/(lỗ) từ thanh lý tài sản cố định | B20: 0 | C20: 0 | D20: 0 | E20: 0 | F20: 0 | G20: 0 | H20: 0 | I20: 0 | J20: 0 | K20: 0
A21: (Lãi)/lỗ từ hoạt động đầu tư | B21: -173.04781 | C21: -155.76618 | D21: -156.68025 | E21: -158.47635 | F21: -117.69981 | G21: -111.92758 | H21: -130.83572 | I21: -265.29046 | J21: -518.47533 | K21: -451.85853
A22: Chi phí lãi vay | B22: 242.45234 | C22: 206.62239 | D22: 182.98653 | E22: 142.05277 | F22: 87.17253 | G22: 43.301059 | H22: 18.580201 | I22: 10.274784 | J22: 10.155714 | K22: 44.380805
A23: Thu lãi và cổ tức | B23: 0 | C23: 0 | D23: 0 | E23: 0 | F23: 0 | G23: 0 | H23: 0 | I23: 0 | J23: 0 | K23: 0
A24: Các khoản điều chỉnh khác | B24: 16.12 | C24: 15 | D24: 72.825538 | E24: 71.305674 | F24: 0 | G24: 79.425415 | H24: 216.72828 | I24: 318.81693 | J24: 108.88589 | K24: 40.507659
A25: Lợi nhuận/(lỗ) từ hoạt động kinh doanh trước những thay đổi vốn lưu động | B25: 2500.5193 | C25: 2090.3561 | D25: 2075.7178 | E25: 2114.3069 | F25: 1757.8843 | G25: 2035.4684 | H25: 3476.5976 | I25: 6890.0908 | J25: 1682.5711 | K25: 1435.6023
A26: (Tăng)/giảm các khoản phải thu | B26: -1.2185283 | C26: -422.50323 | D26: 27.973718 | E26: -48.477093 | F26: 55.14422 | G26: 135.33961 | H26: 30.360921 | I26: -50.564994 | J26: -140.25581 | K26: -40.518052
... A55: Tiền và tương đương tiền cuối kỳ | B55: 1215.0793 | C55: 813.51875 | D55: 1896.1849 | E55: 285.77246 | F55: 471.17332 | G55: 509.99535 | H55: 427.65273 | I55: 2125.6253 | J55: 2284.3998 | K55: 1903.2483
A57: Contact
A58: CÔNG TY CỔ PHẦN FIINGROUP VIỆT NAM
A59: Trụ sở: Tầng 10, Tòa nhà PeakView, 36 Hoàng Cầu, Đống Đa, Hà Nội, Việt Nam
A60: Chi nhánh: Tầng 16, Tòa nhà Bitexco Financial Tower, số 2 Hải Triều , Phường Bến Nghé, Quận 1, TP. Hồ Chí Minh, Việt Nam
A61: Website: https://fiingroup.vn
A63: TRUNG TÂM CHĂM SÓC KHÁCH HÀNG
A64: T: (84-24) - 3562 6962 - Ext: 103
A65: Email: fiinpro.support@fiingroup.vn

Sheet Notes
A5: Tính năng | B5: Thuyết minh - DCM
A6: Ngày trích xuất | B6: 45860.705
A8: Mã CK | B8: DCM | D8: Xem theo | E8: Hằng năm | F8: 2025
A9: Loại | B9: Hợp nhất | D9: Tiền tệ | E9: VND | F9: Tỷ VND
A11: Chỉ tiêuTỷ VND | B11: 2015 | C11: 2016 | D11: 2017 | E11: 2018 | F11: 2019 | G11: 2020 | H11: 2021 | I11: 2022 | J11: 2023 | K11: 2024
A12: Trạng thái kiểm toán | B12: Đã kiểm toán | C12: Đã kiểm toán | D12: Đã kiểm toán | E12: Đã kiểm toán | F12: Đã kiểm toán | G12: Đã kiểm toán | H12: Đã kiểm toán | I12: Đã kiểm toán | J12: Đã kiểm toán | K12: Đã kiểm toán
A13: Công ty kiểm toán | B13: Deloitte Vietnam Audit Co., Ltd | C13: Deloitte Vietnam Audit Co., Ltd | D13: Deloitte Vietnam Audit Co., Ltd | F13: Deloitte Vietnam Audit Co., Ltd | G13: Deloitte Vietnam Audit Co., Ltd | H13: PwC Vietnam | I13: Deloitte Vietnam Audit Co., Ltd | J13: Deloitte Vietnam Audit Co., Ltd | K13: Deloitte Vietnam Audit Co., Ltd
A14: Loại ý kiến kiểm toán | B14: Chấp nhận toàn phần | C14: Chấp nhận toàn phần | D14: Chấp nhận toàn phần | F14: Chấp nhận toàn phần | G14: Chấp nhận toàn phần | H14: Chấp nhận toàn phần | I14: Chấp nhận toàn phần | J14: Chấp nhận toàn phần | K14: Chấp nhận toàn phần
A15: Tiền và tương đương tiền | B15: 1215.0793 | C15: 813.51875 | D15: 1896.1849 | E15: 285.77246 | F15: 471.17332 | G15: 509.99535 | H15: 427.65273 | I15: 2125.6253 | J15: 2284.3998 | K15: 1903.2483
A16: Tiền mặt | B16: 0.30402393 | C16: 0.084430897 | D16: 0.33197281 | E16: 0.95882405 | F16: 0.95280738 | G16: 1.0129324 | H16: 1.4409266 | I16: 0.94037573 | J16: 2.1446524 | K16: 1.7810592
A17: Tiền gửi Ngân hàng | B17: 182.77531 | C17: 481.43432 | D17: 393.50292 | E17: 164.81364 | F17: 370.22052 | G17: 288.98242 | H17: 426.2118 | I17: 2124.6849 | J17: 2272.2551 | K17: 1901.4673
A18: Tiền đang chuyển | B18: 0 | C18: 0 | D18: 0 | E18: 0 | F18: 0 | G18: 0 | H18: 0 | I18: 0 | J18: 0 | K18: 0
A19: Tiền và tương đương tiền | B19: 1032 | C19: 332 | D19: 1502.35 | E19: 120 | F19: 100 | G19: 220 | H19: 0 | I19: 0 | J19: 10 | K19: 0
A20: Đầu tư tài chính NH | B20: 2702.5556 | C20: 2300 | D20: 2100 | E20: 2502 | F20: 2002 | G20: 2302 | H20: 4362 | I20: 6812 | J20: 8242 | K20: 7039.0512
A21: Chứng khoán đầu tư ngắn hạn | B21: 0 | C21: 0 | D21: 0 | E21: 0 | F21: 0 | G21: 0 | H21: 0 | I21: 0 | J21: 0 | K21: 0
A22: Đầu tư nắm giữ đến ngày đáo hạn | B22: 2702.5556 | C22: 2300 | D22: 2100 | E22: 2502 | F22: 2002 | G22: 2302 | H22: 4362 | I22: 6812 | J22: 8242 | K22: 7039.0512
A23: Đầu tư ngắn hạn | B23: 2702.5556 | C23: 2300 | D23: 2100 | E23: 2502 | F23: 2002 | G23: 2302 | H23: 4362 | I23: 6812 | J23: 8242 | K23: 7039.0512
A24: Đầu tư dài hạn | B24: 0 | C24: 0 | D24: 0 | E24: 0 | F24: 0 | G24: 0 | H24: 0 | I24: 0 | J24: 0 | K24: 0
A25: Đầu tư NH khác | B25: 0 | C25: 0 | D25: 0 | E25: 0 | F25: 0 | G25: 0 | H25: 0 | I25: 0 | J25: 0 | K25: 0
A26: Dự phòng giảm giá ĐTNH | B26: 0 | C26: 0 | D26: 0 | E26: 0 | F26: 0 | G26: 0 | H26: 0 | I26: 0 | J26: 0 | K26: 0
... A171: Chi phí khác bằng tiền | B171: 0 | C171: 99.486096 | D171: 322.76439 | E171: 412.57102 | F171: 293.90204 | G171: 364.34541 | H171: 743.85104 | I171: 867.12225 | J171: 608.16808 | K171: 688.0484
A173: Contact
A174: CÔNG TY CỔ PHẦN FIINGROUP VIỆT NAM
A175: Trụ sở: Tầng 10, Tòa nhà PeakView, 36 Hoàng Cầu, Đống Đa, Hà Nội, Việt Nam
A176: Chi nhánh: Tầng 16, Tòa nhà Bitexco Financial Tower, số 2 Hải Triều , Phường Bến Nghé, Quận 1, TP. Hồ Chí Minh, Việt Nam
A177: Website: https://fiingroup.vn
A179: TRUNG TÂM CHĂM SÓC KHÁCH HÀNG
A180: T: (84-24) - 3562 6962 - Ext: 103
A181: Email: fiinpro.support@fiingroup.vn

Sheet Doanh thu DCM
A1: BREAKDOWN | D1: 2019 | E1: =D1+1 -> 2020 | F1: =E1+1 -> 2021 | G1: =F1+1 -> 2022 | H1: =G1+1 -> 2023 | I1: =H1+1 -> 2024 | J1: =I1+1 -> 2025 | K1: =J1+1 -> 2026 | L1: =K1+1 -> 2027 | ... S1: =R1+1 -> 2034
J2: projected | K2: =J2 -> projected | L2: =K2 -> projected | M2: =L2 -> projected | N2: =M2 -> projected | O2: =N2 -> projected | P2: =O2 -> projected | Q2: =P2 -> projected | R2: =Q2 -> projected | S2: =R2 -> projected | U2: FO 180 tại Singapore vào ngày 23 tháng 9 năm 2025 là 403.37 USD/tấn
A3: SUMMARY STATISTICS | U3: https://www.sgx.com/derivatives/products/fuel-oil-380cst
B5: DPM Data
B6: Revenue | D6: ='IS Raw'!F15 -> 7176.5755 | E6: ='IS Raw'!G15 -> 7716.8905 | F6: ='IS Raw'!H15 -> 10088.157 | G6: ='IS Raw'!I15 -> 16380.04 | H6: ='IS Raw'!J15 -> 12949.489 | I6: ='IS Raw'!K15 -> 13942.548 | J6: =J9/(100%-J8) -> 16634.065 | K6: =K9/(100%-K8) -> 17303.93 | L6: =L9/(100%-L8) -> 17415.173 | M6: =M9/(100%-M8) -> 20041.613 | N6: =N9/(100%-N8) -> 19135.1 | O6: =O9/(100%-O8) -> 17899.264 | P6: =P9/(100%-P8) -> 17943.869 | Q6: =Q9/(100%-Q8) -> 18009.288 | ... S6: =S9/(100%-S8) -> 18363.343
B7: Reductions | D7: =-'IS Raw'!F16 -> 133.60855 | E7: =-'IS Raw'!G16 -> 155.61538 | F7: =-'IS Raw'!H16 -> 218.39418 | G7: =-'IS Raw'!I16 -> 455.5129 | H7: =-'IS Raw'!J16 -> 378.94707 | I7: =-'IS Raw'!K16 -> 486.9631 | J7: =J6-J9 -> 422.58938 | K7: =K6-K9 -> 439.60733 | L7: =L6-L9 -> 442.43347 | M7: =M6-M9 -> 509.15831 | N7: =N6-N9 -> 486.1283 | O7: =O6-O9 -> 454.73182 | P7: =P6-P9 -> 455.86501 | Q7: =Q6-Q9 -> 457.527 | ... S7: =S6-S9 -> 466.52179
B8: %Reductions | D8: =D7/D6 -> 0.018617313 | E8: =E7/E6 -> 0.020165555 | F8: =F7/F6 -> 0.02164857 | G8: =G7/G6 -> 0.027809023 | H8: =H7/H6 -> 0.029263477 | I8: =I7/I6 -> 0.034926406 | J8: =AVERAGE(D8:I8) -> 0.025405057 | K8: =J8 -> 0.025405057 | L8: =K8 -> 0.025405057 | M8: =L8 -> 0.025405057 | N8: =M8 -> 0.025405057 | O8: =N8 -> 0.025405057 | P8: =O8 -> 0.025405057 | Q8: =P8 -> 0.025405057 | R8: =Q8 -> 0.025405057 | S8: =R8 -> 0.025405057
B9: Net revenue | D9: ='IS Raw'!F17 -> 7042.9669 | E9: ='IS Raw'!G17 -> 7561.2751 | F9: ='IS Raw'!H17 -> 9869.7629 | G9: ='IS Raw'!I17 -> 15924.527 | H9: ='IS Raw'!J17 -> 12570.542 | I9: ='IS Raw'!K17 -> 13455.585 | J9: =J112+J159+J170+J194+J241 -> 16211.476 | K9: =K112+K159+K170+K194+K241 -> 16864.323 | L9: =L112+L159+L170+L194+L241 -> 16972.74 | M9: =M112+M159+M170+M194+M241 -> 19532.454 | N9: =N112+N159+N170+N194+N241 -> 18648.971 | O9: =O112+O159+O170+O194+O241 -> 17444.532 | P9: =P112+P159+P170+P194+P241 -> 17488.004 | Q9: =Q112+Q159+Q170+Q194+Q241 -> 17551.761 | ... S9: =S112+S159+S170+S194+S241 -> 17896.822
B10: % growth | E10: =E9/D9-1 -> 0.073592305 | F10: =F9/E9-1 -> 0.30530404 | G10: =G9/F9-1 -> 0.613466 | H10: =H9/G9-1 -> -0.21061755 | I10: =I9/H9-1 -> 0.070406117 | J10: =J9/I9-1 -> 0.2048139 | K10: =K9/J9-1 -> 0.040270654 | L10: =L9/K9-1 -> 0.0064287681 | ... S10: =S9/R9-1 -> -0.021470614
B11: COGS | D11: =-'IS Raw'!F18 -> 6083.7747 | E11: =-'IS Raw'!G18 -> 6244.4273 | F11: =-'IS Raw'!H18 -> 7088.826 | G11: =-'IS Raw'!I18 -> 10221.097 | H11: =-'IS Raw'!J18 -> 10538.742 | I11: =-'IS Raw'!K18 -> 10942.101 | J11: =J115+J165+J175+J197+J255 -> 12555.221 | K11: =K115+K165+K175+K197+K255 -> 12841.878 | L11: =L115+L165+L175+L197+L255 -> 12594.457 | M11: =M115+M165+M175+M197+M255 -> 13259.35 | N11: =N115+N165+N175+N197+N255 -> 13320.284 | O11: =O115+O165+O175+O197+O255 -> 12855.792 | P11: =P115+P165+P175+P197+P255 -> 13098.318 | Q11: =Q115+Q165+Q175+Q197+Q255 -> 12889.567 | ... S11: =S115+S165+S175+S197+S255 -> 13119.186
B12: Gross profit | D12: ='IS Raw'!F19 -> 959.1922 | E12: ='IS Raw'!G19 -> 1316.8478 | F12: ='IS Raw'!H19 -> 2780.9369 | G12: ='IS Raw'!I19 -> 5703.4294 | H12: ='IS Raw'!J19 -> 2031.7997 | I12: ='IS Raw'!K19 -> 2513.4843 | J12: =J9-J11 -> 3656.255 | K12: =K9-K11 -> 4022.4445 | L12: =L9-L11 -> 4378.2821 | M12: =M9-M11 -> 6273.1047 | N12: =N9-N11 -> 5328.6875 | O12: =O9-O11 -> 4588.7395 | P12: =P9-P11 -> 4389.6857 | Q12: =Q9-Q11 -> 4662.1944 | ... S12: =S9-S11 -> 4777.6353
B13: GPM | D13: =D12/D9 -> 0.1361915 | E13: =E12/E9 -> 0.17415684 | F13: =F12/F9 -> 0.2817633 | G13: =G12/G9 -> 0.35815378 | H13: =H12/H9 -> 0.16163183 | I13: =I12/I9 -> 0.18679858 | J13: =J12/J9 -> 0.22553499 | K13: =K12/K9 -> 0.238518 | ... S13: =S12/S9 -> 0.2669544
B14: Financial Income (tỷ đồng) | D14: ='IS Raw'!F20 -> 127.01614 | E14: ='IS Raw'!G20 -> 128.31668 | F14: ='IS Raw'!H20 -> 167.53191 | G14: ='IS Raw'!I20 -> 301.00806 | H14: ='IS Raw'!J20 -> 577.08849 | I14: ='IS Raw'!K20 -> 381.8039
B15: Financial X (chi phí tài chính) (tỷ đồng) | D15: =-'IS Raw'!F21 -> 102.75348 | E15: =-'IS Raw'!G21 -> 63.234525 | F15: =-'IS Raw'!H21 -> 45.07293 | G15: =-'IS Raw'!I21 -> 60.402057 | H15: =-'IS Raw'!J21 -> 27.372488 | I15: =-'IS Raw'!K21 -> 76.569108
B16: Selling X (chi phí bán hàng) (tỷ đồng) | D16: =-'IS Raw'!F24 -> 364.0587 | E16: =-'IS Raw'!G24 -> 369.00032 | F16: =-'IS Raw'!H24 -> 420.40125 | G16: =-'IS Raw'!I24 -> 698.29487 | H16: =-'IS Raw'!J24 -> 800.63146 | I16: =-'IS Raw'!K24 -> 1014.3698
B17: G&A X (Chi phí quản lý doanh nghiệp) (tỷ đồng) | D17: =-'IS Raw'!F25 -> 201.3192 | E17: =-'IS Raw'!G25 -> 304.40666 | F17: =-'IS Raw'!H25 -> 528.49174 | G17: =-'IS Raw'!I25 -> 652.59426 | H17: =-'IS Raw'!J25 -> 548.55689 | I17: =-'IS Raw'!K25 -> 481.047
B18: Other Income (thu nhập khác) (tỷ đồng) | D18: ='IS Raw'!F28 -> 48.48338 | E18: ='IS Raw'!G28 -> 10.735344 | F18: ='IS Raw'!H28 -> 4.3711954 | G18: ='IS Raw'!I28 -> 15.225626 | H18: ='IS Raw'!J28 -> 24.751516 | I18: ='IS Raw'!K28 -> 199.87676
B19: Other X (chi phí khác) (tỷ đồng) | D19: =-'IS Raw'!F29 -> 3.4721669 | E19: =-'IS Raw'!G29 -> 2.7245179 | F19: =-'IS Raw'!H29 -> 2.6041186 | G19: =-'IS Raw'!I29 -> 12.059178 | H19: =-'IS Raw'!J29 -> 2.2692702 | I19: =-'IS Raw'!K29 -> 1.1155147
B21: Projection Check
B23: Revenue (excluding NPK)
B24: Revenue
B25: Reductions
B26: %Reductions
B27: Net revenue
B28: %growth
B29: COGS
B30: Gross profit
B31: GPM
B32: Financial Income
B33: Financial X
... B37: Other X
B38: =B125 -> Oil price (USD/barrel) (brent)
B39: =B126 -> MFO (USD/ton)
B40: =B132 -> Natural Gas Price (USD/mmbtu) no VAT
B41: Selling X/Net R
B42: G&A/Net R
B43: Other income/Net R
B44: Other expense/Net R
A46: SALES BREAKDOWN BY PRODUCTS
B47: Locally-produced Products
B48: Ca Mau Urea
B49: NH3
B50: NPK
B51: Sales Discounts (tỷ đồng)
B52: Net Revenues
B54: Imported Products & Other
B55: Other (tỷ đồng)
B56: Imported Fertilier Trading
B57: Sales Discounts
B58: Net Revenue
B60: Total Revenue (tỷ đồng)
... B62: Net Revenue
A64: COCG BREAKDOWN BY PRODUCTS
B65: Locally-produced Products
B66: Phu My Urea
B67: Ca Mau Urea
B68: Chemical
B70: Imported Products
B71: Imported Fertilier Trading
B73: SUM
A75: GROSS PROFITS BREAKDOWN BY PRODUCTS
B76: Locally-produced Products
B77: Phu My Urea
B78: Ca Mau Urea
B79: Chemical
B81: Imported Products
B82: Imported Fertilier Trading
B84: SUM
A86: Revenue Weighting
B87: Urea Fertilizer
B88: Trading Fertilizer
B89: Chemical + Other
A92: Gross Profit Weighting
B93: Urea Fertilizer
B94: Trading Fertilizer
B95: Chemical + Other
A97: DETAILS
A98: Ca Mau Urea
B99: Revenue (billion dong) | D99: =5571385507504/10^9 -> 5571.3855 | E99: =6073425382360/10^9 -> 6073.4254 | F99: =7280394927590/10^9 -> 7280.3949 | G99: =12401793242829/10^9 -> 12401.793 | H99: =8310998746657/10^9 -> 8310.9987 | I99: =7701001784904/10^9 -> 7701.0018 | J99: =(J101*J105*J106) + (J101*(1-J105)*J109) -> 9889.787 | K99: =(K101*K105*K106) + (K101*(1-K105)*K109) -> 10277.636 | L99: =(L101*L105*L106) + (L101*(1-L105)*L109) -> 10162.215 | M99: =(M101*M105*M106) + (M101*(1-M105)*M109) -> 11631.882 | N99: =(N101*N105*N106) + (N101*(1-N105)*N109) -> 11565.757 | O99: =(O101*O105*O106) + (O101*(1-O105)*O109) -> 11116.478 | P99: =(P101*P105*P106) + (P101*(1-P105)*P109) -> 11248.697 | Q99: =(Q101*Q105*Q106) + (Q101*(1-Q105)*Q109) -> 11301.666 | ... S99: =(S101*S105*S106) + (S101*(1-S105)*S109) -> 11372.535
B100: %Growth | E100: =E99/D99-1 -> 0.090110418 | F100: =F99/E99-1 -> 0.19872962 | G100: =G99/F99-1 -> 0.70345062 | H100: =H99/G99-1 -> -0.32985508 | I100: =I99/H99-1 -> -0.073396349 | J100: =J99/I99-1 -> 0.28422085 | K100: =K99/J99-1 -> 0.039217117 | L100: =L99/K99-1 -> -0.01123027 | ... S100: =S99/R99-1 -> -0.050326239
B101: Volume (Thounsand Tons) | D101: =D335 -> 807.13 | E101: =E335 -> 1008.56 | F101: =F335 -> 755.5 | G101: =G335 -> 844.08 | H101: =H335 -> 866.03 | I101: =I335 -> 804.7 | J101: =J335 -> 852.76679 | K101: =K335 -> 859.54264 | ... S101: =S335 -> 892.86558 | V101: Factors Influencing Growth in Fertilizer Use
B102: %Growth | E102: =E101/D101-1 -> 0.24956327 | F102: =F101/E101-1 -> -0.25091219 | G102: =G101/F101-1 -> 0.11724686 | H102: =H101/G101-1 -> 0.026004644 | I102: =I101/H101-1 -> -0.070817408 | V102: Growing Global Population | W102: This leads to increased caloric needs, which in turn drives the demand for greater agricultural output and fertilizer.
B103: Tỷ giá | D103: 23110 | E103: 23225.55 | F103: 23225.55 | G103: 23341.678 | H103: 23866.386 | I103: =H103*(1+0.045) -> 24940.374 | J103: 26382.5 | K103: =J103*(1+K104) -> 27173.975 | L103: =K103*(1+L104) -> 27717.455 | M103: =L103*(1+M104) -> 28271.804 | N103: =M103*(1+N104) -> 28837.24 | O103: =N103*(1+O104) -> 28548.867 | P103: =O103*(1+P104) -> 28263.379 | Q103: =P103*(1+Q104) -> 27980.745 | R103: =Q103*(1+R104) -> 27700.937 | S103: =R103*(1+S104) -> 27423.928 | V103: Technological Advancements | W103: New technologies can influence fertilizer demand and the efficiency of its use
B104: Mất giá VND | J104: =4% -> 0.04 | K104: =3% -> 0.03 | L104: =2% -> 0.02 | M104: =2% -> 0.02 | N104: =2% -> 0.02 | O104: =-1% -> -0.01 | P104: =-1% -> -0.01 | Q104: =P104 -> -0.01 | R104: =Q104 -> -0.01 | S104: =R104 -> -0.01 | V104: Climate Change | W104: Environmental factors like climate change can impact agricultural productivity and affect the need for fertilizers.
B105: Tỷ trọng trong nước/xuất khẩu | J105: =J106/(J106+J109) -> 0.53380259 | K105: =K106/(K106+K109) -> 0.5215006 | L105: =L106/(L106+L109) -> 0.49732298 | M105: =M106/(M106+M109) -> 0.46858618 | N105: =N106/(N106+N109) -> 0.44005624 | O105: =O106/(O106+O109) -> 0.41916706 | P105: =P106/(P106+P109) -> 0.41679459 | Q105: =Q106/(Q106+Q109) -> 0.4241664 | ... S105: =S106/(S106+S109) -> 0.43900854 | V105: Changing Consumer Preferences | W105: Shifts in what consumers want can influence agricultural production methods and fertilizer use
B106: Price (thousand VND/Kg) | D106: =D99/D101 -> 6.9027115 | E106: =E99/E101 -> 6.0218781 | F106: =F99/F101 -> 9.6365254 | G106: =G99/G101 -> 14.692675 | H106: =H99/H101 -> 9.5966638 | I106: =I99/I101 -> 9.5700283 | J106: =14500*0.85/1000 -> 12.325 | K106: =J106*K107 -> 12.44825 | L106: =K106*L107 -> 12.074802 | M106: =L106*M107 -> 12.316299 | N106: =M106*N107 -> 11.330995 | O106: =N106*O107 -> 10.197895 | P106: =O106*P107 -> 10.095916 | Q106: =P106*Q107 -> 10.600712 | R106: =Q106*R107 -> 11.130748 | S106: =R106*S107 -> 11.01944 | V106: accelerated urbanization | W106: increase fertilizer content per hectare of land
B107: %Growth | J107: =J106/I106 -> 1.287875 | K107: =1% + 100% -> 1.01 | L107: =-3% + 100% -> 0.97 | M107: =0% + 100%+2% -> 1.02 | N107: =-8% + 100% -> 0.92 | O107: =-10% + 100% -> 0.9 | P107: =-1% + 100% -> 0.99 | Q107: =5% + 100% -> 1.05 | R107: =5% + 100% -> 1.05 | S107: =-1% + 100% -> 0.99
B108: Price - export (USD/ton) | J108: =480*0.85 -> 408 | K108: =J108*K110 -> 420.3216 | L108: =K108*L110 -> 440.32891 | M108: =L108*M110 -> 494.04903 | N108: =M108*N110 -> 499.97762 | O108: =N108*O110 -> 494.97785 | P108: =O108*P110 -> 499.82863 | Q108: =P108*Q110 -> 514.32366 | R108: =Q108*R110 -> 529.23905 | S108: =R108*S110 -> 513.46772 | U108: https://www.vinachem.com.vn/nd/tin-thi-truong-sp-vnc/phan-bon-binh-dien-khang-dinh-vi-the-thuong-hieu-quoc-gia-voi-tam-nhin-xanh-hoa-so-hoa.html
B109: Price - export (Quy đổi) | J109: =J108*J103/1000000 -> 10.76406 | K109: =K108*K103/1000000 -> 11.421809 | L109: =L108*L103/1000000 -> 12.204796 | M109: =M108*M103/1000000 -> 13.967657 | N109: =N108*N103/1000000 -> 14.417975 | O109: =O108*O103/1000000 -> 14.131057 | P109: =P108*P103/1000000 -> 14.126846 | Q109: =Q108*Q103/1000000 -> 14.391159 | ... S109: =S108*S103/1000000 -> 14.081302
B110: %Growth | J110: =J107*1.05 -> 1.3522687 | K110: =K107*1.02 -> 1.0302 | L110: =L107*1.08 -> 1.0476 | M110: =M107*1.1 -> 1.122 | N110: =N107*1.1 -> 1.012 | O110: =O107*1.1 -> 0.99 | P110: =P107*1.02 -> 1.0098 | Q110: =Q107*0.98 -> 1.029 | R110: =R107*0.98 -> 1.029 | S110: =S107*0.98 -> 0.9702
B111: Reductions | D111: =D99*D8 -> 103.72423 | E111: =E99*E8 -> 122.47399 | F111: =F99*F8 -> 157.61014 | G111: =G99*G8 -> 344.88175 | H111: =H99*H8 -> 243.20872 | I111: =I99*I8 -> 268.96831 | J111: =J99*J8 -> 251.2506 | K111: =K99*K8 -> 261.10393 | ... S111: =S99*S8 -> 288.91989
B112: Net Revenue (billion dong) | D112: =D99-D111 -> 5467.6613 | E112: =E99-E111 -> 5950.9514 | F112: =F99-F111 -> 7122.7848 | G112: =G99-G111 -> 12056.911 | H112: =H99-H111 -> 8067.79 | I112: =I99-I111 -> 7432.0335 | J112: =J99-J111 -> 9638.5364 | K112: =K99-K111 -> 10016.532 | ... S112: =S99-S111 -> 11083.615
B114: COGS theo cách tổng hợp các thành phần
B115: COGS (billion dong) | D115: =4728608570217/10^9 -> 4728.6086 | E115: =4868626033251/10^9 -> 4868.626 | F115: =4786064054966/10^9 -> 4786.0641 | G115: =6654161422282/10^9 -> 6654.1614 | H115: =6433055911189/10^9 -> 6433.0559 | I115: =5498270227049/10^9 -> 5498.2702 | J115: =J116/J118 -> 6918.3945 | K115: =K116/K118 -> 6909.4822 | L115: =L116/L118 -> 6724.0948 | M115: =M116/M118 -> 6985.7695 | N115: =N116/N118 -> 7610.1723 | O115: =O116/O118 -> 7643.8765 | P115: =P116/P118 -> 7932.9796 | Q115: =Q116/Q118 -> 7845.9209 | ... S115: =S116/S118 -> 7995.8431
B116: Raw Materials (billion dong) | D116: =D115*D118 -> 2506.1625 | E116: =E115*E118 -> 2142.1955 | F116: =F115*F118 -> 2440.8927 | G116: =G115*G118 -> 3659.7888 | H116: =H115*H118 -> 4245.8169 | I116: =I115*I118 -> 2958.0694 | J116: =J101*J139*1000*1000/10^9 -> 3322.5175 | K116: =K101*K139*1000*1000/10^9 -> 3318.2374 | L116: =L101*L139*1000*1000/10^9 -> 3229.2062 | M116: =M101*M139*1000*1000/10^9 -> 3354.8739 | N116: =N101*N139*1000*1000/10^9 -> 3654.7396 | O116: =O101*O139*1000*1000/10^9 -> 3670.9258 | P116: =P101*P139*1000*1000/10^9 -> 3809.7659 | Q116: =Q101*Q139*1000*1000/10^9 -> 3767.9564 | ... S116: =S101*S139*1000*1000/10^9 -> 3839.9557
B117: Other COGS | D117: =D115-D116 -> 2222.446 | E117: =E115-E116 -> 2726.4306 | F117: =F115-F116 -> 2345.1714 | G117: =G115-G116 -> 2994.3726 | H117: =H115-H116 -> 2187.239 | I117: =I115-I116 -> 2540.2008 | J117: =J115-J116 -> 3595.8771 | K117: =K115-K116 -> 3591.2449 | ... S117: =S115-S116 -> 4155.8875
B118: % of COGS | D118: 0.53 | E118: 0.44 | F118: 0.51 | G118: 0.55 | H118: 0.66 | I118: =AVERAGE(D118:H118) -> 0.538 | J118: =AVERAGE(E118:I118)*0.89 -> 0.480244 | K118: =J118 -> 0.480244 | L118: =K118 -> 0.480244 | M118: =L118 -> 0.480244 | N118: =M118 -> 0.480244 | O118: =N118 -> 0.480244 | P118: =O118 -> 0.480244 | Q118: =P118 -> 0.480244 | R118: =Q118 -> 0.480244 | S118: =R118 -> 0.480244
B119: Production cost (VND/kg) | D119: =(D115*10^9)/(D101*10^3*10^3) -> 5858.5464 | E119: =(E115*10^9)/(E101*10^3*10^3) -> 4827.3043 | F119: =(F115*10^9)/(F101*10^3*10^3) -> 6334.9623 | G119: =(G115*10^9)/(G101*10^3*10^3) -> 7883.3303 | H119: =(H115*10^9)/(H101*10^3*10^3) -> 7428.2137 | I119: =(I115*10^9)/(I101*10^3*10^3) -> 6832.6957 | J119: =(J115*10^9)/(J101*10^3*10^3) -> 8112.8799 | K119: =(K115*10^9)/(K101*10^3*10^3) -> 8038.5567 | ... S119: =(S115*10^9)/(S101*10^3*10^3) -> 8955.2597
B120: Dry gas cost (billion dong) | D120: =D355 -> 2330.2599 | E120: =E355 -> 1890.7017 | F120: =F355 -> 2718.0107 | G120: =G355 -> 4149.4694 | H120: =H355 -> 4099.4987 | I120: =I355 -> 4423.6961 | J120: =J355 -> 3486.5851 | K120: =K355 -> 3486.6533 | ... S120: =S355 -> 4168.2617
B121: Depreciation | D121: =1200 -> 1200 | E121: =1200 -> 1200 | F121: =1200 -> 1200 | G121: =1200 -> 1200 | H121: =1200 -> 1200 | I121: =0.1*1200 -> 120 | J121: =0.1*1200 -> 120 | K121: =0.1*1200 -> 120 | L121: =0.1*1200 -> 120 | M121: =0.1*1200 -> 120 | N121: =0.1*1200 -> 120 | O121: =0.1*1200 -> 120 | P121: =0.1*1200 -> 120 | ... S121: =0.1*1200 -> 120
...

Sheet Doanh thu KVF
O1: 1 | P1: 2 | Q1: 3 | R1: 4 | S1: 5 | T1: 6 | U1: 7 | V1: 8 | W1: 9 | X1: 10 | Y1: 11 | Z1: 12 | AA1: 13 | AB1: 14 | AC1: 15 | AD1: 16 | AE1: 17 | AF1: 18 | AG1: 19 | AH1: 20 | AI1: 21 | AJ1: 22 | AK1: 23 | AL1: 24 | AM1: 25 | AN1: 26 | AO1: 27 | AP1: 28 | AQ1: 29 | AR1: 30 | AS1: 31 | AT1: 32 | AU1: 33 | AV1: 34 | AW1: 35 | AX1: 36 | AY1: 37 | AZ1: 38 | BA1: 39 | BB1: 40
Q2: Proj | R2: Proj | S2: Proj | T2: Proj | U2: Proj | V2: Proj | W2: Proj | X2: Proj | Y2: Proj | Z2: Proj | AA2: Proj | AB2: Proj | AC2: Proj | AD2: Proj | AE2: Proj | AF2: Proj | AG2: Proj | AH2: Proj | AI2: Proj | AJ2: Proj | AK2: Proj | AL2: Proj | AM2: Proj | AN2: Proj | AO2: Proj | AP2: Proj | AQ2: Proj | AR2: Proj | AS2: Proj | AT2: Proj | AU2: Proj | AV2: Proj | AW2: Proj | AX2: Proj | AY2: Proj | AZ2: Proj | BA2: Proj | BB2: Proj
D3: 41274 | E3: 41639 | F3: 42004 | G3: 42369 | H3: 42735 | I3: 43100 | J3: 43465 | K3: 43830 | L3: 44196 | M3: 44561 | N3: 44926 | O3: 45291 | P3: 45657 | Q3: 46022 | R3: 46387 | S3: 46752 | T3: 47118 | U3: 47483 | V3: 47848 | W3: 48213 | X3: 48579 | Y3: 48944 | Z3: 49309 | AA3: 49674 | AB3: 50040 | AC3: 48944 | AD3: 49309 | AE3: 49674 | AF3: 50040 | AG3: 50405 | AH3: 50770 | AI3: 51135 | AJ3: 51501 | AK3: 51866 | AL3: 52231 | AM3: 52596 | AN3: 52962 | AO3: 53327 | AP3: 53692 | AQ3: 54057 | AR3: 54423 | AS3: 54788 | AT3: 55153 | AU3: 55518 | AV3: 55884 | AW3: 56249 | AX3: 56614 | AY3: 56979 | AZ3: 57345 | BA3: 57710 | BB3: 58075
B6: REVENUE (price - sale - volume)
A8: 1 | B8: DOANH THU (tỷ đồng)
B9: NPK | P9: =P17*1000*P31*1000*1000/(10^9) -> 1132.9956 | Q9: =Q17*1000*Q31*1000*1000/(10^9) -> 1525.4884 | R9: =R17*1000*R31*1000*1000/(10^9) -> 1725.4452 | S9: =S17*1000*S31*1000*1000/(10^9) -> 2143.003 | T9: =T17*1000*T31*1000*1000/(10^9) -> 2996.1725 | U9: =U17*1000*U31*1000*1000/(10^9) -> 3183.7328 | V9: =V17*1000*V31*1000*1000/(10^9) -> 2986.2403 | W9: =W17*1000*W31*1000*1000/(10^9) -> 3469.4821 | ... Z9: =Z17*1000*Z31*1000*1000/(10^9) -> 4933.018
B10: Tổng | P10: =P9 -> 1132.9956 | Q10: =Q9 -> 1525.4884 | R10: =R9 -> 1725.4452 | S10: =S9 -> 2143.003 | T10: =T9 -> 2996.1725 | U10: =U9 -> 3183.7328 | V10: =V9 -> 2986.2403 | W10: =W9 -> 3469.4821 | ... Z10: =Z9 -> 4933.018
A12: 2 | B12: Growth (1.000 tỷ đồng)
B13: NPK | Q13: =Q9/P9-1 -> 0.34642042 | R13: =R9/Q9-1 -> 0.13107724 | S13: =S9/R9-1 -> 0.242 | T13: =T9/S9-1 -> 0.39811867 | U13: =U9/T9-1 -> 0.0626 | V13: =V9/U9-1 -> -0.062031746 | W13: =W9/V9-1 -> 0.16182278 | X13: =X9/W9-1 -> 0.11384052 | ... Z13: =Z9/Y9-1 -> 0.16422317
B14: Growth
A16: 3 | B16: Giá bán trung bình (vnđ/sp)
B17: NPK (nghìn vnd/kg) | P17: =(720000/50)/1000*0.85 -> 12.24 | Q17: =P17*(1+Q18) -> 13.80141 | R17: =Q17*(1+R18) -> 14.353467 | S17: =R17*(1+S18) -> 15.501744 | T17: =S17*(1+T18) -> 19.222163 | U17: =T17*(1+U18) -> 17.68439 | V17: =U17*(1+V18) -> 16.269639 | W17: =V17*(1+W18) -> 16.595031 | X17: =W17*(1+X18) -> 16.760982 | ... Z17: =Y17*(1+Z18) -> 17.775021
B18: Growth | Q18: ='Doanh thu DCM'!J252 -> 0.12756621 | R18: ='Doanh thu DCM'!K252 -> 0.04 | S18: ='Doanh thu DCM'!L252 -> 0.08 | T18: ='Doanh thu DCM'!M252 -> 0.24 | U18: ='Doanh thu DCM'!N252 -> -0.08 | V18: ='Doanh thu DCM'!O252 -> -0.08 | W18: ='Doanh thu DCM'!P252 -> 0.02 | X18: ='Doanh thu DCM'!Q252 -> 0.01 | ... Z18: ='Doanh thu DCM'!S252 -> 0.05
B19: Tổng
A21: 4 | B21: Tăng trưởng giá bán
B22: NPK | Q22: =Q17/P17-1 -> 0.12756621 | R22: =R17/Q17-1 -> 0.04 | S22: =S17/R17-1 -> 0.08 | T22: =T17/S17-1 -> 0.24 | U22: =U17/T17-1 -> -0.08 | V22: =V17/U17-1 -> -0.08 | W22: =W17/V17-1 -> 0.02 | X22: =X17/W17-1 -> 0.01 | ... Z22: =Z17/Y17-1 -> 0.05
B23: Tổng
A25: 5 | B25: Sản lượng sản xuất
B26: NPK (nghìn tấn) | P26: =94142/1000 -> 94.142 | Q26: =120 -> 120 | R26: =Q26*(1+R27) -> 132 | S26: =R26*(1+S27) -> 145.2 | T26: =S26*(1+T27) -> 159.72 | U26: =T26*(1+U27) -> 175.692 | V26: =U26*(1+V27) -> 193.2612 | W26: =V26*(1+W27) -> 212.58732 | X26: =W26*(1+X27) -> 233.84605 | Y26: =X26*(1+Y27) -> 257.23066 | Z26: =Y26*(1+Z27) -> 282.95372
B27: Growth | Q27: ='Doanh thu DCM'!J246 -> 0.065 | R27: ='Doanh thu DCM'!K246 -> 0.1 | S27: ='Doanh thu DCM'!L246 -> 0.1 | T27: ='Doanh thu DCM'!M246 -> 0.1 | U27: =T27 -> 0.1 | V27: =U27 -> 0.1 | W27: =V27 -> 0.1 | X27: =W27 -> 0.1 | Y27: =X27 -> 0.1 | Z27: =Y27 -> 0.1
B28: Tổng
A30: 5 | B30: Sản lượng tiêu thụ
B31: NPK (nghìn tấn) | P31: =92565/1000 -> 92.565 | Q31: =Q26*Q32 -> 110.53134 | R31: =R26*R32 -> 120.21104 | S31: =S26*S32 -> 138.2427 | T31: =T26*T32 -> 155.87073 | U31: =U26*U32 -> 180.03069 | V31: =V26*V32 -> 183.54682 | W31: =W26*W32 -> 209.06752 | X31: =X26*X32 -> 230.56226 | ... Z31: =Z26*Z32 -> 277.5253
B32: % sản xuất | Q32: ='Doanh thu DCM'!J249 + 5% -> 0.92109452 | R32: ='Doanh thu DCM'!K249 -> 0.91068972 | S32: ='Doanh thu DCM'!L249 -> 0.95208471 | T32: ='Doanh thu DCM'!M249 -> 0.97589986 | U32: ='Doanh thu DCM'!N249 -> 1.0246949 | V32: ='Doanh thu DCM'!O249 -> 0.94973443 | W32: ='Doanh thu DCM'!P249 -> 0.98344305 | X32: ='Doanh thu DCM'!Q249 -> 0.98595744 | Y32: ='Doanh thu DCM'!R249 -> 0.97304497 | Z32: ='Doanh thu DCM'!S249 -> 0.98081516
B33: Growth | Q33: =Q31/P31-1 -> 0.19409434 | R33: =R31/Q31-1 -> 0.087574268 | S33: =S31/R31-1 -> 0.15 | T33: =T31/S31-1 -> 0.12751506 | U33: =U31/T31-1 -> 0.155 | V33: =V31/U31-1 -> 0.019530711 | W33: =W31/V31-1 -> 0.13904195 | X33: =X31/W31-1 -> 0.1028124 | ... Z33: =Z31/Y31-1 -> 0.10878397
B34: Tổng
B36: GVHB
A38: 1 | B38: GVHB
B39: NPK | P39: =(P9-P54) -> 1159.3456 | Q39: =Q9-Q54 -> 1363.0227 | R39: =R9-R54 -> 1541.7329 | S39: =S9-S54 -> 1863.2483 | T39: =T9-T54 -> 2436.8761 | U39: =U9-U54 -> 2567.1285 | V39: =V9-V54 -> 2479.0898 | W39: =W9-W54 -> 2846.3011 | X39: =X9-X54 -> 3116.9463 | ... Z39: =Z9-Z54 -> 3681.7682
B40: Tổng | P40: =P39 -> 1159.3456 | Q40: =Q39 -> 1363.0227 | R40: =R39 -> 1541.7329 | S40: =S39 -> 1863.2483 | T40: =T39 -> 2436.8761 | U40: =U39 -> 2567.1285 | V40: =V39 -> 2479.0898 | W40: =W39 -> 2846.3011 | ... Z40: =Z39 -> 3681.7682
B41: % As Revenue | P41: =P40/P10 -> 1.0232569 | Q41: =Q40/Q10 -> 0.8934992 | R41: =R40/R10 -> 0.89352759 | S41: =S40/S10 -> 0.86945673 | T41: =T40/T10 -> 0.81332972 | U41: =U40/U10 -> 0.80632661 | V41: =V40/V10 -> 0.83017088 | W41: =W40/W10 -> 0.82038212 | ... Z41: =Z40/Z10 -> 0.74635207
A43: 2 | B43: GVHB 01 đơn vị sp
B44: NPK | P44: =P39/P31 -> 12.524665 | Q44: =Q39/Q31 -> 12.331549 | R44: =R39/R31 -> 12.825219 | S44: =S39/S31 -> 13.478096 | T44: =T39/T31 -> 15.633956 | U44: =U39/U31 -> 14.259394 | V44: =V39/V31 -> 13.50658 | W44: =W39/W31 -> 13.614267 | ... Z44: =Z39/Z31 -> 13.266424
B45: Tổng
A47: 3 | B47: Tăng trưởng giá vốn (1.000vnđ/m3)
B48: NPK | Q48: =Q39/P39-1 -> 0.1756828 | R48: =R39/Q39-1 -> 0.13111317 | S48: =S39/R39-1 -> 0.2085416 | T48: =T39/S39-1 -> 0.30786436 | U48: =U39/T39-1 -> 0.053450568 | V48: =V39/U39-1 -> -0.034294641 | W48: =W39/V39-1 -> 0.14812343 | X48: =X39/W39-1 -> 0.095086658 | ... Z48: =Z39/Y39-1 -> 0.13150469
B49: Tổng
B51: LNG
A53: 1 | B53: LNG
B54: NPK | P54: =-26.35 -> -26.35 | Q54: =Q9*Q59 -> 162.46573 | R54: =R9*R59 -> 183.71231 | S54: =S9*S59 -> 279.75462 | T54: =T9*T59 -> 559.29635 | U54: =U9*U59 -> 616.60433 | V54: =V9*V59 -> 507.15057 | W54: =W9*W59 -> 623.18102 | X54: =X9*X59 -> 747.50342 | ... Z54: =Z9*Z59 -> 1251.2498
B55: Tổng | P55: =P54 -> -26.35 | Q55: =Q54 -> 162.46573 | R55: =R54 -> 183.71231 | S55: =S54 -> 279.75462 | T55: =T54 -> 559.29635 | U55: =U54 -> 616.60433 | V55: =V54 -> 507.15057 | W55: =W54 -> 623.18102 | ... Z55: =Z54 -> 1251.2498
B56: Growth
A58: 2 | B58: Biên LNG
B59: NPK | P59: =P54/P9 -> -0.023256931 | Q59: ='Doanh thu DCM'!J263/1.8 -> 0.1065008 | R59: ='Doanh thu DCM'!K263/1.5 -> 0.10647241 | S59: ='Doanh thu DCM'!L263/1.7 -> 0.13054327 | T59: ='Doanh thu DCM'!M263/1.7 -> 0.18667028 | U59: ='Doanh thu DCM'!N263/1.5 -> 0.19367339 | V59: ='Doanh thu DCM'!O263/1.5 -> 0.16982912 | W59: ='Doanh thu DCM'!P263/1.3 -> 0.17961788 | X59: ='Doanh thu DCM'!Q263/1.3 -> 0.19343075 | Y59: ='Doanh thu DCM'!R263/1.1 -> 0.23206649 | Z59: ='Doanh thu DCM'!S263/1 -> 0.25364793
B60: Biên LNG | Q60: =Q55/Q10 -> 0.1065008 | R60: =R55/R10 -> 0.10647241 | S60: =S55/S10 -> 0.13054327 | T60: =T55/T10 -> 0.18667028 | U60: =U55/U10 -> 0.19367339 | V60: =V55/V10 -> 0.16982912 | W60: =W55/W10 -> 0.17961788 | X60: =X55/X10 -> 0.19343075 | ... Z60: =Z55/Z10 -> 0.25364793

Sheet Welfare & Dividends
B1: =1 -> 1 | K1: Số liệu 2021 chưa có vì chưa tổ chức ĐHCĐTN 2022, sử dụng số kế hoạch của ĐHCĐTN 2021 | Q1: 1 | R1: 2 | S1: 3 | T1: 4 | U1: 5 | V1: 6 | W1: 7 | X1: 8 | Y1: 9 | Z1: 10
N2: =IF(TODAY()<N3,"Proj","") | O2: =IF(TODAY()<O3,"Proj","") | P2: =IF(TODAY()<P3,"Proj","") | Q2: =IF(TODAY()<Q3,"Proj","") -> Proj | R2: =IF(TODAY()<R3,"Proj","") -> Proj | S2: =IF(TODAY()<S3,"Proj","") -> Proj | T2: =IF(TODAY()<T3,"Proj","") -> Proj | U2: =IF(TODAY()<U3,"Proj","") -> Proj | ... Z2: =IF(TODAY()<Z3,"Proj","") -> Proj
B3: WELFARE & DIVIDENDS | D3: 41274 | E3: =DATE(YEAR(D3),MONTH(D3)+13,0) -> 41639 | F3: =DATE(YEAR(E3),MONTH(E3)+13,0) -> 42004 | G3: =DATE(YEAR(F3),MONTH(F3)+13,0) -> 42369 | H3: =DATE(YEAR(G3),MONTH(G3)+13,0) -> 42735 | I3: =DATE(YEAR(H3),MONTH(H3)+13,0) -> 43100 | J3: =DATE(YEAR(I3),MONTH(I3)+13,0) -> 43465 | K3: =DATE(YEAR(J3),MONTH(J3)+13,0) -> 43830 | L3: =DATE(YEAR(K3),MONTH(K3)+13,0) -> 44196 | ... Z3: =DATE(YEAR(Y3),MONTH(Y3)+13,0) -> 49309
A4: 1 | B4: LNST | K4: =Input!K94 -> 427.72373 | L4: =Input!L94 -> 662.44633 | M4: =Input!M94 -> 1826.1243 | N4: =Input!N94 -> 4321.0807 | O4: =Input!O94 -> 1110.1427 | P4: =Input!P94 -> 1428.0066
A5: 2 | B5: Trích lập các quỹ | K5: =K6+K8 -> 143.3679 | L5: =L6+L8 -> 151.68463 | M5: =M6+M8 -> 646.82729 | N5: =N6+N8 -> 1418.8542 | O5: =O6+O8 -> 455.40282 | P5: =P6+P8 -> 550.15197
A6: 2.1 | B6: Quỹ thuộc công ty | K6: =K7 -> 34.217898 | L6: =L7 -> 66.244633 | M6: =M7 -> 547.83729 | N6: =N7 -> 1296.3242 | O6: =O7 -> 333.04282 | P6: =P7 -> 428.40197
B7: + Quỹ ĐTPT | K7: =0.08*K4 -> 34.217898 | L7: =0.1*L4 -> 66.244633 | M7: =0.3*M4 -> 547.83729 | N7: =0.3*N4 -> 1296.3242 | O7: =0.3*O4 -> 333.04282 | P7: =0.3*P4 -> 428.40197
A8: 2.2 | B8: Quỹ chi ra | K8: =K9 -> 109.15 | L8: =L9 -> 85.44 | M8: =M9 -> 98.99 | N8: =N9 -> 122.53 | O8: =O9 -> 122.36 | P8: =P9 -> 121.75
B9: - Quỹ khen thưởng phúc lợi | K9: =SUM(K10:K11) -> 109.15 | L9: =SUM(L10:L11) -> 85.44 | M9: =SUM(M10:M11) -> 98.99 | N9: =SUM(N10:N11) -> 122.53 | O9: =SUM(O10:O11) -> 122.36 | P9: =SUM(P10:P11) -> 121.75
B10: + Quỹ khen thưởng BLĐ, HĐQT, BKS | K10: 1.56 | L10: 2.08 | M10: =2.31 -> 2.31 | N10: =3.12 -> 3.12 | O10: =2.61 -> 2.61 | P10: =2.61 -> 2.61
B11: + Quỹ khen thưởng, phúc lợi người lao động | K11: 107.59 | L11: 83.36 | M11: =96.68 -> 96.68 | N11: =119.41 -> 119.41 | O11: =119.75 -> 119.75 | P11: =119.14 -> 119.14
A12: 3 | B12: Chi cổ tức | K12: =K13+K15 -> 317.64 | L12: =L13+L15 -> 423.52 | M12: =M13+M15 -> 952.92 | N12: =N13+N15 -> 1588.2 | O12: =O13+O15 -> 1058.8 | P12: =P13+P15 -> 1058.8
B13: - Lần 1 | K13: =317.64 -> 317.64 | L13: =423.52 -> 423.52 | M13: =952.92 -> 952.92 | N13: =1588.2 -> 1588.2 | O13: =1058.8 -> 1058.8 | P13: =1058.8 -> 1058.8
B14: % mệnh giá | K14: =600/10000 -> 0.06 | L14: =800/10000 -> 0.08 | M14: =1800/10000 -> 0.18 | N14: =30% -> 0.3 | O14: =20% -> 0.2 | P14: =20% -> 0.2
B15: - Lần 2 | K15: 0 | L15: 0 | M15: 0 | N15: 0 | O15: 0 | P15: 0
B16: % mệnh giá
B17: LNST CPP | K17: =K4-K5-K12 -> -33.284169 | L17: =L4-L5-L12 -> 87.241701 | M17: =M4-M5-M12 -> 226.377 | N17: =N4-N5-N12 -> 1314.0265 | O17: =O4-O5-O12 -> -404.0601 | P17: =P4-P5-P12 -> -180.94539
B19: THE NUMBER OF COMMON SHARE (triệu CP)
A20: 1 | B20: SLCP phát hành đầu năm
A21: 2 | B21: Cổ tức bằng cổ phiếu
A22: 3 | B22: Cổ phiếu thưởng
A23: 4 | B23: Phát hành riêng lẻ/ công khai
B24: - đợt 1
B25: - đợt 2
A26: 5 | B26: ESOP
A27: 6 | B27: SLCP phát hành cuối năm | K27: 529400000 | L27: 529400000 | M27: 529400000 | N27: 529400000 | O27: 529400000 | P27: 529400000
A28: 7 | B28: CP quỹ | K28: ='BS Raw'!F120 -> 0 | L28: ='BS Raw'!G120 -> 0 | M28: ='BS Raw'!H120 -> 0 | N28: ='BS Raw'!I120 -> 0 | O28: ='BS Raw'!J120 -> 0 | P28: ='BS Raw'!K120 -> 0
A29: 8 | B29: SLCP lưu hành | K29: =K27-K28 -> 529400000 | L29: =L27-L28 -> 529400000 | M29: =M27-M28 -> 529400000 | N29: =N27-N28 -> 529400000 | O29: =O27-O28 -> 529400000 | P29: =P27-P28 -> 529400000 | Q29: https://tapchicongthuong.vn/dam-ca-mau--dcm--chot-chia-co-tuc-20--bang-tien--du-bao-gia-phan-bon-co-the-tang-142081.htm

Sheet Consol. Rev.
B1: 1 | N1: 1 | O1: 2 | P1: 3 | Q1: 4 | R1: 5 | S1: 6 | T1: 7 | U1: 8 | V1: 9 | W1: 10 | X1: 11 | Y1: 12 | Z1: 13 | AA1: 14 | AB1: 15 | AC1: 16 | AD1: 17 | AE1: 18 | AF1: 19 | AG1: 20 | AH1: 21 | AI1: 22 | AJ1: 23 | AK1: 24 | AL1: 25 | AM1: 26 | AN1: 27 | AO1: 28 | AP1: 29 | AQ1: 30 | AR1: 31 | AS1: 32 | AT1: 33 | AU1: 34 | AV1: 35 | AW1: 36 | AX1: 37 | AY1: 38 | AZ1: 39 | BA1: 40
C2: =IF(TODAY()<C3,"Proj","") | D2: =IF(TODAY()<D3,"Proj","") | F2: =IF(TODAY()<F3,"Proj","") | G2: =IF(TODAY()<G3,"Proj","") | H2: =IF(TODAY()<H3,"Proj","") | I2: =IF(TODAY()<I3,"Proj","") | J2: =IF(TODAY()<J3,"Proj","") | K2: =IF(TODAY()<K3,"Proj","") | L2: =IF(TODAY()<L3,"Proj","") | M2: =IF(TODAY()<M3,"Proj","") | ... BA2: =IF(TODAY()<BA3,"Proj","") -> Proj
D3: 41274 | E3: =DATE(YEAR(D3),MONTH(D3)+13,0) -> 41639 | F3: =DATE(YEAR(E3),MONTH(E3)+13,0) -> 42004 | G3: =DATE(YEAR(F3),MONTH(F3)+13,0) -> 42369 | H3: =DATE(YEAR(G3),MONTH(G3)+13,0) -> 42735 | I3: =DATE(YEAR(H3),MONTH(H3)+13,0) -> 43100 | J3: =DATE(YEAR(I3),MONTH(I3)+13,0) -> 43465 | K3: =DATE(YEAR(J3),MONTH(J3)+13,0) -> 43830 | L3: =DATE(YEAR(K3),MONTH(K3)+13,0) -> 44196 | ... BA3: =DATE(YEAR(AZ3),MONTH(AZ3)+13,0) -> 59171 | BC3: Notes
H4: % growth rev | L4: =L8/K8-1 -> 0.073592305 | M4: =M8/L8-1 -> 0.30530404 | N4: =N8/M8-1 -> 0.613466 | O4: =O8/N8-1 -> -0.21061755 | P4: =P8/O8-1 -> 0.16053712 | Q4: =Q8/P8-1 -> 0.21581151 | R4: =R8/Q8-1 -> 0.048080581 | S4: =S8/R8-1 -> 0.028293767 | ... Z4: =Z8/Y8-1 -> 0.013457614
B6: REVENUE (price - sale - volume)
B8: Consol. revenue (FC) | K8: ='Doanh thu DCM'!D9+'Doanh thu KVF'!K9 -> 7042.9669 | L8: ='Doanh thu DCM'!E9+'Doanh thu KVF'!L9 -> 7561.2751 | M8: ='Doanh thu DCM'!F9+'Doanh thu KVF'!M9 -> 9869.7629 | N8: ='Doanh thu DCM'!G9+'Doanh thu KVF'!N9 -> 15924.527 | O8: ='Doanh thu DCM'!H9+'Doanh thu KVF'!O9 -> 12570.542 | P8: ='Doanh thu DCM'!I9+'Doanh thu KVF'!P9 -> 14588.581 | Q8: ='Doanh thu DCM'!J9+'Doanh thu KVF'!Q9 -> 17736.964 | R8: ='Doanh thu DCM'!K9+'Doanh thu KVF'!R9 -> 18589.768 | ... Z8: ='Doanh thu DCM'!S9+'Doanh thu KVF'!Z9 -> 22829.84
B9: Mảng Ure | K9: ='Doanh thu DCM'!D112 -> 5467.6613 | L9: ='Doanh thu DCM'!E112 -> 5950.9514 | M9: ='Doanh thu DCM'!F112 -> 7122.7848 | N9: ='Doanh thu DCM'!G112 -> 12056.911 | O9: ='Doanh thu DCM'!H112 -> 8067.79 | P9: ='Doanh thu DCM'!I112 -> 7432.0335 | Q9: ='Doanh thu DCM'!J112 -> 9638.5364 | R9: ='Doanh thu DCM'!K112 -> 10016.532 | ... Z9: ='Doanh thu DCM'!S112 -> 11083.615
B10: Mảng NPK | K10: ='Doanh thu DCM'!D241+'Doanh thu KVF'!K9 -> 0 | L10: ='Doanh thu DCM'!E241+'Doanh thu KVF'!L9 -> 0 | M10: ='Doanh thu DCM'!F241+'Doanh thu KVF'!M9 -> 391.24903 | N10: ='Doanh thu DCM'!G241+'Doanh thu KVF'!N9 -> 1253.322 | O10: ='Doanh thu DCM'!H241+'Doanh thu KVF'!O9 -> 1675.6449 | P10: ='Doanh thu DCM'!I241+'Doanh thu KVF'!P9+'Doanh thu DCM'!V248 -> 3928.8546 | Q10: ='Doanh thu DCM'!J241+'Doanh thu KVF'!Q9 -> 4011.5978 | R10: ='Doanh thu DCM'!K241+'Doanh thu KVF'!R9 -> 4569.5543 | S10: ='Doanh thu DCM'!L241+'Doanh thu KVF'!S9 -> 5521.8046 | T10: ='Doanh thu DCM'!M241+'Doanh thu KVF'!T9 -> 7696.7645 | U10: ='Doanh thu DCM'!N241+'Doanh thu KVF'!U9 -> 7508.2775 | V10: ='Doanh thu DCM'!O241+'Doanh thu KVF'!V9 -> 6964.8214 | W10: ='Doanh thu DCM'!P241+'Doanh thu KVF'!W9 -> 7527.6348 | X10: ='Doanh thu DCM'!Q241+'Doanh thu KVF'!X9 -> 7963.1839 | ... Z10: ='Doanh thu DCM'!S241+'Doanh thu KVF'!Z9 -> 9279.7257 | AC10: ='Doanh thu KVF'!AC10 -> 0 | AD10: ='Doanh thu KVF'!AD10 -> 0 | AE10: ='Doanh thu KVF'!AE10 -> 0 | AF10: ='Doanh thu KVF'!AF10 -> 0 | AG10: ='Doanh thu KVF'!AG10 -> 0 | AH10: ='Doanh thu KVF'!AH10 -> 0 | AI10: ='Doanh thu KVF'!AI10 -> 0 | AJ10: ='Doanh thu KVF'!AJ10 -> 0 | ... AX10: ='Doanh thu KVF'!AX10 -> 0
B11: Mảng NH3 | K11: ='Doanh thu DCM'!D170 -> 38.074579 | L11: ='Doanh thu DCM'!E170 -> 0 | M11: ='Doanh thu DCM'!F170 -> 24.014973 | N11: ='Doanh thu DCM'!G170 -> 98.512861 | O11: ='Doanh thu DCM'!H170 -> 39.608264 | P11: ='Doanh thu DCM'!I170 -> 47.733036 | Q11: ='Doanh thu DCM'!J170 -> 45.701843 | R11: ='Doanh thu DCM'!K170 -> 44.787806 | ... Z11: ='Doanh thu DCM'!S170 -> 39.683034
B12: Mảng tự doanh | K12: ='Doanh thu DCM'!D159 -> 1311.8823 | L12: ='Doanh thu DCM'!E159 -> 1331.3239 | M12: ='Doanh thu DCM'!F159 -> 1638.1589 | N12: ='Doanh thu DCM'!G159 -> 1972.7754 | O12: ='Doanh thu DCM'!H159 -> 2167.4294 | P12: ='Doanh thu DCM'!I159 -> 2439.9787 | Q12: ='Doanh thu DCM'!J159 -> 3159.7159 | R12: ='Doanh thu DCM'!K159 -> 2965.1725 | ... Z12: ='Doanh thu DCM'!S159 -> 855.50378
B13: Mảng dịch vụ | K13: ='Doanh thu DCM'!D194 -> 225.34878 | L13: ='Doanh thu DCM'!E194 -> 278.9998 | M13: ='Doanh thu DCM'!F194 -> 693.55519 | N13: ='Doanh thu DCM'!G194 -> 543.00515 | O13: ='Doanh thu DCM'!H194 -> 620.0695 | P13: ='Doanh thu DCM'!I194 -> 739.98096 | Q13: ='Doanh thu DCM'!J194 -> 881.41248 | R13: ='Doanh thu DCM'!K194 -> 993.72123 | ... Z13: ='Doanh thu DCM'!S194 -> 1571.3125
B14: Consol. revenue | K14: =SUM(K9:K13) -> 7042.9669 | L14: =SUM(L9:L13) -> 7561.2751 | M14: =SUM(M9:M13) -> 9869.7629 | N14: =SUM(N9:N13) -> 15924.527 | O14: =SUM(O9:O13) -> 12570.542 | P14: =SUM(P9:P13) -> 14588.581 | Q14: =SUM(Q9:Q13) -> 17736.964 | R14: =SUM(R9:R13) -> 18589.768 | ... Z14: =SUM(Z9:Z13) -> 22829.84
B15: Đối chiếu | K15: =K8-K14 -> 0 | L15: =L8-L14 -> 0 | M15: =M8-M14 -> 0 | N15: =N8-N14 -> 0 | O15: =O8-O14 -> 0 | P15: =P8-P14 -> 0 | Q15: =Q8-Q14 -> 0 | R15: =R8-R14 -> 0 | ... Z15: =Z8-Z14 -> 0
B17: Rev. Growth (FC) | D17: =IFERROR(D8/C8-1," ") | E17: =IFERROR(E8/D8-1," ") | F17: =IFERROR(F8/E8-1," ") | G17: =IFERROR(G8/F8-1," ") | H17: =IFERROR(H8/G8-1," ") | I17: =IFERROR(I8/H8-1," ")
B18: Mảng Ure | D18: =IFERROR(D9/C9-1," ") | E18: =IFERROR(E9/D9-1," ") | F18: =IFERROR(F9/E9-1," ") | G18: =IFERROR(G9/F9-1," ") | H18: =IFERROR(H9/G9-1," ") | I18: =IFERROR(I9/H9-1," ") | L18: =IFERROR(L9/K9-1, 0) -> 0.088390646 | M18: =IFERROR(M9/L9-1, 0) -> 0.1969153 | N18: =IFERROR(N9/M9-1, 0) -> 0.69272438 | O18: =IFERROR(O9/N9-1, 0) -> -0.33085766 | P18: =IFERROR(P9/O9-1, 0) -> -0.078801822 | Q18: =IFERROR(Q9/P9-1, 0) -> 0.29689088 | R18: =IFERROR(R9/Q9-1, 0) -> 0.039217117 | S18: =IFERROR(S9/R9-1, 0) -> -0.01123027 | ... Z18: =IFERROR(Z9/Y9-1, 0) -> -0.050326239
B19: Mảng NPK | D19: =IFERROR(D10/C10-1," ") | E19: =IFERROR(E10/D10-1," ") | F19: =IFERROR(F10/E10-1," ") | G19: =IFERROR(G10/F10-1," ") | H19: =IFERROR(H10/G10-1," ") | I19: =IFERROR(I10/H10-1," ") | L19: =IFERROR(L10/K10-1, 0) -> 0 | M19: =IFERROR(M10/L10-1, 0) -> 0 | N19: =IFERROR(N10/M10-1, 0) -> 2.2033868 | O19: =IFERROR(O10/N10-1, 0) -> 0.33696288 | P19: =IFERROR(P10/O10-1, 0) -> 1.344682 | Q19: =IFERROR(Q10/P10-1, 0) -> 0.021060383 | R19: =IFERROR(R10/Q10-1, 0) -> 0.13908587 | S19: =IFERROR(S10/R10-1, 0) -> 0.20839018 | ... Z19: =IFERROR(Z10/Y10-1, 0) -> 0.107776
B20: Mảng NH3 | L20: =IFERROR(L11/K11-1, 0) -> -1 | M20: =IFERROR(M11/L11-1, 0) -> 0 | N20: =IFERROR(N11/M11-1, 0) -> 3.1021433 | O20: =IFERROR(O11/N11-1, 0) -> -0.59793814 | P20: =IFERROR(P11/O11-1, 0) -> 0.20512821 | Q20: =IFERROR(Q11/P11-1, 0) -> -0.042553191 | R20: =IFERROR(R11/Q11-1, 0) -> -0.02 | S20: =IFERROR(S11/R11-1, 0) -> -0.02 | ... Z20: =IFERROR(Z11/Y11-1, 0) -> -0.01
B21: Mảng tự doanh | L21: =IFERROR(L12/K12-1, 0) -> 0.014819634 | M21: =IFERROR(M12/L12-1, 0) -> 0.23047361 | N21: =IFERROR(N12/M12-1, 0) -> 0.20426374 | O21: =IFERROR(O12/N12-1, 0) -> 0.098670103 | P21: =IFERROR(P12/O12-1, 0) -> 0.12574773 | Q21: =IFERROR(Q12/P12-1, 0) -> 0.29497683 | R21: =IFERROR(R12/Q12-1, 0) -> -0.061569881 | S21: =IFERROR(S12/R12-1, 0) -> -0.12687326 | ... Z21: =IFERROR(Z12/Y12-1, 0) -> -0.1735
B22: Mảng dịch vụ | L22: =IFERROR(L13/K13-1, 0) -> 0.23807994 | M22: =IFERROR(M13/L13-1, 0) -> 1.4858627 | N22: =IFERROR(N13/M13-1, 0) -> -0.21707002 | O22: =IFERROR(O13/N13-1, 0) -> 0.14192195 | P22: =IFERROR(P13/O13-1, 0) -> 0.19338389 | Q22: =IFERROR(Q13/P13-1, 0) -> 0.1911286 | R22: =IFERROR(R13/Q13-1, 0) -> 0.12741906 | S22: =IFERROR(S13/R13-1, 0) -> 0.063709532 | ... Z22: =IFERROR(Z13/Y13-1, 0) -> 0.11945537
B23: Rev. Growth | D23: =IFERROR(D14/C14-1," ") | E23: =IFERROR(E14/D14-1," ") | F23: =IFERROR(F14/E14-1," ") | G23: =IFERROR(G14/F14-1," ") | H23: =IFERROR(H14/G14-1," ") | I23: =IFERROR(I14/H14-1," ") | L23: =IFERROR(L14/K14-1, 0) -> 0.073592305 | M23: =IFERROR(M14/L14-1, 0) -> 0.30530404 | N23: =IFERROR(N14/M14-1, 0) -> 0.613466 | O23: =IFERROR(O14/N14-1, 0) -> -0.21061755 | P23: =IFERROR(P14/O14-1, 0) -> 0.16053712 | Q23: =IFERROR(Q14/P14-1, 0) -> 0.21581151 | R23: =IFERROR(R14/Q14-1, 0) -> 0.048080581 | S23: =IFERROR(S14/R14-1, 0) -> 0.028293767 | ... Z23: =IFERROR(Z14/Y14-1, 0) -> 0.013457614
B26: COGS
B28: COGS (FC) (Cách 1: theo từng mảng)
B29: % As Revenue | K29: ='Doanh thu DCM'!D11+'Doanh thu KVF'!K39 -> 6083.7747 | L29: ='Doanh thu DCM'!E11+'Doanh thu KVF'!L39 -> 6244.4273 | M29: ='Doanh thu DCM'!F11+'Doanh thu KVF'!M39 -> 7088.826 | N29: ='Doanh thu DCM'!G11+'Doanh thu KVF'!N39 -> 10221.097 | O29: ='Doanh thu DCM'!H11+'Doanh thu KVF'!O39 -> 10538.742 | P29: ='Doanh thu DCM'!I11+'Doanh thu KVF'!P39 -> 12101.446 | Q29: ='Doanh thu DCM'!J11+'Doanh thu KVF'!Q39 -> 13918.244 | R29: ='Doanh thu DCM'!K11+'Doanh thu KVF'!R39 -> 14383.611 | ... Z29: ='Doanh thu DCM'!S11+'Doanh thu KVF'!Z39 -> 16800.955 | AC29: =AC28/AC8 -> #DIV/0! | AD29: =AD28/AD8 -> #DIV/0! | AE29: =AE28/AE8 -> #DIV/0! | AF29: =AF28/AF8 -> #DIV/0! | AG29: =AG28/AG8 -> #DIV/0! | AH29: =AH28/AH8 -> #DIV/0! | AI29: =AI28/AI8 -> #DIV/0! | AJ29: =AJ28/AJ8 -> #DIV/0! | ... AX29: =AX28/AX8 -> #DIV/0!
B30: Mảng Ure | K30: ='Doanh thu DCM'!D115 -> 4728.6086 | L30: ='Doanh thu DCM'!E115 -> 4868.626 | M30: ='Doanh thu DCM'!F115 -> 4786.0641 | N30: ='Doanh thu DCM'!G115 -> 6654.1614 | O30: ='Doanh thu DCM'!H115 -> 6433.0559 | P30: ='Doanh thu DCM'!I115 -> 5498.2702 | Q30: ='Doanh thu DCM'!J115 -> 6918.3945 | R30: ='Doanh thu DCM'!K115 -> 6909.4822 | ... Z30: ='Doanh thu DCM'!S115 -> 7995.8431 | AC30: =#REF! -> #REF! | AD30: =#REF! -> #REF! | AE30: =#REF! -> #REF! | AF30: =#REF! -> #REF! | AG30: =#REF! -> #REF! | AH30: =#REF! -> #REF! | AI30: =#REF! -> #REF! | AJ30: =#REF! -> #REF! | ... AX30: =#REF! -> #REF!
B31: Mảng NPK | K31: ='Doanh thu DCM'!D255+'Doanh thu KVF'!K39 -> 0 | L31: ='Doanh thu DCM'!E255+'Doanh thu KVF'!L39 -> 0 | M31: ='Doanh thu DCM'!F255+'Doanh thu KVF'!M39 -> 392.88368 | N31: ='Doanh thu DCM'!G255+'Doanh thu KVF'!N39 -> 1192.0004 | O31: ='Doanh thu DCM'!H255+'Doanh thu KVF'!O39 -> 1458.8394 | P31: ='Doanh thu DCM'!I255+'Doanh thu KVF'!P39+'Doanh thu DCM'!V251 -> 3731.8756 | Q31: ='Doanh thu DCM'!J255+'Doanh thu KVF'!Q39 -> 3372.5413 | R31: ='Doanh thu DCM'!K255+'Doanh thu KVF'!R39 -> 3931.6133 | S31: ='Doanh thu DCM'!L255+'Doanh thu KVF'!S39 -> 4492.2143 | T31: ='Doanh thu DCM'!M255+'Doanh thu KVF'!T39 -> 5645.7847 | U31: ='Doanh thu DCM'!N255+'Doanh thu KVF'!U39 -> 5635.3493 | V31: ='Doanh thu DCM'!O255+'Doanh thu KVF'!V39 -> 5444.1524 | W31: ='Doanh thu DCM'!P255+'Doanh thu KVF'!W39 -> 5956.8619 | X31: ='Doanh thu DCM'!Q255+'Doanh thu KVF'!X39 -> 6185.0129 | ... Z31: ='Doanh thu DCM'!S255+'Doanh thu KVF'!Z39 -> 6925.9424
B32: Mảng NH3 | K32: ='Doanh thu DCM'!D175 -> 48.754894 | L32: ='Doanh thu DCM'!E175 -> 0 | M32: ='Doanh thu DCM'!F175 -> 13.466274 | N32: ='Doanh thu DCM'!G175 -> 59.107717 | O32: ='Doanh thu DCM'!H175 -> 23.764958 | P32: ='Doanh thu DCM'!I175 -> 28.639822 | Q32: ='Doanh thu DCM'!J175 -> 27.421106 | R32: ='Doanh thu DCM'!K175 -> 26.872684 | ... Z32: ='Doanh thu DCM'!S175 -> 23.80982
B33: Mảng tự doanh | K33: ='Doanh thu DCM'!D165 -> 1185.3326 | L33: ='Doanh thu DCM'!E165 -> 1232.7444 | M33: ='Doanh thu DCM'!F165 -> 1483.9804 | N33: ='Doanh thu DCM'!G165 -> 1876.0864 | O33: ='Doanh thu DCM'!H165 -> 2023.8157 | P33: ='Doanh thu DCM'!I165 -> 2289.6186 | Q33: ='Doanh thu DCM'!J165 -> 2938.8273 | R33: ='Doanh thu DCM'!K165 -> 2770.3519 | ... Z33: ='Doanh thu DCM'!S165 -> 806.90096
B34: Mảng dịch vụ | K34: ='Doanh thu DCM'!D197 -> 121.07868 | L34: ='Doanh thu DCM'!E197 -> 143.05688 | M34: ='Doanh thu DCM'!F197 -> 412.43157 | N34: ='Doanh thu DCM'!G197 -> 439.74153 | O34: ='Doanh thu DCM'!H197 -> 599.26648 | P34: ='Doanh thu DCM'!I197 -> 553.04217 | Q34: ='Doanh thu DCM'!J197 -> 661.05936 | R34: ='Doanh thu DCM'!K197 -> 745.29092 | ... Z34: ='Doanh thu DCM'!S197 -> 1048.4583
B35: COGS Cách 1: theo từng mảng) | K35: =SUM(K30:K34) -> 6083.7747 | L35: =SUM(L30:L34) -> 6244.4273 | M35: =SUM(M30:M34) -> 7088.826 | N35: =SUM(N30:N34) -> 10221.097 | O35: =SUM(O30:O34) -> 10538.742 | P35: =SUM(P30:P34) -> 12101.446 | Q35: =SUM(Q30:Q34) -> 13918.244 | R35: =SUM(R30:R34) -> 14383.611 | ... Z35: =SUM(Z30:Z34) -> 16800.955
K36: =K29-K35 -> 0 | L36: =L29-L35 -> 0 | M36: =M29-M35 -> 0 | N36: =N29-N35 -> 0 | O36: =O29-O35 -> 0 | P36: =P29-P35 -> 0 | Q36: =Q29-Q35 -> 0 | R36: =R29-R35 -> 0 | ... Z36: =Z29-Z35 -> 0
B37: % As Revenue | D37: =IFERROR(D35/D14," ") | E37: =IFERROR(E35/E14," ") | K37: =K35/K14 -> 0.8638085 | L37: =L35/L14 -> 0.82584316 | M37: =M35/M14 -> 0.7182367 | N37: =N35/N14 -> 0.64184622 | O37: =O35/O14 -> 0.83836817 | P37: =P35/P14 -> 0.829515 | Q37: =Q35/Q14 -> 0.78470269 | R37: =R35/R14 -> 0.77373807 | ... Z37: =Z35/Z14 -> 0.73592083 | AC37: =AC35/AC14 -> #DIV/0! | AD37: =AD35/AD14 -> #DIV/0! | AE37: =AE35/AE14 -> #DIV/0! | AF37: =AF35/AF14 -> #DIV/0! | AG37: =AG35/AG14 -> #DIV/0! | AH37: =AH35/AH14 -> #DIV/0! | AI37: =AI35/AI14 -> #DIV/0! | AJ37: =AJ35/AJ14 -> #DIV/0! | ... AX37: =AX35/AX14 -> #DIV/0!
B40: % sai số | K40: =K41/K29 -> 0.13510338 | L40: =L41/L29 -> 0.22294377 | M40: =M41/M29 -> 0.0022809497 | N40: =N41/N29 -> 0.074917532 | O40: =O41/O29 -> 0.14573987 | P40: =P41/P29 -> 0.17374204 | Q40: =Q41/Q29 -> 0.22319632 | R40: =R41/R29 -> 0.20813913 | ... Z40: =Z41/Z29 -> 0.18423995
B41: sai số | K41: =K29-K42 -> 821.93851 | L41: =L29-L42 -> 1392.1562 | M41: =M29-M42 -> 16.169255 | N41: =N29-N42 -> 765.73939 | O41: =O29-O42 -> 1535.915 | P41: =P29-P42 -> 2102.53 | Q41: =Q29-Q42 -> 3106.5007 | R41: =R29-R42 -> 2993.7923 | ... Z41: =Z29-Z42 -> 3095.4071
B42: COGS (FC) (Cách 2: theo chi phí) | K42: =SUM(K44:K48) -> 5261.8362 | L42: =SUM(L44:L48) -> 4852.2711 | M42: =SUM(M44:M48) -> 7072.6567 | N42: =SUM(N44:N48) -> 9455.358 | O42: =SUM(O44:O48) -> 9002.8274 | P42: =SUM(P44:P48) -> 9998.9165 | Q42: =SUM(Q44:Q48) -> 10811.743 | R42: =SUM(R44:R48) -> 11389.819 | ... Z42: =SUM(Z44:Z48) -> 13705.548
B43: % As Revenue | K43: =K42/K14 -> 0.74710506 | L43: =L42/L14 -> 0.64172657 | M43: =M42/M14 -> 0.71659844 | N43: =N42/N14 -> 0.59376069 | O43: =O42/O14 -> 0.7161845 | P43: =P42/P14 -> 0.68539337 | Q43: =Q42/Q14 -> 0.60955994 | R43: =R42/R14 -> 0.6126929 | ... Z43: =Z42/Z14 -> 0.60033481
B44: Chi phí nguyên liệu, vật liệu | K44: =K144 -> 3218.7692 | L44: =L144 -> 2729.9096 | M44: =M144 -> 4548.9811 | N44: =N144 -> 6495.9937 | O44: =O144 -> 6599.137 | P44: =P144 -> 7793.3568 | Q44: =Q144 -> 8117.7933 | R44: =R144 -> 8510.1391 | ... Z44: =Z144 -> 10918.227
B45: Chi phí nhân công | K45: =K146-K127-K103 -> 313.91059 | L45: =L146-L127-L103 -> 293.36237 | M45: =M146-M127-M103 -> 384.54388 | N45: =N146-N127-N103 -> 404.54535 | O45: =O146-O127-O103 -> 436.76978 | P45: =P146-P127-P103 -> 416.96254 | Q45: =Q146-Q127-Q103 -> 623.93159 | R45: =R146-R127-R103 -> 624.82558 | ... Z45: =Z146-Z127-Z103 -> 743.01708
B46: Chi phí khấu hao tài sản cố định | K46: =K148-K129-K113 -> 1299.2003 | L46: =L148-L129-L113 -> 1298.0551 | M46: =M148-M129-M113 -> 1361.6458 | N46: =N148-N129-N113 -> 1381.7351 | O46: =O148-O129-O113 -> 1062.4147 | P46: =P148-P129-P113 -> 724.30755 | Q46: =Q148-Q129-Q113 -> 827.54801 | R46: =R148-R129-R113 -> 919.46118 | ... Z46: =Z148-Z129-Z113 -> 401.3662
B47: Chi phí dịch vụ mua ngoài | K47: =K150-K133-K117 -> 331.50559 | L47: =L150-L133-L117 -> 361.98153 | M47: =M150-M133-M117 -> 317.31392 | N47: =N150-N133-N117 -> 703.79278 | O47: =O150-O133-O117 -> 805.77911 | P47: =P150-P133-P117 -> 965.87478 | Q47: =Q150-Q133-Q117 -> 866.98351 | R47: =R150-R133-R117 -> 919.57246 | ... Z47: =Z150-Z133-Z117 -> 1220.2565
B48: Chi phí khác bằng tiền | K48: =K152-K135-K115-K111-K107 -> 98.450481 | L48: =L152-L135-L115-L111-L107 -> 168.96258 | M48: =M152-M135-M115-M111-M107 -> 460.17202 | N48: =N152-N135-N115-N111-N107 -> 469.29106 | O48: =O152-O135-O115-O111-O107 -> 98.726863 | P48: =P152-P135-P115-P111-P107 -> 98.414876 | Q48: =Q152-Q135-Q115-Q111-Q107 -> 375.48653 | R48: =R152-R135-R115-R111-R107 -> 415.82049 | ... Z48: =Z152-Z135-Z115-Z111-Z107 -> 422.68058
B49: (Hoàn nhập)/Dự phòng phải thu khó đòi
B50: Sai số
B51: COGS (Cách 2: theo chi phí)
B52: % As Revenue | D52: =IFERROR(D51/D26," ") | E52: =IFERROR(E51/E26," ") | F52: =IFERROR(F51/F26," ") | G52: =IFERROR(G51/G26," ")
B54: % COGS theo Doanh thu (FC) (Cách 2: theo chi phí)
B55: % As Revenue
B56: Chi phí nguyên liệu, vật liệu | I56: =IFERROR(I44/I$14,"") | K56: =K44/K14 -> 0.45701893 | L56: =L44/L14 -> 0.36103826 | M56: =M44/M14 -> 0.46090074 | N56: =N44/N14 -> 0.40792381 | O56: =O44/O14 -> 0.52496837 | P56: =P44/P14 -> 0.53420939 | Q56: =Q44/Q14 -> 0.45767658 | R56: =R44/R14 -> 0.45778619 | ... Z56: =Z44/Z14 -> 0.4782437
B57: Chi phí nhân công | I57: =IFERROR(I45/I$14,"") | K57: =K45/K14 -> 0.044570789 | L57: =L45/L14 -> 0.038798002 | M57: =M45/M14 -> 0.038961816 | N57: =N45/N14 -> 0.025403917 | O57: =O45/O14 -> 0.034745501 | P57: =P45/P14 -> 0.028581433 | Q57: =Q45/Q14 -> 0.03517691 | R57: =R45/R14 -> 0.033611263 | ... Z57: =Z45/Z14 -> 0.032545874
B58: Chi phí khấu hao tài sản cố định | I58: =IFERROR(I46/I$14,"") | K58: =K46/K14 -> 0.18446776 | L58: =L46/L14 -> 0.17167145 | M58: =M46/M14 -> 0.13796135 | N58: =N46/N14 -> 0.086767736 | O58: =O46/O14 -> 0.084516217 | P58: =P46/P14 -> 0.049648938 | Q58: =Q46/Q14 -> 0.046656688 | R58: =R46/R14 -> 0.049460606 | ... Z58: =Z46/Z14 -> 0.017580772
B59: Chi phí dịch vụ mua ngoài | I59: =IFERROR(I47/I$14,"") | K59: =K47/K14 -> 0.047069025 | L59: =L47/L14 -> 0.04787308 | M59: =M47/M14 -> 0.032150106 | N59: =N47/N14 -> 0.044195522 | O59: =O47/O14 -> 0.064100585 | P59: =P47/P14 -> 0.06620759 | Q59: =Q47/Q14 -> 0.048880039 | R59: =R47/R14 -> 0.049466592 | ... Z59: =Z47/Z14 -> 0.053450071
B60: Chi phí khác bằng tiền | I60: =IFERROR(I48/I$14,"") | K60: =K48/K14 -> 0.013978552 | L60: =L48/L14 -> 0.022345779 | M60: =M48/M14 -> 0.046624424 | N60: =N48/N14 -> 0.029469702 | O60: =O48/O14 -> 0.007853827 | P60: =P48/P14 -> 0.0067460213 | Q60: =Q48/Q14 -> 0.021169718 | R60: =R48/R14 -> 0.022368245 | ... Z60: =Z48/Z14 -> 0.018514391
B61: (Hoàn nhập)/Dự phòng phải thu khó đòi | I61: =IFERROR(I49/I$14,"")
B62: Sai số | I62: =IFERROR(I50/I$14,"") | K62: =K41/K14 -> 0.11670345 | L62: =L41/L14 -> 0.18411659 | M62: =M41/M14 -> 0.0016382618 | N62: =N41/N14 -> 0.048085535 | O62: =O41/O14 -> 0.12218367 | P62: =P41/P14 -> 0.14412163 | Q62: =Q41/Q14 -> 0.17514275 | R62: =R41/R14 -> 0.16104517 | ... Z62: =Z41/Z14 -> 0.13558602
B63: % COGS theo Doanh thu (Cách 2: theo chi phí)
B64: % As Revenue
B68: GROSS PROFIT MARGIN
B70: Gross profit (FC) (Cách 1: theo từng mảng) | K70: =K8-K29 -> 959.1922 | L70: =L8-L29 -> 1316.8478 | M70: =M8-M29 -> 2780.9369 | N70: =N8-N29 -> 5703.4294 | O70: =O8-O29 -> 2031.7997 | P70: =P8-P29 -> 2487.1343 | Q70: =Q8-Q29 -> 3818.7208 | R70: =R8-R29 -> 4206.1569 | ... Z70: =Z8-Z29 -> 6028.8851
B71: Growth | I71: =IFERROR(I70/H70-1," ") | L71: =L70/K70-1 -> 0.37287168 | M71: =M70/L70-1 -> 1.1118135 | N71: =N70/M70-1 -> 1.0509021 | O71: =O70/N70-1 -> -0.64375825 | P71: =P70/O70-1 -> 0.22410407 | Q71: =Q70/P70-1 -> 0.53538988 | R71: =R70/Q70-1 -> 0.10145703 | S71: =S70/R70-1 -> 0.10743296 | ... Z71: =Z70/Y70-1 -> -0.012791793
B72: Mảng Ure | K72: =K9-K30 -> 739.05271 | L72: =L9-L30 -> 1082.3254 | M72: =M9-M30 -> 2336.7207 | N72: =N9-N30 -> 5402.7501 | O72: =O9-O30 -> 1634.7341 | P72: =P9-P30 -> 1933.7632 | Q72: =Q9-Q30 -> 2720.1419 | R72: =R9-R30 -> 3107.0498 | ... Z72: =Z9-Z30 -> 3087.7716
B73: Mảng NPK | K73: =K10-K31 -> 0 | L73: =L10-L31 -> 0 | M73: =M10-M31 -> -1.6346573 | N73: =N10-N31 -> 61.321582 | O73: =O10-O31 -> 216.80556 | P73: =P10-P31 -> 196.97897 | Q73: =Q10-Q31 -> 639.05646 | R73: =R10-R31 -> 637.94104 | ... Z73: =Z10-Z31 -> 2353.7832
B74: Mảng NH3 | K74: =K11-K32 -> -10.680314 | L74: =L11-L32 -> 0 | M74: =M11-M32 -> 10.548699 | N74: =N11-N32 -> 39.405145 | O74: =O11-O32 -> 15.843306 | P74: =P11-P32 -> 19.093214 | Q74: =Q11-Q32 -> 18.280737 | R74: =R11-R32 -> 17.915122 | ... Z74: =Z11-Z32 -> 15.873214
B75: Mảng tự doanh | K75: =K12-K33 -> 126.5497 | L75: =L12-L33 -> 98.579528 | M75: =M12-M33 -> 154.17853 | N75: =N12-N33 -> 96.689021 | O75: =O12-O33 -> 143.61368 | P75: =P12-P33 -> 150.36004 | Q75: =Q12-Q33 -> 220.88856 | R75: =R12-R33 -> 194.82059 | ... Z75: =Z12-Z33 -> 48.602817
B76: Mảng dịch vụ | K76: =K13-K34 -> 104.2701 | L76: =L13-L34 -> 135.94291 | M76: =M13-M34 -> 281.12362 | N76: =N13-N34 -> 103.26362 | O76: =O13-O34 -> 20.80302 | P76: =P13-P34 -> 186.93878 | Q76: =Q13-Q34 -> 220.35312 | R76: =R13-R34 -> 248.43031 | ... Z76: =Z13-Z34 -> 522.85424
B77: Gross profit (Cách 1: theo từng mảng) | K77: =SUM(K72:K76) -> 959.1922 | L77: =SUM(L72:L76) -> 1316.8478 | M77: =SUM(M72:M76) -> 2780.9369 | N77: =SUM(N72:N76) -> 5703.4294 | O77: =SUM(O72:O76) -> 2031.7997 | P77: =SUM(P72:P76) -> 2487.1343 | Q77: =SUM(Q72:Q76) -> 3818.7208 | R77: =SUM(R72:R76) -> 4206.1569 | ... Z77: =SUM(Z72:Z76) -> 6028.8851
B78: Growth
B81: Mảng Ure | D81: =IFERROR(D72/D9," ") | E81: =IFERROR(E72/E9," ") | F81: =IFERROR(F72/F9," ") | G81: =IFERROR(G72/G9," ") | H81: =IFERROR(H72/H9," ") | I81: =IFERROR(I72/I9," ") | K81: =IFERROR(K72/K9,0) -> 0.13516798 | L81: =IFERROR(L72/L9,0) -> 0.18187434 | M81: =IFERROR(M72/M9,0) -> 0.3280628 | N81: =IFERROR(N72/N9,0) -> 0.44810398 | O81: =IFERROR(O72/O9,0) -> 0.20262477 | P81: =IFERROR(P72/P9,0) -> 0.26019302 | Q81: =IFERROR(Q72/Q9,0) -> 0.28221524 | R81: =IFERROR(R72/R9,0) -> 0.31019217 | ... Z81: =IFERROR(Z72/Z9,0) -> 0.27858886
B82: Mảng NPK | K82: =IFERROR(K73/K10,0) -> 0 | L82: =IFERROR(L73/L10,0) -> 0 | M82: =IFERROR(M73/M10,0) -> -0.0041780483 | N82: =IFERROR(N73/N10,0) -> 0.048927238 | O82: =IFERROR(O73/O10,0) -> 0.12938634 | P82: =IFERROR(P73/P10,0) -> 0.050136489 | Q82: =IFERROR(Q73/Q10,0) -> 0.15930223 | R82: =IFERROR(R73/R10,0) -> 0.13960684 | ... Z82: =IFERROR(Z73/Z10,0) -> 0.25364793
B83: Mảng NH3 | K83: =IFERROR(K74/K11,0) -> -0.28051036 | L83: =IFERROR(L74/L11,0) -> 0 | M83: =IFERROR(M74/M11,0) -> 0.4392551 | N83: =IFERROR(N74/N11,0) -> 0.4 | O83: =IFERROR(O74/O11,0) -> 0.4 | P83: =IFERROR(P74/P11,0) -> 0.4 | Q83: =IFERROR(Q74/Q11,0) -> 0.4 | R83: =IFERROR(R74/R11,0) -> 0.4 | ... Z83: =IFERROR(Z74/Z11,0) -> 0.4
B84: Mảng tự doanh | D84: =IFERROR(D75/D10," ") | E84: =IFERROR(E75/E10," ") | F84: =IFERROR(F75/F10," ") | G84: =IFERROR(G75/G10," ") | H84: =IFERROR(H75/H10," ") | I84: =IFERROR(I75/I10," ") | K84: =IFERROR(K75/K12,0) -> 0.09646422 | L84: =IFERROR(L75/L12,0) -> 0.074046239 | M84: =IFERROR(M75/M12,0) -> 0.094116954 | N84: =IFERROR(N75/N12,0) -> 0.049011672 | O84: =IFERROR(O75/O12,0) -> 0.066259911 | P84: =IFERROR(P75/P12,0) -> 0.061623505 | Q84: =IFERROR(Q75/Q12,0) -> 0.069907729 | R84: =IFERROR(R75/R12,0) -> 0.065702952 | ... Z84: =IFERROR(Z75/Z12,0) -> 0.056811925
B85: Mảng dịch vụ | D85: =IFERROR(D76/D13," ") | E85: =IFERROR(E76/E13," ") | F85: =IFERROR(F76/F13," ") | G85: =IFERROR(G76/G13," ") | H85: =IFERROR(H76/H13," ") | I85: =IFERROR(I76/I13," ") | K85: =IFERROR(K76/K13,0) -> 0.46270542 | L85: =IFERROR(L76/L13,0) -> 0.48725094 | M85: =IFERROR(M76/M13,0) -> 0.40533706 | N85: =IFERROR(N76/N13,0) -> 0.19017061 | O85: =IFERROR(O76/O13,0) -> 0.033549496 | P85: =IFERROR(P76/P13,0) -> 0.25262648 | Q85: =IFERROR(Q76/Q13,0) -> 0.25 | R85: =IFERROR(R76/R13,0) -> 0.25 | ... Z85: =IFERROR(Z76/Z13,0) -> 0.33275
B86: GPM (Cách 1: theo từng mảng) | D86: =IFERROR(D77/D14," ") | E86: =IFERROR(E77/E14," ") | F86: =IFERROR(F77/F14," ") | G86: =IFERROR(G77/G14," ") | H86: =IFERROR(H77/H14," ") | I86: =IFERROR(I77/I14," ")
B90: Gross profit (FC) (Cách 2: theo chi phí) | I90: =+I8-I42 -> 0
B91: Growth | I91: =IFERROR(I90/H90-1," ")
B92: Gross profit (FC) (Cách 2: theo chi phí)
B93: Growth
B95: GPM (FC) (Cách 2: theo chi phí) | D95: =IFERROR(D90/D28," ") | E95: =IFERROR(E90/E28," ") | F95: =IFERROR(F90/F28," ") | G95: =IFERROR(G90/G28," ") | H95: =IFERROR(H90/H28," ") | I95: =IFERROR(I90/I28," ")
B96: GPM (Cách 2: theo chi phí) | D96: =IFERROR(D92/#REF!," ") | E96: =IFERROR(E92/#REF!," ") | F96: =IFERROR(F92/#REF!," ") | G96: =IFERROR(G92/#REF!," ") | H96: =IFERROR(H92/#REF!," ") | I96: =IFERROR(I92/I14," ")
B99: SG&A
D100: =10^9 -> 1000000000
B101: Selling expense (FC) | K101: =SUM(K103,K105,K107,K109,K111,K113,K115,K117,K119) -> 364.0587 | L101: =SUM(L103,L105,L107,L109,L111,L113,L115,L117,L119) -> 369.00032 | M101: =SUM(M103,M105,M107,M109,M111,M113,M115,M117,M119) -> 420.40125 | N101: =SUM(N103,N105,N107,N109,N111,N113,N115,N117,N119) -> 698.29487 | O101: =SUM(O103,O105,O107,O109,O111,O113,O115,O117,O119) -> 800.63146 | P101: =SUM(P103,P105,P107,P109,P111,P113,P115,P117,P119) -> 1014.3698 | Q101: =SUM(Q103,Q105,Q107,Q109,Q111,Q113,Q115,Q117,Q119) -> 971.02815 | R101: =SUM(R103,R105,R107,R109,R111,R113,R115,R117,R119) -> 1021.888 | ... Z101: =SUM(Z103,Z105,Z107,Z109,Z111,Z113,Z115,Z117,Z119) -> 1316.1205
B102: % As revenue (incl Depr) | K102: =K101/K14 -> 0.051691098 | L102: =L101/L14 -> 0.048801334 | M102: =M101/M14 -> 0.042594868 | N102: =N101/N14 -> 0.043850274 | O102: =O101/O14 -> 0.063691084 | P102: =P101/P14 -> 0.069531767 | Q102: =Q101/Q14 -> 0.054746017 | R102: =R101/R14 -> 0.054970453 | ... Z102: =Z101/Z14 -> 0.057649133
B103: Chi phí nhân viên bán hàng | K103: =41729489841/D100 -> 41.72949 | L103: =47651223228/D100 -> 47.651223 | M103: =53627510921/D100 -> 53.627511 | N103: =51034609414/D100 -> 51.034609 | O103: =71214237760/D100 -> 71.214238 | P103: =79647797903/D100 -> 79.647798 | Q103: =Q14*Q104 -> 94.567757 | R103: =R14*R104 -> 97.276378 | S103: =S14*S104 -> 96.622212 | T103: =T14*T104 -> 112.45015 | U103: =U14*U104 -> 115.47775 | V103: =V14*V104 -> 106.78245 | W103: =W14*W104 -> 108.72132 | X103: =X14*X104 -> 110.58718 | ... Z103: =Z14*Z104 -> 117.99533
B104: % revenue | K104: =K103/K14 -> 0.0059249873 | L104: =L103/L14 -> 0.0063020089 | M104: =M103/M14 -> 0.0054335156 | N104: =N103/N14 -> 0.0032047803 | O104: =O103/O14 -> 0.0056651684 | P104: =P103/P14 -> 0.0054595988 | Q104: =AVERAGE(K104:P104) -> 0.0053316766 | R104: =AVERAGE(L104:Q104) -> 0.0052327914 | S104: =AVERAGE(M104:R104) -> 0.0050545885 | T104: =AVERAGE(N104:S104) -> 0.004991434 | U104: =AVERAGE(O104:T104) -> 0.0052892096 | V104: =AVERAGE(P104:U104) -> 0.0052265498 | W104: =AVERAGE(Q104:V104) -> 0.0051877083 | X104: =AVERAGE(R104:W104) -> 0.0051637136 | ... Z104: =AVERAGE(T104:Y104) -> 0.0051684693
B105: Chi phí vận chuyển, bốc xếp lưu kho | K105: =159016645857/D100 -> 159.01665 | L105: =174316931256/D100 -> 174.31693 | M105: =86281217917/D100 -> 86.281218 | N105: =282963154121/D100 -> 282.96315 | O105: =299880797451/D100 -> 299.8808 | P105: =336808533230/D100 -> 336.80853 | Q105: =Q14*Q106 -> 352.03719 | R105: =R14*R106 -> 360.5037 | S105: =S14*S106 -> 359.0389 | T105: =T14*T106 -> 460.84033 | U105: =U14*U106 -> 456.38121 | V105: =V14*V106 -> 417.02296 | W105: =W14*W106 -> 418.42826 | X105: =X14*X106 -> 428.00786 | ... Z105: =Z14*Z106 -> 463.46721
B106: % revenue | K106: =K105/K14 -> 0.022578076 | L106: =L105/L14 -> 0.023053907 | M106: =M105/M14 -> 0.0087419747 | N106: =N105/N14 -> 0.017769015 | O106: =O105/O14 -> 0.023855837 | P106: =P105/P14 -> 0.023087135 | Q106: =AVERAGE(K106:P106) -> 0.019847657 | R106: =AVERAGE(L106:Q106) -> 0.019392588 | S106: =AVERAGE(M106:R106) -> 0.018782368 | T106: =AVERAGE(N106:S106) -> 0.020455766 | U106: =AVERAGE(O106:T106) -> 0.020903558 | V106: =AVERAGE(P106:U106) -> 0.020411512 | W106: =AVERAGE(Q106:V106) -> 0.019965575 | X106: =AVERAGE(R106:W106) -> 0.019985228 | ... Z106: =AVERAGE(T106:Y106) -> 0.02030094
B107: Chi phí quảng cáo, truyền thông | K107: =53102728030/D100 -> 53.102728 | L107: =56288023466/D100 -> 56.288023 | M107: =106443848845/D100 -> 106.44385 | N107: =197520179576/D100 -> 197.52018 | O107: =246392482098/D100 -> 246.39248 | P107: =341235698819/D100 -> 341.2357 | Q107: =Q14*Q108 -> 239.93331 | R107: =R14*R108 -> 270.02042 | S107: =S14*S108 -> 300.21997 | T107: =T14*T108 -> 372.2961 | U107: =U14*U108 -> 375.79453 | V107: =V14*V108 -> 343.53128 | W107: =W14*W108 -> 329.41756 | X107: =X14*X108 -> 344.4487 | ... Z107: =Z14*Z108 -> 375.54145
B108: % revenue | K108: =K107/K14 -> 0.0075398236 | L108: =L107/L14 -> 0.0074442502 | M108: =M107/M14 -> 0.010784844 | N108: =N107/N14 -> 0.012403519 | O108: =O107/O14 -> 0.019600784 | P108: =P107/P14 -> 0.023390603 | Q108: =AVERAGE(K108:P108) -> 0.013527304 | R108: =AVERAGE(L108:Q108) -> 0.014525217 | S108: =AVERAGE(M108:R108) -> 0.015705379 | T108: =AVERAGE(N108:S108) -> 0.016525468 | U108: =AVERAGE(O108:T108) -> 0.017212459 | V108: =AVERAGE(P108:U108) -> 0.016814405 | W108: =AVERAGE(Q108:V108) -> 0.015718372 | X108: =AVERAGE(R108:W108) -> 0.01608355 | ... Z108: =AVERAGE(T108:Y108) -> 0.016449588
B109: Chi phỉ an sinh xã hội | K109: =14457600000/D100 -> 14.4576 | L109: =13037400790/D100 -> 13.037401 | M109: =57412538334/D100 -> 57.412538 | N109: =38671503413/D100 -> 38.671503 | O109: =67577857639/D100 -> 67.577858 | P109: =86928198091/D100 -> 86.928198 | Q109: =Q14*Q110 -> 69.046982 | R109: =R14*R110 -> 78.067845 | S109: =S14*S110 -> 88.162792 | T109: =T14*T110 -> 99.378837 | U109: =U14*U110 -> 103.52395 | V109: =V14*V110 -> 94.716892 | W109: =W14*W110 -> 92.538812 | X109: =X14*X110 -> 96.430115 | ... Z109: =Z14*Z110 -> 103.7248
B110: % revenue | K110: =K109/K14 -> 0.0020527712 | L110: =L109/L14 -> 0.0017242331 | M110: =M109/M14 -> 0.0058170129 | N110: =N109/N14 -> 0.002428424 | O110: =O109/O14 -> 0.0053758905 | P110: =P109/P14 -> 0.0059586467 | Q110: =AVERAGE(K110:P110) -> 0.0038928297 | R110: =AVERAGE(L110:Q110) -> 0.0041995062 | S110: =AVERAGE(M110:R110) -> 0.0046120517 | T110: =AVERAGE(N110:S110) -> 0.0044112248 | U110: =AVERAGE(O110:T110) -> 0.0047416916 | V110: =AVERAGE(P110:U110) -> 0.0046359918 | W110: =AVERAGE(Q110:V110) -> 0.0044155493 | X110: =AVERAGE(R110:W110) -> 0.0045026692 | ... Z110: =AVERAGE(T110:Y110) -> 0.0045433872
B111: Chỉ phí bán hàng tự doanh | K111: =34490279782/D100 -> 34.49028 | L111: =15676718449/D100 -> 15.676718 | M111: =18826047196/D100 -> 18.826047 | N111: =13793086855 /D100 -> 13.793087 | O111: =16458026303/D100 -> 16.458026 | P111: =24260635186/D100 -> 24.260635 | Q111: =Q14*Q112 -> 37.591296 | R111: =R14*R112 -> 30.792427 | S111: =S14*S112 -> 30.335523 | T111: =T14*T112 -> 34.548132 | U111: =U14*U112 -> 35.909327 | V111: =V14*V112 -> 34.745907 | W111: =W14*W112 -> 35.773274 | X111: =X14*X112 -> 35.084174 | ... Z111: =Z14*Z112 -> 37.514216
B112: % revenue | K112: =K111/K14 -> 0.0048971236 | L112: =L111/L14 -> 0.0020732903 | M112: =M111/M14 -> 0.0019074468 | N112: =N111/N14 -> 0.00086615364 | O112: =O111/O14 -> 0.0013092535 | P112: =P111/P14 -> 0.001662988 | Q112: =AVERAGE(K112:P112) -> 0.002119376 | R112: =AVERAGE(L112:Q112) -> 0.001656418 | S112: =AVERAGE(M112:R112) -> 0.0015869393 | T112: =AVERAGE(N112:S112) -> 0.0015335214 | U112: =AVERAGE(O112:T112) -> 0.0016447494 | V112: =AVERAGE(P112:U112) -> 0.0017006654 | W112: =AVERAGE(Q112:V112) -> 0.0017069449 | X112: =AVERAGE(R112:W112) -> 0.0016382064 | ... Z112: =AVERAGE(T112:Y112) -> 0.0016432098
B113: Chi phí khẩu hao tài sản cổ định | K113: =1096379858/D100 -> 1.0963799 | L113: =3536378703/D100 -> 3.5363787 | M113: =5713708158/D100 -> 5.7137082 | N113: =5805533279/D100 -> 5.8055333 | O113: =5872019078/D100 -> 5.8720191 | P113: =8292820760/D100 -> 8.2928208 | Q113: =Q14*Q114 -> 7.6931527 | R113: =R14*R114 -> 8.9245725 | S113: =S14*S114 -> 9.2165364 | T113: =T14*T114 -> 10.498701 | U113: =U14*U114 -> 10.543546 | V113: =V14*V114 -> 9.920317 | W113: =W14*W114 -> 9.8865447 | X113: =X14*X114 -> 10.238607 | ... Z113: =Z14*Z114 -> 10.89007
B114: % revenue | K114: =K113/K14 -> 0.00015567017 | L114: =L113/L14 -> 0.00046769608 | M114: =M113/M14 -> 0.00057891038 | N114: =N113/N14 -> 0.00036456551 | O114: =O113/O14 -> 0.00046712537 | P114: =P113/P14 -> 0.00056844603 | Q114: =AVERAGE(K114:P114) -> 0.00043373559 | R114: =AVERAGE(L114:Q114) -> 0.00048007982 | S114: =AVERAGE(M114:R114) -> 0.00048214378 | T114: =AVERAGE(N114:S114) -> 0.00046601602 | U114: =AVERAGE(O114:T114) -> 0.00048292443 | V114: =AVERAGE(P114:U114) -> 0.00048555761 | W114: =AVERAGE(Q114:V114) -> 0.00047174288 | X114: =AVERAGE(R114:W114) -> 0.00047807742 | ... Z114: =AVERAGE(T114:Y114) -> 0.00047701034
B115: Các khoản chi phí bán hàng khác | K115: =60165573885/D100 -> 60.165574 | L115: =58493639259/D100 -> 58.493639 | M115: =92096381473/D100 -> 92.096381 | N115: =72834320382/D100 -> 72.83432 | O115: =55803746985/D100 -> 55.803747 | P115: =92003628605/D100 -> 92.003629 | Q115: =Q14*Q116 -> 120.99352 | R115: =R14*R116 -> 121.47849 | S115: =S14*S116 -> 121.08843 | T115: =T14*T116 -> 131.45547 | U115: =U14*U116 -> 131.98441 | V115: =V14*V116 -> 128.97805 | W115: =W14*W116 -> 132.32544 | X115: =X14*X116 -> 133.41019 | ... Z115: =Z14*Z116 -> 140.46116
B116: % revenue | K116: =K115/K14 -> 0.0085426461 | L116: =L115/L14 -> 0.0077359491 | M116: =M115/M14 -> 0.0093311645 | N116: =N115/N14 -> 0.0045737196 | O116: =O115/O14 -> 0.0044392475 | P116: =P115/P14 -> 0.006306551 | Q116: =AVERAGE(K116:P116) -> 0.0068215463 | R116: =AVERAGE(L116:Q116) -> 0.0065346963 | S116: =AVERAGE(M116:R116) -> 0.0063344875 | T116: =AVERAGE(N116:S116) -> 0.0058350414 | U116: =AVERAGE(O116:T116) -> 0.0060452617 | V116: =AVERAGE(P116:U116) -> 0.0063129307 | W116: =AVERAGE(Q116:V116) -> 0.006313994 | X116: =AVERAGE(R116:W116) -> 0.0062294019 | ... Z116: =AVERAGE(T116:Y116) -> 0.0061525249
B117: Chi phí dịch vụ mua ngoài khác | K117: 0 | L117: 0 | M117: 0 | N117: =35672486604/D100 -> 35.672487 | O117: =37432290857/D100 -> 37.432291 | P117: =45192488154/D100 -> 45.192488 | Q117: =Q14*Q118 -> 49.164941 | R117: =R14*R118 -> 54.824131 | S117: =S14*S118 -> 56.192934 | T117: =T14*T118 -> 65.037617 | U117: =U14*U118 -> 63.86546 | V117: =V14*V118 -> 59.601488 | W117: =W14*W118 -> 60.981734 | X117: =X14*X118 -> 62.479967 | ... Z117: =Z14*Z118 -> 66.526232
B118: % revenue | K118: =K117/K14 -> 0 | L118: =L117/L14 -> 0 | M118: =M117/M14 -> 0 | N118: =N117/N14 -> 0.0022400971 | O118: =O117/O14 -> 0.0029777786 | P118: =P117/P14 -> 0.0030977988 | Q118: =AVERAGE(N118:P118) -> 0.0027718915 | R118: =AVERAGE(O118:Q118) -> 0.0029491563 | S118: =AVERAGE(P118:R118) -> 0.0029396155 | T118: =AVERAGE(Q118:S118) -> 0.0028868878 | U118: =AVERAGE(R118:T118) -> 0.0029252199 | V118: =AVERAGE(S118:U118) -> 0.0029172411 | W118: =AVERAGE(T118:V118) -> 0.0029097829 | X118: =AVERAGE(U118:W118) -> 0.0029174146 | ... Z118: =AVERAGE(W118:Y118) -> 0.0029140035
B119: (Hoàn nhập)/Dự phòng phải thu khó đòi | K119: 0 | L119: 0 | M119: 0 | N119: 0 | O119: 0 | P119: 0 | Q119: =Q14*Q120 -> 0 | R119: =R14*R120 -> 0 | S119: =S14*S120 -> 0 | T119: =T14*T120 -> 0 | U119: =U14*U120 -> 0 | V119: =V14*V120 -> 0 | W119: =W14*W120 -> 0 | X119: =X14*X120 -> 0 | ... Z119: =Z14*Z120 -> 0
B120: % revenue | K120: =K119/K14 -> 0 | L120: =L119/L14 -> 0 | M120: =M119/M14 -> 0 | N120: =N119/N14 -> 0 | O120: =O119/O14 -> 0 | P120: =P119/P14 -> 0 | Q120: 0 | R120: 0 | S120: 0 | T120: 0 | U120: 0 | V120: 0 | W120: 0 | X120: 0 | Y120: 0 | Z120: 0
B121: Selling expense
...

Sheet Debt
B1: =1 -> 1 | C1: THÔNG TIN KHOẢN VAY | R1: DỰ PHÓNG KHOẢN VAY
I2: Phân bổ cho các nhà máy | S2: 1 | T2: 2 | U2: 3 | V2: 4 | W2: 5 | X2: 6 | Y2: 7 | Z2: 8 | AA2: 9 | AB2: 10 | AC2: 11 | AD2: 12 | AE2: 13 | AF2: 14 | AG2: 15 | AH2: 16 | AI2: 17 | AJ2: 18 | AK2: 19 | AL2: 20 | AM2: 21 | AN2: 22 | AO2: 23 | AP2: 24 | AQ2: 25 | AR2: 26 | AS2: 27 | AT2: 28 | AU2: 29 | AV2: 30 | AW2: 31 | AX2: 32 | AY2: 33 | AZ2: 34 | BA2: 35 | BB2: 36 | BC2: 37 | BD2: 38 | BE2: 39 | BF2: 40
R3: =IF(TODAY()<R4,"Proj","") | S3: =IF(TODAY()<S4,"Proj","") -> Proj | T3: =IF(TODAY()<T4,"Proj","") -> Proj | U3: =IF(TODAY()<U4,"Proj","") -> Proj | V3: =IF(TODAY()<V4,"Proj","") -> Proj | W3: =IF(TODAY()<W4,"Proj","") -> Proj | X3: =IF(TODAY()<X4,"Proj","") -> Proj | Y3: =IF(TODAY()<Y4,"Proj","") -> Proj | ... BF3: =IF(TODAY()<BF4,"Proj","") -> Proj
B4: Debt | C4: Gốc vay | D4: Thời điểm vay | E4: Kỳ hạn (tháng) | F4: Lãi suất năm | G4: Loại lãi suất | H4: Kỳ điều chỉnh | R4: 45657 | S4: =DATE(YEAR(R4),MONTH(R4)+13,0) -> 46022 | T4: =DATE(YEAR(S4),MONTH(S4)+13,0) -> 46387 | U4: =DATE(YEAR(T4),MONTH(T4)+13,0) -> 46752 | V4: =DATE(YEAR(U4),MONTH(U4)+13,0) -> 47118 | W4: =DATE(YEAR(V4),MONTH(V4)+13,0) -> 47483 | X4: =DATE(YEAR(W4),MONTH(W4)+13,0) -> 47848 | Y4: =DATE(YEAR(X4),MONTH(X4)+13,0) -> 48213 | Z4: =DATE(YEAR(Y4),MONTH(Y4)+13,0) -> 48579 | ... BF4: =DATE(YEAR(BE4),MONTH(BE4)+13,0) -> 60267 | BH4: Notes
B6: ƯỚC TÍNH LÃI SUẤT NGÂN HÀNG
B7: Tổng nợ vay ngân hàng ngắn và dài hạn | BH7: Chênh lệch nợ vay dài và ngắn hạn | BI7: 0.017
B8: Dư nợ gốc đầu năm | R8: =IF(ISTEXT('BS Raw'!J11),('BS Raw'!J92+'BS Raw'!J105)/Debt!$B$1,R17+R24) -> 848.77029 | S8: =IF(ISTEXT('BS Raw'!K11),('BS Raw'!K92+'BS Raw'!K105)/Debt!$B$1,S17+S24) -> 1348.7555 | T8: =IF(ISTEXT('BS Raw'!L11),('BS Raw'!L92+'BS Raw'!L105)/Debt!$B$1,T17+T24) -> 1978.8247 | U8: =IF(ISTEXT('BS Raw'!M11),('BS Raw'!M92+'BS Raw'!M105)/Debt!$B$1,U17+U24) -> 2182.4561 | V8: =IF(ISTEXT('BS Raw'!N11),('BS Raw'!N92+'BS Raw'!N105)/Debt!$B$1,V17+V24) -> 2134.2635 | W8: =IF(ISTEXT('BS Raw'!O11),('BS Raw'!O92+'BS Raw'!O105)/Debt!$B$1,W17+W24) -> 2951.1765 | X8: =IF(ISTEXT('BS Raw'!P11),('BS Raw'!P92+'BS Raw'!P105)/Debt!$B$1,X17+X24) -> 2865.6917 | Y8: =IF(ISTEXT('BS Raw'!Q11),('BS Raw'!Q92+'BS Raw'!Q105)/Debt!$B$1,Y17+Y24) -> 2620.8254 | ... AB8: =IF(ISTEXT('BS Raw'!T11),('BS Raw'!T92+'BS Raw'!T105)/Debt!$B$1,AB17+AB24) -> 2705.5746
B9: + Trả nợ gốc hàng năm
B10: + Vay mới trong năm
B11: Dư nợ gốc cuối năm | R11: =IF(ISTEXT('BS Raw'!K11),('BS Raw'!K92+'BS Raw'!K105)/Debt!$B$1,R20+R27) -> 1348.7555 | S11: =IF(ISTEXT('BS Raw'!L11),('BS Raw'!L92+'BS Raw'!L105)/Debt!$B$1,S17+S24) -> 1348.7555 | T11: =IF(ISTEXT('BS Raw'!M11),('BS Raw'!M92+'BS Raw'!M105)/Debt!$B$1,T17+T24) -> 1978.8247 | U11: =IF(ISTEXT('BS Raw'!N11),('BS Raw'!N92+'BS Raw'!N105)/Debt!$B$1,U17+U24) -> 2182.4561 | V11: =IF(ISTEXT('BS Raw'!O11),('BS Raw'!O92+'BS Raw'!O105)/Debt!$B$1,V17+V24) -> 2134.2635 | W11: =IF(ISTEXT('BS Raw'!P11),('BS Raw'!P92+'BS Raw'!P105)/Debt!$B$1,W17+W24) -> 2951.1765 | X11: =IF(ISTEXT('BS Raw'!Q11),('BS Raw'!Q92+'BS Raw'!Q105)/Debt!$B$1,X17+X24) -> 2865.6917 | Y11: =IF(ISTEXT('BS Raw'!R11),('BS Raw'!R92+'BS Raw'!R105)/Debt!$B$1,Y17+Y24) -> 2620.8254 | Z11: =IF(ISTEXT('BS Raw'!S11),('BS Raw'!S92+'BS Raw'!S105)/Debt!$B$1,Z17+Z24) -> 2551.4777 | ... AB11: =IF(ISTEXT('BS Raw'!U11),('BS Raw'!U92+'BS Raw'!U105)/Debt!$B$1,AB17+AB24) -> 2705.5746
B12: + Lãi vay hàng năm | R12: =Notes!K158/Debt!$B$1 -> 44.380805
B13: + Lãi suất chung ước tính | R13: =IFERROR(R12/AVERAGE(R8,R11),0) + 0 -> 0.040391612 | S13: =IF(S12="",R13,S12/AVERAGE(S8,S11)) -> 0.040391612 | T13: =IF(T12="",S13,T12/AVERAGE(T8,T11)) -> 0.040391612 | U13: =IF(U12="",T13,U12/AVERAGE(U8,U11)) -> 0.040391612 | V13: =IF(V12="",U13,V12/AVERAGE(V8,V11)) -> 0.040391612 | W13: =IF(W12="",V13,W12/AVERAGE(W8,W11)) -> 0.040391612 | X13: =IF(X12="",W13,X12/AVERAGE(X8,X11)) -> 0.040391612 | Y13: =IF(Y12="",X13,Y12/AVERAGE(Y8,Y11)) -> 0.040391612 | Z13: =IF(Z12="",Y13,Z12/AVERAGE(Z8,Z11)) -> 0.040391612 | ... AB13: =IF(AB12="",AA13,AB12/AVERAGE(AB8,AB11)) -> 0.040391612
B15: TỔNG HỢP NỢ VAY
A16: 1 | B16: Vay ngắn hạn ngân hàng
B17: Dư nợ gốc đầu năm | R17: =R43 -> 845.80581 | S17: =S43 -> 1229.228 | T17: =T43 -> 1627.7236 | U17: =U43 -> 1685.448 | V17: =V43 -> 1550.5483 | W17: =W43 -> 2136.8592 | X17: =X43 -> 2154.1676 | Y17: =Y43 -> 2045.1654 | ... AB17: =AB43 -> 2367.7131
B18: + Trả nợ gốc hàng năm
B19: + Vay mới trong năm
B20: Dư nợ gốc cuối năm | R20: =R46 -> 1229.228 | S20: =S46 -> 1627.7236 | T20: =T46 -> 1685.448 | U20: =U46 -> 1550.5483 | V20: =V46 -> 2136.8592 | W20: =W46 -> 2154.1676 | X20: =X46 -> 2045.1654 | Y20: =Y46 -> 2106.1436 | ... AB20: =AB46 -> 2492.9776
B21: + Lãi vay hàng năm | R21: =+R48 -> 40.923836 | S21: =+S48 -> 53.461651 | T21: =+T48 -> 60.877171 | U21: =+U48 -> 58.543259 | V21: =+V48 -> 64.204686 | W21: =+W48 -> 77.231774 | X21: =+X48 -> 76.792497 | Y21: =+Y48 -> 76.965831 | ... AB21: =+AB48 -> 92.953407
A23: 2 | B23: Vay dài hạn ngân hàng
B24: Dư nợ gốc đầu năm | R24: =R54 -> 2.9644799 | S24: =+S54+S104+S151+S162+S173+S184+S195+S206+S217+S228+S239 -> 119.5275 | T24: =+T54+T104+T151+T162+T173+T184+T195+T206+T217+T228+T239 -> 351.10114 | U24: =+U54+U104+U151+U162+U173+U184+U195+U206+U217+U228+U239 -> 497.00808 | V24: =+V54+V104+V151+V162+V173+V184+V195+V206+V217+V228+V239 -> 583.71521 | W24: =+W54+W104+W151+W162+W173+W184+W195+W206+W217+W228+W239 -> 814.31731 | X24: =+X54+X104+X151+X162+X173+X184+X195+X206+X217+X228+X239 -> 711.52402 | Y24: =+Y54+Y104+Y151+Y162+Y173+Y184+Y195+Y206+Y217+Y228+Y239 -> 575.66 | Z24: =+Z54+Z104+Z151+Z162+Z173+Z184+Z195+Z206+Z217+Z228+Z239 -> 445.33407 | ... AB24: =+AB54+AB104+AB151+AB162+AB173+AB184+AB195+AB206+AB217+AB228+AB239 -> 337.86153
B25: + Trả nợ gốc hàng năm | S25: =+S55+S106+S153+S164+S175+S186+S197+S208+S219+S230+S241 -> 100.1572 | T25: =+T55+T106+T153+T164+T175+T186+T197+T208+T219+T230+T241 -> 154.83812 | U25: =+U55+U106+U153+U164+U175+U186+U197+U208+U219+U230+U241 -> 208.51484 | V25: =+V55+V106+V153+V164+V175+V186+V197+V208+V219+V230+V241 -> 257.39999 | W25: =+W55+W106+W153+W164+W175+W186+W197+W208+W219+W230+W241 -> 291.75704 | X25: =+X55+X106+X153+X164+X175+X186+X197+X208+X219+X230+X241 -> 289.54095 | Y25: =+Y55+Y106+Y153+Y164+Y175+Y186+Y197+Y208+Y219+Y230+Y241 -> 254.64696 | Z25: =+Z55+Z106+Z153+Z164+Z175+Z186+Z197+Z208+Z219+Z230+Z241 -> 225.75525 | ... AB25: =+AB55+AB106+AB153+AB164+AB175+AB186+AB197+AB208+AB219+AB230+AB241 -> 151.54535
B26: + Vay mới trong năm | S26: =+S56+S105+S152+S163+S174+S185+S196+S207+S218+S229+S240 -> 301.57349 | T26: =+T56+T105+T152+T163+T174+T185+T196+T207+T218+T229+T240 -> 273.4046 | U26: =+U56+U105+U152+U163+U174+U185+U196+U207+U218+U229+U240 -> 268.38361 | V26: =+V56+V105+V152+V163+V174+V185+V196+V207+V218+V229+V240 -> 443.63826 | W26: =+W56+W105+W152+W163+W174+W185+W196+W207+W218+W229+W240 -> 171.78522 | X26: =+X56+X105+X152+X163+X174+X185+X196+X207+X218+X229+X240 -> 139.70631 | Y26: =+Y56+Y105+Y152+Y163+Y174+Y185+Y196+Y207+Y218+Y229+Y240 -> 113.01912 | Z26: =+Z56+Z105+Z152+Z163+Z174+Z185+Z196+Z207+Z218+Z229+Z240 -> 126.43555 | ... AB26: =+AB56+AB105+AB152+AB163+AB174+AB185+AB196+AB207+AB218+AB229+AB240 -> 144.05465
B27: Dư nợ gốc cuối năm | R27: =R57 -> 119.5275 | S27: =+S57+S107+S154+S165+S176+S187+S198+S209+S220+S231+S242 -> 351.10114 | T27: =+T57+T107+T154+T165+T176+T187+T198+T209+T220+T231+T242 -> 497.00808 | U27: =+U57+U107+U154+U165+U176+U187+U198+U209+U220+U231+U242 -> 583.71521 | V27: =+V57+V107+V154+V165+V176+V187+V198+V209+V220+V231+V242 -> 814.31731 | W27: =+W57+W107+W154+W165+W176+W187+W198+W209+W220+W231+W242 -> 711.52402 | X27: =+X57+X107+X154+X165+X176+X187+X198+X209+X220+X231+X242 -> 575.66 | Y27: =+Y57+Y107+Y154+Y165+Y176+Y187+Y198+Y209+Y220+Y231+Y242 -> 445.33407 | Z27: =+Z57+Z107+Z154+Z165+Z176+Z187+Z198+Z209+Z220+Z231+Z242 -> 358.65792 | ... AB27: =+AB57+AB107+AB154+AB165+AB176+AB187+AB198+AB209+AB220+AB231+AB242 -> 344.77629
B28: + Lãi vay hàng năm | R28: =+R59+R109+R156+R167+R178+R189+R200+R211+R222+R233+R244 -> 4.7771871 | S28: =+S59+S109+S156+S167+S178+S189+S200+S211+S222+S233+S244 -> 18.354517 | T28: =+T59+T109+T156+T167+T178+T189+T200+T211+T222+T233+T244 -> 33.07626 | U28: =+U59+U109+U156+U167+U178+U189+U200+U211+U222+U233+U244 -> 42.148208 | V28: =+V59+V109+V156+V167+V178+V189+V200+V211+V222+V233+V244 -> 54.523268 | W28: =+W59+W109+W156+W167+W178+W189+W200+W211+W222+W233+W244 -> 59.507812 | X28: =+X59+X109+X156+X167+X178+X189+X200+X211+X222+X233+X244 -> 50.200177 | Y28: =+Y59+Y109+Y156+Y167+Y178+Y189+Y200+Y211+Y222+Y233+Y244 -> 39.818769 | ... AB28: =+AB59+AB109+AB156+AB167+AB178+AB189+AB200+AB211+AB222+AB233+AB244 -> 26.622875
A30: 3 | B30: Vay dài hạn trái phiếu
B31: Dư nợ gốc đầu năm
B32: + Trả nợ gốc hàng năm
B33: + Vay mới trong năm
B34: Dư nợ gốc cuối năm
B35: + Lãi vay hàng năm
B38: CHI TIẾT NỢ VAY HIỆN HỮU
A39: 1 | B39: Vay ngắn hạn Ngân hàng
A41: 1.1 | B41: Ngân hàng 1
B42: Khoản 1 | D42: 45627 | E42: 12 | G42: floating | H42: 0.5
B43: Dư nợ gốc đầu năm | R43: ='BS Raw'!J92/B1 -> 845.80581 | S43: =R46 -> 1229.228 | T43: =S46 -> 1627.7236 | U43: =T46 -> 1685.448 | V43: =U46 -> 1550.5483 | W43: =V46 -> 2136.8592 | X43: =W46 -> 2154.1676 | Y43: =X46 -> 2045.1654 | Z43: =Y46 -> 2106.1436 | ... AB43: =AA46 -> 2367.7131
B44: + Trả nợ gốc hàng năm
B45: + Vay mới trong năm
B46: Dư nợ gốc cuối năm | R46: ='BS Raw'!K92/B1 -> 1229.228 | S46: =Input!Q279 -> 1627.7236 | T46: =Input!R279 -> 1685.448 | U46: =Input!S279 -> 1550.5483 | V46: =Input!T279 -> 2136.8592 | W46: =Input!U279 -> 2154.1676 | X46: =Input!V279 -> 2045.1654 | Y46: =Input!W279 -> 2106.1436 | Z46: =Input!X279 -> 2248.6224 | ... AB46: =Input!Z279 -> 2492.9776
B47: + Lãi suất | R47: =IF($F$42,$F$42,IFERROR(R13-$BI$7*AVERAGE(R24,R27)/AVERAGE(R8,R11),0)) -> 0.039444018 | S47: =IF(S12="",S13-$BI$7*AVERAGE(S24,S27)/AVERAGE(S8,S11),R47) -> 0.037425661 | T47: =IF(T12="",T13-$BI$7*AVERAGE(T24,T27)/AVERAGE(T8,T11),S47) -> 0.036748577 | U47: =IF(U12="",U13-$BI$7*AVERAGE(U24,U27)/AVERAGE(U8,U11),T47) -> 0.036182525 | V47: =IF(V12="",V13-$BI$7*AVERAGE(V24,V27)/AVERAGE(V8,V11),U47) -> 0.034823754 | W47: =IF(W12="",W13-$BI$7*AVERAGE(W24,W27)/AVERAGE(W8,W11),V47) -> 0.035996873 | X47: =IF(X12="",X13-$BI$7*AVERAGE(X24,X27)/AVERAGE(X8,X11),W47) -> 0.036573664 | Y47: =IF(Y12="",Y13-$BI$7*AVERAGE(Y24,Y27)/AVERAGE(Y8,Y11),X47) -> 0.03708027 | Z47: =IF(Z12="",Z13-$BI$7*AVERAGE(Z24,Z27)/AVERAGE(Z8,Z11),Y47) -> 0.037713191 | ... AB47: =IF(AB12="",AB13-$BI$7*AVERAGE(AB24,AB27)/AVERAGE(AB8,AB11),AA47) -> 0.038246995 | BH47: Lãi suất ước tính dựa vào: (1) CP lãi vay trong kỳ, (2) tổng dư nợ đầu, cuối kỳ và (3) chênh lệch thực tế giữa lãi suất ngắn hạn và dài hạn
B48: + Lãi vay hàng năm | R48: =R47*AVERAGE(R43,R46) -> 40.923836 | S48: =S47*AVERAGE(S43,S46) -> 53.461651 | T48: =T47*AVERAGE(T43,T46) -> 60.877171 | U48: =U47*AVERAGE(U43,U46) -> 58.543259 | V48: =V47*AVERAGE(V43,V46) -> 64.204686 | W48: =W47*AVERAGE(W43,W46) -> 77.231774 | X48: =X47*AVERAGE(X43,X46) -> 76.792497 | Y48: =Y47*AVERAGE(Y43,Y46) -> 76.965831 | ... AB48: =AB47*AVERAGE(AB43,AB46) -> 92.953407
A50: 2 | B50: Vay dài hạn Ngân hàng
A52: 2.1 | B52: Ngân hàng 1 | C52: Khoản vay dài hạn từ ừ Ngân hàng Thương mại Cổ phần Ngoại thương Việt Nam hết hạn vào năm 2027, các thông tin khoản vay coi trong thuyết minh BCTC 2024
B53: Khoản 1/ long-term debt A | C53: =R57 -> 119.5275 | D53: 45649 | E53: 36 | F53: 0.078 | G53: floating | H53: 0.5 | BH53: Chú thích: Long-term debt A là toàn bộ nợ dài hạn cuối 2021 của công ty
B54: Dư nợ gốc đầu năm | R54: ='BS Raw'!J105/Debt!$B$1 -> 2.9644799 | S54: =R57 -> 119.5275 | T54: =S57 -> 79.684997 | U54: =T57 -> 39.842499 | V54: =U57 -> 0 | W54: =V57 -> 0 | X54: =W57 -> 0 | Y54: =X57 -> 0 | Z54: =Y57 -> 0 | ... AB54: =AA57 -> 0
B55: + Trả nợ gốc hàng năm | S55: =C53/(E53/12) -> 39.842499 | T55: =MIN(S55,S57) -> 39.842499 | U55: =MIN(T55,T57) -> 39.842499 | V55: =MIN(U55,U57) -> 0 | W55: =MIN(V55,V57) -> 0 | X55: =MIN(W55,W57) -> 0 | Y55: =MIN(X55,X57) -> 0 | Z55: =MIN(Y55,Y57) -> 0 | AA55: =MIN(Z55,Z57) -> 0 | AB55: =MIN(AA55,AA57) -> 0
B56: + Vay mới trong năm
B57: Dư nợ gốc cuối năm | R57: ='BS Raw'!K105/Debt!$B$1 -> 119.5275 | S57: =S54-S55 -> 79.684997 | T57: =T54-T55 -> 39.842499 | U57: =U54-U55 -> 0 | V57: =V54-V55 -> 0 | W57: =W54-W55 -> 0 | X57: =X54-X55 -> 0 | Y57: =Y54-Y55 -> 0 | Z57: =Z54-Z55 -> 0 | ... AB57: =AB54-AB55 -> 0
B58: + Lãi suất | R58: =IF($F$53="",R47+$BI$7,$F$53) -> 0.078 | S58: =IF($F$53="",S47+$BI$7,$F$53) -> 0.078 | T58: =IF($F$53="",T47+$BI$7,$F$53) -> 0.078 | U58: =IF($F$53="",U47+$BI$7,$F$53) -> 0.078 | V58: =IF($F$53="",V47+$BI$7,$F$53) -> 0.078 | W58: =IF($F$53="",W47+$BI$7,$F$53) -> 0.078 | X58: =IF($F$53="",X47+$BI$7,$F$53) -> 0.078 | Y58: =IF($F$53="",Y47+$BI$7,$F$53) -> 0.078 | ... AB58: =IF($F$53="",AB47+$BI$7,$F$53) -> 0.078 | BH58: Lãi suất ước tính dựa vào: (1) CP lãi vay trong kỳ, (2) tổng dư nợ đầu, cuối kỳ và (3) chênh lệch thực tế giữa lãi suất ngắn hạn và dài hạn
B59: + Lãi vay hàng năm | R59: =R58*AVERAGE(R54,R57) -> 4.7771871 | S59: =S58*AVERAGE(S54,S57) -> 7.7692872 | T59: =T58*AVERAGE(T54,T57) -> 4.6615723 | U59: =U58*AVERAGE(U54,U57) -> 1.5538574 | V59: =V58*AVERAGE(V54,V57) -> 0 | W59: =W58*AVERAGE(W54,W57) -> 0 | X59: =X58*AVERAGE(X54,X57) -> 0 | Y59: =Y58*AVERAGE(Y54,Y57) -> 0 | ... AB59: =AB58*AVERAGE(AB54,AB57) -> 0
A61: 2.2 | B61: Ngân hàng 2
B62: Khoản 1
B63: Dư nợ gốc đầu năm
B64: + Trả nợ gốc hàng năm
B65: + Vay mới trong năm
B66: Dư nợ gốc cuối năm
B67: + Lãi vay hàng năm
B69: Khoản 2
B70: Dư nợ gốc đầu năm
B71: + Trả nợ gốc hàng năm
B72: + Vay mới trong năm
B73: Dư nợ gốc cuối năm
B74: + Lãi vay hàng năm
A76: 2.3 | B76: Vay cá nhân (vi)
B77: Nguyễn Văn A
A83: 2.4 | B83: Trái phiếu phát hành (vii)
B84: Đợt 1
B90: Đợt 2
B99: CHI TIẾT NỢ VAY MỚI | C99: Các khoản vay dài hạn có thời hạn trả nợ tối đa là 60 tháng (tham khảo BCTC 2024 DCM)
A100: 1 | B100: Vay dài hạn Ngân hàng năm 2025
A102: 1.1 | B102: Ngân hàng 1
B103: Khoản 1/ long-term debt B | C103: ='LT. Asset'!BD20 -> 301.57349 | D103: 45809 | E103: 60 | F103: =R58 -> 0.078 | G103: floating | H103: 0.5 | BH103: Chi tiết các khoản vay mới dài hạn để tài trợ các dự án xây mới và mở rộng nhà máy sản xuất được ước lượng dựa vào thông tin dưới đây, lấy trong bản cáo bạch niêm yết HSX 2018
B104: Dư nợ gốc đầu năm | R104: 0 | S104: 0 | T104: =S107 -> 271.41614 | U104: =T107 -> 211.10144 | V104: =U107 -> 150.78675 | W104: =V107 -> 90.472047 | X104: =W107 -> 30.157349 | Y104: =X107 -> 0 | Z104: =Y107 -> 0 | AA104: =Z107 -> 0 | AB104: =AA107 -> 0
B105: + Vay mới trong năm | S105: =IF(YEAR($D$103)=YEAR(S4),$C$103,0) -> 301.57349 | T105: 0 | U105: =IF(YEAR($D$103)=YEAR(U4),$C$103,0) -> 0 | V105: =IF(YEAR($D$103)=YEAR(V4),$C$103,0) -> 0 | W105: =IF(YEAR($D$103)=YEAR(W4),$C$103,0) -> 0 | X105: =IF(YEAR($D$103)=YEAR(X4),$C$103,0) -> 0 | Y105: =IF(YEAR($D$103)=YEAR(Y4),$C$103,0) -> 0 | Z105: =IF(YEAR($D$103)=YEAR(Z4),$C$103,0) -> 0 | AA105: =IF(YEAR($D$103)=YEAR(AA4),$C$103,0) -> 0 | AB105: =IF(YEAR($D$103)=YEAR(AB4),$C$103,0) -> 0
B106: + Trả nợ gốc hàng năm | S106: =IF($C103=S105,$C103/($E103/12),MIN(R107,R106)) -> 60.314698 | T106: =IF($C103=T105,$C103/($E103/12),MIN(S107,S106)) -> 60.314698 | U106: =IF($C103=U105,$C103/($E103/12),MIN(T107,T106)) -> 60.314698 | V106: =IF($C103=V105,$C103/($E103/12),MIN(U107,U106)) -> 60.314698 | W106: =IF($C103=W105,$C103/($E103/12),MIN(V107,V106)) -> 60.314698 | X106: =IF($C103=X105,$C103/($E103/12),MIN(W107,W106)) -> 30.157349 | Y106: =IF($C103=Y105,$C103/($E103/12),MIN(X107,X106)) -> 0 | Z106: =IF($C103=Z105,$C103/($E103/12),MIN(Y107,Y106)) -> 0 | ... AB106: =IF($C103=AB105,$C103/($E103/12),MIN(AA107,AA106)) -> 0
B107: Dư nợ gốc cuối năm | R107: 0 | S107: =S104+S105-S106*0.5 -> 271.41614 | T107: =T104+T105-T106 -> 211.10144 | U107: =U104+U105-U106 -> 150.78675 | V107: =V104+V105-V106 -> 90.472047 | W107: =W104+W105-W106 -> 30.157349 | X107: =X104+X105-X106 -> 0 | Y107: =Y104+Y105-Y106 -> 0 | Z107: =Z104+Z105-Z106 -> 0 | AA107: =AA104+AA105-AA106 -> 0 | AB107: =AB104+AB105-AB106 -> 0
B108: + Lãi suất | R108: =F103 -> 0.078 | S108: =R108 -> 0.078 | T108: =S108 -> 0.078 | U108: =T108 -> 0.078 | V108: =U108 -> 0.078 | W108: =V108 -> 0.078 | X108: =W108 -> 0.078 | Y108: =X108 -> 0.078 | Z108: =Y108 -> 0.078 | ... AB108: =AA108 -> 0.078
B109: + Lãi vay hàng năm | R109: =R108*AVERAGE(R104,R107) -> 0 | S109: =S108*AVERAGE(S104,S107) -> 10.58523 | T109: =T108*AVERAGE(T104,T107) -> 18.818186 | U109: =U108*AVERAGE(U104,U107) -> 14.113639 | V109: =V108*AVERAGE(V104,V107) -> 9.4090929 | W109: =W108*AVERAGE(W104,W107) -> 4.7045465 | X109: =X108*AVERAGE(X104,X107) -> 1.1761366 | Y109: =Y108*AVERAGE(Y104,Y107) -> 0 | ... AB109: =AB108*AVERAGE(AB104,AB107) -> 0
A111: 1.2 | B111: Ngân hàng 2
B112: Khoản 1
B113: Dư nợ gốc đầu năm
B114: + Trả nợ gốc hàng năm
B115: + Vay mới trong năm
B116: Dư nợ gốc cuối năm
B117: + Lãi vay hàng năm
B119: Khoản 2
B120: Dư nợ gốc đầu năm
B121: + Trả nợ gốc hàng năm
B122: + Vay mới trong năm
B123: Dư nợ gốc cuối năm
B124: + Lãi vay hàng năm
A126: 1.3 | B126: Vay cá nhân (vi)
B127: Nguyễn Văn A
A133: 1.4 | B133: Trái phiếu phát hành (vii)
B134: Đợt 1
B140: Đợt 2
A147: 2 | B147: Vay dài hạn Ngân hàng năm 2026
A149: 2.1 | B149: Ngân hàng 1
B150: Khoản 1/ long-term debt C | C150: ='LT. Asset'!BE20 -> 273.4046 | D150: 46174 | E150: 60 | F150: =F103 -> 0.078 | G150: floating | H150: 0.5
B151: Dư nợ gốc đầu năm | R151: 0 | S151: 0 | T151: =S154 -> 0 | U151: =T154 -> 246.06414 | V151: =U154 -> 191.38322 | W151: =V154 -> 136.7023 | X151: =W154 -> 82.021379 | Y151: =X154 -> 27.34046 | Z151: =Y154 -> 0 | AA151: =Z154 -> 0 | AB151: =AA154 -> 0
...

Sheet LT. Asset
B1: =1 -> 1 | N1: 1 | O1: 2 | P1: 3 | Q1: 1 | R1: 2 | S1: 3 | T1: 4 | U1: 5 | V1: 6 | W1: 7 | X1: 8 | Y1: 9 | Z1: 10 | AA1: 11 | AB1: 12 | AC1: 13 | AD1: 14 | AE1: 15 | AF1: 16 | AG1: 17 | AH1: 18 | AI1: 19 | AJ1: 1 | AK1: 2 | AL1: 3 | AM1: 4 | AN1: 5 | AO1: 6 | AP1: 7 | AQ1: 8 | AR1: 9 | AS1: 10 | AT1: 11 | AU1: 12 | AV1: 13 | AW1: 14 | AX1: 15 | AY1: 16 | AZ1: 17 | BA1: 18
E2: =IF(TODAY()<E3,"Proj","") | F2: =IF(TODAY()<F3,"Proj","") | H2: =IF(TODAY()<H3,"Proj","") | I2: =IF(TODAY()<I3,"Proj","") | J2: =IF(TODAY()<J3,"Proj","") | K2: =IF(TODAY()<K3,"Proj","") | L2: =IF(TODAY()<L3,"Proj","") | M2: =IF(TODAY()<M3,"Proj","") | N2: =IF(TODAY()<N3,"Proj","") | O2: =IF(TODAY()<O3,"Proj","") | ... BA2: =IF(TODAY()<BA3,"Proj","") -> Proj
B3: Fixed Assets | D3: 41274 | E3: =DATE(YEAR(D3),MONTH(D3)+13,0) -> 41639 | F3: =DATE(YEAR(E3),MONTH(E3)+13,0) -> 42004 | G3: =DATE(YEAR(F3),MONTH(F3)+13,0) -> 42369 | H3: =DATE(YEAR(G3),MONTH(G3)+13,0) -> 42735 | I3: =DATE(YEAR(H3),MONTH(H3)+13,0) -> 43100 | J3: =DATE(YEAR(I3),MONTH(I3)+13,0) -> 43465 | K3: =DATE(YEAR(J3),MONTH(J3)+13,0) -> 43830 | L3: =DATE(YEAR(K3),MONTH(K3)+13,0) -> 44196 | ... BA3: =DATE(YEAR(AZ3),MONTH(AZ3)+13,0) -> 59171
K4: ='Consol. Rev.'!K4 -> 0 | L4: ='Consol. Rev.'!L4 -> 0.073592305 | M4: ='Consol. Rev.'!M4 -> 0.30530404 | N4: ='Consol. Rev.'!N4 -> 0.613466 | O4: ='Consol. Rev.'!O4 -> -0.21061755 | P4: ='Consol. Rev.'!P4 -> 0.16053712 | Q4: ='Consol. Rev.'!Q4 -> 0.21581151 | R4: ='Consol. Rev.'!R4 -> 0.048080581 | ... Z4: ='Consol. Rev.'!Z4 -> 0.013457614
B5: TỔNG HỢP CÁC LOẠI TÀI SẢN CỐ ĐỊNH (1+2+3) | I5: Time line đầu tư capex | K5: 334.78 | L5: 122.89 | M5: 72.58 | N5: 85.78 | O5: 404.72 | P5: 1173.2
B6: Nguyên giá cuối kỳ | K6: =SUM(K28,K63,K96,K130) -> 14332.143 | L6: =SUM(L28,L63,L96,L130) -> 14419.172 | M6: =SUM(M28,M63,M96,M130) -> 15257.152 | N6: =SUM(N28,N63,N96,N130) -> 15449.404 | O6: =SUM(O28,O63,O96,O130) -> 15930.495 | P6: =SUM(P28,P63,P96,P130) -> 17036.285 | Q6: =SUM(Q28,Q63,Q96,Q130) -> 17775.326 | R6: =SUM(R28,R63,R96,R130) -> 18445.335 | ... Z6: =SUM(Z28,Z63,Z96,Z130) -> 22257.614
B7: GTCL cuối kỳ | K7: =SUM(K41,K75,K108,K142) -> 5187.6362 | L7: =SUM(L41,L75,L108,L142) -> 3955.4286 | M7: =SUM(M41,M75,M108,M142) -> 3405.6233 | N7: =SUM(N41,N75,N108,N142) -> 2206.8526 | O7: =SUM(O41,O75,O108,O142) -> 1600.1754 | P7: =SUM(P41,P75,P108,P142) -> 1946.1945 | Q7: =SUM(Q41,Q75,Q108,Q142) -> 1819.0391 | R7: =SUM(R41,R75,R108,R142) -> 1530.9702 | ... Z7: =SUM(Z41,Z75,Z108,Z142) -> 2142.3771
B8: Khấu hao trong kỳ | K8: =SUM(K37,K71,K104,K138) -> 1322.2267 | L8: =SUM(L37,L71,L104,L138) -> 1319.2364 | M8: =SUM(M37,M71,M104,M138) -> 1387.7848 | N8: =SUM(N37,N71,N104,N138) -> 1400.1902 | O8: =SUM(O37,O71,O104,O138) -> 1087.7682 | P8: =SUM(P37,P71,P104,P138) -> 764.84694 | Q8: =SUM(Q37,Q71,Q104,Q138) -> 866.19597 | R8: =SUM(R37,R71,R104,R138) -> 958.07836 | ... Z8: =SUM(Z37,Z71,Z104,Z138) -> 447.65036 | BC8: Đầu tư capex 2025-2035 | BD8: Nhà máy NPK | BE8: Nhà máy Ure
B9: Capex | K9: =(K26+K27)+(K61+K62)+(K94+K95)+(K128)+(K216-K215) -> 525.57928 | L9: =(L26+L27)+(L61+L62)+(L94+L95)+(L128)+(L216-L215) -> 149.478 | M9: =(M26+M27)+(M61+M62)+(M94+M95)+(M128)+(M216-M215) -> 143.14214 | N9: =(N26+N27)+(N61+N62)+(N94+N95)+(N128)+(N216-N215) -> 159.31022 | O9: =(O26+O27)+(O61+O62)+(O94+O95)+(O128)+(O216-O215) -> 536.10483 | P9: =(P26+P27)+(P61+P62)+(P94+P95)+(P128)+(P216-P215) -> 1618.7663 | Q9: =Q10*Input!Q45 -> 793.61445 | R9: =R10*Input!R45 -> 719.48578 | S9: =S10*Input!S45 -> 706.27265 | T9: =T10*Input!T45 -> 1167.4691 | U9: =U10*Input!U45 -> 452.06637 | V9: =V10*Input!V45 -> 367.64817 | W9: =W10*Input!W45 -> 297.41873 | X9: =X10*Input!X45 -> 332.72512 | ... Z9: =Z10*Input!Z45 -> 379.09118 | BC9: =SUM(Q9:Z9) -> 5606.893 | BD9: 768 | BE9: =900000000*16000/10^9 -> 14400
B10: As % EBIT | K10: =K9/Input!K47 -> 1.3345866 | L10: =L9/Input!L47 -> 0.23231041 | M10: =M9/Input!M47 -> 0.078132483 | N10: =N9/Input!N47 -> 0.036601664 | O10: =O9/Input!O47 -> 0.78537347 | P10: =P9/Input!P47 -> 1.5900383 | Q10: 0.379 | R10: 0.3 | S10: 0.25 | T10: 0.25 | U10: 0.12 | V10: 0.12 | W10: 0.1 | X10: 0.1 | Y10: 0.1 | Z10: 0.1 | BC10: Đầu tư Capex nhiều >> Tăng trưởng dài hạn sau thời gian dự phóng ~ 5-6% | BD10: =BC9/BD9 -> 7.3006419 | BE10: =BC9/BE9 -> 0.38936757
B12: Trong đó: Capex duy trì | BC12: Nguồn vốn
B13: Capex TSCĐ hữu hình | K13: =(K26+K27)/K9 -> 0.28517388 | L13: =(L26+L27)/L9 -> 0.46677901 | M13: =(M26+M27)/M9 -> 5.8095387 | N13: =(N26+N27)/N9 -> 1.0475612 | O13: =(O26+O27)/O9 -> 0.29702964 | P13: =(P26+P27)/P9 -> 0.65244429 | Q13: =73% -> 0.73 | R13: =Q13 -> 0.73 | S13: =R13 -> 0.73 | T13: =S13 -> 0.73 | U13: =T13 -> 0.73 | V13: =U13 -> 0.73 | W13: =V13 -> 0.73 | X13: =W13 -> 0.73 | Y13: =X13 -> 0.73 | Z13: =Y13 -> 0.73 | BC13: Vốn chủ sở hữu | BD13: Vốn vay
B14: Capex TSCĐ thuê tài chính | K14: =(K61+K62)/K9 -> 0 | L14: =(L61+L62)/L9 -> 0 | M14: =(M61+M62)/M9 -> 0 | N14: =(N61+N62)/N9 -> 0 | O14: =(O61+O62)/O9 -> 0 | P14: =(P61+P62)/P9 -> 0.007402814 | Q14: =AVERAGE(K14:P14) -> 0.0012338023 | R14: =Q14 -> 0.0012338023 | S14: =R14 -> 0.0012338023 | T14: =S14 -> 0.0012338023 | U14: =T14 -> 0.0012338023 | V14: =U14 -> 0.0012338023 | W14: =V14 -> 0.0012338023 | X14: =W14 -> 0.0012338023 | Y14: =X14 -> 0.0012338023 | Z14: =Y14 -> 0.0012338023 | AB14: =AA14 -> 0 | AC14: =AB14 -> 0 | AD14: =AC14 -> 0 | AE14: =AD14 -> 0 | AF14: =AE14 -> 0 | AG14: =AF14 -> 0 | AH14: =AG14 -> 0 | AI14: =AH14 -> 0 | ... BA14: =AZ14 -> 0 | BC14: 0.62 | BD14: 0.38
B15: Capex TSCĐ vô hình | K15: =(K94+K95)/K9 -> 0.04483826 | L15: =(L94+L95)/L9 -> 0.11543905 | M15: =(M94+M95)/M9 -> 0.044638854 | N15: =(N94+N95)/N9 -> 0.15921612 | O15: =(O94+O95)/O9 -> 0.60035283 | P15: =(P94+P95)/P9 -> 0.023259943 | Q15: =20% -> 0.2 | R15: =Q15 -> 0.2 | S15: =R15 -> 0.2 | T15: =S15 -> 0.2 | U15: =T15 -> 0.2 | V15: =U15 -> 0.2 | W15: =V15 -> 0.2 | X15: =W15 -> 0.2 | Y15: =X15 -> 0.2 | Z15: =Y15 -> 0.2 | BC15: =BC9*BC14 -> 3476.2736 | BD15: =BC9*BD14 -> 2130.6193
B16: Capex BĐS đầu tư | K16: =K128/K9 -> 0 | L16: =L128/L9 -> 0 | M16: =M128/M9 -> 0 | N16: =N128/N9 -> 0 | O16: =O128/O9 -> 0 | P16: =P128/P9 -> 0 | Q16: =AVERAGE(K16:P16) -> 0 | R16: =Q16 -> 0 | S16: =R16 -> 0 | T16: =S16 -> 0 | U16: =T16 -> 0 | V16: =U16 -> 0 | W16: =V16 -> 0 | X16: =W16 -> 0 | Y16: =X16 -> 0 | Z16: =Y16 -> 0
B17: Capex TS dở dang | K17: =(K216-K215)/K9 -> 0.66998786 | L17: =(L216-L215)/L9 -> 0.41778194 | M17: =(M216-M215)/M9 -> -4.8541775 | N17: =(N216-N215)/N9 -> -0.20677731 | O17: =(O216-O215)/O9 -> 0.10261753 | P17: =(P216-P215)/P9 -> 0.31689296 | Q17: =100%-SUM(Q13:Q16) -> 0.068766198 | R17: =100%-SUM(R13:R16) -> 0.068766198 | S17: =100%-SUM(S13:S16) -> 0.068766198 | T17: =100%-SUM(T13:T16) -> 0.068766198 | U17: =100%-SUM(U13:U16) -> 0.068766198 | V17: =100%-SUM(V13:V16) -> 0.068766198 | W17: =100%-SUM(W13:W16) -> 0.068766198 | X17: =100%-SUM(X13:X16) -> 0.068766198 | ... Z17: =100%-SUM(Z13:Z16) -> 0.068766198 | BC17: Vay dài hạn 2025-2034 ở sheet debt
K18: =SUM(K13:K17) -> 1 | L18: =SUM(L13:L17) -> 1 | M18: =SUM(M13:M17) -> 1 | N18: =SUM(N13:N17) -> 1 | O18: =SUM(O13:O17) -> 1 | P18: =SUM(P13:P17) -> 1 | Q18: =SUM(Q13:Q17) -> 1 | R18: =SUM(R13:R17) -> 1 | ... Z18: =SUM(Z13:Z17) -> 1 | BD18: =Q3 -> 46022 | BE18: =R3 -> 46387 | BF18: =S3 -> 46752 | BG18: =T3 -> 47118 | BH18: =U3 -> 47483 | BI18: =V3 -> 47848 | BJ18: =W3 -> 48213 | BK18: =X3 -> 48579 | ... BM18: =Z3 -> 49309
B19: CHI TIẾT CÁC LOẠI TSCĐ | BC19: Vốn chủ sở hữu | BD19: =Q9*$BC$14 -> 492.04096 | BE19: =R9*$BC$14 -> 446.08119 | BF19: =S9*$BC$14 -> 437.88904 | BG19: =T9*$BC$14 -> 723.83085 | BH19: =U9*$BC$14 -> 280.28115 | BI19: =V9*$BC$14 -> 227.94187 | BJ19: =W9*$BC$14 -> 184.39961 | BK19: =X9*$BC$14 -> 206.28958 | ... BM19: =Z9*$BC$14 -> 235.03653 | BN19: =SUM(BD19:BM19) -> 3476.2736
BC20: Vốn vay | BD20: =Q9*$BD$14 -> 301.57349 | BE20: =R9*$BD$14 -> 273.4046 | BF20: =S9*$BD$14 -> 268.38361 | BG20: =T9*$BD$14 -> 443.63826 | BH20: =U9*$BD$14 -> 171.78522 | BI20: =V9*$BD$14 -> 139.70631 | BJ20: =W9*$BD$14 -> 113.01912 | BK20: =X9*$BD$14 -> 126.43555 | ... BM20: =Z9*$BD$14 -> 144.05465 | BN20: =SUM(BD20:BM20) -> 2130.6193
B21: 1. TÀI SẢN CỐ ĐỊNH HỮU HÌNH | BN21: =SUM(BN19:BN20) -> 5606.893
B22: Nguyên giá
B23: Số dư đầu kỳ | K23: =Notes!F53 -> 14052.806 | L23: =Notes!G53 -> 14202.688 | M23: =Notes!H53 -> 14272.461 | N23: =Notes!I53 -> 15104.051 | O23: =Notes!J53 -> 15270.938 | P23: =Notes!K53 -> 15430.177 | Q23: =P28 -> 16486.332 | R23: =Q28 -> 17065.67 | S23: =R28 -> 17590.895 | T23: =S28 -> 18106.474 | U23: =T28 -> 18958.726 | V23: =U28 -> 19288.735 | W23: =V28 -> 19557.118 | X23: =W28 -> 19774.234 | ... Z23: =Y28 -> 20302.627 | BC23: Capex hữu hình 2025-2035
B24: Tăng trong kỳ (FC) | Q24: =Q9*Q13 -> 579.33855 | R24: =R9*R13 -> 525.22462 | S24: =S9*S13 -> 515.57904 | T24: =T9*T13 -> 852.25246 | U24: =U9*U13 -> 330.00845 | V24: =V9*V13 -> 268.38317 | W24: =W9*W13 -> 217.11567 | X24: =X9*X13 -> 242.88934 | ... Z24: =Z9*Z13 -> 276.73656 | BC24: =SUM(Q24:Z24) -> 4093.0319
B25: Giảm trong kỳ (FC) | Q25: 0 | R25: 0 | S25: 0 | T25: 0 | U25: 0 | V25: 0 | W25: 0 | X25: 0 | Y25: 0 | Z25: 0
B26: Tăng trong kỳ | K26: =Notes!F54 -> 149.88148 | L26: =Notes!G54 -> 69.773194 | M26: =Notes!H54 -> 837.37984 | N26: =Notes!I54 -> 176.05477 | O26: =Notes!J54 -> 159.2542 | P26: =Notes!K54 -> 1064.6371 | Q26: =Q24 -> 579.33855 | R26: =R24 -> 525.22462 | S26: =S24 -> 515.57904 | T26: =T24 -> 852.25246 | U26: =U24 -> 330.00845 | V26: =V24 -> 268.38317 | W26: =W24 -> 217.11567 | X26: =X24 -> 242.88934 | ... Z26: =Z24 -> 276.73656
B27: Giảm trong kỳ | K27: =Notes!F55 -> 0 | L27: =Notes!G55 -> 0 | M27: =Notes!H55 -> -5.7900314 | N27: =Notes!I55 -> -9.1675696 | O27: =Notes!J55 -> -0.015172172 | P27: =Notes!K55 -> -8.4822776 | Q27: =Q25 -> 0 | R27: =R25 -> 0 | S27: =S25 -> 0 | T27: =T25 -> 0 | U27: =U25 -> 0 | V27: =V25 -> 0 | W27: =W25 -> 0 | X27: =X25 -> 0 | ... Z27: =Z25 -> 0
B28: Nguyên giá cuối kỳ | K28: =SUM(K23,K26,K27) -> 14202.688 | L28: =SUM(L23,L26,L27) -> 14272.461 | M28: =SUM(M23,M26,M27) -> 15104.051 | N28: =SUM(N23,N26,N27) -> 15270.938 | O28: =SUM(O23,O26,O27) -> 15430.177 | P28: =SUM(P23,P26,P27) -> 16486.332 | Q28: =SUM(Q23,Q26,Q27) -> 17065.67 | R28: =SUM(R23,R26,R27) -> 17590.895 | ... Z28: =SUM(Z23,Z26,Z27) -> 20579.364
L29: =L28/K28-1 -> 0.0049126754 | M29: =M28/L28-1 -> 0.058265342 | N29: =N28/M28-1 -> 0.011049169 | O29: =O28/N28-1 -> 0.010427587 | P29: =P28/O28-1 -> 0.068447357 | Q29: =Q28/P28-1 -> 0.035140537 | R29: =R28/Q28-1 -> 0.030776677 | S29: =S28/R28-1 -> 0.029309426 | ... Z29: =Z28/Y28-1 -> 0.013630579
B30: Trong đó đã khấu hao hết nhưng còn sử dụng
B31: Check nguyên giá cuối kỳ | K31: =IF(ISTEXT(Notes!F11),K28-'BS Raw'!F52/$B$1,"Chưa có BCTC") -> 0 | L31: =IF(ISTEXT(Notes!G11),L28-'BS Raw'!G52/$B$1,"Chưa có BCTC") -> 0 | M31: =IF(ISTEXT(Notes!H11),M28-'BS Raw'!H52/$B$1,"Chưa có BCTC") -> 0 | N31: =IF(ISTEXT(Notes!I11),N28-'BS Raw'!I52/$B$1,"Chưa có BCTC") -> 0 | O31: =IF(ISTEXT(Notes!J11),O28-'BS Raw'!J52/$B$1,"Chưa có BCTC") -> 0 | P31: =IF(ISTEXT(Notes!K11),P28-'BS Raw'!K52/$B$1,"Chưa có BCTC") -> 0 | Q31: =IF(ISTEXT(Notes!L11),Q28-'BS Raw'!L52/$B$1,"Chưa có BCTC") -> Chưa có BCTC | R31: =IF(ISTEXT(Notes!M11),R28-'BS Raw'!M52/$B$1,"Chưa có BCTC") -> Chưa có BCTC | ... Z31: =IF(ISTEXT(Notes!U11),Z28-'BS Raw'!U52/$B$1,"Chưa có BCTC") -> Chưa có BCTC
B33: Giá trị hao mòn lũy kế
B34: Số dư đầu kỳ | K34: =Notes!F57 -> 7755.1697 | L34: =Notes!G57 -> 9068.2 | M34: =Notes!H57 -> 10372.83 | N34: =Notes!I57 -> 11737.363 | O34: =Notes!J57 -> 13111.293 | P34: =Notes!K57 -> 14180.409 | Q34: =P39 -> 14915.135 | R34: =Q39 -> 15703.215 | S34: =R39 -> 16535.063 | T34: =S39 -> 16761.669 | U34: =T39 -> 16967.702 | V34: =U39 -> 17201.235 | W34: =V39 -> 17457.134 | X34: =W39 -> 17731.126 | ... Z34: =Y39 -> 18343.383
B35: Tăng trong kỳ (FC) | Q35: =Q242 -> 788.07959 | R35: =R242 -> 831.8483 | S35: =S242 -> 226.60556 | T35: =T242 -> 206.03289 | U35: =U242 -> 233.53359 | V35: =V242 -> 255.89886 | W35: =W242 -> 273.99183 | X35: =X242 -> 294.23261 | ... Z35: =Z242 -> 341.08599 | AB35: =AB242 -> 0 | AC35: =AC242 -> 0 | AD35: =AD242 -> 0 | AE35: =AE242 -> 0 | AF35: =AF242 -> 0 | AG35: =AG242 -> 0 | AH35: =AH242 -> 0
B36: Giảm trong kỳ (FC) | Q36: 0 | R36: 0 | S36: 0 | T36: 0 | U36: 0 | V36: 0 | W36: 0 | X36: 0 | Y36: 0 | Z36: 0
B37: Tăng trong kỳ | K37: =Notes!F58 -> 1313.0304 | L37: =Notes!G58 -> 1304.6297 | M37: =Notes!H58 -> 1364.5327 | N37: =Notes!I58 -> 1383.0979 | O37: =Notes!J58 -> 1069.1163 | P37: =Notes!K58 -> 739.80137 | Q37: =Q35 -> 788.07959 | R37: =R35 -> 831.8483 | S37: =S35 -> 226.60556 | T37: =T35 -> 206.03289 | U37: =U35 -> 233.53359 | V37: =V35 -> 255.89886 | W37: =W35 -> 273.99183 | X37: =X35 -> 294.23261 | ... Z37: =Z35 -> 341.08599
B38: Giảm trong kỳ | K38: =Notes!F59 -> 0 | L38: =Notes!G59 -> 0 | M38: =Notes!H59 -> 0 | N38: =Notes!I59 -> -9.1675696 | O38: =Notes!J59 -> 0 | P38: =Notes!K59 -> -5.075308 | Q38: =Q36 -> 0 | R38: =R36 -> 0 | S38: =S36 -> 0 | T38: =T36 -> 0 | U38: =U36 -> 0 | V38: =V36 -> 0 | W38: =W36 -> 0 | X38: =X36 -> 0 | ... Z38: =Z36 -> 0
B39: Giá trị hao mòn lũy kế cuối kỳ | K39: =SUM(K34,K37,K38) -> 9068.2 | L39: =SUM(L34,L37,L38) -> 10372.83 | M39: =SUM(M34,M37,M38) -> 11737.363 | N39: =SUM(N34,N37,N38) -> 13111.293 | O39: =SUM(O34,O37,O38) -> 14180.409 | P39: =SUM(P34,P37,P38) -> 14915.135 | Q39: =SUM(Q34,Q37,Q38) -> 15703.215 | R39: =SUM(R34,R37,R38) -> 16535.063 | ... Z39: =SUM(Z34,Z37,Z38) -> 18684.469
B40: GTCL đầu kỳ | K40: =K23-K34 -> 6297.6364 | L40: =L23-L34 -> 5134.4876 | M40: =M23-M34 -> 3899.631 | N40: =N23-N34 -> 3366.6881 | O40: =O23-O34 -> 2159.6449 | P40: =P23-P34 -> 1249.7677 | Q40: =Q23-Q34 -> 1571.1965 | R40: =R23-R34 -> 1362.4554 | ... Z40: =Z23-Z34 -> 1959.2439
B41: GTCL cuối kỳ | K41: =K28-K39 -> 5134.4876 | L41: =L28-L39 -> 3899.631 | M41: =M28-M39 -> 3366.6881 | N41: =N28-N39 -> 2159.6449 | O41: =O28-O39 -> 1249.7677 | P41: =P28-P39 -> 1571.1965 | Q41: =Q28-Q39 -> 1362.4554 | R41: =R28-R39 -> 1055.8317 | ... Z41: =Z28-Z39 -> 1894.8945
B42: Check GTCL cuối kỳ | K42: =IF(ISTEXT(Notes!F11),K41-'BS Raw'!F51/$B$1,"Chưa có BCTC") -> 0 | L42: =IF(ISTEXT(Notes!G11),L41-'BS Raw'!G51/$B$1,"Chưa có BCTC") -> 1.3642421e-12 | M42: =IF(ISTEXT(Notes!H11),M41-'BS Raw'!H51/$B$1,"Chưa có BCTC") -> 0 | N42: =IF(ISTEXT(Notes!I11),N41-'BS Raw'!I51/$B$1,"Chưa có BCTC") -> -4.5474735e-13 | O42: =IF(ISTEXT(Notes!J11),O41-'BS Raw'!J51/$B$1,"Chưa có BCTC") -> -6.8212103e-13 | P42: =IF(ISTEXT(Notes!K11),P41-'BS Raw'!K51/$B$1,"Chưa có BCTC") -> 2.7284841e-12 | Q42: =IF(ISTEXT(Notes!L11),Q41-'BS Raw'!L51/$B$1,"Chưa có BCTC") -> Chưa có BCTC | R42: =IF(ISTEXT(Notes!M11),R41-'BS Raw'!M51/$B$1,"Chưa có BCTC") -> Chưa có BCTC | ... Z42: =IF(ISTEXT(Notes!U11),Z41-'BS Raw'!U51/$B$1,"Chưa có BCTC") -> Chưa có BCTC
B43: ="- Giá trị còn lại của tài sản đầu tư thêm năm "&YEAR($P$3) -> - Giá trị còn lại của tài sản đầu tư thêm năm 2024 | P43: =P41 -> 1571.1965 | Q43: =P43-Q230 -> 831.39508 | R43: =Q43-R230 -> 91.593706 | S43: =R43-S230 -> 0 | T43: =S43-T230 -> 0 | U43: =T43-U230 -> 0 | V43: =U43-V230 -> 0 | W43: =V43-W230 -> 0 | X43: =W43-X230 -> 0 | ... Z43: =Y43-Z230 -> 0
B44: ="- Giá trị còn lại của tài sản đầu tư thêm năm "&YEAR($P$3)+1 -> - Giá trị còn lại của tài sản đầu tư thêm năm 2025 | Q44: =(Q26+Q27)-Q231 -> 531.06034 | R44: =+Q44-R231 -> 482.78212 | S44: =+R44-S231 -> 434.50391 | T44: =+S44-T231 -> 386.2257 | U44: =+T44-U231 -> 337.94749 | V44: =+U44-V231 -> 289.66927 | W44: =+V44-W231 -> 241.39106 | X44: =+W44-X231 -> 193.11285 | Y44: =+X44-Y231 -> 144.83464 | Z44: =+Y44-Z231 -> 96.556425
B45: ="- Giá trị còn lại của tài sản đầu tư thêm năm "&YEAR($P$3)+2 -> - Giá trị còn lại của tài sản đầu tư thêm năm 2026 | R45: =(R26+R27-R232) -> 481.4559 | S45: =+R45-S232 -> 437.68719 | T45: =+S45-T232 -> 393.91847 | U45: =+T45-U232 -> 350.14975 | V45: =+U45-V232 -> 306.38103 | W45: =+V45-W232 -> 262.61231 | X45: =+W45-X232 -> 218.84359 | Y45: =+X45-Y232 -> 175.07487 | Z45: =+Y45-Z232 -> 131.30616
B46: ="- Giá trị còn lại của tài sản đầu tư thêm năm "&YEAR($P$3)+3 -> - Giá trị còn lại của tài sản đầu tư thêm năm 2027 | S46: =S26+S27-S233 -> 472.61412 | T46: =+S46-T233 -> 429.6492 | U46: =+T46-U233 -> 386.68428 | V46: =+U46-V233 -> 343.71936 | W46: =+V46-W233 -> 300.75444 | X46: =+W46-X233 -> 257.78952 | Y46: =+X46-Y233 -> 214.8246 | Z46: =+Y46-Z233 -> 171.85968
B47: ="- Giá trị còn lại của tài sản đầu tư thêm năm "&YEAR($P$3)+4 -> - Giá trị còn lại của tài sản đầu tư thêm năm 2028 | T47: =T26+T27-T234 -> 781.23142 | U47: =T47-U234 -> 710.21038 | V47: =U47-V234 -> 639.18934 | W47: =V47-W234 -> 568.1683 | X47: =W47-X234 -> 497.14727 | Y47: =X47-Y234 -> 426.12623 | Z47: =Y47-Z234 -> 355.10519
B48: ="- Giá trị còn lại của tài sản đầu tư thêm năm "&YEAR($P$3)+5 -> - Giá trị còn lại của tài sản đầu tư thêm năm 2029 | U48: =U26+U27-U235 -> 302.50775 | V48: =U48-V235 -> 275.00704 | W48: =V48-W235 -> 247.50634 | X48: =W48-X235 -> 220.00563 | Y48: =X48-Y235 -> 192.50493 | Z48: =Y48-Z235 -> 165.00423
B49: ="- Giá trị còn lại của tài sản đầu tư thêm năm "&YEAR($P$3)+6 -> - Giá trị còn lại của tài sản đầu tư thêm năm 2030 | V49: =V26+V27-V236 -> 246.0179 | W49: =V49-W236 -> 223.65264 | X49: =W49-X236 -> 201.28738 | Y49: =X49-Y236 -> 178.92211 | Z49: =Y49-Z236 -> 156.55685 | AB49: =AA49-AB236 -> 0 | AC49: =AB49-AC236 -> 0 | AD49: =AC49-AD236 -> 0 | AE49: =AD49-AE236 -> 0 | AF49: =AE49-AF236 -> 0 | AG49: =AF49-AG236 -> 0 | AH49: =AG49-AH236 -> 0
B50: ="- Giá trị còn lại của tài sản đầu tư thêm năm "&YEAR($P$3)+7 -> - Giá trị còn lại của tài sản đầu tư thêm năm 2031 | W50: =W26+W27-W237 -> 199.0227 | X50: =W50-X237 -> 180.92973 | Y50: =X50-Y237 -> 162.83676 | Z50: =Y50-Z237 -> 144.74378
B51: ="- Giá trị còn lại của tài sản đầu tư thêm năm "&YEAR($P$3)+8 -> - Giá trị còn lại của tài sản đầu tư thêm năm 2032 | X51: =X26+X27-X238 -> 222.64856 | Y51: =X51-Y238 -> 202.40778 | Z51: =Y51-Z238 -> 182.16701
B52: ="- Giá trị còn lại của tài sản đầu tư thêm năm "&YEAR($P$3)+9 -> - Giá trị còn lại của tài sản đầu tư thêm năm 2033 | Y52: =Y26+Y27-Y239 -> 261.71201 | Z52: =Y52-Z239 -> 237.92001
B53: ="- Giá trị còn lại của tài sản đầu tư thêm năm "&YEAR($P$3)+10 -> - Giá trị còn lại của tài sản đầu tư thêm năm 2034 | Z53: =Z26+Z27-Z240 -> 253.67518
B54: ="- Giá trị còn lại của tài sản đầu tư thêm năm "&YEAR($P$3)+11 -> - Giá trị còn lại của tài sản đầu tư thêm năm 2035
B56: 2. TÀI SẢN THUÊ TÀI CHÍNH
B57: Nguyên giá
B58: Số dư đầu kỳ | K58: =Notes!F61 -> 0 | L58: =Notes!G61 -> 0 | M58: =Notes!H61 -> 0 | N58: =Notes!I61 -> 0 | O58: =Notes!J61 -> 0 | P58: =Notes!K61 -> 0 | Q58: =P63 -> 11.983426 | R58: =Q63 -> 12.962589 | S58: =R63 -> 13.850292 | T58: =S63 -> 14.721693 | U58: =T63 -> 16.162119 | V58: =U63 -> 16.71988 | W58: =V63 -> 17.173485 | X58: =W63 -> 17.540441 | ... Z58: =Y63 -> 18.4335
B59: Tăng trong kỳ (FC) | Q59: =Q9*Q14 -> 0.97916336 | R59: =R9*R14 -> 0.88770324 | S59: =S9*S14 -> 0.87140085 | T59: =T9*T14 -> 1.4404261 | U59: =U9*U14 -> 0.55776055 | V59: =V9*V14 -> 0.45360518 | W59: =W9*W14 -> 0.36695593 | X59: =X9*X14 -> 0.41051704 | ... Z59: =Z9*Z14 -> 0.46772359
B60: Giảm trong kỳ (FC) | Q60: 0 | R60: 0 | S60: 0 | T60: 0 | U60: 0 | V60: 0 | W60: 0 | X60: 0 | Y60: 0 | Z60: 0
B61: Tăng trong kỳ | K61: =Notes!F62 -> 0 | L61: =Notes!G62 -> 0 | M61: =Notes!H62 -> 0 | N61: =Notes!I62 -> 0 | O61: =Notes!J62 -> 0 | P61: =Notes!K62 -> 11.983426 | Q61: =Q59 -> 0.97916336 | R61: =R59 -> 0.88770324 | S61: =S59 -> 0.87140085 | T61: =T59 -> 1.4404261 | U61: =U59 -> 0.55776055 | V61: =V59 -> 0.45360518 | W61: =W59 -> 0.36695593 | X61: =X59 -> 0.41051704 | ... Z61: =Z59 -> 0.46772359
B62: Giảm trong kỳ | K62: =Notes!F63 -> 0 | L62: =Notes!G63 -> 0 | M62: =Notes!H63 -> 0 | N62: =Notes!I63 -> 0 | O62: =Notes!J63 -> 0 | P62: =Notes!K63 -> 0 | Q62: =Q60 -> 0 | R62: =R60 -> 0 | S62: =S60 -> 0 | T62: =T60 -> 0 | U62: =U60 -> 0 | V62: =V60 -> 0 | W62: =W60 -> 0 | X62: =X60 -> 0 | ... Z62: =Z60 -> 0
B63: Nguyên giá cuối kỳ | K63: =SUM(K58,K61,K62) -> 0 | L63: =SUM(L58,L61,L62) -> 0 | M63: =SUM(M58,M61,M62) -> 0 | N63: =SUM(N58,N61,N62) -> 0 | O63: =SUM(O58,O61,O62) -> 0 | P63: =SUM(P58,P61,P62) -> 11.983426 | Q63: =SUM(Q58,Q61,Q62) -> 12.962589 | R63: =SUM(R58,R61,R62) -> 13.850292 | ... Z63: =SUM(Z58,Z61,Z62) -> 18.901223
B64: Trong đó đã khấu hao hết nhưng còn sử dụng
B65: Check nguyên giá cuối kỳ | K65: =IF(ISTEXT(Notes!F11),K63-'BS Raw'!F55/$B$1,"Chưa có BCTC") -> 0 | L65: =IF(ISTEXT(Notes!G11),L63-'BS Raw'!G55/$B$1,"Chưa có BCTC") -> 0 | M65: =IF(ISTEXT(Notes!H11),M63-'BS Raw'!H55/$B$1,"Chưa có BCTC") -> 0 | N65: =IF(ISTEXT(Notes!I11),N63-'BS Raw'!I55/$B$1,"Chưa có BCTC") -> 0 | O65: =IF(ISTEXT(Notes!J11),O63-'BS Raw'!J55/$B$1,"Chưa có BCTC") -> 0 | P65: =IF(ISTEXT(Notes!K11),P63-'BS Raw'!K55/$B$1,"Chưa có BCTC") -> 0 | Q65: =IF(ISTEXT(Notes!L11),Q63-'BS Raw'!L55/$B$1,"Chưa có BCTC") -> Chưa có BCTC | R65: =IF(ISTEXT(Notes!M11),R63-'BS Raw'!M55/$B$1,"Chưa có BCTC") -> Chưa có BCTC | ... Z65: =IF(ISTEXT(Notes!U11),Z63-'BS Raw'!U55/$B$1,"Chưa có BCTC") -> Chưa có BCTC
B67: Giá trị hao mòn lũy kế
B68: Số dư đầu kỳ | K68: =Notes!F65 -> 0 | L68: =Notes!G65 -> 0 | M68: =Notes!H65 -> 0 | N68: =Notes!I65 -> 0 | O68: =Notes!J65 -> 0 | P68: =Notes!K65 -> 0 | Q68: =P73 -> 0.77113698 | R68: =Q73 -> 1.7054679 | S68: =R73 -> 2.7877493 | T68: =S73 -> 4.0152642 | U68: =T73 -> 5.4828501 | V68: =U73 -> 7.0433961 | W68: =V73 -> 8.6795429 | X68: =W73 -> 10.213655 | ... Z68: =Y73 -> 13.058008
B69: Tăng trong kỳ (FC) | Q69: =Q257 -> 0.93433087 | R69: =R257 -> 1.0822814 | S69: =S257 -> 1.2275149 | T69: =T257 -> 1.4675859 | U69: =U257 -> 1.560546 | V69: =V257 -> 1.6361469 | W69: =W257 -> 1.5341123 | X69: =X257 -> 1.4545813 | ... Z69: =Z257 -> 1.2276543
B70: Giảm trong kỳ (FC) | Q70: 0 | R70: 0 | S70: 0 | T70: 0 | U70: 0 | V70: 0 | W70: 0 | X70: 0 | Y70: 0 | Z70: 0
B71: Tăng trong kỳ | K71: =Notes!F66 -> 0 | L71: =Notes!G66 -> 0 | M71: =Notes!H66 -> 0 | N71: =Notes!I66 -> 0 | O71: =Notes!J66 -> 0 | P71: =Notes!K66 -> 0.77113698 | Q71: =Q69 -> 0.93433087 | R71: =R69 -> 1.0822814 | S71: =S69 -> 1.2275149 | T71: =T69 -> 1.4675859 | U71: =U69 -> 1.560546 | V71: =V69 -> 1.6361469 | W71: =W69 -> 1.5341123 | X71: =X69 -> 1.4545813 | ... Z71: =Z69 -> 1.2276543
B72: Giảm trong kỳ | K72: =Notes!F67 -> 0 | L72: =Notes!G67 -> 0 | M72: =Notes!H67 -> 0 | N72: =Notes!I67 -> 0 | O72: =Notes!J67 -> 0 | P72: =Notes!K67 -> 0 | Q72: =Q70 -> 0 | R72: =R70 -> 0 | S72: =S70 -> 0 | T72: =T70 -> 0 | U72: =U70 -> 0 | V72: =V70 -> 0 | W72: =W70 -> 0 | X72: =X70 -> 0 | ... Z72: =Z70 -> 0
B73: Giá trị hao mòn lũy kế cuối kỳ | K73: =SUM(K68,K71,K72) -> 0 | L73: =SUM(L68,L71,L72) -> 0 | M73: =SUM(M68,M71,M72) -> 0 | N73: =SUM(N68,N71,N72) -> 0 | O73: =SUM(O68,O71,O72) -> 0 | P73: =SUM(P68,P71,P72) -> 0.77113698 | Q73: =SUM(Q68,Q71,Q72) -> 1.7054679 | R73: =SUM(R68,R71,R72) -> 2.7877493 | ... Z73: =SUM(Z68,Z71,Z72) -> 14.285662
B74: GTCL đầu kỳ | K74: =K58-K68 -> 0 | L74: =L58-L68 -> 0 | M74: =M58-M68 -> 0 | N74: =N58-N68 -> 0 | O74: =O58-O68 -> 0 | P74: =P58-P68 -> 0 | Q74: =Q58-Q68 -> 11.212289 | R74: =R58-R68 -> 11.257121 | ... Z74: =Z58-Z68 -> 5.375492
B75: GTCL cuối kỳ | K75: =K63-K73 -> 0 | L75: =L63-L73 -> 0 | M75: =M63-M73 -> 0 | N75: =N63-N73 -> 0 | O75: =O63-O73 -> 0 | P75: =P63-P73 -> 11.212289 | Q75: =Q63-Q73 -> 11.257121 | R75: =R63-R73 -> 11.062543 | ... Z75: =Z63-Z73 -> 4.6155612
B76: Check GTCL cuối kỳ | K76: =IF(ISTEXT(Notes!F11),K75-'BS Raw'!F54/$B$1,"Chưa có BCTC") -> 0 | L76: =IF(ISTEXT(Notes!G11),L75-'BS Raw'!G54/$B$1,"Chưa có BCTC") -> 0 | M76: =IF(ISTEXT(Notes!H11),M75-'BS Raw'!H54/$B$1,"Chưa có BCTC") -> 0 | N76: =IF(ISTEXT(Notes!I11),N75-'BS Raw'!I54/$B$1,"Chưa có BCTC") -> 0 | O76: =IF(ISTEXT(Notes!J11),O75-'BS Raw'!J54/$B$1,"Chưa có BCTC") -> 0 | P76: =IF(ISTEXT(Notes!K11),P75-'BS Raw'!K54/$B$1,"Chưa có BCTC") -> 1.7763568e-15 | Q76: =IF(ISTEXT(Notes!L11),Q75-'BS Raw'!L54/$B$1,"Chưa có BCTC") -> Chưa có BCTC | R76: =IF(ISTEXT(Notes!M11),R75-'BS Raw'!M54/$B$1,"Chưa có BCTC") -> Chưa có BCTC | ... Z76: =IF(ISTEXT(Notes!U11),Z75-'BS Raw'!U54/$B$1,"Chưa có BCTC") -> Chưa có BCTC
B77: ="- Giá trị còn lại của tài sản đầu tư thêm năm "&YEAR($P$3) -> - Giá trị còn lại của tài sản đầu tư thêm năm 2024 | P77: =P75 -> 11.212289 | Q77: =P77-Q245 -> 10.441152 | R77: =Q77-R245 -> 9.6700149 | S77: =R77-S245 -> 8.8988779 | T77: =S77-T245 -> 8.1277409 | U77: =T77-U245 -> 7.3566039 | V77: =U77-V245 -> 6.5854669 | W77: =V77-W245 -> 5.8143299 | X77: =W77-X245 -> 5.043193 | ... Z77: =Y77-Z245 -> 3.500919
B78: ="- Giá trị còn lại của tài sản đầu tư thêm năm "&YEAR($P$3)+1 -> - Giá trị còn lại của tài sản đầu tư thêm năm 2025 | Q78: =Q61+Q62-Q246 -> 0.81596947 | R78: =Q78-R246 -> 0.65277558 | S78: =R78-S246 -> 0.48958168 | T78: =S78-T246 -> 0.32638779 | U78: =T78-U246 -> 0.16319389 | V78: =U78-V246 -> 0 | W78: =V78-W246 -> 0 | X78: =W78-X246 -> 0 | Y78: =X78-Y246 -> 0 | Z78: =Y78-Z246 -> 0
B79: ="- Giá trị còn lại của tài sản đầu tư thêm năm "&YEAR($P$3)+2 -> - Giá trị còn lại của tài sản đầu tư thêm năm 2026 | R79: =R61+R62-R247 -> 0.7397527 | S79: =R79-S247 -> 0.59180216 | T79: =S79-T247 -> 0.44385162 | U79: =T79-U247 -> 0.29590108 | V79: =U79-V247 -> 0.14795054 | W79: =V79-W247 -> 0 | X79: =W79-X247 -> 0 | Y79: =X79-Y247 -> 0 | Z79: =Y79-Z247 -> 0
B80: ="- Giá trị còn lại của tài sản đầu tư thêm năm "&YEAR($P$3)+3 -> - Giá trị còn lại của tài sản đầu tư thêm năm 2027 | S80: =S61+S62-S248 -> 0.72616738 | T80: =S80-T248 -> 0.5809339 | U80: =T80-U248 -> 0.43570043 | V80: =U80-V248 -> 0.29046695 | W80: =V80-W248 -> 0.14523348 | X80: =W80-X248 -> 0 | Y80: =X80-Y248 -> 0 | Z80: =Y80-Z248 -> 0
B81: ="- Giá trị còn lại của tài sản đầu tư thêm năm "&YEAR($P$3)+4 -> - Giá trị còn lại của tài sản đầu tư thêm năm 2028 | T81: =T61+T62-T249 -> 1.2003551 | U81: =T81-U249 -> 0.96028409 | V81: =U81-V249 -> 0.72021306 | W81: =V81-W249 -> 0.48014204 | X81: =W81-X249 -> 0.24007102 | Y81: =X81-Y249 -> 0 | Z81: =Y81-Z249 -> 0
B82: ="- Giá trị còn lại của tài sản đầu tư thêm năm "&YEAR($P$3)+5 -> - Giá trị còn lại của tài sản đầu tư thêm năm 2029 | U82: =U61+U62-U250 -> 0.46480046 | V82: =U82-V250 -> 0.37184036 | W82: =V82-W250 -> 0.27888027 | X82: =W82-X250 -> 0.18592018 | Y82: =X82-Y250 -> 0.092960091 | Z82: =Y82-Z250 -> 0
B83: ="- Giá trị còn lại của tài sản đầu tư thêm năm "&YEAR($P$3)+6 -> - Giá trị còn lại của tài sản đầu tư thêm năm 2030 | V83: =V61+V62-V251 -> 0.37800431 | W83: =V83-W251 -> 0.30240345 | X83: =W83-X251 -> 0.22680259 | Y83: =X83-Y251 -> 0.15120173 | Z83: =Y83-Z251 -> 0.075600863
B84: ="- Giá trị còn lại của tài sản đầu tư thêm năm "&YEAR($P$3)+7 -> - Giá trị còn lại của tài sản đầu tư thêm năm 2031 | W84: =W61+W62-W252 -> 0.30579661 | X84: =W84-X252 -> 0.24463728 | Y84: =X84-Y252 -> 0.18347796 | Z84: =Y84-Z252 -> 0.12231864
B85: ="- Giá trị còn lại của tài sản đầu tư thêm năm "&YEAR($P$3)+8 -> - Giá trị còn lại của tài sản đầu tư thêm năm 2032 | X85: =X61+X62-X253 -> 0.34209753 | Y85: =X85-Y253 -> 0.27367802 | Z85: =Y85-Z253 -> 0.20525852
B86: ="- Giá trị còn lại của tài sản đầu tư thêm năm "&YEAR($P$3)+9 -> - Giá trị còn lại của tài sản đầu tư thêm năm 2033 | Y86: =Y61+Y62-Y254 -> 0.40211817 | Z86: =Y86-Z254 -> 0.32169454
B87: ="- Giá trị còn lại của tài sản đầu tư thêm năm "&YEAR($P$3)+10 -> - Giá trị còn lại của tài sản đầu tư thêm năm 2034 | Z87: =Z61+Z62-Z255 -> 0.38976965
B88: ="- Giá trị còn lại của tài sản đầu tư thêm năm "&YEAR($P$3)+11 -> - Giá trị còn lại của tài sản đầu tư thêm năm 2035
B89: 3. TÀI SẢN CỐ ĐỊNH VÔ HÌNH
B90: Nguyên giá
B91: Số dư đầu kỳ | K91: =Notes!F69 -> 105.8896 | L91: =Notes!G69 -> 129.45566 | M91: =Notes!H69 -> 146.71126 | N91: =Notes!I69 -> 153.10096 | O91: =Notes!J69 -> 178.46572 | P91: =Notes!K69 -> 500.31777 | Q91: =P96 -> 537.97018 | R91: =Q96 -> 696.69307 | S91: =R96 -> 840.59023 | T91: =S96 -> 981.84476 | U91: =T96 -> 1215.3386 | V91: =U96 -> 1305.7519 | W91: =V96 -> 1379.2815 | X91: =W96 -> 1438.7652 | ... Z91: =Y96 -> 1583.5305 | BC91: Capex vô hình 2025-2035
B92: Tăng trong kỳ (FC) | Q92: =Q9*Q15 -> 158.72289 | R92: =R9*R15 -> 143.89716 | S92: =S9*S15 -> 141.25453 | T92: =T9*T15 -> 233.49382 | U92: =U9*U15 -> 90.413274 | V92: =V9*V15 -> 73.529635 | W92: =W9*W15 -> 59.483746 | X92: =X9*X15 -> 66.545025 | ... Z92: =Z9*Z15 -> 75.818236 | BC92: =SUM(Q92:Z92) -> 1121.3786
B93: Giảm trong kỳ (FC) | Q93: 0 | R93: 0 | S93: 0 | T93: 0 | U93: 0 | V93: 0 | W93: 0 | X93: 0 | Y93: 0 | Z93: 0
B94: Tăng trong kỳ | K94: =Notes!F70 -> 23.56606 | L94: =Notes!G70 -> 17.255598 | M94: =Notes!H70 -> 6.3897012 | N94: =Notes!I70 -> 25.364754 | O94: =Notes!J70 -> 321.85205 | P94: =Notes!K70 -> 37.652412 | Q94: =Q92 -> 158.72289 | R94: =R92 -> 143.89716 | S94: =S92 -> 141.25453 | T94: =T92 -> 233.49382 | U94: =U92 -> 90.413274 | V94: =V92 -> 73.529635 | W94: =W92 -> 59.483746 | X94: =X92 -> 66.545025 | ... Z94: =Z92 -> 75.818236
B95: Giảm trong kỳ | K95: =Notes!F71 -> 0 | L95: =Notes!G71 -> 0 | M95: =Notes!H71 -> 0 | N95: =Notes!I71 -> 0 | O95: =Notes!J71 -> 0 | P95: =Notes!K71 -> 0 | Q95: =Q93 -> 0 | R95: =R93 -> 0 | S95: =S93 -> 0 | T95: =T93 -> 0 | U95: =U93 -> 0 | V95: =V93 -> 0 | W95: =W93 -> 0 | X95: =X93 -> 0 | ... Z95: =Z93 -> 0
B96: Nguyên giá cuối kỳ | K96: =SUM(K91,K94,K95) -> 129.45566 | L96: =SUM(L91,L94,L95) -> 146.71126 | M96: =SUM(M91,M94,M95) -> 153.10096 | N96: =SUM(N91,N94,N95) -> 178.46572 | O96: =SUM(O91,O94,O95) -> 500.31777 | P96: =SUM(P91,P94,P95) -> 537.97018 | Q96: =SUM(Q91,Q94,Q95) -> 696.69307 | R96: =SUM(R91,R94,R95) -> 840.59023 | ... Z96: =SUM(Z91,Z94,Z95) -> 1659.3488
B97: Trong đó đã khấu hao hết nhưng còn sử dụng & Quyền SD đất không KH
B98: Check nguyên giá cuối kỳ | K98: =IF(ISTEXT(Notes!F11),K96-'BS Raw'!F58/$B$1,"Chưa có BCTC") -> 0 | L98: =IF(ISTEXT(Notes!G11),L96-'BS Raw'!G58/$B$1,"Chưa có BCTC") -> 0 | M98: =IF(ISTEXT(Notes!H11),M96-'BS Raw'!H58/$B$1,"Chưa có BCTC") -> 0 | N98: =IF(ISTEXT(Notes!I11),N96-'BS Raw'!I58/$B$1,"Chưa có BCTC") -> 0 | O98: =IF(ISTEXT(Notes!J11),O96-'BS Raw'!J58/$B$1,"Chưa có BCTC") -> 0 | P98: =IF(ISTEXT(Notes!K11),P96-'BS Raw'!K58/$B$1,"Chưa có BCTC") -> -1.1368684e-13 | Q98: =IF(ISTEXT(Notes!L11),Q96-'BS Raw'!L58/$B$1,"Chưa có BCTC") -> Chưa có BCTC | R98: =IF(ISTEXT(Notes!M11),R96-'BS Raw'!M58/$B$1,"Chưa có BCTC") -> Chưa có BCTC | ... Z98: =IF(ISTEXT(Notes!U11),Z96-'BS Raw'!U58/$B$1,"Chưa có BCTC") -> Chưa có BCTC
B100: Giá trị hao mòn lũy kế
B101: Số dư đầu kỳ | K101: =Notes!F73 -> 67.110599 | L101: =Notes!G73 -> 76.306987 | M101: =Notes!H73 -> 90.91369 | N101: =Notes!I73 -> 114.16576 | O101: =Notes!J73 -> 131.25809 | P101: =Notes!K73 -> 149.91003 | Q101: =P106 -> 174.18446 | R101: =Q106 -> 251.36652 | S101: =R106 -> 376.51429 | T101: =S106 -> 548.74691 | U101: =T106 -> 745.90318 | V101: =U106 -> 902.62817 | W101: =V106 -> 1036.7782 | X101: =W106 -> 1112.9248 | ... Z101: =Y106 -> 1311.1451
B102: Tăng trong kỳ (FC) | Q102: =Q273 -> 77.182059 | R102: =R273 -> 125.14778 | S102: =S273 -> 172.23262 | T102: =T273 -> 197.15627 | U102: =U273 -> 156.72499 | V102: =V273 -> 134.15002 | W102: =W273 -> 76.146662 | X102: =X273 -> 98.328337 | ... Z102: =Z273 -> 105.33671
B103: Giảm trong kỳ (FC) | Q103: 0 | R103: 0 | S103: 0 | T103: 0 | U103: 0 | V103: 0 | W103: 0 | X103: 0 | Y103: 0 | Z103: 0
B104: Tăng trong kỳ | K104: =Notes!F74 -> 9.1963881 | L104: =Notes!G74 -> 14.606703 | M104: =Notes!H74 -> 23.25207 | N104: =Notes!I74 -> 17.092327 | O104: =Notes!J74 -> 18.651942 | P104: =Notes!K74 -> 24.274429 | Q104: =Q102 -> 77.182059 | R104: =R102 -> 125.14778 | S104: =S102 -> 172.23262 | T104: =T102 -> 197.15627 | U104: =U102 -> 156.72499 | V104: =V102 -> 134.15002 | W104: =W102 -> 76.146662 | X104: =X102 -> 98.328337 | ... Z104: =Z102 -> 105.33671
B105: Giảm trong kỳ | K105: =Notes!F75 -> 0 | L105: =Notes!G75 -> 0 | M105: =Notes!H75 -> 0 | N105: =Notes!I75 -> 0 | O105: =Notes!J75 -> 0 | P105: =Notes!K75 -> 0 | Q105: =Q103 -> 0 | R105: =R103 -> 0 | S105: =S103 -> 0 | T105: =T103 -> 0 | U105: =U103 -> 0 | V105: =V103 -> 0 | W105: =W103 -> 0 | X105: =X103 -> 0 | ... Z105: =Z103 -> 0
...

Sheet Input
B1: =1 -> 1 | N1: 1 | O1: 2 | P1: 3 | Q1: 1 | R1: 2 | S1: 3 | T1: 4 | U1: 5 | V1: 6 | W1: 7 | X1: 8 | Y1: 9 | Z1: 10 | AA1: 14 | AB1: 15 | AC1: 16 | AD1: 17 | AE1: 18 | AF1: 19 | AG1: 20 | AH1: 21 | AI1: 22 | AJ1: 23 | AK1: 24 | AL1: 25 | AM1: 26 | AN1: 27 | AO1: 28 | AP1: 29 | AQ1: 30 | AR1: 31 | AS1: 32 | AT1: 33 | AU1: 34 | AV1: 35 | AW1: 36 | AX1: 37 | AY1: 38 | AZ1: 39 | BA1: 40
E2: =IF(TODAY()<E3,"Proj","") | F2: =IF(TODAY()<F3,"Proj","") | G2: =IF(TODAY()<G3,"Proj","") | K2: =IF(TODAY()<K3,"Proj","") | L2: =IF(TODAY()<L3,"Proj","") | M2: =IF(TODAY()<M3,"Proj","") | N2: =IF(TODAY()<N3,"Proj","") | O2: =IF(TODAY()<O3,"Proj","") | P2: =IF(TODAY()<P3,"Proj","") | Q2: =IF(TODAY()<Q3,"Proj","") -> Proj | R2: =IF(TODAY()<R3,"Proj","") -> Proj | ... BA2: =IF(TODAY()<BA3,"Proj","") -> Proj
B3: INCOME STATEMENT | D3: 41274 | E3: =DATE(YEAR(D3),MONTH(D3)+13,0) -> 41639 | F3: =DATE(YEAR(E3),MONTH(E3)+13,0) -> 42004 | G3: =DATE(YEAR(F3),MONTH(F3)+13,0) -> 42369 | H3: =DATE(YEAR(G3),MONTH(G3)+13,0) -> 42735 | I3: =DATE(YEAR(H3),MONTH(H3)+13,0) -> 43100 | J3: =DATE(YEAR(I3),MONTH(I3)+13,0) -> 43465 | K3: =DATE(YEAR(J3),MONTH(J3)+13,0) -> 43830 | L3: =DATE(YEAR(K3),MONTH(K3)+13,0) -> 44196 | ... BA3: =DATE(YEAR(AZ3),MONTH(AZ3)+13,0) -> 59171 | BC3: Note
P4: LNST | Q4: =Q94 -> 2210.902 | R4: =R94 -> 2502.7952 | S4: =S94 -> 2929.8525 | T4: =T94 -> 4577.6438 | U4: =U94 -> 3913.8244 | V4: =V94 -> 3417.0537 | W4: =W94 -> 3420.2135 | X4: =X94 -> 3799.2048 | ... Z4: =Z94 -> 4342.1332
A5: 1 | B5: Revenue (FC) | K5: ='Consol. Rev.'!K8 -> 7042.9669 | L5: ='Consol. Rev.'!L8 -> 7561.2751 | M5: ='Consol. Rev.'!M8 -> 9869.7629 | N5: ='Consol. Rev.'!N8 -> 15924.527 | O5: ='Consol. Rev.'!O8 -> 12570.542 | P5: ='Consol. Rev.'!P8-'Doanh thu KVF'!P9 -> 13455.585 | Q5: ='Consol. Rev.'!Q8 -> 17736.964 | R5: ='Consol. Rev.'!R8 -> 18589.768 | S5: ='Consol. Rev.'!S8 -> 19115.743 | T5: ='Consol. Rev.'!T8 -> 22528.627 | U5: ='Consol. Rev.'!U8 -> 21832.704 | V5: ='Consol. Rev.'!V8 -> 20430.772 | W5: ='Consol. Rev.'!W8 -> 20957.486 | X5: ='Consol. Rev.'!X8 -> 21416.211 | ... Z5: ='Consol. Rev.'!Z8 -> 22829.84
B6: Growth % | L6: =L5/K5-1 -> 0.073592305 | M6: =M5/L5-1 -> 0.30530404 | N6: =N5/M5-1 -> 0.613466 | O6: =O5/N5-1 -> -0.21061755 | P6: =P5/O5-1 -> 0.070406117 | Q6: =Q5/P5-1 -> 0.31818603 | R6: =R5/Q5-1 -> 0.048080581 | S6: =S5/R5-1 -> 0.028293767 | ... Z6: =Z5/Y5-1 -> 0.013457614
B7: Revenue | K7: ='Consol. Rev.'!K14 -> 7042.9669 | L7: ='Consol. Rev.'!L14 -> 7561.2751 | M7: ='Consol. Rev.'!M14 -> 9869.7629 | N7: ='Consol. Rev.'!N14 -> 15924.527 | O7: ='Consol. Rev.'!O14 -> 12570.542 | P7: ='Consol. Rev.'!P14-'Doanh thu KVF'!P9 -> 13455.585 | Q7: ='Consol. Rev.'!Q14 -> 17736.964 | R7: ='Consol. Rev.'!R14 -> 18589.768 | S7: ='Consol. Rev.'!S14 -> 19115.743 | T7: ='Consol. Rev.'!T14 -> 22528.627 | U7: ='Consol. Rev.'!U14 -> 21832.704 | V7: ='Consol. Rev.'!V14 -> 20430.772 | W7: ='Consol. Rev.'!W14 -> 20957.486 | X7: ='Consol. Rev.'!X14 -> 21416.211 | ... Z7: ='Consol. Rev.'!Z14 -> 22829.84
A9: 2 | B9: COGS (FC) | K9: ='Consol. Rev.'!K29 -> 6083.7747 | L9: ='Consol. Rev.'!L29 -> 6244.4273 | M9: ='Consol. Rev.'!M29 -> 7088.826 | N9: ='Consol. Rev.'!N29 -> 10221.097 | O9: ='Consol. Rev.'!O29 -> 10538.742 | P9: ='Consol. Rev.'!P29-'Doanh thu KVF'!P39 -> 10942.101 | Q9: ='Consol. Rev.'!Q29 -> 13918.244 | R9: ='Consol. Rev.'!R29 -> 14383.611 | S9: ='Consol. Rev.'!S29 -> 14457.706 | T9: ='Consol. Rev.'!T29 -> 15696.226 | U9: ='Consol. Rev.'!U29 -> 15887.412 | V9: ='Consol. Rev.'!V29 -> 15334.882 | W9: ='Consol. Rev.'!W29 -> 15944.619 | X9: ='Consol. Rev.'!X29 -> 16006.513 | ... Z9: ='Consol. Rev.'!Z29 -> 16800.955 | BB9: COGS mang trọng số cao ảnh hưởng đến các chỉ số lợi nhuận còn lại của DCM
B10: As % revenue | K10: =K9/K5 -> 0.8638085 | L10: =L9/L5 -> 0.82584316 | M10: =M9/M5 -> 0.7182367 | N10: =N9/N5 -> 0.64184622 | O10: =O9/O5 -> 0.83836817 | P10: =P9/P5 -> 0.81320142 | Q10: =Q9/Q5 -> 0.78470269 | R10: =R9/R5 -> 0.77373807 | ... Z10: =Z9/Z5 -> 0.73592083
B11: COGS | K11: ='Consol. Rev.'!K35 -> 6083.7747 | L11: ='Consol. Rev.'!L35 -> 6244.4273 | M11: ='Consol. Rev.'!M35 -> 7088.826 | N11: ='Consol. Rev.'!N35 -> 10221.097 | O11: ='Consol. Rev.'!O35 -> 10538.742 | P11: ='Consol. Rev.'!P35-'Doanh thu KVF'!P39 -> 10942.101 | Q11: ='Consol. Rev.'!Q35 -> 13918.244 | R11: ='Consol. Rev.'!R35 -> 14383.611 | S11: ='Consol. Rev.'!S35 -> 14457.706 | T11: ='Consol. Rev.'!T35 -> 15696.226 | U11: ='Consol. Rev.'!U35 -> 15887.412 | V11: ='Consol. Rev.'!V35 -> 15334.882 | W11: ='Consol. Rev.'!W35 -> 15944.619 | X11: ='Consol. Rev.'!X35 -> 16006.513 | ... Z11: ='Consol. Rev.'!Z35 -> 16800.955
B13: Gross profit (FC) | K13: =K5-K9 -> 959.1922 | L13: =L5-L9 -> 1316.8478 | M13: =M5-M9 -> 2780.9369 | N13: =N5-N9 -> 5703.4294 | O13: =O5-O9 -> 2031.7997 | P13: =P5-P9 -> 2513.4843 | Q13: =Q5-Q9 -> 3818.7208 | R13: =R5-R9 -> 4206.1569 | ... Z13: =Z5-Z9 -> 6028.8851
B14: Gross margin | K14: =K13/K5 -> 0.1361915 | L14: =L13/L5 -> 0.17415684 | M14: =M13/M5 -> 0.2817633 | N14: =N13/N5 -> 0.35815378 | O14: =O13/O5 -> 0.16163183 | P14: =P13/P5 -> 0.18679858 | Q14: =Q13/Q5 -> 0.21529731 | R14: =R13/R5 -> 0.22626193 | ... Z14: =Z13/Z5 -> 0.26407917
B15: Gross profit | K15: =K7-K11 -> 959.1922 | L15: =L7-L11 -> 1316.8478 | M15: =M7-M11 -> 2780.9369 | N15: =N7-N11 -> 5703.4294 | O15: =O7-O11 -> 2031.7997 | P15: =P7-P11 -> 2513.4843 | Q15: =Q7-Q11 -> 3818.7208 | R15: =R7-R11 -> 4206.1569 | ... Z15: =Z7-Z11 -> 6028.8851
B17: SG&A (FC) | K17: =K21+K25 -> 565.3779 | L17: =L21+L25 -> 673.40698 | M17: =M21+M25 -> 948.89299 | N17: =N21+N25 -> 1350.8891 | O17: =O21+O25 -> 1349.1883 | P17: =P21+P25 -> 1495.4168 | Q17: =Q21+Q25 -> 1724.7513 | R17: =R21+R25 -> 1807.8709 | ... Z17: =Z21+Z25 -> 2237.9733
B18: As % revenue | K18: =K17/K5 -> 0.080275529 | L18: =L17/L5 -> 0.089059976 | M18: =M17/M5 -> 0.096141417 | N18: =N17/N5 -> 0.084830723 | O18: =O17/O5 -> 0.10732937 | P18: =P17/P5 -> 0.11113726 | Q18: =Q17/Q5 -> 0.097240498 | R18: =R17/R5 -> 0.09725086 | ... Z18: =Z17/Z5 -> 0.098028428
B19: SG&A | K19: =-('IS Raw'!F24+'IS Raw'!F25) -> 565.3779 | L19: =-('IS Raw'!G24+'IS Raw'!G25) -> 673.40698 | M19: =-('IS Raw'!H24+'IS Raw'!H25) -> 948.89299 | N19: =-('IS Raw'!I24+'IS Raw'!I25) -> 1350.8891 | O19: =-('IS Raw'!J24+'IS Raw'!J25) -> 1349.1883 | P19: =-('IS Raw'!K24+'IS Raw'!K25) -> 1495.4168 | Q19: =Q17 -> 1724.7513 | R19: =R17 -> 1807.8709 | S19: =S17 -> 1832.9461 | T19: =T17 -> 2162.5246 | U19: =U17 -> 2178.0721 | V19: =V17 -> 2032.1553 | W19: =W17 -> 2038.6794 | X19: =X17 -> 2082.4466 | ... Z19: =Z17 -> 2237.9733
A21: 3 | B21: Selling expenses (FC) | K21: ='Consol. Rev.'!K101 -> 364.0587 | L21: ='Consol. Rev.'!L101 -> 369.00032 | M21: ='Consol. Rev.'!M101 -> 420.40125 | N21: ='Consol. Rev.'!N101 -> 698.29487 | O21: ='Consol. Rev.'!O101 -> 800.63146 | P21: ='Consol. Rev.'!P101 -> 1014.3698 | Q21: ='Consol. Rev.'!Q101 -> 971.02815 | R21: ='Consol. Rev.'!R101 -> 1021.888 | ... Z21: ='Consol. Rev.'!Z101 -> 1316.1205
B22: As % revenue | K22: =K21/K5 -> 0.051691098 | L22: =L21/L5 -> 0.048801334 | M22: =M21/M5 -> 0.042594868 | N22: =N21/N5 -> 0.043850274 | O22: =O21/O5 -> 0.063691084 | P22: =P21/P5 -> 0.075386525 | Q22: =Q21/Q5 -> 0.054746017 | R22: =R21/R5 -> 0.054970453 | ... Z22: =Z21/Z5 -> 0.057649133
B23: Selling expenses | K23: =-'IS Raw'!F24 -> 364.0587 | L23: =-'IS Raw'!G24 -> 369.00032 | M23: =-'IS Raw'!H24 -> 420.40125 | N23: =-'IS Raw'!I24 -> 698.29487 | O23: =-'IS Raw'!J24 -> 800.63146 | P23: =-'IS Raw'!K24 -> 1014.3698 | Q23: =Q21 -> 971.02815 | R23: =R21 -> 1021.888 | S23: =S21 -> 1060.8773 | T23: =T21 -> 1286.5053 | U23: =U21 -> 1293.4802 | V23: =V21 -> 1195.2993 | W23: =W21 -> 1188.0729 | X23: =X21 -> 1220.6868 | ... Z23: =Z21 -> 1316.1205
A25: 4 | B25: Administration expenses (FC) | K25: ='Consol. Rev.'!K125 -> 201.3192 | L25: ='Consol. Rev.'!L125 -> 304.40666 | M25: ='Consol. Rev.'!M125 -> 528.49174 | N25: ='Consol. Rev.'!N125 -> 652.59426 | O25: ='Consol. Rev.'!O125 -> 548.55689 | P25: ='Consol. Rev.'!P125 -> 481.047 | Q25: ='Consol. Rev.'!Q125 -> 753.7231 | R25: ='Consol. Rev.'!R125 -> 785.98295 | ... Z25: ='Consol. Rev.'!Z125 -> 921.85283
B26: As % revenue | K26: =K25/K5 -> 0.028584431 | L26: =L25/L5 -> 0.040258641 | M26: =M25/M5 -> 0.053546548 | N26: =N25/N5 -> 0.040980449 | O26: =O25/O5 -> 0.043638284 | P26: =P25/P5 -> 0.035750731 | Q26: =Q25/Q5 -> 0.042494481 | R26: =R25/R5 -> 0.042280407 | ... Z26: =Z25/Z5 -> 0.040379295
B27: Administration expenses | K27: =-'IS Raw'!F25 -> 201.3192 | L27: =-'IS Raw'!G25 -> 304.40666 | M27: =-'IS Raw'!H25 -> 528.49174 | N27: =-'IS Raw'!I25 -> 652.59426 | O27: =-'IS Raw'!J25 -> 548.55689 | P27: =-'IS Raw'!K25 -> 481.047 | Q27: =Q25 -> 753.7231 | R27: =R25 -> 785.98295 | S27: =S25 -> 772.0688 | T27: =T25 -> 876.01922 | U27: =U25 -> 884.5919 | V27: =V25 -> 836.85597 | W27: =W25 -> 850.60644 | X27: =X25 -> 861.75978 | ... Z27: =Z25 -> 921.85283
B29: Operating Expenses (FC) | K29: =K9+K17 -> 6649.1526 | L29: =L9+L17 -> 6917.8343 | M29: =M9+M17 -> 8037.719 | N29: =N9+N17 -> 11571.987 | O29: =O9+O17 -> 11887.931 | P29: =P9+P17 -> 12437.518 | Q29: =Q9+Q17 -> 15642.995 | R29: =R9+R17 -> 16191.482 | ... Z29: =Z9+Z17 -> 19038.928
B30: As % revenue | K30: =K29/K5 -> 0.94408403 | L30: =L29/L5 -> 0.91490313 | M30: =M29/M5 -> 0.81437812 | N30: =N29/N5 -> 0.72667695 | O30: =O29/O5 -> 0.94569754 | P30: =P29/P5 -> 0.92433867 | Q30: =Q29/Q5 -> 0.88194319 | R30: =R29/R5 -> 0.87098893 | ... Z30: =Z29/Z5 -> 0.83394926
B31: Operating Expense | K31: =K11+K19 -> 6649.1526 | L31: =L11+L19 -> 6917.8343 | M31: =M11+M19 -> 8037.719 | N31: =N11+N19 -> 11571.987 | O31: =O11+O19 -> 11887.931 | P31: =P11+P19 -> 12437.518 | Q31: =Q11+Q19 -> 15642.995 | R31: =R11+R19 -> 16191.482 | ... Z31: =Z11+Z19 -> 19038.928
B33: EBITDA (FC) | K33: =K13-K17+K37 -> 1712.6549 | L33: =L13-L17+L37 -> 1961.5933 | M33: =M13-M17+M37 -> 3217.8549 | N33: =N13-N17+N37 -> 5750.5697 | O33: =O13-O17+O37 -> 1765.992 | P33: =P13-P17+P37 -> 1286.1489 | Q33: =Q13-Q17+Q37 -> 2960.1655 | R33: =R13-R17+R37 -> 3356.3643 | ... Z33: =Z13-Z17+Z37 -> 4238.5622
B34: EBITDA margin | K34: =K33/K5 -> 0.24317237 | L34: =L33/L5 -> 0.25942625 | M34: =M33/M5 -> 0.32603163 | N34: =N33/N5 -> 0.36111401 | O34: =O33/O5 -> 0.14048655 | P34: =P33/P5 -> 0.095584763 | Q34: =Q33/Q5 -> 0.16689245 | R34: =R33/R5 -> 0.18054902 | ... Z34: =Z33/Z5 -> 0.18565887
B35: EBITDA | K35: =K15-K19+K40 -> 1712.6549 | L35: =L15-L19+L40 -> 1961.5933 | M35: =M15-M19+M40 -> 3217.8549 | N35: =N15-N19+N40 -> 5750.5697 | O35: =O15-O19+O40 -> 1765.992 | P35: =P15-P19+P40 -> 1286.1489 | Q35: =Q15-Q19+Q40 -> 2960.1655 | R35: =R15-R19+R40 -> 3356.3643 | ... Z35: =Z15-Z19+Z40 -> 4238.5622
A37: 5 | B37: Depreciation/ Amortization (FC) | K37: ='Output-FR (show)'!K132 -> 1318.8406 | L37: ='Output-FR (show)'!L132 -> 1318.1525 | M37: ='Output-FR (show)'!M132 -> 1385.8109 | N37: ='Output-FR (show)'!N132 -> 1398.0294 | O37: ='Output-FR (show)'!O132 -> 1083.3807 | P37: ='Output-FR (show)'!P132 -> 268.08146 | Q37: ='LT. Asset'!Q8 -> 866.19597 | R37: ='LT. Asset'!R8 -> 958.07836 | S37: ='LT. Asset'!S8 -> 400.06569 | T37: ='LT. Asset'!T8 -> 404.65674 | U37: ='LT. Asset'!U8 -> 391.81912 | V37: ='LT. Asset'!V8 -> 391.68502 | W37: ='LT. Asset'!W8 -> 351.6726 | X37: ='LT. Asset'!X8 -> 394.01553 | ... Z37: ='LT. Asset'!Z8 -> 447.65036
B38: As % revenue | K38: =K37/K5 -> 0.1872564 | L38: =L37/L5 -> 0.17432939 | M38: =M37/M5 -> 0.14040975 | N38: =N37/N5 -> 0.087790953 | O38: =O37/O5 -> 0.086184087 | P38: =P37/P5 -> 0.019923434 | Q38: =Q37/Q5 -> 0.048835638 | R38: =R37/R5 -> 0.051537941 | ... Z38: =Z37/Z5 -> 0.019608125
B39: As % prior fixed assets
B40: Depreciation/ Amortization | K40: =K37 -> 1318.8406 | L40: =L37 -> 1318.1525 | M40: =M37 -> 1385.8109 | N40: =N37 -> 1398.0294 | O40: =O37 -> 1083.3807 | P40: =P37 -> 268.08146 | Q40: =Q37 -> 866.19597 | R40: =R37 -> 958.07836 | ... Z40: =Z37 -> 447.65036
B41: As % revenue
B42: Depreciation of tangibles
B43: Amortization of intangibles
B45: EBIT (FC) | K45: =K13-K17 -> 393.8143 | L45: =L13-L17 -> 643.44082 | M45: =M13-M17 -> 1832.0439 | N45: =N13-N17 -> 4352.5403 | O45: =O13-O17 -> 682.61133 | P45: =P13-P17 -> 1018.0675 | Q45: =Q13-Q17 -> 2093.9695 | R45: =R13-R17 -> 2398.2859 | ... Z45: =Z13-Z17 -> 3790.9118
B46: EBIT margin | K46: =K45/K5 -> 0.055915966 | L46: =L45/L5 -> 0.085096867 | M46: =M45/M5 -> 0.18562188 | N46: =N45/N5 -> 0.27332305 | O46: =O45/O5 -> 0.054302458 | P46: =P45/P5 -> 0.075661329 | Q46: =Q45/Q5 -> 0.11805681 | R46: =R45/R5 -> 0.12901107 | ... Z46: =Z45/Z5 -> 0.16605074
B47: EBIT | K47: =K35-K40 -> 393.8143 | L47: =L35-L40 -> 643.44082 | M47: =M35-M40 -> 1832.0439 | N47: =N35-N40 -> 4352.5403 | O47: =O35-O40 -> 682.61133 | P47: =P35-P40 -> 1018.0675 | Q47: =Q35-Q40 -> 2093.9695 | R47: =R35-R40 -> 2398.2859 | ... Z47: =Z35-Z40 -> 3790.9118
B48: Thu nhập khác (loại trừ đột biến từ M&A) | K48: =K49 -> 48.48338 | L48: =L49 -> 10.735344 | M48: =M49 -> 4.3711954 | N48: =N49 -> 15.225626 | O48: =O49 -> 24.751516 | P48: =P49-(168141106493/10^9) -> 31.735653 | Q48: =AVERAGE(K48:P48) -> 22.550452 | R48: =AVERAGE(L48:Q48) -> 18.228298 | S48: =AVERAGE(M48:R48) -> 19.477123 | T48: =AVERAGE(N48:S48) -> 21.994778 | U48: =AVERAGE(O48:T48) -> 23.12297 | V48: =AVERAGE(P48:U48) -> 22.851546 | W48: =AVERAGE(Q48:V48) -> 21.370861 | X48: =AVERAGE(R48:W48) -> 21.174263 | ... Z48: =AVERAGE(T48:Y48) -> 22.029946
A49: 6 | B49: Gain (loss) on asset sales (FC) (thu nhập khác) | K49: ='IS Raw'!F28/Input!$B$1 -> 48.48338 | L49: ='IS Raw'!G28/Input!$B$1 -> 10.735344 | M49: ='IS Raw'!H28/Input!$B$1 -> 4.3711954 | N49: ='IS Raw'!I28/Input!$B$1 -> 15.225626 | O49: ='IS Raw'!J28/Input!$B$1 -> 24.751516 | P49: ='IS Raw'!K28/Input!$B$1 -> 199.87676 | Q49: =Q48 -> 22.550452 | R49: =R48 -> 18.228298 | S49: =S48 -> 19.477123 | T49: =T48 -> 21.994778 | U49: =U48 -> 23.12297 | V49: =V48 -> 22.851546 | W49: =W48 -> 21.370861 | X49: =X48 -> 21.174263 | ... Z49: =Z48 -> 22.029946
B50: Gross proceeds from asset sales
B51: Book value of assets sold
B52: Gain (loss) on asset sales | K52: =IF(ISTEXT('IS Raw'!F11), 'IS Raw'!F28/Input!$B$1, Input!K49) -> 48.48338 | L52: =IF(ISTEXT('IS Raw'!G11), 'IS Raw'!G28/Input!$B$1, Input!L49) -> 10.735344 | M52: =IF(ISTEXT('IS Raw'!H11), 'IS Raw'!H28/Input!$B$1, Input!M49) -> 4.3711954 | N52: =IF(ISTEXT('IS Raw'!I11), 'IS Raw'!I28/Input!$B$1, Input!N49) -> 15.225626 | O52: =IF(ISTEXT('IS Raw'!J11), 'IS Raw'!J28/Input!$B$1, Input!O49) -> 24.751516 | P52: =IF(ISTEXT('IS Raw'!K11), 'IS Raw'!K28/Input!$B$1, Input!P49) -> 199.87676 | Q52: =IF(ISTEXT('IS Raw'!L11), 'IS Raw'!L28/Input!$B$1, Input!Q49) -> 22.550452 | R52: =IF(ISTEXT('IS Raw'!M11), 'IS Raw'!M28/Input!$B$1, Input!R49) -> 18.228298 | ... Z52: =IF(ISTEXT('IS Raw'!U11), 'IS Raw'!U28/Input!$B$1, Input!Z49) -> 22.029946
A54: 7 | B54: Non-Operating expenses (FC) (chi phí khác) | K54: =-'IS Raw'!F29 -> 3.4721669 | L54: =-'IS Raw'!G29 -> 2.7245179 | M54: =-'IS Raw'!H29 -> 2.6041186 | N54: =-'IS Raw'!I29 -> 12.059178 | O54: =-'IS Raw'!J29 -> 2.2692702 | P54: =-'IS Raw'!K29 -> 1.1155147 | Q54: =Q5*Q55 -> 6.3198817 | R54: =R5*R55 -> 6.2002506 | S54: =S5*S55 -> 6.2903116 | T54: =T5*T55 -> 7.6582429 | U54: =U5*U55 -> 5.9030766 | V54: =V5*V55 -> 5.8299928 | W54: =W5*W55 -> 6.6874331 | X54: =X5*X55 -> 6.700972 | ... Z54: =Z5*Z55 -> 6.990138
B55: As % revenue | K55: =K54/K5 -> 0.00049299776 | L55: =L54/L5 -> 0.00036032519 | M55: =M54/M5 -> 0.00026384814 | N55: =N54/N5 -> 0.00075727069 | O55: =O54/O5 -> 0.00018052286 | P55: =P54/P5 -> 8.2903469e-05 | Q55: =AVERAGE(K55:P55) -> 0.00035631135 | R55: =AVERAGE(L55:Q55) -> 0.00033353028 | S55: =AVERAGE(M55:R55) -> 0.00032906447 | T55: =AVERAGE(N55:S55) -> 0.00033993385 | U55: =AVERAGE(O55:T55) -> 0.00027037771 | V55: =AVERAGE(P55:U55) -> 0.00028535352 | W55: =AVERAGE(Q55:V55) -> 0.0003190952 | X55: =AVERAGE(R55:W55) -> 0.00031289251 | ... Z55: =AVERAGE(T55:Y55) -> 0.00030618428
B56: Non-Operating expenses | K56: =IF(ISTEXT('IS Raw'!F11), -'IS Raw'!F29/Input!$B$1, Input!K54) -> 3.4721669 | L56: =IF(ISTEXT('IS Raw'!G11), -'IS Raw'!G29/Input!$B$1, Input!L54) -> 2.7245179 | M56: =IF(ISTEXT('IS Raw'!H11), -'IS Raw'!H29/Input!$B$1, Input!M54) -> 2.6041186 | N56: =IF(ISTEXT('IS Raw'!I11), -'IS Raw'!I29/Input!$B$1, Input!N54) -> 12.059178 | O56: =IF(ISTEXT('IS Raw'!J11), -'IS Raw'!J29/Input!$B$1, Input!O54) -> 2.2692702 | P56: =IF(ISTEXT('IS Raw'!K11), -'IS Raw'!K29/Input!$B$1, Input!P54) -> 1.1155147 | Q56: =IF(ISTEXT('IS Raw'!L11), -'IS Raw'!L29/Input!$B$1, Input!Q54) -> 6.3198817 | R56: =IF(ISTEXT('IS Raw'!M11), -'IS Raw'!M29/Input!$B$1, Input!R54) -> 6.2002506 | ... Z56: =IF(ISTEXT('IS Raw'!U11), -'IS Raw'!U29/Input!$B$1, Input!Z54) -> 6.990138
A58: 8 | B58: Financial Revenues (FC) | K58: ='IS Raw'!F20/$B$1 -> 127.01614 | L58: ='IS Raw'!G20/$B$1 -> 128.31668 | M58: ='IS Raw'!H20/$B$1 -> 167.53191 | N58: ='IS Raw'!I20/$B$1 -> 301.00806 | O58: ='IS Raw'!J20/$B$1 -> 577.08849 | P58: ='IS Raw'!K20/$B$1 -> 381.8039 | Q58: =Q59+SUM(Q62:Q65) -> 612.61692 | R58: =R59+SUM(R62:R65) -> 680.8309 | S58: =S59+SUM(S62:S65) -> 767.18909 | T58: =T59+SUM(T62:T65) -> 895.09609 | U58: =U59+SUM(U62:U65) -> 1017.65 | V58: =V59+SUM(V62:V65) -> 1125.6841 | W58: =W59+SUM(W62:W65) -> 1210.8158 | X58: =X59+SUM(X62:X65) -> 1303.9966 | ... Z58: =Z59+SUM(Z62:Z65) -> 1490.5862
B59: Interest income | K59: =SUM(K60,K61) -> 117.69981 | L59: =SUM(L60,L61) -> 111.93925 | M59: =SUM(M60,M61) -> 130.83572 | N59: =SUM(N60,N61) -> 262.14902 | O59: =SUM(O60,O61) -> 518.47533 | P59: =SUM(P60,P61) -> 282.72828 | Q59: =SUM(Q60,Q61) -> 581.9727 | R59: =SUM(R60,R61) -> 645.43108 | ... Z59: =SUM(Z60,Z61) -> 1456.2158
B60: Excess cash | Q60: =Q157 -> 0.025371453 | R60: =R157 -> 0.087591255 | S60: =S157 -> 0.092069873 | T60: =T157 -> 0.066691364 | U60: =U157 -> 0.13624508 | V60: =V157 -> 0.21662463 | W60: =W157 -> 0.26330702 | X60: =X157 -> 0.27322785 | ... Z60: =Z157 -> 0.12633189
B61: Operating cash | K61: =Notes!F148/$B$1 -> 117.69981 | L61: =Notes!G148/$B$1 -> 111.93925 | M61: =Notes!H148/$B$1 -> 130.83572 | N61: =Notes!I148/$B$1 -> 262.14902 | O61: =Notes!J148/$B$1 -> 518.47533 | P61: =Notes!K148/$B$1 -> 282.72828 | Q61: =Q165+Q175 -> 581.94733 | R61: =R165+R175 -> 645.34349 | S61: =S165+S175 -> 732.12933 | T61: =T165+T175 -> 861.35882 | U61: =U165+U175 -> 982.83444 | V61: =V165+V175 -> 1091.0283 | W61: =W165+W175 -> 1176.2895 | X61: =X165+X175 -> 1269.2629 | ... Z61: =Z165+Z175 -> 1456.0895
B62: Marketable securities (Lãi chuyển nhượng chứng khoán) | K62: =Notes!F149/$B$1 -> 0 | L62: =Notes!G149/$B$1 -> 0 | M62: =Notes!H149/$B$1 -> 0 | N62: =Notes!I149/$B$1 -> 0 | O62: =Notes!J149/$B$1 -> 0 | P62: =Notes!K149/$B$1 -> 0 | Q62: =P62 -> 0 | R62: =Q62 -> 0 | S62: =R62 -> 0 | T62: =S62 -> 0 | U62: =T62 -> 0 | V62: =U62 -> 0 | W62: =V62 -> 0 | X62: =W62 -> 0 | ... Z62: =Y62 -> 0
B63: Profits/dividends receive | K63: =Notes!F150/$B$1 -> 0 | L63: =Notes!G150/$B$1 -> 0 | M63: =Notes!H150/$B$1 -> 0 | N63: =Notes!I150/$B$1 -> 0 | O63: =Notes!J150/$B$1 -> 0 | P63: =Notes!K150/$B$1 -> 0 | Q63: =P63 -> 0 | R63: =Q63 -> 0 | S63: =R63 -> 0 | T63: =S63 -> 0 | U63: =T63 -> 0 | V63: =U63 -> 0 | W63: =V63 -> 0 | X63: =W63 -> 0 | ... Z63: =Y63 -> 0
B64: Lãi từ bán, thanh lý các khoản đầu tư | K64: =Notes!F151/$B$1 -> 0 | L64: =Notes!G151/$B$1 -> 0 | M64: =Notes!H151/$B$1 -> 0 | N64: =Notes!I151/$B$1 -> 0 | O64: =Notes!J151/$B$1 -> 0 | P64: =Notes!K151/$B$1 -> 0 | Q64: =P64 -> 0 | R64: =Q64 -> 0 | S64: =R64 -> 0 | T64: =S64 -> 0 | U64: =T64 -> 0 | V64: =U64 -> 0 | W64: =V64 -> 0 | X64: =W64 -> 0 | ... Z64: =Y64 -> 0
B65: Others | K65: =SUM(Notes!F152, Notes!F153, Notes!F154, Notes!F155, Notes!F156)/$B$1 -> 9.3163297 | L65: =SUM(Notes!G152, Notes!G153, Notes!G154, Notes!G155, Notes!G156)/$B$1 -> 16.377435 | M65: =SUM(Notes!H152, Notes!H153, Notes!H154, Notes!H155, Notes!H156)/$B$1 -> 36.696185 | N65: =SUM(Notes!I152, Notes!I153, Notes!I154, Notes!I155, Notes!I156)/$B$1 -> 38.859044 | O65: =SUM(Notes!J152, Notes!J153, Notes!J154, Notes!J155, Notes!J156)/$B$1 -> 58.613161 | P65: =SUM(Notes!K152, Notes!K153, Notes!K154, Notes!K155, Notes!K156)/$B$1 -> 99.075621 | Q65: =AVERAGE(L65:N65) -> 30.644221 | R65: =AVERAGE(M65:N65,Q65) -> 35.399817 | S65: =AVERAGE(N65,Q65:R65) -> 34.967694 | T65: =AVERAGE(Q65:S65) -> 33.670577 | U65: =AVERAGE(R65:T65) -> 34.679363 | V65: =AVERAGE(S65:U65) -> 34.439211 | W65: =AVERAGE(T65:V65) -> 34.26305 | X65: =AVERAGE(U65:W65) -> 34.460541 | Y65: =AVERAGE(V65:X65) -> 34.387601 | Z65: =AVERAGE(W65:Y65) -> 34.370398
B66: Financial Revenues | K66: =IF(ISTEXT('IS Raw'!F11),'IS Raw'!F20/Input!$B$1,Input!K58) -> 127.01614 | L66: =IF(ISTEXT('IS Raw'!G11),'IS Raw'!G20/Input!$B$1,Input!L58) -> 128.31668 | M66: =IF(ISTEXT('IS Raw'!H11),'IS Raw'!H20/Input!$B$1,Input!M58) -> 167.53191 | N66: =IF(ISTEXT('IS Raw'!I11),'IS Raw'!I20/Input!$B$1,Input!N58) -> 301.00806 | O66: =IF(ISTEXT('IS Raw'!J11),'IS Raw'!J20/Input!$B$1,Input!O58) -> 577.08849 | P66: =IF(ISTEXT('IS Raw'!K11),'IS Raw'!K20/Input!$B$1,Input!P58) -> 381.8039 | Q66: =IF(ISTEXT('IS Raw'!L11),'IS Raw'!L20/Input!$B$1,Input!Q58) -> 612.61692 | R66: =IF(ISTEXT('IS Raw'!M11),'IS Raw'!M20/Input!$B$1,Input!R58) -> 680.8309 | ... Z66: =IF(ISTEXT('IS Raw'!U11),'IS Raw'!U20/Input!$B$1,Input!Z58) -> 1490.5862
A68: 9 | B68: Financial Expenses (FC) | K68: =-'IS Raw'!F21/Input!$B$1 -> 102.75348 | L68: =-'IS Raw'!G21/Input!$B$1 -> 63.234525 | M68: =-'IS Raw'!H21/Input!$B$1 -> 45.07293 | N68: =-'IS Raw'!I21/Input!$B$1 -> 60.402057 | O68: =-'IS Raw'!J21/Input!$B$1 -> 27.372488 | P68: =-'IS Raw'!K21/Input!$B$1 -> 76.569108 | Q68: =+Q69+Q75+Q76 -> 101.62259 | R68: =+R69+R75+R76 -> 123.88871 | S68: =+S69+S75+S76 -> 131.901 | T68: =+T69+T75+T76 -> 152.16027 | U68: =+U69+U75+U76 -> 161.94977 | V68: =+V69+V75+V76 -> 155.26046 | W68: =+W69+W75+W76 -> 144.76034 | X68: =+X69+X75+X76 -> 141.47159 | ... Z68: =+Z69+Z75+Z76 -> 148.60486
A69: 9.1 | B69: Interest expenses | K69: =Notes!F158/Input!$B$1 -> 87.17253 | L69: =Notes!G158/Input!$B$1 -> 43.301059 | M69: =Notes!H158/Input!$B$1 -> 18.580201 | N69: =Notes!I158/Input!$B$1 -> 10.274784 | O69: =Notes!J158/Input!$B$1 -> 10.155714 | P69: =Notes!K158/Input!$B$1 -> 44.380805 | Q69: =SUM(Q70:Q74) -> 74.699342 | R69: =SUM(R70:R74) -> 95.075078 | S69: =SUM(S70:S74) -> 101.60734 | T69: =SUM(T70:T74) -> 121.23313 | U69: =SUM(U70:U74) -> 134.22264 | V69: =SUM(V70:V74) -> 125.78161 | W69: =SUM(W70:W74) -> 115.73306 | X69: =SUM(X70:X74) -> 112.09364 | ... Z69: =SUM(Z70:Z74) -> 119.2698
B70: Revolver | Q70: =Q272 -> 0 | R70: =R272 -> 0 | S70: =S272 -> 0 | T70: =T272 -> 0 | U70: =U272 -> 0 | V70: =V272 -> 0 | W70: =W272 -> 0 | X70: =X272 -> 0 | ... Z70: =Z272 -> 0
B71: Short-term notes | Q71: =Q277 -> 56.344825 | R71: =R277 -> 61.998819 | S71: =S277 -> 59.45913 | T71: =T277 -> 66.709857 | U71: =U277 -> 74.714832 | V71: =V277 -> 75.58143 | W71: =W277 -> 75.914291 | X71: =X277 -> 80.737951 | ... Z71: =Z277 -> 92.646923
B72: Debt A (long-term) | Q72: =Q307 -> 18.354517 | R72: =R307 -> 33.07626 | S72: =S307 -> 42.148208 | T72: =T307 -> 54.523268 | U72: =U307 -> 59.507812 | V72: =V307 -> 50.200177 | W72: =W307 -> 39.818769 | X72: =X307 -> 31.355688 | ... Z72: =Z307 -> 26.622875
B73: Debt B (long-term) | Q73: =Q317 -> 0 | R73: =R317 -> 0 | S73: =S317 -> 0 | T73: =T317 -> 0 | U73: =U317 -> 0 | V73: =V317 -> 0 | W73: =W317 -> 0 | X73: =X317 -> 0 | ... Z73: =Z317 -> 0
B74: Debt C (long-term) | Q74: =Q327 -> 0 | R74: =R327 -> 0 | S74: =S327 -> 0 | T74: =T327 -> 0 | U74: =U327 -> 0 | V74: =V327 -> 0 | W74: =W327 -> 0 | X74: =X327 -> 0 | ... Z74: =Z327 -> 0
A75: 9.2 | B75: Loss from Foreign exchange differences | K75: =(Notes!F162 + Notes!F163)/Input!$B$1 -> 10.77102 | L75: =(Notes!G162 + Notes!G163)/Input!$B$1 -> 17.436037 | M75: =(Notes!H162 + Notes!H163)/Input!$B$1 -> 23.976005 | N75: =(Notes!I162 + Notes!I163)/Input!$B$1 -> 50.127272 | O75: =(Notes!J162 + Notes!J163)/Input!$B$1 -> 17.216773 | P75: =(Notes!K162 + Notes!K163)/Input!$B$1 -> 32.188302 | Q75: =AVERAGE(K75:P75) -> 25.285902 | R75: =AVERAGE(L75:Q75) -> 27.705049 | S75: =AVERAGE(M75:R75) -> 29.416551 | T75: =AVERAGE(N75:S75) -> 30.323308 | U75: =AVERAGE(O75:T75) -> 27.022648 | V75: =AVERAGE(P75:U75) -> 28.65696 | W75: =AVERAGE(Q75:V75) -> 28.068403 | X75: =AVERAGE(R75:W75) -> 28.532153 | ... Z75: =AVERAGE(T75:Y75) -> 28.545579
A76: 9.3 | B76: Others (dự phòng + khác ) | K76: =SUM(Notes!F159, Notes!F160, Notes!F161, Notes!F164, Notes!F165) -> 4.8099317 | L76: =SUM(Notes!G159, Notes!G160, Notes!G161, Notes!G164, Notes!G165) -> 2.4974286 | M76: =SUM(Notes!H159, Notes!H160, Notes!H161, Notes!H164, Notes!H165) -> 2.5167232 | N76: =SUM(Notes!I159, Notes!I160, Notes!I161, Notes!I164, Notes!I165) -> 0 | O76: =SUM(Notes!J159, Notes!J160, Notes!J161, Notes!J164, Notes!J165) -> 0 | P76: =SUM(Notes!K159, Notes!K160, Notes!K161, Notes!K164, Notes!K165) -> 0 | Q76: =AVERAGE(K76:P76) -> 1.6373473 | R76: =AVERAGE(L76:Q76) -> 1.1085832 | S76: =AVERAGE(M76:R76) -> 0.87710893 | T76: =AVERAGE(N76:S76) -> 0.60383989 | U76: =AVERAGE(O76:T76) -> 0.70447987 | V76: =AVERAGE(P76:U76) -> 0.82189319 | W76: =AVERAGE(Q76:V76) -> 0.95887538 | X76: =AVERAGE(R76:W76) -> 0.84579674 | ... Z76: =AVERAGE(T76:Y76) -> 0.78948068
B77: Financial Expenses | K77: =IF(ISTEXT('IS Raw'!F11), -'IS Raw'!F21/Input!$B$1,Input!K68) -> 102.75348 | L77: =IF(ISTEXT('IS Raw'!G11), -'IS Raw'!G21/Input!$B$1,Input!L68) -> 63.234525 | M77: =IF(ISTEXT('IS Raw'!H11), -'IS Raw'!H21/Input!$B$1,Input!M68) -> 45.07293 | N77: =IF(ISTEXT('IS Raw'!I11), -'IS Raw'!I21/Input!$B$1,Input!N68) -> 60.402057 | O77: =IF(ISTEXT('IS Raw'!J11), -'IS Raw'!J21/Input!$B$1,Input!O68) -> 27.372488 | P77: =IF(ISTEXT('IS Raw'!K11), -'IS Raw'!K21/Input!$B$1,Input!P68) -> 76.569108 | Q77: =IF(ISTEXT('IS Raw'!L11), -'IS Raw'!L21/Input!$B$1,Input!Q68) -> 101.62259 | R77: =IF(ISTEXT('IS Raw'!M11), -'IS Raw'!M21/Input!$B$1,Input!R68) -> 123.88871 | ... Z77: =IF(ISTEXT('IS Raw'!U11), -'IS Raw'!U21/Input!$B$1,Input!Z68) -> 148.60486
A79: 10 | B79: Equity earnings in affiliates (FC) | K79: ='IS Raw'!F30/Input!$B$1 -> 0 | L79: ='IS Raw'!G30/Input!$B$1 -> 0 | M79: ='IS Raw'!H30/Input!$B$1 -> 0 | N79: ='IS Raw'!I30/Input!$B$1 -> 0 | O79: ='IS Raw'!J30/Input!$B$1 -> 0 | P79: ='IS Raw'!K30/Input!$B$1 -> 0 | Q79: =P79 -> 0 | R79: =Q79 -> 0 | S79: =R79 -> 0 | T79: =S79 -> 0 | U79: =T79 -> 0 | V79: =U79 -> 0 | W79: =V79 -> 0 | X79: =W79 -> 0 | ... Z79: =Y79 -> 0
B80: As % revenue | K80: =K79/K7 -> 0 | L80: =L79/L7 -> 0 | M80: =M79/M7 -> 0 | N80: =N79/N7 -> 0 | O80: =O79/O7 -> 0 | P80: =P79/P7 -> 0 | Q80: =Q79/Q7 -> 0 | R80: =R79/R7 -> 0 | ... Z80: =Z79/Z7 -> 0
B81: Percent growth %
B82: Equity earnings in affiliates | K82: =IF(ISTEXT('IS Raw'!F11), 'IS Raw'!F30/Input!$B$1, Input!K79) -> 0 | L82: =IF(ISTEXT('IS Raw'!G11), 'IS Raw'!G30/Input!$B$1, Input!L79) -> 0 | M82: =IF(ISTEXT('IS Raw'!H11), 'IS Raw'!H30/Input!$B$1, Input!M79) -> 0 | N82: =IF(ISTEXT('IS Raw'!I11), 'IS Raw'!I30/Input!$B$1, Input!N79) -> 0 | O82: =IF(ISTEXT('IS Raw'!J11), 'IS Raw'!J30/Input!$B$1, Input!O79) -> 0 | P82: =IF(ISTEXT('IS Raw'!K11), 'IS Raw'!K30/Input!$B$1, Input!P79) -> 0 | Q82: =IF(ISTEXT('IS Raw'!L11), 'IS Raw'!L30/Input!$B$1, Input!Q79) -> 0 | R82: =IF(ISTEXT('IS Raw'!M11), 'IS Raw'!M30/Input!$B$1, Input!R79) -> 0 | ... Z82: =IF(ISTEXT('IS Raw'!U11), 'IS Raw'!U30/Input!$B$1, Input!Z79) -> 0
B84: LNTT (FC) | K84: =+K45+K49-K54+K58-K68+K79 -> 463.08817 | L84: =+L45+L49-L54+L58-L68+L79 -> 716.5338 | M84: =+M45+M49-M54+M58-M68+M79 -> 1956.27 | N84: =+N45+N49-N54+N58-N68+N79 -> 4596.3128 | O84: =+O45+O49-O54+O58-O68+O79 -> 1254.8096 | P84: =+P45+P49-P54+P58-P68+P79 -> 1522.0635 | Q84: =+Q45+Q49-Q54+Q58-Q68+Q79 -> 2621.1944 | R84: =+R45+R49-R54+R58-R68+R79 -> 2967.2562 | ... Z84: =+Z45+Z49-Z54+Z58-Z68+Z79 -> 5147.9329
B85: EBT margin | K85: =IFERROR(K86/K7, " ") -> 0.065751859 | L85: =IFERROR(L86/L7, " ") -> 0.094763621 | M85: =IFERROR(M86/M7, " ") -> 0.19820841 | N85: =IFERROR(N86/N7, " ") -> 0.28863104 | O85: =IFERROR(O86/O7, " ") -> 0.099821438 | P85: =IFERROR(P86/P7, " ") -> 0.1131176 | Q85: =IFERROR(Q86/Q7, " ") -> 0.14778146 | R85: =IFERROR(R86/R7, " ") -> 0.15961771 | ... Z85: =IFERROR(Z86/Z7, " ") -> 0.22549142
B86: LNTT | K86: =+K47+K52-K56+K66-K77+K82 -> 463.08817 | L86: =+L47+L52-L56+L66-L77+L82 -> 716.5338 | M86: =+M47+M52-M56+M66-M77+M82 -> 1956.27 | N86: =+N47+N52-N56+N66-N77+N82 -> 4596.3128 | O86: =+O47+O52-O56+O66-O77+O82 -> 1254.8096 | P86: =+P47+P52-P56+P66-P77+P82 -> 1522.0635 | Q86: =+Q47+Q52-Q56+Q66-Q77+Q82 -> 2621.1944 | R86: =+R47+R52-R56+R66-R77+R82 -> 2967.2562 | ... Z86: =+Z47+Z52-Z56+Z66-Z77+Z82 -> 5147.9329
B87: Tax rate % (DPM) | K87: 0.167 | L87: 0.172 | M87: =16.5% -> 0.165 | N87: =15.4% -> 0.154 | O87: =23.3% -> 0.233 | P87: =17.2% -> 0.172
A88: 11 | B88: Provision for taxes (FC) | K88: =-'IS Raw'!F32/Input!$B$1 -> 35.364442 | L88: =-'IS Raw'!G32/Input!$B$1 -> 54.08747 | M88: =-'IS Raw'!H32/Input!$B$1 -> 130.1457 | N88: =-'IS Raw'!I32/Input!$B$1 -> 275.23203 | O88: =-'IS Raw'!J32/Input!$B$1 -> 144.66687 | P88: =-'IS Raw'!K32/Input!$B$1 -> 94.056907 | Q88: =Q84*Q89 -> 410.2924 | R88: =R84*R89 -> 464.46102 | S88: =S84*S89 -> 543.71301 | T88: =T84*T89 -> 849.50505 | U88: =U84*U89 -> 726.3155 | V88: =V84*V89 -> 634.12631 | W88: =W84*W89 -> 634.7127 | X88: =X84*X89 -> 705.04475 | ... Z88: =Z84*Z89 -> 805.79972
B89: Tax rate % | K89: =IF(K84,K88/K84,0) -> 0.076366542 | L89: =IF(L84,L88/L84,0) -> 0.075484883 | M89: =IF(M84,M88/M84,0) -> 0.066527475 | N89: =IF(N84,N88/N84,0) -> 0.059881049 | O89: =IF(O84,O88/O84,0) -> 0.1152899 | P89: =IF(P84,P88/P84,0) -> 0.061795653 | Q89: =AVERAGE(AVERAGE(K87:P87), AVERAGE(K89:P89))+3% -> 0.15652879 | R89: =Q89 -> 0.15652879 | S89: =R89 -> 0.15652879 | T89: =S89 -> 0.15652879 | U89: =T89 -> 0.15652879 | V89: =U89 -> 0.15652879 | W89: =V89 -> 0.15652879 | X89: =W89 -> 0.15652879 | Y89: =X89 -> 0.15652879 | Z89: =Y89 -> 0.15652879
B90: Provision for taxes | K90: =IF(ISTEXT('IS Raw'!F11), -'IS Raw'!F32/Input!$B$1, Input!K88) -> 35.364442 | L90: =IF(ISTEXT('IS Raw'!G11), -'IS Raw'!G32/Input!$B$1, Input!L88) -> 54.08747 | M90: =IF(ISTEXT('IS Raw'!H11), -'IS Raw'!H32/Input!$B$1, Input!M88) -> 130.1457 | N90: =IF(ISTEXT('IS Raw'!I11), -'IS Raw'!I32/Input!$B$1, Input!N88) -> 275.23203 | O90: =IF(ISTEXT('IS Raw'!J11), -'IS Raw'!J32/Input!$B$1, Input!O88) -> 144.66687 | P90: =IF(ISTEXT('IS Raw'!K11), -'IS Raw'!K32/Input!$B$1, Input!P88) -> 94.056907 | Q90: =IF(ISTEXT('IS Raw'!L11), -'IS Raw'!L32/Input!$B$1, Input!Q88) -> 410.2924 | R90: =IF(ISTEXT('IS Raw'!M11), -'IS Raw'!M32/Input!$B$1, Input!R88) -> 464.46102 | ... Z90: =IF(ISTEXT('IS Raw'!U11), -'IS Raw'!U32/Input!$B$1, Input!Z88) -> 805.79972
B91: Tax rate % (BFC) | K91: =27.7% -> 0.277 | L91: =17% -> 0.17 | M91: =19.95% -> 0.1995 | N91: =20.94% -> 0.2094 | O91: =31.6% -> 0.316 | P91: =19.77% -> 0.1977
B92: Net income (FC) | K92: =K84-K88 -> 427.72373 | L92: =L84-L88 -> 662.44633 | M92: =M84-M88 -> 1826.1243 | N92: =N84-N88 -> 4321.0807 | O92: =O84-O88 -> 1110.1427 | P92: =P84-P88 -> 1428.0066 | Q92: =Q84-Q88 -> 2210.902 | R92: =R84-R88 -> 2502.7952 | ... Z92: =Z84-Z88 -> 4342.1332
B93: Net margin | K93: =K92/K5 -> 0.060730617 | L93: =L92/L5 -> 0.0876104 | M93: =M92/M5 -> 0.1850221 | N93: =N92/N5 -> 0.27134751 | O93: =O92/O5 -> 0.088313034 | P93: =P92/P5 -> 0.10612742 | Q93: =Q92/Q5 -> 0.1246494 | R93: =R92/R5 -> 0.13463294 | ... Z93: =Z92/Z5 -> 0.19019552 | BB93: Hiệu chỉnh tăng SG&A nếu net margin cao quá
B94: Net income | K94: =K86-K90 -> 427.72373 | L94: =L86-L90 -> 662.44633 | M94: =M86-M90 -> 1826.1243 | N94: =N86-N90 -> 4321.0807 | O94: =O86-O90 -> 1110.1427 | P94: =P86-P90 -> 1428.0066 | Q94: =Q86-Q90 -> 2210.902 | R94: =R86-R90 -> 2502.7952 | ... Z94: =Z86-Z90 -> 4342.1332
B95: Growth | L95: =L94/K94-1 -> 0.54877153 | M95: =M94/L94-1 -> 1.7566373 | N95: =N94/M94-1 -> 1.3662577 | O95: =O94/N94-1 -> -0.74308679 | P95: =P94/O94-1 -> 0.28632703 | Q95: =Q94/P94-1 -> 0.54824358 | R95: =R94/Q94-1 -> 0.13202445 | S95: =S94/R94-1 -> 0.17063216 | ... Z95: =Z94/Y94-1 -> -0.0082930817
B96: Check BCTC | K96: =IF(ISTEXT('IS Raw'!F11), Input!K94 - 'IS Raw'!F35, "Chưa có BCTC") -> 1.1368684e-13 | L96: =IF(ISTEXT('IS Raw'!G11), Input!L94 - 'IS Raw'!G35, "Chưa có BCTC") -> 1.1368684e-13 | M96: =IF(ISTEXT('IS Raw'!H11), Input!M94 - 'IS Raw'!H35, "Chưa có BCTC") -> 2.2737368e-13 | N96: =IF(ISTEXT('IS Raw'!I11), Input!N94 - 'IS Raw'!I35, "Chưa có BCTC") -> 0 | O96: =IF(ISTEXT('IS Raw'!J11), Input!O94 - 'IS Raw'!J35, "Chưa có BCTC") -> 6.8212103e-13 | P96: =IF(ISTEXT('IS Raw'!K11), Input!P94 - 'IS Raw'!K35, "Chưa có BCTC") -> 6.8212103e-13 | Q96: =IF(ISTEXT('IS Raw'!L11), Input!Q94 - 'IS Raw'!L35, "Chưa có BCTC") -> Chưa có BCTC | R96: =IF(ISTEXT('IS Raw'!M11), Input!R94 - 'IS Raw'!M35, "Chưa có BCTC") -> Chưa có BCTC | ... Z96: =IF(ISTEXT('IS Raw'!U11), Input!Z94 - 'IS Raw'!U35, "Chưa có BCTC") -> Chưa có BCTC
A98: 12 | B98: Minority interest in earnings (FC) | K98: ='IS Raw'!F36/Input!$B$1 -> 1.5484997 | L98: ='IS Raw'!G36/Input!$B$1 -> 1.4002601 | M98: ='IS Raw'!H36/Input!$B$1 -> 2.6652292 | N98: ='IS Raw'!I36/Input!$B$1 -> 5.1274449 | O98: ='IS Raw'!J36/Input!$B$1 -> 1.2498918 | P98: ='IS Raw'!K36/Input!$B$1 -> 8.3486434 | Q98: =Q92*Q99 -> 5.6571294 | R98: =R92*R99 -> 5.9611876 | S98: =S92*S99 -> 7.1092445 | T98: =T92*T99 -> 11.845338 | U98: =U92*U99 -> 11.041509 | V98: =V92*V99 -> 10.605514 | W98: =W92*W99 -> 9.0519069 | X98: =X92*X99 -> 10.110568 | ... Z98: =Z92*Z99 -> 11.961226
B99: % net income | K99: =K98/K92 -> 0.0036203269 | L99: =L98/L92 -> 0.0021137713 | M99: =M98/M92 -> 0.0014595005 | N99: =N98/N92 -> 0.0011866117 | O99: =O98/O92 -> 0.0011258839 | P99: =P98/P92 -> 0.005846362 | Q99: =AVERAGE(K99:P99) -> 0.0025587427 | R99: =AVERAGE(L99:Q99) -> 0.002381812 | S99: =AVERAGE(M99:R99) -> 0.0024264855 | T99: =AVERAGE(N99:S99) -> 0.0025876496 | U99: =AVERAGE(O99:T99) -> 0.0028211559 | V99: =AVERAGE(P99:U99) -> 0.0031037013 | W99: =AVERAGE(Q99:V99) -> 0.0026465912 | X99: =AVERAGE(R99:W99) -> 0.0026612326 | ... Z99: =AVERAGE(T99:Y99) -> 0.0027546889
B100: Minority interest in earnings | K100: =IF(ISTEXT('IS Raw'!F11),'IS Raw'!F36, Input!K98) -> 1.5484997 | L100: =IF(ISTEXT('IS Raw'!G11),'IS Raw'!G36, Input!L98) -> 1.4002601 | M100: =IF(ISTEXT('IS Raw'!H11),'IS Raw'!H36, Input!M98) -> 2.6652292 | N100: =IF(ISTEXT('IS Raw'!I11),'IS Raw'!I36, Input!N98) -> 5.1274449 | O100: =IF(ISTEXT('IS Raw'!J11),'IS Raw'!J36, Input!O98) -> 1.2498918 | P100: =IF(ISTEXT('IS Raw'!K11),'IS Raw'!K36, Input!P98) -> 8.3486434 | Q100: =IF(ISTEXT('IS Raw'!L11),'IS Raw'!L36, Input!Q98) -> 5.6571294 | R100: =IF(ISTEXT('IS Raw'!M11),'IS Raw'!M36, Input!R98) -> 5.9611876 | ... Z100: =IF(ISTEXT('IS Raw'!U11),'IS Raw'!U36, Input!Z98) -> 11.961226
A102: 13 | B102: Net Income Attributable to Controlling Interest (FC) | K102: ='IS Raw'!F37/Input!$B$1 -> 426.17523 | L102: ='IS Raw'!G37/Input!$B$1 -> 661.04607 | M102: ='IS Raw'!H37/Input!$B$1 -> 1823.4591 | N102: ='IS Raw'!I37/Input!$B$1 -> 4315.9533 | O102: ='IS Raw'!J37/Input!$B$1 -> 1108.8928 | P102: ='IS Raw'!K37/Input!$B$1 -> 1419.6579 | Q102: =Q92-Q98 -> 2205.2449 | R102: =R92-R98 -> 2496.834 | S102: =S92-S98 -> 2922.7433 | T102: =T92-T98 -> 4565.7984 | U102: =U92-U98 -> 3902.7829 | V102: =V92-V98 -> 3406.4482 | W102: =W92-W98 -> 3411.1616 | X102: =X92-X98 -> 3789.0943 | ... Z102: =Z92-Z98 -> 4330.172
B103: Parent company
B104: Subsidiaries
B105: Affiliates
B106: Net Income Attributable to Controlling Interest | K106: =IF(ISTEXT('IS Raw'!F11), 'IS Raw'!F37/Input!$B$1, Input!K102) -> 426.17523 | L106: =IF(ISTEXT('IS Raw'!G11), 'IS Raw'!G37/Input!$B$1, Input!L102) -> 661.04607 | M106: =IF(ISTEXT('IS Raw'!H11), 'IS Raw'!H37/Input!$B$1, Input!M102) -> 1823.4591 | N106: =IF(ISTEXT('IS Raw'!I11), 'IS Raw'!I37/Input!$B$1, Input!N102) -> 4315.9533 | O106: =IF(ISTEXT('IS Raw'!J11), 'IS Raw'!J37/Input!$B$1, Input!O102) -> 1108.8928 | P106: =IF(ISTEXT('IS Raw'!K11), 'IS Raw'!K37/Input!$B$1, Input!P102) -> 1419.6579 | Q106: =IF(ISTEXT('IS Raw'!L11), 'IS Raw'!L37/Input!$B$1, Input!Q102) -> 2205.2449 | R106: =IF(ISTEXT('IS Raw'!M11), 'IS Raw'!M37/Input!$B$1, Input!R102) -> 2496.834 | ... Z106: =IF(ISTEXT('IS Raw'!U11), 'IS Raw'!U37/Input!$B$1, Input!Z102) -> 4330.172
L107: =L106/K106-1 -> 0.55111332 | M107: =M106/L106-1 -> 1.7584447 | N107: =N106/M106-1 -> 1.3669044 | O107: =O106/N106-1 -> -0.74307117 | P107: =P106/O106-1 -> 0.28024811 | Q107: =Q106/P106-1 -> 0.55336355 | R107: =R106/Q106-1 -> 0.13222526 | S107: =S106/R106-1 -> 0.17057974 | ... Z107: =Z106/Y106-1 -> -0.0083397054
A108: 14 | B108: EPS chưa điều chỉnh (FC) VND/share
B109: Basic EPS | K109: =IFERROR(K102/K138*1000, " ") -> 805.01554 | L109: =IFERROR(L102/L138*1000, " ") -> 1248.6703 | M109: =IFERROR(M102/M138*1000, " ") -> 3444.3881 | N109: =IFERROR(N102/N138*1000, " ") -> 8152.5374 | O109: =IFERROR(O102/O138*1000, " ") -> 2094.6219 | P109: =IFERROR(P102/P138*1000, " ") -> 2681.6357 | Q109: =IFERROR(Q102/Q138*1000, " ") -> 4165.5552 | R109: =IFERROR(R102/R138*1000, " ") -> 4716.3468 | ... Z109: =IFERROR(Z102/Z138*1000, " ") -> 8179.3955
B110: Diluted EPS | K110: =IFERROR(K102/K139*1000, " ") -> 805.01554 | L110: =IFERROR(L102/L139*1000, " ") -> 1248.6703 | M110: =IFERROR(M102/M139*1000, " ") -> 3444.3881 | N110: =IFERROR(N102/N139*1000, " ") -> 8152.5374 | O110: =IFERROR(O102/O139*1000, " ") -> 2094.6219 | P110: =IFERROR(P102/P139*1000, " ") -> 2681.6357 | Q110: =IFERROR(Q102/Q139*1000, " ") -> 4165.5552 | R110: =IFERROR(R102/R139*1000, " ") -> 4716.3468 | ... Z110: =IFERROR(Z102/Z139*1000, " ") -> 8179.3955
B111: EPS chưa điều chỉnh VND/share
B112: Basic EPS | K112: =IFERROR(K106/K138*1000, " ") -> 805.01554 | L112: =IFERROR(L106/L138*1000, " ") -> 1248.6703 | M112: =IFERROR(M106/M138*1000, " ") -> 3444.3881 | N112: =IFERROR(N106/N138*1000, " ") -> 8152.5374 | O112: =IFERROR(O106/O138*1000, " ") -> 2094.6219 | P112: =IFERROR(P106/P138*1000, " ") -> 2681.6357 | Q112: =IFERROR(Q106/Q138*1000, " ") -> 4165.5552 | R112: =IFERROR(R106/R138*1000, " ") -> 4716.3468 | ... Z112: =IFERROR(Z106/Z138*1000, " ") -> 8179.3955
B113: Diluted EPS | K113: =IFERROR(K106/K139*1000, " ") -> 805.01554 | L113: =IFERROR(L106/L139*1000, " ") -> 1248.6703 | M113: =IFERROR(M106/M139*1000, " ") -> 3444.3881 | N113: =IFERROR(N106/N139*1000, " ") -> 8152.5374 | O113: =IFERROR(O106/O139*1000, " ") -> 2094.6219 | P113: =IFERROR(P106/P139*1000, " ") -> 2681.6357 | Q113: =IFERROR(Q106/Q139*1000, " ") -> 4165.5552 | R113: =IFERROR(R106/R139*1000, " ") -> 4716.3468 | ... Z113: =IFERROR(Z106/Z139*1000, " ") -> 8179.3955
B114: Growth diluted EPS chưa điều chỉnh | L114: =L109/K109-1 -> 0.55111332 | M114: =M109/L109-1 -> 1.7584447 | N114: =N109/M109-1 -> 1.3669044 | O114: =O109/N109-1 -> -0.74307117 | P114: =P109/O109-1 -> 0.28024811 | Q114: =Q109/P109-1 -> 0.55336355 | R114: =R109/Q109-1 -> 0.13222526 | S114: =S109/R109-1 -> 0.17057974 | ... Z114: =Z109/Y109-1 -> -0.0083397054
A116: 15 | B116: Welfare Fund & others (FC) | K116: ='Welfare & Dividends'!K8 -> 109.15 | L116: ='Welfare & Dividends'!L8 -> 85.44 | M116: ='Welfare & Dividends'!M8 -> 98.99 | N116: ='Welfare & Dividends'!N8 -> 122.53 | O116: ='Welfare & Dividends'!O8 -> 122.36 | P116: ='Welfare & Dividends'!P8 -> 121.75 | Q116: =Q5*Q119 -> 188.90934 | R116: =R5*R119 -> 192.26927 | S116: =S5*S119 -> 240.53832 | T116: =T5*T119 -> 416.97928 | U116: =U5*U119 -> 319.00356 | V116: =V5*V119 -> 280.19111 | W116: =W5*W119 -> 285.05992 | X116: =X5*X119 -> 329.67448 | ... Z116: =Z5*Z119 -> 340.64147
B117: As % earnings after taxes in year (t) | C117: Nếu tính theo earning after taxes sẽ bị loop lúc tính tỷ giá | K117: =K118/K106 -> 0.25611531 | L117: =L118/L106 -> 0.12924969 | M117: =M118/M106 -> 0.054286933 | N117: =N118/N106 -> 0.02839002 | O117: =O118/O106 -> 0.1103443 | P117: =P118/P106 -> 0.085760095 | Q117: =AVERAGE(L117:P117) -> 0.081606207 | R117: =AVERAGE(M117:Q117) -> 0.072077511 | S117: =AVERAGE(N117:R117) -> 0.075635626 | T117: =AVERAGE(O117:S117) -> 0.085084747 | U117: =AVERAGE(P117:T117) -> 0.080032837 | V117: =AVERAGE(Q117:U117) -> 0.078887386 | W117: =AVERAGE(R117:V117) -> 0.078343621 | X117: =AVERAGE(S117:W117) -> 0.079596844 | ... Z117: =AVERAGE(U117:Y117) -> 0.079449955
...

Sheet Output-FR (show)
Q1: 1 | R1: 2 | S1: 3 | T1: 4 | U1: 5 | V1: 6 | W1: 7 | X1: 8 | Y1: 9 | Z1: 10 | AA1: 11 | AB1: 15 | AC1: 16 | AD1: 17 | AE1: 18 | AF1: 19 | AG1: 20 | AH1: 21 | AI1: 22 | AJ1: 23 | AK1: 24 | AL1: 25 | AM1: 26 | AN1: 27 | AO1: 28 | AP1: 29 | AQ1: 30 | AR1: 31 | AS1: 32 | AT1: 33 | AU1: 34 | AV1: 35 | AW1: 36 | AX1: 37 | AY1: 38 | AZ1: 39 | BA1: 40
B2: BÁO CÁO KẾT QUẢ KINH DOANH | C2: INCOME STATEMENT | F2: =IF(TODAY()<F3,"Proj","") | G2: =IF(TODAY()<G3,"Proj","") | H2: =IF(TODAY()<H3,"Proj","") | I2: =IF(TODAY()<I3,"Proj","") | J2: =IF(TODAY()<J3,"Proj","") | K2: =IF(TODAY()<K3,"Proj","") | L2: =IF(TODAY()<L3,"Proj","") | M2: =IF(TODAY()<M3,"Proj","") | ... BA2: =IF(TODAY()<BA3,"Proj","") -> Proj
D3: 41274 | E3: =DATE(YEAR(D3),MONTH(D3)+13,0) -> 41639 | F3: =DATE(YEAR(E3),MONTH(E3)+13,0) -> 42004 | G3: =DATE(YEAR(F3),MONTH(F3)+13,0) -> 42369 | H3: =DATE(YEAR(G3),MONTH(G3)+13,0) -> 42735 | I3: =DATE(YEAR(H3),MONTH(H3)+13,0) -> 43100 | J3: =DATE(YEAR(I3),MONTH(I3)+13,0) -> 43465 | K3: =DATE(YEAR(J3),MONTH(J3)+13,0) -> 43830 | L3: =DATE(YEAR(K3),MONTH(K3)+13,0) -> 44196 | ... BA3: =DATE(YEAR(AZ3),MONTH(AZ3)+13,0) -> 59171
A5: 1 | B5: Doanh thu | C5: Revenue | K5: =Input!K7 -> 7042.9669 | L5: =Input!L7 -> 7561.2751 | M5: =Input!M7 -> 9869.7629 | N5: =Input!N7 -> 15924.527 | O5: =Input!O7 -> 12570.542 | P5: =Input!P7 -> 13455.585 | Q5: =Input!Q7 -> 17736.964 | R5: =Input!R7 -> 18589.768 | ... Z5: =Input!Z7 -> 22829.84
A6: 2 | B6: Giá vốn hàng bán | C6: COGS | K6: =Input!K11 -> 6083.7747 | L6: =Input!L11 -> 6244.4273 | M6: =Input!M11 -> 7088.826 | N6: =Input!N11 -> 10221.097 | O6: =Input!O11 -> 10538.742 | P6: =Input!P11 -> 10942.101 | Q6: =Input!Q11 -> 13918.244 | R6: =Input!R11 -> 14383.611 | ... Z6: =Input!Z11 -> 16800.955
B7: LN gộp | C7: Gross profit | K7: =Input!K15 -> 959.1922 | L7: =Input!L15 -> 1316.8478 | M7: =Input!M15 -> 2780.9369 | N7: =Input!N15 -> 5703.4294 | O7: =Input!O15 -> 2031.7997 | P7: =Input!P15 -> 2513.4843 | Q7: =Input!Q15 -> 3818.7208 | R7: =Input!R15 -> 4206.1569 | ... Z7: =Input!Z15 -> 6028.8851
B8: Biên LNG | C8: Gross margin | K8: =K7/K5 -> 0.1361915 | L8: =L7/L5 -> 0.17415684 | M8: =M7/M5 -> 0.2817633 | N8: =N7/N5 -> 0.35815378 | O8: =O7/O5 -> 0.16163183 | P8: =P7/P5 -> 0.18679858 | Q8: =Q7/Q5 -> 0.21529731 | R8: =R7/R5 -> 0.22626193 | ... Z8: =Z7/Z5 -> 0.26407917
B10: Chi phí bán hàng & QLDN | C10: SG&A | K10: =Input!K19 -> 565.3779 | L10: =Input!L19 -> 673.40698 | M10: =Input!M19 -> 948.89299 | N10: =Input!N19 -> 1350.8891 | O10: =Input!O19 -> 1349.1883 | P10: =Input!P19 -> 1495.4168 | Q10: =Input!Q19 -> 1724.7513 | R10: =Input!R19 -> 1807.8709 | ... Z10: =Input!Z19 -> 2237.9733
C11: Operating Expense
B12: EBITDA | C12: EBITDA | K12: =Input!K35 -> 1712.6549 | L12: =Input!L35 -> 1961.5933 | M12: =Input!M35 -> 3217.8549 | N12: =Input!N35 -> 5750.5697 | O12: =Input!O35 -> 1765.992 | P12: =Input!P35 -> 1286.1489 | Q12: =Input!Q35 -> 2960.1655 | R12: =Input!R35 -> 3356.3643 | ... Z12: =Input!Z35 -> 4238.5622
C13: EBITDA margin | K13: =K12/K$5 -> 0.24317237 | L13: =L12/L$5 -> 0.25942625 | M13: =M12/M$5 -> 0.32603163 | N13: =N12/N$5 -> 0.36111401 | O13: =O12/O$5 -> 0.14048655 | P13: =P12/P$5 -> 0.095584763 | Q13: =Q12/Q$5 -> 0.16689245 | R13: =R12/R$5 -> 0.18054902 | ... Z13: =Z12/Z$5 -> 0.18565887
A15: 5 | B15: Khấu hao | C15: Depreciation/ Amortization | K15: =Input!K40 -> 1318.8406 | L15: =Input!L40 -> 1318.1525 | M15: =Input!M40 -> 1385.8109 | N15: =Input!N40 -> 1398.0294 | O15: =Input!O40 -> 1083.3807 | P15: =Input!P40 -> 268.08146 | Q15: =Input!Q40 -> 866.19597 | R15: =Input!R40 -> 958.07836 | ... Z15: =Input!Z40 -> 447.65036
C16: Depreciation of tangibles
C17: Amortization of intangibles
B18: EBIT | C18: EBIT | K18: =Input!K47 -> 393.8143 | L18: =Input!L47 -> 643.44082 | M18: =Input!M47 -> 1832.0439 | N18: =Input!N47 -> 4352.5403 | O18: =Input!O47 -> 682.61133 | P18: =Input!P47 -> 1018.0675 | Q18: =Input!Q47 -> 2093.9695 | R18: =Input!R47 -> 2398.2859 | ... Z18: =Input!Z47 -> 3790.9118
C19: EBIT margin | K19: =K18/K$5 -> 0.055915966 | L19: =L18/L$5 -> 0.085096867 | M19: =M18/M$5 -> 0.18562188 | N19: =N18/N$5 -> 0.27332305 | O19: =O18/O$5 -> 0.054302458 | P19: =P18/P$5 -> 0.075661329 | Q19: =Q18/Q$5 -> 0.11805681 | R19: =R18/R$5 -> 0.12901107 | ... Z19: =Z18/Z$5 -> 0.16605074
A21: 6 | B21: Doanh thu tài chính | C21: Financial Revenues | K21: =Input!K66 -> 127.01614 | L21: =Input!L66 -> 128.31668 | M21: =Input!M66 -> 167.53191 | N21: =Input!N66 -> 301.00806 | O21: =Input!O66 -> 577.08849 | P21: =Input!P66 -> 381.8039 | Q21: =Input!Q66 -> 612.61692 | R21: =Input!R66 -> 680.8309 | ... Z21: =Input!Z66 -> 1490.5862
A22: 7 | B22: Chi phí tài chính | C22: Financial Expenses | K22: =Input!K77 -> 102.75348 | L22: =Input!L77 -> 63.234525 | M22: =Input!M77 -> 45.07293 | N22: =Input!N77 -> 60.402057 | O22: =Input!O77 -> 27.372488 | P22: =Input!P77 -> 76.569108 | Q22: =Input!Q77 -> 101.62259 | R22: =Input!R77 -> 123.88871 | ... Z22: =Input!Z77 -> 148.60486
B23: Trong đó: CP lãi vay | K23: =Input!K69 -> 87.17253 | L23: =Input!L69 -> 43.301059 | M23: =Input!M69 -> 18.580201 | N23: =Input!N69 -> 10.274784 | O23: =Input!O69 -> 10.155714 | P23: =Input!P69 -> 44.380805 | Q23: =Input!Q69 -> 74.699342 | R23: =Input!R69 -> 95.075078 | ... Z23: =Input!Z69 -> 119.2698
A24: 8 | B24: Lãi/lỗ trong công ty LDLK | C24: Equity earnings in affiliates | K24: =Input!K82 -> 0 | L24: =Input!L82 -> 0 | M24: =Input!M82 -> 0 | N24: =Input!N82 -> 0 | O24: =Input!O82 -> 0 | P24: =Input!P82 -> 0 | Q24: =Input!Q82 -> 0 | R24: =Input!R82 -> 0 | ... Z24: =Input!Z82 -> 0
A25: 9 | B25: Lợi nhuận khác | C25: Other profit and loss | K25: =K26-K27 -> 45.011213 | L25: =L26-L27 -> 8.0108264 | M25: =M26-M27 -> 1.7670768 | N25: =N26-N27 -> 3.1664485 | O25: =O26-O27 -> 22.482246 | P25: =P26-P27 -> 198.76124 | Q25: =Q26-Q27 -> 16.230571 | R25: =R26-R27 -> 12.028047 | ... Z25: =Z26-Z27 -> 15.039808
C26: Gain (loss) on asset sales | K26: =Input!K52 -> 48.48338 | L26: =Input!L52 -> 10.735344 | M26: =Input!M52 -> 4.3711954 | N26: =Input!N52 -> 15.225626 | O26: =Input!O52 -> 24.751516 | P26: =Input!P52 -> 199.87676 | Q26: =Input!Q52 -> 22.550452 | R26: =Input!R52 -> 18.228298 | ... Z26: =Input!Z52 -> 22.029946
C27: Non-Operating expenses | K27: =Input!K56 -> 3.4721669 | L27: =Input!L56 -> 2.7245179 | M27: =Input!M56 -> 2.6041186 | N27: =Input!N56 -> 12.059178 | O27: =Input!O56 -> 2.2692702 | P27: =Input!P56 -> 1.1155147 | Q27: =Input!Q56 -> 6.3198817 | R27: =Input!R56 -> 6.2002506 | ... Z27: =Input!Z56 -> 6.990138
B28: LNTT | C28: Earning before taxes (EBT) | K28: =Input!K86 -> 463.08817 | L28: =Input!L86 -> 716.5338 | M28: =Input!M86 -> 1956.27 | N28: =Input!N86 -> 4596.3128 | O28: =Input!O86 -> 1254.8096 | P28: =Input!P86 -> 1522.0635 | Q28: =Input!Q86 -> 2621.1944 | R28: =Input!R86 -> 2967.2562 | ... Z28: =Input!Z86 -> 5147.9329
C29: EBT margin | K29: =K28/K$5 -> 0.065751859 | L29: =L28/L$5 -> 0.094763621 | M29: =M28/M$5 -> 0.19820841 | N29: =N28/N$5 -> 0.28863104 | O29: =O28/O$5 -> 0.099821438 | P29: =P28/P$5 -> 0.1131176 | Q29: =Q28/Q$5 -> 0.14778146 | R29: =R28/R$5 -> 0.15961771 | ... Z29: =Z28/Z$5 -> 0.22549142
A31: 10 | B31: Thuế TNDN | C31: Provision for taxes | K31: =Input!K90 -> 35.364442 | L31: =Input!L90 -> 54.08747 | M31: =Input!M90 -> 130.1457 | N31: =Input!N90 -> 275.23203 | O31: =Input!O90 -> 144.66687 | P31: =Input!P90 -> 94.056907 | Q31: =Input!Q90 -> 410.2924 | R31: =Input!R90 -> 464.46102 | ... Z31: =Input!Z90 -> 805.79972
B32: LNST | C32: Net Income | K32: =Input!K94 -> 427.72373 | L32: =Input!L94 -> 662.44633 | M32: =Input!M94 -> 1826.1243 | N32: =Input!N94 -> 4321.0807 | O32: =Input!O94 -> 1110.1427 | P32: =Input!P94 -> 1428.0066 | Q32: =Input!Q94 -> 2210.902 | R32: =Input!R94 -> 2502.7952 | ... Z32: =Input!Z94 -> 4342.1332
B33: Biên LNST | C33: NI margin | K33: =K32/K$5 -> 0.060730617 | L33: =L32/L$5 -> 0.0876104 | M33: =M32/M$5 -> 0.1850221 | N33: =N32/N$5 -> 0.27134751 | O33: =O32/O$5 -> 0.088313034 | P33: =P32/P$5 -> 0.10612742 | Q33: =Q32/Q$5 -> 0.1246494 | R33: =R32/R$5 -> 0.13463294 | ... Z33: =Z32/Z$5 -> 0.19019552
B34: Lợi ích cổ đông thiểu số | C34: Minority interest in earnings | K34: =Input!K100 -> 1.5484997 | L34: =Input!L100 -> 1.4002601 | M34: =Input!M100 -> 2.6652292 | N34: =Input!N100 -> 5.1274449 | O34: =Input!O100 -> 1.2498918 | P34: =Input!P100 -> 8.3486434 | Q34: =Input!Q100 -> 5.6571294 | R34: =Input!R100 -> 5.9611876 | ... Z34: =Input!Z100 -> 11.961226
B35: Lợi ích cổ đông mẹ | C35: Net Income Attributable to Controlling Interest | K35: =Input!K106 -> 426.17523 | L35: =Input!L106 -> 661.04607 | M35: =Input!M106 -> 1823.4591 | N35: =Input!N106 -> 4315.9533 | O35: =Input!O106 -> 1108.8928 | P35: =Input!P106 -> 1419.6579 | Q35: =Input!Q106 -> 2205.2449 | R35: =Input!R106 -> 2496.834 | ... Z35: =Input!Z106 -> 4330.172
B37: Quỹ khen thưởng phúc lợi | C37: Welfare Fund | K37: =Input!K118 -> 109.15 | L37: =Input!L118 -> 85.44 | M37: =Input!M118 -> 98.99 | N37: =Input!N118 -> 122.53 | O37: =Input!O118 -> 122.36 | P37: =Input!P118 -> 121.75 | Q37: =Input!Q118 -> 188.90934 | R37: =Input!R118 -> 192.26927 | ... Z37: =Input!Z118 -> 340.64147
B38: Chi phí bất thường | C38: Extraordinary expense | K38: =Input!K121 -> 0 | L38: =Input!L121 -> 0 | M38: =Input!M121 -> 0 | N38: =Input!N121 -> 0 | O38: =Input!O121 -> 0 | P38: =Input!P121 -> 0 | Q38: =Input!Q121 -> 0 | R38: =Input!R121 -> 0 | ... Z38: =Input!Z121 -> 0
B39: Cổ tức CPƯĐ | C39: Preferred dividends | K39: =Input!K125 -> 0 | L39: =Input!L125 -> 0 | M39: =Input!M125 -> 0 | N39: =Input!N125 -> 0 | O39: =Input!O125 -> 0 | P39: =Input!P125 -> 0 | Q39: =Input!Q125 -> 0 | R39: =Input!R125 -> 0 | ... Z39: =Input!Z125 -> 0
B40: LNST sẵn có cổ đông công ty mẹ | C40: Net income available to common shareholders | K40: =K35-K37-K38-K39 -> 317.02523 | L40: =L35-L37-L38-L39 -> 575.60607 | M40: =M35-M37-M38-M39 -> 1724.4691 | N40: =N35-N37-N38-N39 -> 4193.4233 | O40: =O35-O37-O38-O39 -> 986.53283 | P40: =P35-P37-P38-P39 -> 1297.9079 | Q40: =Q35-Q37-Q38-Q39 -> 2016.3356 | R40: =R35-R37-R38-R39 -> 2304.5647 | ... Z40: =Z35-Z37-Z38-Z39 -> 3989.5305
B42: Chi trả cổ tức | C42: Common dividends | K42: =Input!K133 -> 317.64 | L42: =Input!L133 -> 423.52 | M42: =Input!M133 -> 952.92 | N42: =Input!N133 -> 1588.2 | O42: =Input!O133 -> 1058.8 | P42: =Input!P133 -> 1058.8 | Q42: =Input!Q133 -> 1058.8 | R42: =Input!R133 -> 1323.5 | ... Z42: =Input!Z133 -> 3176.4
B43: LN giữ lại | C43: Net to retained earnings | K43: =Input!K136 -> -0.61477061 | L43: =Input!L136 -> 152.08607 | M43: =Input!M136 -> 771.54906 | N43: =Input!N136 -> 2605.2233 | O43: =Input!O136 -> -72.267175 | P43: =Input!P136 -> 239.10794 | Q43: =Input!Q136 -> 957.53556 | R43: =Input!R136 -> 981.06471 | ... Z43: =Input!Z136 -> 813.13053
B44: Check | K44: =K32-Input!K94 -> 0 | L44: =L32-Input!L94 -> 0 | M44: =M32-Input!M94 -> 0 | N44: =N32-Input!N94 -> 0 | O44: =O32-Input!O94 -> 0 | P44: =P32-Input!P94 -> 0 | Q44: =Q32-Input!Q94 -> 0 | R44: =R32-Input!R94 -> 0 | ... Z44: =Z32-Input!Z94 -> 0
B56: BẢNG CÂN ĐỐI KẾ TOÁN | C56: BALANCE SHEET
D57: 41274 | E57: =DATE(YEAR(D57),MONTH(D57)+13,0) -> 41639 | F57: =DATE(YEAR(E57),MONTH(E57)+13,0) -> 42004 | G57: =DATE(YEAR(F57),MONTH(F57)+13,0) -> 42369 | H57: =DATE(YEAR(G57),MONTH(G57)+13,0) -> 42735 | I57: =DATE(YEAR(H57),MONTH(H57)+13,0) -> 43100 | J57: =DATE(YEAR(I57),MONTH(I57)+13,0) -> 43465 | K57: =DATE(YEAR(J57),MONTH(J57)+13,0) -> 43830 | L57: =DATE(YEAR(K57),MONTH(K57)+13,0) -> 44196 | ... AR57: =DATE(YEAR(AQ57),MONTH(AQ57)+13,0) -> 55884
B58: TÀI SẢN | C58: ASSETS
B59: Tiền & tương đương tiền | K59: =K60+K61 -> 471.17332 | L59: =L60+L61 -> 509.99535 | M59: =M60+M61 -> 427.65273 | N59: =N60+N61 -> 2125.6253 | O59: =O60+O61 -> 2284.3998 | P59: =P60+P61 -> 1903.2483 | Q59: =Q60+Q61 -> 2701.1739 | R59: =R60+R61 -> 3135.0965 | ... Z59: =Z60+Z61 -> 4840.4743
A60: 1 | B60: Tương đương tiền | C60: Excess cash | K60: =Input!K158 -> 0 | L60: =Input!L158 -> 0 | M60: =Input!M158 -> 0 | N60: =Input!N158 -> 0 | O60: =Input!O158 -> 0 | P60: =Input!P158 -> 0 | Q60: =Input!Q158 -> 1.2864538 | R60: =Input!R158 -> 3.394359 | ... Z60: =Input!Z158 -> 3.484933
A61: 2 | B61: Tiền hoạt động | C61: Operating cash | K61: =+Input!K166 -> 471.17332 | L61: =+Input!L166 -> 509.99535 | M61: =+Input!M166 -> 427.65273 | N61: =+Input!N166 -> 2125.6253 | O61: =+Input!O166 -> 2284.3998 | P61: =+Input!P166 -> 1903.2483 | Q61: =+Input!Q166 -> 2699.8874 | R61: =+Input!R166 -> 3131.7022 | ... Z61: =+Input!Z166 -> 4836.9894
A62: 3 | B62: Đầu tư tài chính ngắn hạn | C62: Short-term invesments | K62: =+Input!K176 -> 2002 | L62: =+Input!L176 -> 2302 | M62: =+Input!M176 -> 4362 | N62: =+Input!N176 -> 6812 | O62: =+Input!O176 -> 8242 | P62: =+Input!P176 -> 7039.0512 | Q62: =+Input!Q176 -> 7240.527 | R62: =+Input!R176 -> 8369.0463 | ... Z62: =+Input!Z176 -> 19404.118
A63: 4 | B63: Khoản phải thu ngắn hạn | C63: Account receivable (AR) | K63: =+Input!K195 -> 401.90973 | L63: =+Input!L195 -> 217.3963 | M63: =+Input!M195 -> 187.45808 | N63: =+Input!N195 -> 188.14971 | O63: =+Input!O195 -> 365.83833 | P63: =+Input!P195 -> 528.62319 | Q63: =+Input!Q195 -> 707.68393 | R63: =+Input!R195 -> 770.21438 | ... Z63: =+Input!Z195 -> 1147.3553
A64: 5 | B64: Hàng tồn kho | C64: Inventory | K64: =Input!K207 -> 1301.1231 | L64: =Input!L207 -> 834.13489 | M64: =Input!M207 -> 2204.0777 | N64: =Input!N207 -> 2282.5277 | O64: =Input!O207 -> 2160.5882 | P64: =Input!P207 -> 2950.3006 | Q64: =Input!Q207 -> 3932.8571 | R64: =Input!R207 -> 4099.4141 | ... Z64: =Input!Z207 -> 5113.487
A65: 6 | B65: TSNH khác | C65: Other current assets | K65: =Input!K211 -> 73.830829 | L65: =Input!L211 -> 114.66559 | M65: =Input!M211 -> 95.103134 | N65: =Input!N211 -> 215.88389 | O65: =Input!O211 -> 451.66915 | P65: =Input!P211 -> 499.6394 | Q65: =Input!Q211 -> 715.10567 | R65: =Input!R211 -> 841.92393 | ... Z65: =Input!Z211 -> 2096.1365
B66: Tài sản ngắn hạn | C66: Current assets | K66: =SUM(K62:K65)+K59 -> 4250.037 | L66: =SUM(L62:L65)+L59 -> 3978.1921 | M66: =SUM(M62:M65)+M59 -> 7276.2916 | N66: =SUM(N62:N65)+N59 -> 11624.187 | O66: =SUM(O62:O65)+O59 -> 13504.495 | P66: =SUM(P62:P65)+P59 -> 12920.863 | Q66: =SUM(Q62:Q65)+Q59 -> 15297.348 | R66: =SUM(R62:R65)+R59 -> 17215.695 | ... Z66: =SUM(Z62:Z65)+Z59 -> 32601.571
B67: Check | K67: =K66-Input!K214 -> 0 | L67: =L66-Input!L214 -> 0 | M67: =M66-Input!M214 -> 0 | N67: =N66-Input!N214 -> 0 | O67: =O66-Input!O214 -> 0 | P67: =P66-Input!P214 -> 0 | Q67: =Q66-Input!Q214 -> 0 | R67: =R66-Input!R214 -> 0 | ... Z67: =Z66-Input!Z214 -> 0
A69: 7 | B69: Các khoản phải thu dài hạn | K69: =+Input!K220 -> 0.003 | L69: =+Input!L220 -> 0.003 | M69: =+Input!M220 -> 0.003 | N69: =+Input!N220 -> 0 | O69: =+Input!O220 -> 0 | P69: =+Input!P220 -> 0.51152602 | Q69: =+Input!Q220 -> 0.1157117 | R69: =+Input!R220 -> 0.14016798 | ... Z69: =+Input!Z220 -> 0.25328251
A70: 8 | B70: TSCĐ hữu hình | C70: Net PPE | K70: =Input!K226 -> 5134.4876 | L70: =Input!L226 -> 3899.631 | M70: =Input!M226 -> 3366.6881 | N70: =Input!N226 -> 2159.6449 | O70: =Input!O226 -> 1249.7677 | P70: =Input!P226 -> 1571.1965 | Q70: =Input!Q226 -> 1362.4554 | R70: =Input!R226 -> 1055.8317 | ... Z70: =Input!Z226 -> 1894.8945
A71: 9 | B71: TSCĐ vô hình | C71: Intangibles | K71: =Input!K232 -> 53.148677 | L71: =Input!L232 -> 55.797572 | M71: =Input!M232 -> 38.935203 | N71: =Input!N232 -> 47.20763 | O71: =Input!O232 -> 350.40774 | P71: =Input!P232 -> 363.78572 | Q71: =Input!Q232 -> 445.32656 | R71: =Input!R232 -> 464.07593 | ... Z71: =Input!Z232 -> 242.86699
A72: 10 | B72: TSCĐ thuê tài chính | K72: =Input!K238 -> 0 | L72: =Input!L238 -> 0 | M72: =Input!M238 -> 0 | N72: =Input!N238 -> 0 | O72: =Input!O238 -> 0 | P72: =Input!P238 -> 11.212289 | Q72: =Input!Q238 -> 11.257121 | R72: =Input!R238 -> 11.062543 | ... Z72: =Input!Z238 -> 4.6155612
A73: 11 | B73: BĐS đầu tư | K73: =Input!K244 -> 0 | L73: =Input!L244 -> 0 | M73: =Input!M244 -> 0 | N73: =Input!N244 -> 0 | O73: =Input!O244 -> 0 | P73: =Input!P244 -> 0 | Q73: =Input!Q244 -> 0 | R73: =Input!R244 -> 0 | ... Z73: =Input!Z244 -> 0
A74: 12 | B74: TSDD dài hạn | K74: =Input!K249 -> 698.50609 | L74: =Input!L249 -> 760.9553 | M74: =Input!M249 -> 66.117927 | N74: =Input!N249 -> 33.176188 | O74: =Input!O249 -> 88.189942 | P74: =Input!P249 -> 601.16557 | Q74: =Input!Q249 -> 655.73942 | R74: =Input!R249 -> 705.21572 | ... Z74: =Input!Z249 -> 986.73028
A75: 13 | B75: Đầu tư công ty con, LDLK | C75: Investment in affiliates | K75: =+Input!K254 -> 0 | L75: =+Input!L254 -> 0 | M75: =+Input!M254 -> 0 | N75: =+Input!N254 -> 0 | O75: =+Input!O254 -> 0 | P75: =+Input!P254 -> 0 | Q75: =+Input!Q254 -> 0 | R75: =+Input!R254 -> 0 | ... Z75: =+Input!Z254 -> 0
A76: 14 | B76: TSDH khác | C76: Long-term assets | K76: =Input!K259 -> 36.412462 | L76: =Input!L259 -> 22.901671 | M76: =Input!M259 -> 324.08547 | N76: =Input!N259 -> 302.64536 | O76: =Input!O259 -> 45.10562 | P76: =Input!P259 -> 260.11299 | Q76: =Input!Q259 -> 245.24151 | R76: =Input!R259 -> 283.85335 | ... Z76: =Input!Z259 -> 343.85292
B77: Tài sản dài hạn | C77: Non-current assets | K77: =SUM(K69:K76) -> 5922.5578 | L77: =SUM(L69:L76) -> 4739.2886 | M77: =SUM(M69:M76) -> 3795.8297 | N77: =SUM(N69:N76) -> 2542.6741 | O77: =SUM(O69:O76) -> 1733.471 | P77: =SUM(P69:P76) -> 2807.9846 | Q77: =SUM(Q69:Q76) -> 2720.1357 | R77: =SUM(R69:R76) -> 2520.1795 | ... Z77: =SUM(Z69:Z76) -> 3473.2135
B78: TỔNG TÀI SẢN | C78: Total assets | K78: =K66+K77 -> 10172.595 | L78: =L66+L77 -> 8717.4807 | M78: =M66+M77 -> 11072.121 | N78: =N66+N77 -> 14166.861 | O78: =O66+O77 -> 15237.966 | P78: =P66+P77 -> 15728.847 | Q78: =Q66+Q77 -> 18017.483 | R78: =R66+R77 -> 19735.875 | ... Z78: =Z66+Z77 -> 36074.785
B79: Check | K79: =K78-Input!K265 -> 0 | L79: =L78-Input!L265 -> 0 | M79: =M78-Input!M265 -> 0 | N79: =N78-Input!N265 -> 0 | O79: =O78-Input!O265 -> 0 | P79: =P78-Input!P265 -> 0 | Q79: =Q78-Input!Q265 -> 0 | R79: =R78-Input!R265 -> 0 | ... Z79: =Z78-Input!Z265 -> 0
B81: NỢ PHẢI TRẢ | C81: LIABILITIES
B82: Nợ vay ngắn hạn | K82: =+K83+K84 -> 1156.3717 | L82: =+L83+L84 -> 685.40656 | M82: =+M83+M84 -> 689.16295 | N82: =+N83+N84 -> 2.5594055 | O82: =+O83+O84 -> 845.80581 | P82: =+P83+P84 -> 1229.228 | Q82: =+Q83+Q84 -> 1627.7236 | R82: =+R83+R84 -> 1685.448 | ... Z82: =+Z83+Z84 -> 2492.9776
A83: 15 | B83: Vay thêm | C83: Revolver | K83: =Input!K273 -> 0 | L83: =Input!L273 -> 0 | M83: =Input!M273 -> 0 | N83: =Input!N273 -> 0 | O83: =Input!O273 -> 0 | P83: =Input!P273 -> 0 | Q83: =Input!Q273 -> 0 | R83: =Input!R273 -> 0 | ... Z83: =Input!Z273 -> 0
A84: 16 | B84: Vay hiện hữu | C84: Short-term notes | K84: =+Input!K279 -> 1156.3717 | L84: =+Input!L279 -> 685.40656 | M84: =+Input!M279 -> 689.16295 | N84: =+Input!N279 -> 2.5594055 | O84: =+Input!O279 -> 845.80581 | P84: =+Input!P279 -> 1229.228 | Q84: =+Input!Q279 -> 1627.7236 | R84: =+Input!R279 -> 1685.448 | ... Z84: =+Input!Z279 -> 2492.9776
A85: 17 | B85: Người mua trả tiền trước ngắn hạn | K85: =Input!K284 -> 45.098301 | L85: =Input!L284 -> 118.18308 | M85: =Input!M284 -> 285.54736 | N85: =Input!N284 -> 106.45108 | O85: =Input!O284 -> 23.307675 | P85: =Input!P284 -> 233.21169 | Q85: =Input!Q284 -> 227.13875 | R85: =Input!R284 -> 257.89699 | ... Z85: =Input!Z284 -> 282.1528
A86: 18 | B86: Phải trả người bán ngắn hạn | C86: Account payable | K86: =Input!K289 -> 879.30164 | L86: =Input!L289 -> 709.1268 | M86: =Input!M289 -> 794.79729 | N86: =Input!N289 -> 1028.4757 | O86: =Input!O289 -> 1989.2834 | P86: =Input!P289 -> 1611.5109 | Q86: =Input!Q289 -> 1517.7164 | R86: =Input!R289 -> 1493.3278 | ... Z86: =Input!Z289 -> 1268.007
A87: 19 | B87: Phải trả ngắn hạn khác | C87: Other current liabilities | K87: =Input!K293 -> 1219.2262 | L87: =Input!L293 -> 537.43534 | M87: =Input!M293 -> 1417.1029 | N87: =Input!N293 -> 1736.9498 | O87: =Input!O293 -> 1658.8609 | P87: =Input!P293 -> 1606.7795 | Q87: =Input!Q293 -> 2211.8638 | R87: =Input!R293 -> 2168.2263 | ... Z87: =Input!Z293 -> 2780.8822
B88: Nợ phải trả ngắn hạn | C88: Current liabilities | K88: =K82+SUM(K85:K87) -> 3299.9979 | L88: =L82+SUM(L85:L87) -> 2050.1518 | M88: =M82+SUM(M85:M87) -> 3186.6105 | N88: =N82+SUM(N85:N87) -> 2874.436 | O88: =O82+SUM(O85:O87) -> 4517.2578 | P88: =P82+SUM(P85:P87) -> 4680.7301 | Q88: =Q82+SUM(Q85:Q87) -> 5584.4425 | R88: =R82+SUM(R85:R87) -> 5604.899 | ... Z88: =Z82+SUM(Z85:Z87) -> 6824.0195
B89: Check | K89: =K88-Input!K296 -> 0 | L89: =L88-Input!L296 -> 0 | M89: =M88-Input!M296 -> 0 | N89: =N88-Input!N296 -> 0 | O89: =O88-Input!O296 -> 0 | P89: =P88-Input!P296 -> 0 | Q89: =Q88-Input!Q296 -> 0 | R89: =R88-Input!R296 -> 0 | ... Z89: =Z88-Input!Z296 -> 0
A91: 22 | B91: Phải trả người bán dài hạn | C91: Long-term account payable | K91: =Input!K343 -> 0 | L91: =Input!L343 -> 0 | M91: =Input!M343 -> 0 | N91: =Input!N343 -> 0 | O91: =Input!O343 -> 0 | P91: =Input!P343 -> 0 | Q91: =Input!Q343 -> 0 | R91: =Input!R343 -> 0 | ... Z91: =Input!Z343 -> 0
A92: 20 | B92: Nợ vay dài hạn | K92: =+Input!K330 -> 628.4725 | L92: =+Input!L330 -> 137.06222 | M92: =+Input!M330 -> 2.6763435 | N92: =+Input!N330 -> 1.0484815 | O92: =+Input!O330 -> 2.9644799 | P92: =+Input!P330 -> 119.5275 | Q92: =+Input!Q330 -> 351.10114 | R92: =+Input!R330 -> 497.00808 | ... Z92: =+Input!Z330 -> 344.77629
C93: Debt A (long-term debt)
C94: Debt B (long-term debt)
C95: Debt C (long-term debt)
A96: 21 | B96: Trái phiếu chuyển đổi | C96: Convertible bond | K96: =Input!K336 -> 0 | L96: =Input!L336 -> 0 | M96: =Input!M336 -> 0 | N96: =Input!N336 -> 0 | O96: =Input!O336 -> 0 | P96: =Input!P336 -> 0 | Q96: =Input!Q336 -> 0 | R96: =Input!R336 -> 0 | ... Z96: =Input!Z336 -> 0
A97: 23 | B97: Phải trả dài hạn khác | C97: Other long-term liabilities | K97: =Input!K347 -> 137.79715 | L97: =Input!L347 -> 203.81901 | M97: =Input!M347 -> 404.73717 | N97: =Input!N347 -> 685.92744 | O97: =Input!O347 -> 754.36092 | P97: =Input!P347 -> 751.41313 | Q97: =Input!Q347 -> 728.56492 | R97: =Input!R347 -> 830.24174 | ... Z97: =Input!Z347 -> 1097.4854
B98: Nợ phải trả dài hạn | C98: Non-current liabilities | K98: =K91+K92+K96+K97 -> 766.26965 | L98: =L91+L92+L96+L97 -> 340.88124 | M98: =M91+M92+M96+M97 -> 407.41352 | N98: =N91+N92+N96+N97 -> 686.97592 | O98: =O91+O92+O96+O97 -> 757.3254 | P98: =P91+P92+P96+P97 -> 870.94062 | Q98: =Q91+Q92+Q96+Q97 -> 1079.6661 | R98: =R91+R92+R96+R97 -> 1327.2498 | ... Z98: =Z91+Z92+Z96+Z97 -> 1442.2617
B99: Nợ phải trả | C99: Total liabilities | K99: =K98+K88 -> 4066.2675 | L99: =L98+L88 -> 2391.033 | M99: =M98+M88 -> 3594.0241 | N99: =N98+N88 -> 3561.4119 | O99: =O98+O88 -> 5274.5832 | P99: =P98+P88 -> 5551.6707 | Q99: =Q98+Q88 -> 6664.1086 | R99: =R98+R88 -> 6932.1488 | ... Z99: =Z98+Z88 -> 8266.2813
B100: Check | K100: =K99-Input!K353 -> 0 | L100: =L99-Input!L353 -> 0 | M100: =M99-Input!M353 -> 0 | N100: =N99-Input!N353 -> 0 | O100: =O99-Input!O353 -> 0 | P100: =P99-Input!P353 -> 0 | Q100: =Q99-Input!Q353 -> 0 | R100: =R99-Input!R353 -> 0 | ... Z100: =Z99-Input!Z353 -> 0
B102: LỢI ÍCH CỔ ĐÔNG THIỂU SỐ | C102: MINORITY INTEREST
A103: 24 | B103: Lợi ích cổ đông thiểu số | C103: Minority interest | K103: =Input!K359 -> 27.277893 | L103: =Input!L359 -> 26.347426 | M103: =Input!M359 -> 26.588185 | N103: =Input!N359 -> 29.143335 | O103: =Input!O359 -> 27.591066 | P103: =Input!P359 -> 32.786197 | Q103: =Input!Q359 -> 48.149162 | R103: =Input!R359 -> 45.49854 | ... AS103: =Input!AS359 -> 0
B105: VỐN CHỦ SỞ HỮU | C105: SHARE HOLDER'S EQUITY
A106: 25 | B106: Cổ phiếu ưu đãi | C106: Preferred stock | K106: =Input!K366 -> 0 | L106: =Input!L366 -> 0 | M106: =Input!M366 -> 0 | N106: =Input!N366 -> 0 | O106: =Input!O366 -> 0 | P106: =Input!P366 -> 0 | Q106: =Input!Q366 -> 0 | R106: =Input!R366 -> 0 | ... Z106: =Input!Z366 -> 0
A107: 26 | B107: Cổ phiếu thường | C107: Common stock | K107: =+Input!K370 -> 5294 | L107: =+Input!L370 -> 5294 | M107: =+Input!M370 -> 5294 | N107: =+Input!N370 -> 5294 | O107: =+Input!O370 -> 5294 | P107: =+Input!P370 -> 5294 | Q107: =+Input!Q370 -> 5294 | R107: =+Input!R370 -> 5294 | ... Z107: =+Input!Z370 -> 5294
A108: 27 | B108: Thặng dư vốn cổ phần | K108: =+Input!K374 -> 0 | L108: =+Input!L374 -> 0 | M108: =+Input!M374 -> 0 | N108: =+Input!N374 -> 0 | O108: =+Input!O374 -> 0 | P108: =+Input!P374 -> 0 | Q108: =+Input!Q374 -> 0 | R108: =+Input!R374 -> 0 | ... Z108: =+Input!Z374 -> 0
A109: 28 | B109: LN giữ lại | C109: Retained earnings | K109: =Input!K378 -> 428.84563 | L109: =Input!L378 -> 583.46741 | M109: =Input!M378 -> 1187.9854 | N109: =Input!N378 -> 3018.4551 | O109: =Input!O378 -> 2044.8513 | P109: =Input!P378 -> 1882.5131 | Q109: =Input!Q378 -> 2840.0486 | R109: =Input!R378 -> 3821.1134 | ... Z109: =Input!Z378 -> 15504.155
A110: 29 | B110: Quỹ khác thuộc CSH | C110: Other equity accounts | K110: =+Input!K382 -> 356.20373 | L110: =+Input!L382 -> 422.63284 | M110: =+Input!M382 -> 969.52369 | N110: =+Input!N382 -> 2263.8504 | O110: =+Input!O382 -> 2596.9408 | P110: =+Input!P382 -> 2967.8773 | Q110: =+Input!Q382 -> 3171.1769 | R110: =+Input!R382 -> 3643.1139 | ... Z110: =+Input!Z382 -> 6922.4263
B111: Vốn chủ sở hữu | C111: Shareholder's equity | J111: ='BS Raw'!E113 -> 6268.8723 | K111: =SUM(K106:K110) -> 6079.0494 | L111: =SUM(L106:L110) -> 6300.1002 | M111: =SUM(M106:M110) -> 7451.5091 | N111: =SUM(N106:N110) -> 10576.305 | O111: =SUM(O106:O110) -> 9935.7922 | P111: =SUM(P106:P110) -> 10144.39 | Q111: =SUM(Q106:Q110) -> 11305.226 | R111: =SUM(R106:R110) -> 12758.227 | ... Z111: =SUM(Z106:Z110) -> 27720.581
B112: TỔNG NGUỒN VỐN | C112: Total Liabilities & Equity | K112: =+K99+K103+K111 -> 10172.595 | L112: =+L99+L103+L111 -> 8717.4807 | M112: =+M99+M103+M111 -> 11072.121 | N112: =+N99+N103+N111 -> 14166.861 | O112: =+O99+O103+O111 -> 15237.966 | P112: =+P99+P103+P111 -> 15728.847 | Q112: =+Q99+Q103+Q111 -> 18017.483 | R112: =+R99+R103+R111 -> 19735.875 | ... Z112: =+Z99+Z103+Z111 -> 36074.785
B113: Check | K113: =K112-Input!K388 -> 0 | L113: =L112-Input!L388 -> 0 | M113: =M112-Input!M388 -> 0 | N113: =N112-Input!N388 -> 0 | O113: =O112-Input!O388 -> 0 | P113: =P112-Input!P388 -> 0 | Q113: =Q112-Input!Q388 -> 0 | R113: =R112-Input!R388 -> 0 | ... Z113: =Z112-Input!Z388 -> 0
A124: 1
B125: LƯU CHUYỂN TIỀN TỆ | C125: CASH FLOW
D126: =D3 -> 41274 | E126: =E3 -> 41639 | F126: =F3 -> 42004 | G126: =G3 -> 42369 | H126: =H3 -> 42735 | I126: =I3 -> 43100 | J126: =J3 -> 43465 | K126: =K3 -> 43830 | ... AR126: =AR3 -> 55884
B128: Lợi nhuận trước thuế | C128: Net income | K128: ='Output-FR (show)'!K28 -> 463.08817 | L128: ='Output-FR (show)'!L28 -> 716.5338 | M128: ='Output-FR (show)'!M28 -> 1956.27 | N128: ='Output-FR (show)'!N28 -> 4596.3128 | O128: ='Output-FR (show)'!O28 -> 1254.8096 | P128: ='Output-FR (show)'!P28 -> 1522.0635 | Q128: ='Output-FR (show)'!Q28 -> 2621.1944 | R128: ='Output-FR (show)'!R28 -> 2967.2562 | ... Z128: ='Output-FR (show)'!Z28 -> 5147.9329
B131: Điều chỉnh: | C131: Add back:
